Workbook
Name MeanMinAge16: '07_Тарифы'!$X$39
Name MeanMinAge09: '07_Тарифы'!$X$32
Name RevenueAge09: '07_Тарифы'!$B$32:$U$32
Name ThresholdAge23: '07_Тарифы'!$B$136:$U$136
Name CapacityYear2: '07_Тарифы'!$W$36:$W$47
Name WeightedRevAge10: '07_Тарифы'!$B$153:$U$153
Name MinimumAge12: '07_Тарифы'!$B$65:$U$65
Name УчитыватьИсторию: '01_Вводные'!$B$322
Name ДатаИндексацииЗП: '01_Вводные'!$B$251
Name СтавкаУСН: '01_Вводные'!$B$156
Name RevenueAge25: '07_Тарифы'!$B$48:$U$48
Name WeightedRevAge25: '07_Тарифы'!$B$168:$U$168
Name WeightedMinAge22: '07_Тарифы'!$B$195:$U$195
Name WeightedMinAge16: '07_Тарифы'!$B$189:$U$189
Name CapacityAge09: '07_Тарифы'!$W$32
Name CAPEXРазовый: '01_Вводные'!$B$287
Name MinimumAge03: '07_Тарифы'!$B$56:$U$56
Name ДетиК12Мес: '01_Вводные'!$B$46
Name WeightedMinAge14: '07_Тарифы'!$B$187:$U$187
Name ДатаLegacy: '01_Вводные'!$B$244
Name MinimumAge09: '07_Тарифы'!$B$62:$U$62
Name WeightedRevAge15: '07_Тарифы'!$B$158:$U$158
Name СреднийФиксТочки: '01_Вводные'!$B$52
Name RevenueAge14: '07_Тарифы'!$B$37:$U$37
Name WeightedMinAge10: '07_Тарифы'!$B$183:$U$183
Name CAPEXДата: '01_Вводные'!$B$289
Name WeightedRevAge17: '07_Тарифы'!$B$160:$U$160
Name MinimumAge16: '07_Тарифы'!$B$69:$U$69
Name CAPEXБаза: '01_Вводные'!$B$288
Name RevenueAge03: '07_Тарифы'!$B$26:$U$26
Name ERPШколВБазе: '01_Вводные'!$B$106
Name ЛагСледующихШкол: '01_Вводные'!$B$311
Name CapacityAge11: '07_Тарифы'!$W$34
Name CapacityAge07: '07_Тарифы'!$W$30
Name ДатаОфисМенеджера: '01_Вводные'!$B$247
Name ПремияГДвБазе: '01_Вводные'!$D$138
Name RevenueAge02: '07_Тарифы'!$B$25:$U$25
Name ThresholdAge13: '07_Тарифы'!$B$126:$U$126
Name ПрочиеIT: '01_Вводные'!$B$110
Name ЗапасДляЗайма: '01_Вводные'!$B$310
Name WeightedRevAge22: '07_Тарифы'!$B$165:$U$165
Name СуммаForbes: '01_Вводные'!$B$32
Name RevenueAge06: '07_Тарифы'!$B$29:$U$29
Name WeightedMinAge07: '07_Тарифы'!$B$180:$U$180
Name MinimumAge13: '07_Тарифы'!$B$66:$U$66
Name MeanMinAge17: '07_Тарифы'!$X$40
Name NetGross: '01_Вводные'!$B$132
Name ШколыСтарт: '01_Вводные'!$B$9
Name ДатаЗаменыДиректора: '01_Вводные'!$B$255
Name CapacityAge14: '07_Тарифы'!$W$37
Name ШколНаПродажу: '01_Вводные'!$B$22
Name MinimumAge15: '07_Тарифы'!$B$68:$U$68
Name РостДетей: '01_Вводные'!$B$12
Name CapacityAge22: '07_Тарифы'!$W$45
Name RevenueAge15: '07_Тарифы'!$B$38:$U$38
Name ОфисМенеджерNet: '01_Вводные'!$B$133
Name ДатаОсобогоЛага: '01_Вводные'!$B$242
Name ЗакрытиеГод: '01_Вводные'!$B$13
Name RevenueAge19: '07_Тарифы'!$B$42:$U$42
Name ДоляФКПаушальные: '01_Вводные'!$B$59

Sheet 00_Дашборд
B2: Финмодель «Спартак» — итог | G2: Сценарий: | H2: =СценарийТекст | I2: #gid=322657005&range=B192
B3: ="старт "&TEXT(MONTH(СтартМодели),"00")&"."&YEAR(СтартМодели)&" · горизонт "&ГоризонтМес&" мес." | G3: Сезон 25/26 в итоге: | H3: =УчитыватьИсторию | I3: #gid=322657005&range=B322
G4: =IF(УчитыватьИсторию="Да","Колонка слева — факт сезона 25/26, итог справа считает и его.","Колонка слева пуста: итог только за пять лет прогноза.")&" Сценарий пересчитывает всю модель, история — только показ."
B5: Показатель | C5: Сезон 25/26 09.2025 – 07.2026 | D5: ="Год 1"&CHAR(10)&TEXT(MONTH(DATE(YEAR(СтартМодели),MONTH(СтартМодели)+0,1)),"00")&"."&YEAR(DATE(YEAR(СтартМодели),MONTH(СтартМодели)+0,1))&" – "&TEXT(MONTH(DATE(YEAR(СтартМодели),MONTH(СтартМодели)+11,1)),"00")&"."&YEAR(DATE(YEAR(СтартМодели),MONTH(СтартМодели)+11,1)) | E5: ="Год 2"&CHAR(10)&TEXT(MONTH(DATE(YEAR(СтартМодели),MONTH(СтартМодели)+12,1)),"00")&"."&YEAR(DATE(YEAR(СтартМодели),MONTH(СтартМодели)+12,1))&" – "&TEXT(MONTH(DATE(YEAR(СтартМодели),MONTH(СтартМодели)+23,1)),"00")&"."&YEAR(DATE(YEAR(СтартМодели),MONTH(СтартМодели)+23,1)) | F5: ="Год 3"&CHAR(10)&TEXT(MONTH(DATE(YEAR(СтартМодели),MONTH(СтартМодели)+24,1)),"00")&"."&YEAR(DATE(YEAR(СтартМодели),MONTH(СтартМодели)+24,1))&" – "&TEXT(MONTH(DATE(YEAR(СтартМодели),MONTH(СтартМодели)+35,1)),"00")&"."&YEAR(DATE(YEAR(СтартМодели),MONTH(СтартМодели)+35,1)) | G5: ="Год 4"&CHAR(10)&TEXT(MONTH(DATE(YEAR(СтартМодели),MONTH(СтартМодели)+36,1)),"00")&"."&YEAR(DATE(YEAR(СтартМодели),MONTH(СтартМодели)+36,1))&" – "&TEXT(MONTH(DATE(YEAR(СтартМодели),MONTH(СтартМодели)+47,1)),"00")&"."&YEAR(DATE(YEAR(СтартМодели),MONTH(СтартМодели)+47,1)) | H5: ="Год 5"&CHAR(10)&TEXT(MONTH(DATE(YEAR(СтартМодели),MONTH(СтартМодели)+48,1)),"00")&"."&YEAR(DATE(YEAR(СтартМодели),MONTH(СтартМодели)+48,1))&" – "&TEXT(MONTH(DATE(YEAR(СтартМодели),MONTH(СтартМодели)+59,1)),"00")&"."&YEAR(DATE(YEAR(СтартМодели),MONTH(СтартМодели)+59,1)) | I5: ="Итого 5 лет"&CHAR(10)&TEXT(MONTH(DATE(YEAR(СтартМодели),MONTH(СтартМодели)+0,1)),"00")&"."&YEAR(DATE(YEAR(СтартМодели),MONTH(СтартМодели)+0,1))&" – "&TEXT(MONTH(DATE(YEAR(СтартМодели),MONTH(СтартМодели)+59,1)),"00")&"."&YEAR(DATE(YEAR(СтартМодели),MONTH(СтартМодели)+59,1)) | J5: С сезоном 25/26
B6: Паушальные взносы | C6: =IF(УчитыватьИсторию="Да",'01_Вводные'!$B$324,"") | D6: =SUM('02_Результат'!L12:'02_Результат'!W12) | E6: =SUM('02_Результат'!X12:'02_Результат'!AI12) | F6: =SUM('02_Результат'!AJ12:'02_Результат'!AU12) | G6: =SUM('02_Результат'!AV12:'02_Результат'!BG12) | H6: =SUM('02_Результат'!BH12:'02_Результат'!BS12) | I6: =SUM('02_Результат'!L12:'02_Результат'!BS12) | J6: =I6+IF(УчитыватьИсторию="Да",'01_Вводные'!$B$324,0)
B7: Роялти | C7: =IF(УчитыватьИсторию="Да",'01_Вводные'!$B$325,"") | D7: =SUM('02_Результат'!L13:'02_Результат'!W13) | E7: =SUM('02_Результат'!X13:'02_Результат'!AI13) | F7: =SUM('02_Результат'!AJ13:'02_Результат'!AU13) | G7: =SUM('02_Результат'!AV13:'02_Результат'!BG13) | H7: =SUM('02_Результат'!BH13:'02_Результат'!BS13) | I7: =SUM('02_Результат'!L13:'02_Результат'!BS13) | J7: =I7+IF(УчитыватьИсторию="Да",'01_Вводные'!$B$325,0)
B8: Мерч | C8: =IF(УчитыватьИсторию="Да",'01_Вводные'!$B$326,"") | D8: =SUM('02_Результат'!L14:'02_Результат'!W14) | E8: =SUM('02_Результат'!X14:'02_Результат'!AI14) | F8: =SUM('02_Результат'!AJ14:'02_Результат'!AU14) | G8: =SUM('02_Результат'!AV14:'02_Результат'!BG14) | H8: =SUM('02_Результат'!BH14:'02_Результат'!BS14) | I8: =SUM('02_Результат'!L14:'02_Результат'!BS14) | J8: =I8+IF(УчитыватьИсторию="Да",'01_Вводные'!$B$326,0)
B9: Выручка без НДС | C9: =IF(УчитыватьИсторию="Да",'01_Вводные'!$B$327,"") | D9: =SUM('02_Результат'!L16:'02_Результат'!W16) | E9: =SUM('02_Результат'!X16:'02_Результат'!AI16) | F9: =SUM('02_Результат'!AJ16:'02_Результат'!AU16) | G9: =SUM('02_Результат'!AV16:'02_Результат'!BG16) | H9: =SUM('02_Результат'!BH16:'02_Результат'!BS16) | I9: =SUM('02_Результат'!L16:'02_Результат'!BS16) | J9: =I9+IF(УчитыватьИсторию="Да",'01_Вводные'!$B$327,0)
B11: Прямые расходы | C11: =IF(УчитыватьИсторию="Да",'01_Вводные'!$B$328,"") | D11: =SUM('02_Результат'!L22:'02_Результат'!W22) | E11: =SUM('02_Результат'!X22:'02_Результат'!AI22) | F11: =SUM('02_Результат'!AJ22:'02_Результат'!AU22) | G11: =SUM('02_Результат'!AV22:'02_Результат'!BG22) | H11: =SUM('02_Результат'!BH22:'02_Результат'!BS22) | I11: =SUM('02_Результат'!L22:'02_Результат'!BS22) | J11: =I11+IF(УчитыватьИсторию="Да",'01_Вводные'!$B$328,0)
B12: Валовая прибыль | C12: =IF(УчитыватьИсторию="Да",'01_Вводные'!$B$329,"") | D12: =SUM('02_Результат'!L23:'02_Результат'!W23) | E12: =SUM('02_Результат'!X23:'02_Результат'!AI23) | F12: =SUM('02_Результат'!AJ23:'02_Результат'!AU23) | G12: =SUM('02_Результат'!AV23:'02_Результат'!BG23) | H12: =SUM('02_Результат'!BH23:'02_Результат'!BS23) | I12: =SUM('02_Результат'!L23:'02_Результат'!BS23) | J12: =I12+IF(УчитыватьИсторию="Да",'01_Вводные'!$B$329,0)
B13: ФОТ и кадровые расходы | C13: =IF(УчитыватьИсторию="Да",'01_Вводные'!$B$330,"") | D13: =SUM('02_Результат'!L24:'02_Результат'!W24) | E13: =SUM('02_Результат'!X24:'02_Результат'!AI24) | F13: =SUM('02_Результат'!AJ24:'02_Результат'!AU24) | G13: =SUM('02_Результат'!AV24:'02_Результат'!BG24) | H13: =SUM('02_Результат'!BH24:'02_Результат'!BS24) | I13: =SUM('02_Результат'!L24:'02_Результат'!BS24) | J13: =I13+IF(УчитыватьИсторию="Да",'01_Вводные'!$B$330,0)
B14: OPEX — прочие (без ФОТ) | C14: =IF(УчитыватьИсторию="Да",'01_Вводные'!$B$331,"") | D14: =SUM('02_Результат'!L31:'02_Результат'!W31) | E14: =SUM('02_Результат'!X31:'02_Результат'!AI31) | F14: =SUM('02_Результат'!AJ31:'02_Результат'!AU31) | G14: =SUM('02_Результат'!AV31:'02_Результат'!BG31) | H14: =SUM('02_Результат'!BH31:'02_Результат'!BS31) | I14: =SUM('02_Результат'!L31:'02_Результат'!BS31) | J14: =I14+IF(УчитыватьИсторию="Да",'01_Вводные'!$B$331,0)
B15: EBITDA | C15: =IF(УчитыватьИсторию="Да",'01_Вводные'!$B$332,"") | D15: =SUM('02_Результат'!L33:'02_Результат'!W33) | E15: =SUM('02_Результат'!X33:'02_Результат'!AI33) | F15: =SUM('02_Результат'!AJ33:'02_Результат'!AU33) | G15: =SUM('02_Результат'!AV33:'02_Результат'!BG33) | H15: =SUM('02_Результат'!BH33:'02_Результат'!BS33) | I15: =SUM('02_Результат'!L33:'02_Результат'!BS33) | J15: =I15+IF(УчитыватьИсторию="Да",'01_Вводные'!$B$332,0)
B16: УСН / минимальный налог | C16: =IF(УчитыватьИсторию="Да",'01_Вводные'!$B$333,"") | D16: =SUM('02_Результат'!L35:'02_Результат'!W35) | E16: =SUM('02_Результат'!X35:'02_Результат'!AI35) | F16: =SUM('02_Результат'!AJ35:'02_Результат'!AU35) | G16: =SUM('02_Результат'!AV35:'02_Результат'!BG35) | H16: =SUM('02_Результат'!BH35:'02_Результат'!BS35) | I16: =SUM('02_Результат'!L35:'02_Результат'!BS35) | J16: =I16+IF(УчитыватьИсторию="Да",'01_Вводные'!$B$333,0)
B17: Прибыль после налога | C17: =IF(УчитыватьИсторию="Да",'01_Вводные'!$B$334,"") | D17: =SUM('02_Результат'!L36:'02_Результат'!W36) | E17: =SUM('02_Результат'!X36:'02_Результат'!AI36) | F17: =SUM('02_Результат'!AJ36:'02_Результат'!AU36) | G17: =SUM('02_Результат'!AV36:'02_Результат'!BG36) | H17: =SUM('02_Результат'!BH36:'02_Результат'!BS36) | I17: =SUM('02_Результат'!L36:'02_Результат'!BS36) | J17: =I17+IF(УчитыватьИсторию="Да",'01_Вводные'!$B$334,0)
B19: Денежный поток за период | C19: =IF(УчитыватьИсторию="Да",'01_Вводные'!$B$335,"") | D19: =SUM('02_Результат'!L58:'02_Результат'!W58) | E19: =SUM('02_Результат'!X58:'02_Результат'!AI58) | F19: =SUM('02_Результат'!AJ58:'02_Результат'!AU58) | G19: =SUM('02_Результат'!AV58:'02_Результат'!BG58) | H19: =SUM('02_Результат'!BH58:'02_Результат'!BS58) | I19: =SUM('02_Результат'!L58:'02_Результат'!BS58) | J19: =I19+IF(УчитыватьИсторию="Да",'01_Вводные'!$B$335,0)
B20: Деньги на конец периода | C20: =IF(УчитыватьИсторию="Да",'01_Вводные'!$B$336,"") | D20: ='02_Результат'!W59 | E20: ='02_Результат'!AI59 | F20: ='02_Результат'!AU59 | G20: ='02_Результат'!BG59 | H20: ='02_Результат'!BS59 | I20: ='02_Результат'!BS59 | J20: =I20
B22: Школы на конец периода | C22: =IF(УчитыватьИсторию="Да",'01_Вводные'!$B$337,"") | D22: ='02_Результат'!W7 | E22: ='02_Результат'!AI7 | F22: ='02_Результат'!AU7 | G22: ='02_Результат'!BG7 | H22: ='02_Результат'!BS7 | I22: ='02_Результат'!BS7 | J22: =I22
B23: Партнёры на конец периода | C23: =IF(УчитыватьИсторию="Да",'01_Вводные'!$B$338,"") | D23: ='02_Результат'!W8 | E23: ='02_Результат'!AI8 | F23: ='02_Результат'!AU8 | G23: ='02_Результат'!BG8 | H23: ='02_Результат'!BS8 | I23: ='02_Результат'!BS8 | J23: =I23
B24: Дети, среднее за период | C24: =IF(УчитыватьИсторию="Да",'01_Вводные'!$B$339,"") | D24: =AVERAGE('02_Результат'!L9:'02_Результат'!W9) | E24: =AVERAGE('02_Результат'!X9:'02_Результат'!AI9) | F24: =AVERAGE('02_Результат'!AJ9:'02_Результат'!AU9) | G24: =AVERAGE('02_Результат'!AV9:'02_Результат'!BG9) | H24: =AVERAGE('02_Результат'!BH9:'02_Результат'!BS9) | I24: =AVERAGE('02_Результат'!L9:'02_Результат'!BS9) | J24: =I24 | K24: дети на март сезона
B25: Дети на пике сезона (март) | D25: =SUMPRODUCT((MONTH('02_Результат'!L$5:W$5)=3)*'02_Результат'!L9:W9) | E25: =SUMPRODUCT((MONTH('02_Результат'!X$5:AI$5)=3)*'02_Результат'!X9:AI9) | F25: =SUMPRODUCT((MONTH('02_Результат'!AJ$5:AU$5)=3)*'02_Результат'!AJ9:AU9) | G25: =SUMPRODUCT((MONTH('02_Результат'!AV$5:BG$5)=3)*'02_Результат'!AV9:BG9) | H25: =SUMPRODUCT((MONTH('02_Результат'!BH$5:BS$5)=3)*'02_Результат'!BH9:BS9) | I25: =H25 | J25: =I25
B26: На что смотреть
B27: Минимальный остаток денег за все 60 месяцев | C27: =MIN('02_Результат'!L59:'02_Результат'!BS59)
B28: Месяцев с отрицательным остатком | C28: =COUNTIF('02_Результат'!L59:'02_Результат'!BS59,"<0")
B29: Срок закрытия займа клубу, мес. | C29: =IF('06_Деньги'!BS19>0.01,"не закрыт за 60 мес.",SUMPRODUCT(--('06_Деньги'!L19:BS19>0.01))+1) | D29: {=IF(ISNUMBER(C29),INDEX('02_Результат'!$L$5:$BS$5,C29),"")}
B30: Рентабельность EBITDA за 5 лет | C30: =IF(I9=0,0,I15/I9)
B32: Ограничение: минимальный остаток на счёте | C32: =МинОстатокДляЗайма
B33: Клубу возвращаем займ только теми деньгами, что остаются сверх этого порога и сверх запаса на ближайшие убыточные месяцы. Сезон проседает летом — в июле и августе активны 14 % детей от мартовского уровня, а аренда и ФОТ идут как обычно, — и без такого резерва платёж клубу уводил счёт в минус. Поэтому в первые два года «Чистый поток за год» близок к нулю: вся свободная сумма уходит на склад формы и в погашение займа, а остаток на конец упирается в порог. Это не потеря денег, а их перекладывание в склад и в уменьшение долга — видно по строкам «Закупка на склад» и «Займ на конец» листа 06_Деньги. Порог меняется на листе 01_Вводные.
B35: Как это выглядит
B36: Шесть графиков по годам — значения подписаны на самих точках, деньги в миллионах. Нижний по месяцам: склад живёт внутри года, годовой срез его не показывает. Над каждым графиком строка «что смотреть».
B38: Выручка и EBITDA по годам. Масштаб бизнеса и сколько от него остаётся. Разрыв между столбцами — операционные расходы года. | L38: Откуда выручка: паушальные, роялти, мерч. Чем дальше год, тем меньше доля разовых паушальных и больше повторяющихся роялти и мерча — это и есть устойчивость модели.
B59: Продажи франшиз и открытия школ за год. Открытий больше, чем продаж: один партнёр со временем открывает несколько школ. Разрыв — это лаг открытия следующих школ. | L59: Сеть на конец года: школы и дети. Накопленный размер сети. Дети на правой оси: школа выходит на мощность за два года, поэтому линия отстаёт от столбцов.
B80: Форма: выручка и прибыль за год. Мерч — второй по размеру источник денег. Нижний столбец — что остаётся до того, как клуб заберёт свою долю. | L80: Займ клубу: погашено за год и остаток на конец. Как гасится займ на мерч. Гасим только свободными деньгами — линия остатка идёт вниз ступенями, а не равномерно.
B101: Склад формы по месяцам. Хватает ли формы на складе. Пока синяя линия выше оранжевой, спрос обеспечен; провал под неё — дефицит формы.
B123: Где что лежит
B124: 01_Вводные | C124: Единственное место, где что-то вводится руками
B125: 02_Результат | C125: БДР и БДДС: годы слева, месяцы справа
B126: 03_Сеть | C126: Расшифровка: продажи, открытия, школы, дети
B127: 04_Доходы | C127: Расшифровка: паушальные, роялти, мерч
B128: 05_Расходы | C128: Расшифровка: ФОТ, OPEX, выплаты ФК
B129: 06_Деньги | C129: Расшифровка: склад, займ, НДС, оборотка
B130: 07_Тарифы | C130: Справочник: индексы цен, возрастные тарифы
B131: 08_Проверки | C131: Основные контроли — их немного и они по делу
B132: 09_Инструкция | C132: Как пользоваться, гипотезы и словарь терминов
B133: 10_История | C133: Сезон 25/26 фактом: P&L, реестр начислений
B198: Служебное: те же годовые значения в миллионах — из них графики берут подписи. Ничего не вводится и не считается заново.
B200: 02_Результат строка 16 | E200: ='02_Результат'!E16/1000000 | F200: ='02_Результат'!F16/1000000 | G200: ='02_Результат'!G16/1000000 | H200: ='02_Результат'!H16/1000000 | I200: ='02_Результат'!I16/1000000
B201: 02_Результат строка 33 | E201: ='02_Результат'!E33/1000000 | F201: ='02_Результат'!F33/1000000 | G201: ='02_Результат'!G33/1000000 | H201: ='02_Результат'!H33/1000000 | I201: ='02_Результат'!I33/1000000
B202: 02_Результат строка 12 | E202: ='02_Результат'!E12/1000000 | F202: ='02_Результат'!F12/1000000 | G202: ='02_Результат'!G12/1000000 | H202: ='02_Результат'!H12/1000000 | I202: ='02_Результат'!I12/1000000
B203: 02_Результат строка 13 | E203: ='02_Результат'!E13/1000000 | F203: ='02_Результат'!F13/1000000 | G203: ='02_Результат'!G13/1000000 | H203: ='02_Результат'!H13/1000000 | I203: ='02_Результат'!I13/1000000
B204: 02_Результат строка 14 | E204: ='02_Результат'!E14/1000000 | F204: ='02_Результат'!F14/1000000 | G204: ='02_Результат'!G14/1000000 | H204: ='02_Результат'!H14/1000000 | I204: ='02_Результат'!I14/1000000
B205: 04_Доходы строка 131 | E205: ='04_Доходы'!E131/1000000 | F205: ='04_Доходы'!F131/1000000 | G205: ='04_Доходы'!G131/1000000 | H205: ='04_Доходы'!H131/1000000 | I205: ='04_Доходы'!I131/1000000
B206: 04_Доходы строка 135 | E206: ='04_Доходы'!E135/1000000 | F206: ='04_Доходы'!F135/1000000 | G206: ='04_Доходы'!G135/1000000 | H206: ='04_Доходы'!H135/1000000 | I206: ='04_Доходы'!I135/1000000
B207: 02_Результат строка 57 | E207: ='02_Результат'!E57/1000000 | F207: ='02_Результат'!F57/1000000 | G207: ='02_Результат'!G57/1000000 | H207: ='02_Результат'!H57/1000000 | I207: ='02_Результат'!I57/1000000
B208: 06_Деньги строка 19 | E208: ='06_Деньги'!E19/1000000 | F208: ='06_Деньги'!F19/1000000 | G208: ='06_Деньги'!G19/1000000 | H208: ='06_Деньги'!H19/1000000 | I208: ='06_Деньги'!I19/1000000

Sheet 01_Вводные
A1: Финмодель Спартак — единый лист вводных
A2: Легенда: | B2: ввод | C2: уточнить | D2: переключатель | E2: добавлено по договору | F2: формула — не трогать | G2: #gid=561835286 | H2: #gid=724336794
A3: Правило работы | B3: Менять жёлтые ячейки только здесь. Сценарий: B192. Чувствительность: B233:B234. Параметры, микс и история собраны на одном листе.
A4: #gid=322657005&range=A190 | G4: #gid=322657005&range=A190 | H4: #gid=322657005&range=A260
A5: 1. Календарь, стартовая сеть и оборотный капитал
A6: Параметр | B6: Значение | C6: Ед. | D6: Статус / источник | E6: Комментарий | G6: #gid=322657005&range=A232 | H6: #gid=322657005&range=A285
A7: Дата старта модели | B7: 46266 | C7: дата | E7: Сезон считается от даты старта: 12 месяцев — один сезон. Сезонность посещаемости, веса плана продаж и согласованный мерч привязаны к календарю и не зависят от месяца старта.
A8: Горизонт прогноза | B8: 60 | C8: мес. | G8: #gid=322657005&range=A309 | H8: #gid=322657005&range=A321
A9: Активные школы действующей сети на старте | B9: 104 | C9: шт. | D9: Фактический реестр на 09.09.2026 | E9: 104 действующие школы у 51 действующего партнёра; 3 новых партнёра пока без школ и в 104 не входят.
A10: Активные юрлица на старте | B10: 49 | C10: шт. | D10: Реестр сети 21.08.2026
A11: Дети действующей сети, 100% база | B11: 5200 | C11: чел.
A12: Рост детей действующей сети | B12: 0.1 | C12: %/год | E12: Сложный рост, пересчёт каждый сентябрь
A13: Закрытие школ / юрлиц | B13: 0.03 | C13: %/год | E13: =IF($B$13=0,"Механика работает, пока 0%","Закрывается "&ROUND($B$13*100,1)&" % школ и юрлиц в год; помесячно через коэффициент B14")
A14: Месячный коэффициент сохранения | B14: =(1-B13)^(1/12) | C14: коэфф. | E14: Технический коэффициент для закрытий
A15: Лаг продажа → открытие | B15: 2 | C15: мес. | E15: Продажа, открытие и ERP — разные события
A16: Новых юрлиц на 1 продажу | B16: 1 | C16: юрлиц/продажу | D16: Временно | E16: Связь продаж с новыми юрлицами. Пока 1:1; отдельно от количества школ на партнёра.
A17: Стартовый денежный остаток | B17: 187878 | C17: ₽ | D17: ДДС на 02.07.2026
A18: Дебиторка | B18: =$B$225*$F$203 | C18: дней | D18: Расчет по сценарию | E18: Базовое допущение | G18: ← формула; база: B225
A19: Кредиторка | B19: 15 | C19: дней | E19: Базовое допущение
A20: Доля поступления в текущем месяце | B20: =MAX(0,MIN(1,(30-B18)/30)) | C20: % | E20: 15 дней ≈ 50% текущий / 50% следующий месяц
A21: Доля оплаты в текущем месяце | B21: =MAX(0,MIN(1,(30-B19)/30)) | C21: % | E21: 15 дней ≈ 50% текущий / 50% следующий месяц
A22: Новых школ на 1 продажу / нового партнёра | B22: 1.1 | C22: школ/продажу | E22: ="Новый партнёр открывает "&ROUND($B$22,1)&" школы. Действующая сеть: 2,04 школы на партнёра (104 на 51)"
A23: 2. Продажи франшиз и маркетинг
A24: Параметр | B24: Значение | C24: Ед. | D24: Статус / источник | E24: Комментарий
A25: Конверсия лид → продажа | B25: 0.03 | C25: %
A26: Таргет на будущую продажу | B26: =$B$224*$F$202 | C26: ₽/продажа | D26: Расчет по сценарию | E26: Обычно M-2; для октября 2026 исключение M-1 | G26: ← формула; база: B224
A27: Лаг таргета до продажи | B27: 2 | C27: мес. | E27: Октябрь 2026 — отдельное исключение
A28: БИБОСС — сумма | B28: 200000 | C28: ₽ | E28: Ежегодно
A29: БИБОСС — месяц | B29: 10 | C29: номер месяца | E29: Октябрь
A30: TopFranchise — сумма | B30: 200000 | C30: ₽ | E30: Ежегодно
A31: TopFranchise — месяц | B31: 11 | C31: номер месяца | E31: Ноябрь
A32: Forbes — сумма | B32: 200000 | C32: ₽ | E32: Ежегодно
A33: Forbes — месяц | B33: 12 | C33: номер месяца | E33: Декабрь
A34: 2а. Планы продаж и сезонность (веса — по календарным месяцам, первый месяц модели без продаж)
A35: Сезон | B35: Годовой план | C35: Сен | D35: Окт | E35: Ноя | F35: Дек | G35: Янв | H35: Фев | I35: Мар | J35: Апр | K35: Май | L35: Июн | M35: Июл | N35: Авг | O35: Контроль
A36: 1 | B36: =$B$210*$F$198 | C36: 0.18 | D36: 0.04 | E36: 0.03 | F36: 0.02 | G36: 0.08 | H36: 0.13 | I36: 0.1 | J36: 0.06 | K36: 0.08 | L36: 0.05 | M36: 0.09 | N36: 0.14 | O36: =SUM(C36:N36)
A37: 2 | B37: =$B$211*$F$198 | C37: 0.18 | D37: 0.09 | E37: 0.03 | F37: 0.02 | G37: 0.08 | H37: 0.13 | I37: 0.05 | J37: 0.06 | K37: 0.08 | L37: 0.05 | M37: 0.09 | N37: 0.14 | O37: =SUM(C37:N37)
A38: 3 | B38: =$B$212*$F$198 | C38: 0.18 | D38: 0.09 | E38: 0.03 | F38: 0.02 | G38: 0.08 | H38: 0.13 | I38: 0.05 | J38: 0.06 | K38: 0.08 | L38: 0.05 | M38: 0.09 | N38: 0.14 | O38: =SUM(C38:N38)
A39: 4 | B39: =$B$213*$F$198 | C39: 0.18 | D39: 0.09 | E39: 0.03 | F39: 0.02 | G39: 0.08 | H39: 0.13 | I39: 0.05 | J39: 0.06 | K39: 0.08 | L39: 0.05 | M39: 0.09 | N39: 0.14 | O39: =SUM(C39:N39)
A40: 5 | B40: =$B$214*$F$198 | C40: 0.18 | D40: 0.09 | E40: 0.03 | F40: 0.02 | G40: 0.08 | H40: 0.13 | I40: 0.05 | J40: 0.06 | K40: 0.08 | L40: 0.05 | M40: 0.09 | N40: 0.14 | O40: =SUM(C40:N40)
A42: 3. Дети и сезонность посещаемости
A43: Месяц | B43: Янв | C43: Фев | D43: Мар | E43: Апр | F43: Май | G43: Июн | H43: Июл | I43: Авг | J43: Сен | K43: Окт | L43: Ноя | M43: Дек
A44: Индекс посещаемости | B44: 0.96323529 | C44: 1 | D44: 0.99264706 | E44: 0.92647059 | F44: 0.82352941 | G44: 0.31617647 | H44: 0.13970588 | I44: 0.13970588 | J44: 0.79411765 | K44: 0.94117647 | L44: 0.94117647 | M44: 0.92647059
A46: Дети к концу 12-го месяца, 100% | B46: =$B$215*$F$199 | C46: чел. при 100% | D46: Расчет по сценарию | E46: Взвешенное среднее | G46: ← формула; база: B215
A47: Дети к концу 24-го месяца, 100% | B47: =$B$216*$F$199 | C47: чел. при 100% | E47: Не полный план с 13-го месяца: плавный рост за месяцы 13-24. | G47: ← формула; база: B216
A49: 4. Паушальный взнос и роялти
A50: Параметр | B50: Значение | C50: Ед. | D50: Статус / источник | E50: Комментарий
A51: Абонемент действующей сети | B51: =$B$217*$F$200 | C51: ₽/мес. | D51: Расчет по сценарию | G51: ← формула; база: B217
A52: Средний фикс на точку начисления | B52: =SUMPRODUCT(B314:B318,D314:D318)/SUM(B314:B318) | C52: ₽/точку/мес. | D52: Расчёт из групп | E52: Считается из таблицы групп в разделе 16. Руками не вводится: в роялти входят фиксы групп, а не это среднее.
A53: Мин. роялти новой школы — 1-й год | B53: =SUMPRODUCT($C$263:$C$282,$I$263:$I$282)/$C$283 | C53: ₽/школа/мес. | D53: Взвешенный микс | E53: Минимум применяется по каждой школе | G53: ← формула; база: I263:I282
A54: Мин. роялти новой школы — 2-й год+ | B54: =SUMPRODUCT($C$263:$C$282,$J$263:$J$282)/$C$283 | C54: ₽/школа/мес. | D54: Взвешенный микс | E54: Минимум применяется по каждой школе | G54: ← формула; база: J263:J282
A55: ="Роялти старых / продаж до "&TEXT(DAY($B$244),"00")&"."&TEXT(MONTH($B$244),"00")&"."&YEAR($B$244) | B55: 0.065 | C55: % | E55: До 31.12.2029
A56: ="Роялти новых с "&TEXT(DAY($B$244+1),"00")&"."&TEXT(MONTH($B$244+1),"00")&"."&YEAR($B$244+1) | B56: 0.085 | C56: % | E56: До 31.12.2029
A57: ="Роялти всех с "&TEXT(DAY($B$245),"00")&"."&TEXT(MONTH($B$245),"00")&"."&YEAR($B$245) | B57: 0.1 | C57: % | E57: Дата перехода задаётся в B245; подпись слева следует за ней.
A58: НДС основной деятельности | B58: 0.05 | C58: % | D58: Временно | E58: Требует налоговой сверки
A59: Доля ФК от паушального | B59: 0.35 | C59: % от суммы с НДС | D59: Договор, п. 3.1 а) | E59: «35 % от валовой выручки» — без оговорки «за вычетом НДС», которая стоит в подпунктах д/е/ж. База считается по строке 13 листа «04_Доходы» (с НДС), а не по строке 14. | F59: 35% выручки. Не связано с B76: там 35% ПРИБЫЛИ мерча. Совпадение ставок случайно — пересмотр одной не двигает другую.
A60: Доля ФК от роялти — 1-я ступень | B60: 0.1 | C60: % без НДС | D60: Договор, п. 3.1 д) | E60: Базовая ставка первой ступени. Дальше растёт по календарю — ступени и их даты в разделе 18. База — за вычетом НДС, как написано в договоре.
A61: Средние по взвешенному миксу продуктов — по сезонам
A62: Сезон | B62: Средний паушальный, ₽ с НДС | C62: Средний абонемент, ₽/мес.
A63: 1 | B63: =SUMPRODUCT($C$263:$C$282,$D$263:$D$282)/$C$283 | C63: =$B$218*$F$200 | G63: ← формула; база: D263:D282
A64: 2 | B64: =SUMPRODUCT($C$263:$C$282,$D$263:$D$282)/$C$283 | C64: =$B$219*$F$200 | G64: ← формула; база: D263:D282
A65: 3 | B65: =SUMPRODUCT($C$263:$C$282,$D$263:$D$282)/$C$283 | C65: =$B$220*$F$200 | G65: ← формула; база: D263:D282
A66: 4 | B66: =SUMPRODUCT($C$263:$C$282,$D$263:$D$282)/$C$283 | C66: =$B$221*$F$200 | G66: ← формула; база: D263:D282
A67: 5 | B67: =SUMPRODUCT($C$263:$C$282,$D$263:$D$282)/$C$283 | C67: =$B$222*$F$200 | G67: ← формула; база: D263:D282
A69: 5. Мерч, склад и займ
A70: Параметр | B70: Значение | C70: Ед. | D70: Статус / источник | E70: Комментарий
A71: Себестоимость комплекта | B71: 1900 | C71: ₽
A72: Наценка мерча | B72: 0.9 | C72: % к COGS
A73: Цена комплекта | B73: =B71*(1+B72) | C73: ₽
A74: Коэффициент мерча | B74: =$B$223*$F$201 | C74: компл./ребёнок/сезон | E74: Ежегодная докупка | G74: ← формула; база: B223
A75: Логистика/возвраты/брак | B75: 0.01 | C75: % выручки без НДС
A76: Доля ФК от прибыли мерча | B76: 0.35 | C76: % | E76: Отдельно от возврата займа | F76: 35% прибыли (выручка − COGS − логистика). Не связано с B59: там 35% ВЫРУЧКИ по паушальным. Базы разные.
A77: Стартовый товарный запас | B77: 50000000 | C77: ₽ по COGS
A78: Стартовый займ на мерч | B78: 50000000 | C78: ₽
A79: Доля COGS на погашение займа | B79: 1 | C79: %
A80: Целевой запас | B80: 3 | C80: мес. будущих продаж | E80: ="При закупке доводим склад до будущих "&$B$80&" мес. продаж по себестоимости"
A81: Начало регулярного пополнения | B81: 46692 | C81: дата
A82: Месяц проверки закупки 1 | B82: 2 | C82: номер месяца | E82: Февраль; уточнить точные месяцы закупок
A83: Месяц проверки закупки 2 | B83: 5 | C83: номер месяца | E83: Май; уточнить точные месяцы закупок
A84: Месяц проверки закупки 3 | B84: 8 | C84: номер месяца | E84: Август; уточнить точные месяцы закупок
A85: Месяц проверки закупки 4 | B85: 11 | C85: номер месяца | E85: Ноябрь; уточнить точные месяцы закупок
A86: Первичная закупка новой школы
A87: 1-й месяц после открытия | B87: 0
A88: 2-й месяц после открытия | B88: 0.8
A89: 3-й месяц после открытия | B89: 0.2
A90: Контроль | B90: =SUM(B87:B89)
A92: Сезонность повторной закупки мерча
B93: Янв | C93: Фев | D93: Мар | E93: Апр | F93: Май | G93: Июн | H93: Июл | I93: Авг | J93: Сен | K93: Окт | L93: Ноя | M93: Дек
A94: Доля годовых повторных продаж | B94: 0 | C94: 0 | D94: 0 | E94: 0 | F94: 0 | G94: 0 | H94: 0 | I94: 0.25 | J94: 0.4 | K94: 0.25 | L94: 0.1 | M94: 0
A95: Контроль | B95: =SUM(B94:M94)
A97: 5а. Согласованный мерч действующей сети — факт сентябрь–декабрь 2026
A98: Месяц (факт, ищется по дате) | B98: 46266 | C98: 46296 | D98: 46327 | E98: 46357
A99: SKU, шт. | B99: 800 | C99: 1300 | D99: 650 | E99: 450
A100: Выручка, ₽ с НДС | B100: 5377590 | C100: 5850000 | D100: 2925000 | E100: 2025000
A101: COGS, ₽ | B101: 2958841 | C101: 2925000 | D101: 1462500 | E101: 1012500
A103: 6. ERP и операционные расходы
A104: Параметр | B104: Значение | C104: Ед. | D104: Статус / источник | E104: Комментарий
A105: ERP база | B105: 80000 | C105: ₽/мес.
A106: Школ в ERP-базе | B106: 104 | C106: шт. | D106: Фактический реестр на 09.09.2026 | E106: Базовые 80 тыс. ₽ ERP покрывают 104 действующие школы на старте; доплата 3 тыс. ₽ применяется к новым подключённым школам сверх этой базы.
A107: ERP на новую активную школу | B107: 3000 | C107: ₽/мес. | E107: С месяца открытия
...

Sheet 02_Результат
B1: Результат: БДР и БДДС
B2: Начисления и деньги на одном листе, но в разных блоках. Слева итоги по годам, справа те же строки по месяцам.
B4: Показатель | C4: Ед. | D4: Как считается | E4: Год 1 | F4: Год 2 | G4: Год 3 | H4: Год 4 | I4: Год 5 | J4: Итого 5 лет | L4: М1 | M4: М2 | N4: М3 | O4: М4 | P4: М5 | Q4: М6 | R4: М7 | S4: М8 | T4: М9 | U4: М10 | V4: М11 | W4: М12 | X4: М13 | Y4: М14 | Z4: М15 | AA4: М16 | AB4: М17 | AC4: М18 | AD4: М19 | AE4: М20 | AF4: М21 | AG4: М22 | AH4: М23 | AI4: М24 | AJ4: М25 | AK4: М26 | AL4: М27 | AM4: М28 | AN4: М29 | AO4: М30 | AP4: М31 | AQ4: М32 | AR4: М33 | AS4: М34 | AT4: М35 | AU4: М36 | AV4: М37 | AW4: М38 | AX4: М39 | AY4: М40 | AZ4: М41 | BA4: М42 | BB4: М43 | BC4: М44 | BD4: М45 | BE4: М46 | BF4: М47 | BG4: М48 | BH4: М49 | BI4: М50 | BJ4: М51 | BK4: М52 | BL4: М53 | BM4: М54 | BN4: М55 | BO4: М56 | BP4: М57 | BQ4: М58 | BR4: М59 | BS4: М60 | BT4: тех. 1 | BU4: тех. 2 | BV4: тех. 3 | BW4: тех. 4 | BX4: тех. 5 | BY4: тех. 6
E5: =TEXT(MONTH(DATE(YEAR(СтартМодели),MONTH(СтартМодели)+0,1)),"00")&"."&YEAR(DATE(YEAR(СтартМодели),MONTH(СтартМодели)+0,1))&" – "&TEXT(MONTH(DATE(YEAR(СтартМодели),MONTH(СтартМодели)+11,1)),"00")&"."&YEAR(DATE(YEAR(СтартМодели),MONTH(СтартМодели)+11,1)) | F5: =TEXT(MONTH(DATE(YEAR(СтартМодели),MONTH(СтартМодели)+12,1)),"00")&"."&YEAR(DATE(YEAR(СтартМодели),MONTH(СтартМодели)+12,1))&" – "&TEXT(MONTH(DATE(YEAR(СтартМодели),MONTH(СтартМодели)+23,1)),"00")&"."&YEAR(DATE(YEAR(СтартМодели),MONTH(СтартМодели)+23,1)) | G5: =TEXT(MONTH(DATE(YEAR(СтартМодели),MONTH(СтартМодели)+24,1)),"00")&"."&YEAR(DATE(YEAR(СтартМодели),MONTH(СтартМодели)+24,1))&" – "&TEXT(MONTH(DATE(YEAR(СтартМодели),MONTH(СтартМодели)+35,1)),"00")&"."&YEAR(DATE(YEAR(СтартМодели),MONTH(СтартМодели)+35,1)) | H5: =TEXT(MONTH(DATE(YEAR(СтартМодели),MONTH(СтартМодели)+36,1)),"00")&"."&YEAR(DATE(YEAR(СтартМодели),MONTH(СтартМодели)+36,1))&" – "&TEXT(MONTH(DATE(YEAR(СтартМодели),MONTH(СтартМодели)+47,1)),"00")&"."&YEAR(DATE(YEAR(СтартМодели),MONTH(СтартМодели)+47,1)) | I5: =TEXT(MONTH(DATE(YEAR(СтартМодели),MONTH(СтартМодели)+48,1)),"00")&"."&YEAR(DATE(YEAR(СтартМодели),MONTH(СтартМодели)+48,1))&" – "&TEXT(MONTH(DATE(YEAR(СтартМодели),MONTH(СтартМодели)+59,1)),"00")&"."&YEAR(DATE(YEAR(СтартМодели),MONTH(СтартМодели)+59,1)) | J5: =TEXT(MONTH(DATE(YEAR(СтартМодели),MONTH(СтартМодели)+0,1)),"00")&"."&YEAR(DATE(YEAR(СтартМодели),MONTH(СтартМодели)+0,1))&" – "&TEXT(MONTH(DATE(YEAR(СтартМодели),MONTH(СтартМодели)+59,1)),"00")&"."&YEAR(DATE(YEAR(СтартМодели),MONTH(СтартМодели)+59,1)) | L5: =DATE(YEAR(СтартМодели),MONTH(СтартМодели)+1-1,1) | M5: =DATE(YEAR(СтартМодели),MONTH(СтартМодели)+2-1,1) | N5: =DATE(YEAR(СтартМодели),MONTH(СтартМодели)+3-1,1) | O5: =DATE(YEAR(СтартМодели),MONTH(СтартМодели)+4-1,1) | P5: =DATE(YEAR(СтартМодели),MONTH(СтартМодели)+5-1,1) | Q5: =DATE(YEAR(СтартМодели),MONTH(СтартМодели)+6-1,1) | R5: =DATE(YEAR(СтартМодели),MONTH(СтартМодели)+7-1,1) | S5: =DATE(YEAR(СтартМодели),MONTH(СтартМодели)+8-1,1) | T5: =DATE(YEAR(СтартМодели),MONTH(СтартМодели)+9-1,1) | U5: =DATE(YEAR(СтартМодели),MONTH(СтартМодели)+10-1,1) | V5: =DATE(YEAR(СтартМодели),MONTH(СтартМодели)+11-1,1) | W5: =DATE(YEAR(СтартМодели),MONTH(СтартМодели)+12-1,1) | X5: =DATE(YEAR(СтартМодели),MONTH(СтартМодели)+13-1,1) | Y5: =DATE(YEAR(СтартМодели),MONTH(СтартМодели)+14-1,1) | Z5: =DATE(YEAR(СтартМодели),MONTH(СтартМодели)+15-1,1) | AA5: =DATE(YEAR(СтартМодели),MONTH(СтартМодели)+16-1,1) | AB5: =DATE(YEAR(СтартМодели),MONTH(СтартМодели)+17-1,1) | AC5: =DATE(YEAR(СтартМодели),MONTH(СтартМодели)+18-1,1) | AD5: =DATE(YEAR(СтартМодели),MONTH(СтартМодели)+19-1,1) | AE5: =DATE(YEAR(СтартМодели),MONTH(СтартМодели)+20-1,1) | AF5: =DATE(YEAR(СтартМодели),MONTH(СтартМодели)+21-1,1) | AG5: =DATE(YEAR(СтартМодели),MONTH(СтартМодели)+22-1,1) | AH5: =DATE(YEAR(СтартМодели),MONTH(СтартМодели)+23-1,1) | AI5: =DATE(YEAR(СтартМодели),MONTH(СтартМодели)+24-1,1) | AJ5: =DATE(YEAR(СтартМодели),MONTH(СтартМодели)+25-1,1) | AK5: =DATE(YEAR(СтартМодели),MONTH(СтартМодели)+26-1,1) | AL5: =DATE(YEAR(СтартМодели),MONTH(СтартМодели)+27-1,1) | AM5: =DATE(YEAR(СтартМодели),MONTH(СтартМодели)+28-1,1) | AN5: =DATE(YEAR(СтартМодели),MONTH(СтартМодели)+29-1,1) | AO5: =DATE(YEAR(СтартМодели),MONTH(СтартМодели)+30-1,1) | AP5: =DATE(YEAR(СтартМодели),MONTH(СтартМодели)+31-1,1) | AQ5: =DATE(YEAR(СтартМодели),MONTH(СтартМодели)+32-1,1) | AR5: =DATE(YEAR(СтартМодели),MONTH(СтартМодели)+33-1,1) | AS5: =DATE(YEAR(СтартМодели),MONTH(СтартМодели)+34-1,1) | AT5: =DATE(YEAR(СтартМодели),MONTH(СтартМодели)+35-1,1) | AU5: =DATE(YEAR(СтартМодели),MONTH(СтартМодели)+36-1,1) | AV5: =DATE(YEAR(СтартМодели),MONTH(СтартМодели)+37-1,1) | AW5: =DATE(YEAR(СтартМодели),MONTH(СтартМодели)+38-1,1) | AX5: =DATE(YEAR(СтартМодели),MONTH(СтартМодели)+39-1,1) | AY5: =DATE(YEAR(СтартМодели),MONTH(СтартМодели)+40-1,1) | AZ5: =DATE(YEAR(СтартМодели),MONTH(СтартМодели)+41-1,1) | BA5: =DATE(YEAR(СтартМодели),MONTH(СтартМодели)+42-1,1) | BB5: =DATE(YEAR(СтартМодели),MONTH(СтартМодели)+43-1,1) | BC5: =DATE(YEAR(СтартМодели),MONTH(СтартМодели)+44-1,1) | BD5: =DATE(YEAR(СтартМодели),MONTH(СтартМодели)+45-1,1) | BE5: =DATE(YEAR(СтартМодели),MONTH(СтартМодели)+46-1,1) | BF5: =DATE(YEAR(СтартМодели),MONTH(СтартМодели)+47-1,1) | BG5: =DATE(YEAR(СтартМодели),MONTH(СтартМодели)+48-1,1) | BH5: =DATE(YEAR(СтартМодели),MONTH(СтартМодели)+49-1,1) | BI5: =DATE(YEAR(СтартМодели),MONTH(СтартМодели)+50-1,1) | BJ5: =DATE(YEAR(СтартМодели),MONTH(СтартМодели)+51-1,1) | BK5: =DATE(YEAR(СтартМодели),MONTH(СтартМодели)+52-1,1) | BL5: =DATE(YEAR(СтартМодели),MONTH(СтартМодели)+53-1,1) | BM5: =DATE(YEAR(СтартМодели),MONTH(СтартМодели)+54-1,1) | BN5: =DATE(YEAR(СтартМодели),MONTH(СтартМодели)+55-1,1) | BO5: =DATE(YEAR(СтартМодели),MONTH(СтартМодели)+56-1,1) | BP5: =DATE(YEAR(СтартМодели),MONTH(СтартМодели)+57-1,1) | BQ5: =DATE(YEAR(СтартМодели),MONTH(СтартМодели)+58-1,1) | BR5: =DATE(YEAR(СтартМодели),MONTH(СтартМодели)+59-1,1) | BS5: =DATE(YEAR(СтартМодели),MONTH(СтартМодели)+60-1,1) | BT5: =DATE(YEAR(СтартМодели),MONTH(СтартМодели)+61-1,1) | BU5: =DATE(YEAR(СтартМодели),MONTH(СтартМодели)+62-1,1) | BV5: =DATE(YEAR(СтартМодели),MONTH(СтартМодели)+63-1,1) | BW5: =DATE(YEAR(СтартМодели),MONTH(СтартМодели)+64-1,1) | BX5: =DATE(YEAR(СтартМодели),MONTH(СтартМодели)+65-1,1) | BY5: =DATE(YEAR(СтартМодели),MONTH(СтартМодели)+66-1,1)
B6: Сеть (справочно)
B7: Школы всего | C7: шт. | D7: Подробности — на листе «Сеть» В колонках лет — значение на конец года, в «Итого» — на конец пятого года. Это остаток, а не сумма. | E7: =W7 | F7: =AI7 | G7: =AU7 | H7: =BG7 | I7: =BS7 | J7: =BS7 | L7: ='03_Сеть'!L60 | M7: ='03_Сеть'!M60 | N7: ='03_Сеть'!N60 | O7: ='03_Сеть'!O60 | P7: ='03_Сеть'!P60 | Q7: ='03_Сеть'!Q60 | R7: ='03_Сеть'!R60 | S7: ='03_Сеть'!S60 | ... BY7: ='03_Сеть'!BY60
B8: Партнёры (юрлица) | C8: шт. | D8: В колонках лет — значение на конец года, в «Итого» — на конец пятого года. Это остаток, а не сумма. | E8: =W8 | F8: =AI8 | G8: =AU8 | H8: =BG8 | I8: =BS8 | J8: =BS8 | L8: ='03_Сеть'!L61 | M8: ='03_Сеть'!M61 | N8: ='03_Сеть'!N61 | O8: ='03_Сеть'!O61 | P8: ='03_Сеть'!P61 | Q8: ='03_Сеть'!Q61 | R8: ='03_Сеть'!R61 | S8: ='03_Сеть'!S61 | ... BY8: ='03_Сеть'!BY61
B9: Дети, активные | C9: чел. | D9: В колонках лет — значение на конец года, в «Итого» — на конец пятого года. Это остаток, а не сумма. | E9: =W9 | F9: =AI9 | G9: =AU9 | H9: =BG9 | I9: =BS9 | J9: =BS9 | L9: ='03_Сеть'!L62 | M9: ='03_Сеть'!M62 | N9: ='03_Сеть'!N62 | O9: ='03_Сеть'!O62 | P9: ='03_Сеть'!P62 | Q9: ='03_Сеть'!Q62 | R9: ='03_Сеть'!R62 | S9: ='03_Сеть'!S62 | ... BY9: ='03_Сеть'!BY62
B11: БДР — начисления
B12: Паушальные взносы | C12: ₽ | D12: Без НДС | E12: =SUM(L12:W12) | F12: =SUM(X12:AI12) | G12: =SUM(AJ12:AU12) | H12: =SUM(AV12:BG12) | I12: =SUM(BH12:BS12) | J12: =SUM(L12:BS12) | L12: ='04_Доходы'!L14 | M12: ='04_Доходы'!M14 | N12: ='04_Доходы'!N14 | O12: ='04_Доходы'!O14 | P12: ='04_Доходы'!P14 | Q12: ='04_Доходы'!Q14 | R12: ='04_Доходы'!R14 | S12: ='04_Доходы'!S14 | ... BY12: ='04_Доходы'!BY14
B13: Роялти | C13: ₽ | D13: Без НДС | E13: =SUM(L13:W13) | F13: =SUM(X13:AI13) | G13: =SUM(AJ13:AU13) | H13: =SUM(AV13:BG13) | I13: =SUM(BH13:BS13) | J13: =SUM(L13:BS13) | L13: ='04_Доходы'!L103/(1+НДС) | M13: ='04_Доходы'!M103/(1+НДС) | N13: ='04_Доходы'!N103/(1+НДС) | O13: ='04_Доходы'!O103/(1+НДС) | P13: ='04_Доходы'!P103/(1+НДС) | Q13: ='04_Доходы'!Q103/(1+НДС) | R13: ='04_Доходы'!R103/(1+НДС) | S13: ='04_Доходы'!S103/(1+НДС) | ... BY13: ='04_Доходы'!BY103/(1+НДС)
B14: Мерч | C14: ₽ | D14: Без НДС | E14: =SUM(L14:W14) | F14: =SUM(X14:AI14) | G14: =SUM(AJ14:AU14) | H14: =SUM(AV14:BG14) | I14: =SUM(BH14:BS14) | J14: =SUM(L14:BS14) | L14: ='04_Доходы'!L132 | M14: ='04_Доходы'!M132 | N14: ='04_Доходы'!N132 | O14: ='04_Доходы'!O132 | P14: ='04_Доходы'!P132 | Q14: ='04_Доходы'!Q132 | R14: ='04_Доходы'!R132 | S14: ='04_Доходы'!S132 | ... BY14: ='04_Доходы'!BY132
B15: Лагеря | C15: ₽ | D15: Блок отключён переключателем на листе вводных | E15: =SUM(L15:W15) | F15: =SUM(X15:AI15) | G15: =SUM(AJ15:AU15) | H15: =SUM(AV15:BG15) | I15: =SUM(BH15:BS15) | J15: =SUM(L15:BS15) | L15: =0 | M15: =0 | N15: =0 | O15: =0 | P15: =0 | Q15: =0 | R15: =0 | S15: =0 | ... BY15: =0
B16: Выручка — всего | C16: ₽ | E16: =SUM(L16:W16) | F16: =SUM(X16:AI16) | G16: =SUM(AJ16:AU16) | H16: =SUM(AV16:BG16) | I16: =SUM(BH16:BS16) | J16: =SUM(L16:BS16) | L16: =SUM(L12:L15) | M16: =SUM(M12:M15) | N16: =SUM(N12:N15) | O16: =SUM(O12:O15) | P16: =SUM(P12:P15) | Q16: =SUM(Q12:Q15) | R16: =SUM(R12:R15) | S16: =SUM(S12:S15) | ... BY16: =SUM(BY12:BY15)
B17: COGS мерча | C17: ₽ | E17: =SUM(L17:W17) | F17: =SUM(X17:AI17) | G17: =SUM(AJ17:AU17) | H17: =SUM(AV17:BG17) | I17: =SUM(BH17:BS17) | J17: =SUM(L17:BS17) | L17: ='04_Доходы'!L133 | M17: ='04_Доходы'!M133 | N17: ='04_Доходы'!N133 | O17: ='04_Доходы'!O133 | P17: ='04_Доходы'!P133 | Q17: ='04_Доходы'!Q133 | R17: ='04_Доходы'!R133 | S17: ='04_Доходы'!S133 | ... BY17: ='04_Доходы'!BY133
B18: Логистика, возвраты, брак | C18: ₽ | E18: =SUM(L18:W18) | F18: =SUM(X18:AI18) | G18: =SUM(AJ18:AU18) | H18: =SUM(AV18:BG18) | I18: =SUM(BH18:BS18) | J18: =SUM(L18:BS18) | L18: ='04_Доходы'!L134 | M18: ='04_Доходы'!M134 | N18: ='04_Доходы'!N134 | O18: ='04_Доходы'!O134 | P18: ='04_Доходы'!P134 | Q18: ='04_Доходы'!Q134 | R18: ='04_Доходы'!R134 | S18: ='04_Доходы'!S134 | ... BY18: ='04_Доходы'!BY134
B19: Клубу: доля прибыли мерча | C19: ₽ | E19: =SUM(L19:W19) | F19: =SUM(X19:AI19) | G19: =SUM(AJ19:AU19) | H19: =SUM(AV19:BG19) | I19: =SUM(BH19:BS19) | J19: =SUM(L19:BS19) | L19: ='05_Расходы'!L49 | M19: ='05_Расходы'!M49 | N19: ='05_Расходы'!N49 | O19: ='05_Расходы'!O49 | P19: ='05_Расходы'!P49 | Q19: ='05_Расходы'!Q49 | R19: ='05_Расходы'!R49 | S19: ='05_Расходы'!S49 | ... BY19: ='05_Расходы'!BY49
B20: Клубу: доля паушальных | C20: ₽ | E20: =SUM(L20:W20) | F20: =SUM(X20:AI20) | G20: =SUM(AJ20:AU20) | H20: =SUM(AV20:BG20) | I20: =SUM(BH20:BS20) | J20: =SUM(L20:BS20) | L20: ='05_Расходы'!L47 | M20: ='05_Расходы'!M47 | N20: ='05_Расходы'!N47 | O20: ='05_Расходы'!O47 | P20: ='05_Расходы'!P47 | Q20: ='05_Расходы'!Q47 | R20: ='05_Расходы'!R47 | S20: ='05_Расходы'!S47 | ... BY20: ='05_Расходы'!BY47
B21: Клубу: доля роялти | C21: ₽ | E21: =SUM(L21:W21) | F21: =SUM(X21:AI21) | G21: =SUM(AJ21:AU21) | H21: =SUM(AV21:BG21) | I21: =SUM(BH21:BS21) | J21: =SUM(L21:BS21) | L21: ='05_Расходы'!L48 | M21: ='05_Расходы'!M48 | N21: ='05_Расходы'!N48 | O21: ='05_Расходы'!O48 | P21: ='05_Расходы'!P48 | Q21: ='05_Расходы'!Q48 | R21: ='05_Расходы'!R48 | S21: ='05_Расходы'!S48 | ... BY21: ='05_Расходы'!BY48
B22: Прямые расходы — всего | C22: ₽ | E22: =SUM(L22:W22) | F22: =SUM(X22:AI22) | G22: =SUM(AJ22:AU22) | H22: =SUM(AV22:BG22) | I22: =SUM(BH22:BS22) | J22: =SUM(L22:BS22) | L22: =SUM(L17:L21) | M22: =SUM(M17:M21) | N22: =SUM(N17:N21) | O22: =SUM(O17:O21) | P22: =SUM(P17:P21) | Q22: =SUM(Q17:Q21) | R22: =SUM(R17:R21) | S22: =SUM(S17:S21) | ... BY22: =SUM(BY17:BY21)
B23: Валовая прибыль | C23: ₽ | E23: =SUM(L23:W23) | F23: =SUM(X23:AI23) | G23: =SUM(AJ23:AU23) | H23: =SUM(AV23:BG23) | I23: =SUM(BH23:BS23) | J23: =SUM(L23:BS23) | L23: =L16-L22 | M23: =M16-M22 | N23: =N16-N22 | O23: =O16-O22 | P23: =P16-P22 | Q23: =Q16-Q22 | R23: =R16-R22 | S23: =S16-S22 | ... BY23: =BY16-BY22
B24: ФОТ и кадровые расходы | C24: ₽ | E24: =SUM(L24:W24) | F24: =SUM(X24:AI24) | G24: =SUM(AJ24:AU24) | H24: =SUM(AV24:BG24) | I24: =SUM(BH24:BS24) | J24: =SUM(L24:BS24) | L24: ='05_Расходы'!L30 | M24: ='05_Расходы'!M30 | N24: ='05_Расходы'!N30 | O24: ='05_Расходы'!O30 | P24: ='05_Расходы'!P30 | Q24: ='05_Расходы'!Q30 | R24: ='05_Расходы'!R30 | S24: ='05_Расходы'!S30 | ... BY24: ='05_Расходы'!BY30
B25: ERP | C25: ₽ | E25: =SUM(L25:W25) | F25: =SUM(X25:AI25) | G25: =SUM(AJ25:AU25) | H25: =SUM(AV25:BG25) | I25: =SUM(BH25:BS25) | J25: =SUM(L25:BS25) | L25: ='05_Расходы'!L35 | M25: ='05_Расходы'!M35 | N25: ='05_Расходы'!N35 | O25: ='05_Расходы'!O35 | P25: ='05_Расходы'!P35 | Q25: ='05_Расходы'!Q35 | R25: ='05_Расходы'!R35 | S25: ='05_Расходы'!S35 | ... BY25: ='05_Расходы'!BY35
B26: Офис, аренда, уборка | C26: ₽ | E26: =SUM(L26:W26) | F26: =SUM(X26:AI26) | G26: =SUM(AJ26:AU26) | H26: =SUM(AV26:BG26) | I26: =SUM(BH26:BS26) | J26: =SUM(L26:BS26) | L26: ='05_Расходы'!L36 | M26: ='05_Расходы'!M36 | N26: ='05_Расходы'!N36 | O26: ='05_Расходы'!O36 | P26: ='05_Расходы'!P36 | Q26: ='05_Расходы'!Q36 | R26: ='05_Расходы'!R36 | S26: ='05_Расходы'!S36 | ... BY26: ='05_Расходы'!BY36
B27: Юристы, аудит, бухгалтерия | C27: ₽ | E27: =SUM(L27:W27) | F27: =SUM(X27:AI27) | G27: =SUM(AJ27:AU27) | H27: =SUM(AV27:BG27) | I27: =SUM(BH27:BS27) | J27: =SUM(L27:BS27) | L27: ='05_Расходы'!L37 | M27: ='05_Расходы'!M37 | N27: ='05_Расходы'!N37 | O27: ='05_Расходы'!O37 | P27: ='05_Расходы'!P37 | Q27: ='05_Расходы'!Q37 | R27: ='05_Расходы'!R37 | S27: ='05_Расходы'!S37 | ... BY27: ='05_Расходы'!BY37
B28: Прочие IT | C28: ₽ | E28: =SUM(L28:W28) | F28: =SUM(X28:AI28) | G28: =SUM(AJ28:AU28) | H28: =SUM(AV28:BG28) | I28: =SUM(BH28:BS28) | J28: =SUM(L28:BS28) | L28: ='05_Расходы'!L38 | M28: ='05_Расходы'!M38 | N28: ='05_Расходы'!N38 | O28: ='05_Расходы'!O38 | P28: ='05_Расходы'!P38 | Q28: ='05_Расходы'!Q38 | R28: ='05_Расходы'!R38 | S28: ='05_Расходы'!S38 | ... BY28: ='05_Расходы'!BY38
B29: SMM и подрядчики | C29: ₽ | E29: =SUM(L29:W29) | F29: =SUM(X29:AI29) | G29: =SUM(AJ29:AU29) | H29: =SUM(AV29:BG29) | I29: =SUM(BH29:BS29) | J29: =SUM(L29:BS29) | L29: ='05_Расходы'!L39 | M29: ='05_Расходы'!M39 | N29: ='05_Расходы'!N39 | O29: ='05_Расходы'!O39 | P29: ='05_Расходы'!P39 | Q29: ='05_Расходы'!Q39 | R29: ='05_Расходы'!R39 | S29: ='05_Расходы'!S39 | ... BY29: ='05_Расходы'!BY39
B30: Маркетинг привлечения | C30: ₽ | E30: =SUM(L30:W30) | F30: =SUM(X30:AI30) | G30: =SUM(AJ30:AU30) | H30: =SUM(AV30:BG30) | I30: =SUM(BH30:BS30) | J30: =SUM(L30:BS30) | L30: ='05_Расходы'!L43 | M30: ='05_Расходы'!M43 | N30: ='05_Расходы'!N43 | O30: ='05_Расходы'!O43 | P30: ='05_Расходы'!P43 | Q30: ='05_Расходы'!Q43 | R30: ='05_Расходы'!R43 | S30: ='05_Расходы'!S43 | ... BY30: ='05_Расходы'!BY43
B31: OPEX — прочие (без ФОТ) | C31: ₽ | D31: ERP, офис, юристы, IT, SMM, маркетинг привлечения | E31: =SUM(L31:W31) | F31: =SUM(X31:AI31) | G31: =SUM(AJ31:AU31) | H31: =SUM(AV31:BG31) | I31: =SUM(BH31:BS31) | J31: =SUM(L31:BS31) | L31: =SUM(L25:L30) | M31: =SUM(M25:M30) | N31: =SUM(N25:N30) | O31: =SUM(O25:O30) | P31: =SUM(P25:P30) | Q31: =SUM(Q25:Q30) | R31: =SUM(R25:R30) | S31: =SUM(S25:S30) | ... BY31: =SUM(BY25:BY30)
B32: OPEX — всего | C32: ₽ | D32: ФОТ плюс всё остальное | E32: =SUM(L32:W32) | F32: =SUM(X32:AI32) | G32: =SUM(AJ32:AU32) | H32: =SUM(AV32:BG32) | I32: =SUM(BH32:BS32) | J32: =SUM(L32:BS32) | L32: =L24+L31 | M32: =M24+M31 | N32: =N24+N31 | O32: =O24+O31 | P32: =P24+P31 | Q32: =Q24+Q31 | R32: =R24+R31 | S32: =S24+S31 | ... BY32: =BY24+BY31
B33: EBITDA | C33: ₽ | E33: =SUM(L33:W33) | F33: =SUM(X33:AI33) | G33: =SUM(AJ33:AU33) | H33: =SUM(AV33:BG33) | I33: =SUM(BH33:BS33) | J33: =SUM(L33:BS33) | L33: =L23-L32 | M33: =M23-M32 | N33: =N23-N32 | O33: =O23-O32 | P33: =P23-P32 | Q33: =Q23-Q32 | R33: =R23-R32 | S33: =S23-S32 | ... BY33: =BY23-BY32
B34: EBITDA, % выручки | C34: % | D34: В колонках лет — EBITDA года, делённая на выручку года, а не среднее из помесячных долей | E34: =IF(SUM(L16:W16)=0,0,SUM(L33:W33)/SUM(L16:W16)) | F34: =IF(SUM(X16:AI16)=0,0,SUM(X33:AI33)/SUM(X16:AI16)) | G34: =IF(SUM(AJ16:AU16)=0,0,SUM(AJ33:AU33)/SUM(AJ16:AU16)) | H34: =IF(SUM(AV16:BG16)=0,0,SUM(AV33:BG33)/SUM(AV16:BG16)) | I34: =IF(SUM(BH16:BS16)=0,0,SUM(BH33:BS33)/SUM(BH16:BS16)) | J34: =IF(SUM(L16:BS16)=0,0,SUM(L33:BS33)/SUM(L16:BS16)) | L34: =IF(L16=0,0,L33/L16) | M34: =IF(M16=0,0,M33/M16) | N34: =IF(N16=0,0,N33/N16) | O34: =IF(O16=0,0,O33/O16) | P34: =IF(P16=0,0,P33/P16) | Q34: =IF(Q16=0,0,Q33/Q16) | R34: =IF(R16=0,0,R33/R16) | S34: =IF(S16=0,0,S33/S16) | ... BY34: =IF(BY16=0,0,BY33/BY16)
B35: УСН / минимальный налог | C35: ₽ | E35: =SUM(L35:W35) | F35: =SUM(X35:AI35) | G35: =SUM(AJ35:AU35) | H35: =SUM(AV35:BG35) | I35: =SUM(BH35:BS35) | J35: =SUM(L35:BS35) | L35: ='06_Деньги'!L24 | M35: ='06_Деньги'!M24 | N35: ='06_Деньги'!N24 | O35: ='06_Деньги'!O24 | P35: ='06_Деньги'!P24 | Q35: ='06_Деньги'!Q24 | R35: ='06_Деньги'!R24 | S35: ='06_Деньги'!S24 | ... BY35: ='06_Деньги'!BY24
B36: Прибыль после налога | C36: ₽ | E36: =SUM(L36:W36) | F36: =SUM(X36:AI36) | G36: =SUM(AJ36:AU36) | H36: =SUM(AV36:BG36) | I36: =SUM(BH36:BS36) | J36: =SUM(L36:BS36) | L36: =L33-L35 | M36: =M33-M35 | N36: =N33-N35 | O36: =O33-O35 | P36: =P33-P35 | Q36: =Q33-Q35 | R36: =R33-R35 | S36: =S33-S35 | ... BY36: =BY33-BY35
B38: БДДС — движение денег
B39: Остаток на начало | C39: ₽ | D39: В колонках лет — значение на конец года, в «Итого» — на конец пятого года. Это остаток, а не сумма. | E39: =W39 | F39: =AI39 | G39: =AU39 | H39: =BG39 | I39: =BS39 | J39: =BS39 | L39: =ДеньгиСтарт | M39: =L59 | N39: =M59 | O39: =N59 | P39: =O59 | Q39: =P59 | R39: =Q59 | S39: =R59 | T39: =S59 | ... BY39: =BX59
B40: Поступления: паушальные | C40: ₽ | D40: С НДС, в месяц продажи — она считается после оплаты | E40: =SUM(L40:W40) | F40: =SUM(X40:AI40) | G40: =SUM(AJ40:AU40) | H40: =SUM(AV40:BG40) | I40: =SUM(BH40:BS40) | J40: =SUM(L40:BS40) | L40: ='04_Доходы'!L13 | M40: ='04_Доходы'!M13 | N40: ='04_Доходы'!N13 | O40: ='04_Доходы'!O13 | P40: ='04_Доходы'!P13 | Q40: ='04_Доходы'!Q13 | R40: ='04_Доходы'!R13 | S40: ='04_Доходы'!S13 | ... BY40: ='04_Доходы'!BY13
B41: Поступления: роялти | C41: ₽ | D41: Половина в текущем месяце, половина в следующем | E41: =SUM(L41:W41) | F41: =SUM(X41:AI41) | G41: =SUM(AJ41:AU41) | H41: =SUM(AV41:BG41) | I41: =SUM(BH41:BS41) | J41: =SUM(L41:BS41) | L41: =ДоляПоступлТек*'04_Доходы'!$L103 | M41: =ДоляПоступлТек*'04_Доходы'!M103+(1-ДоляПоступлТек)*'04_Доходы'!L103 | N41: =ДоляПоступлТек*'04_Доходы'!N103+(1-ДоляПоступлТек)*'04_Доходы'!M103 | O41: =ДоляПоступлТек*'04_Доходы'!O103+(1-ДоляПоступлТек)*'04_Доходы'!N103 | P41: =ДоляПоступлТек*'04_Доходы'!P103+(1-ДоляПоступлТек)*'04_Доходы'!O103 | Q41: =ДоляПоступлТек*'04_Доходы'!Q103+(1-ДоляПоступлТек)*'04_Доходы'!P103 | R41: =ДоляПоступлТек*'04_Доходы'!R103+(1-ДоляПоступлТек)*'04_Доходы'!Q103 | S41: =ДоляПоступлТек*'04_Доходы'!S103+(1-ДоляПоступлТек)*'04_Доходы'!R103 | T41: =ДоляПоступлТек*'04_Доходы'!T103+(1-ДоляПоступлТек)*'04_Доходы'!S103 | ... BY41: =ДоляПоступлТек*'04_Доходы'!BY103+(1-ДоляПоступлТек)*'04_Доходы'!BX103
B42: Поступления: мерч | C42: ₽ | D42: С НДС | E42: =SUM(L42:W42) | F42: =SUM(X42:AI42) | G42: =SUM(AJ42:AU42) | H42: =SUM(AV42:BG42) | I42: =SUM(BH42:BS42) | J42: =SUM(L42:BS42) | L42: ='04_Доходы'!L131 | M42: ='04_Доходы'!M131 | N42: ='04_Доходы'!N131 | O42: ='04_Доходы'!O131 | P42: ='04_Доходы'!P131 | Q42: ='04_Доходы'!Q131 | R42: ='04_Доходы'!R131 | S42: ='04_Доходы'!S131 | ... BY42: ='04_Доходы'!BY131
B43: Поступления: лагеря | C43: ₽ | D43: Блок отключён | E43: =SUM(L43:W43) | F43: =SUM(X43:AI43) | G43: =SUM(AJ43:AU43) | H43: =SUM(AV43:BG43) | I43: =SUM(BH43:BS43) | J43: =SUM(L43:BS43) | L43: =0 | M43: =0 | N43: =0 | O43: =0 | P43: =0 | Q43: =0 | R43: =0 | S43: =0 | ... BY43: =0
B44: Поступления — всего | C44: ₽ | E44: =SUM(L44:W44) | F44: =SUM(X44:AI44) | G44: =SUM(AJ44:AU44) | H44: =SUM(AV44:BG44) | I44: =SUM(BH44:BS44) | J44: =SUM(L44:BS44) | L44: =SUM(L40:L43) | M44: =SUM(M40:M43) | N44: =SUM(N40:N43) | O44: =SUM(O40:O43) | P44: =SUM(P40:P43) | Q44: =SUM(Q40:Q43) | R44: =SUM(R40:R43) | S44: =SUM(S40:S43) | ... BY44: =SUM(BY40:BY43)
B45: Оплата: CAPEX | C45: ₽ | E45: =SUM(L45:W45) | F45: =SUM(X45:AI45) | G45: =SUM(AJ45:AU45) | H45: =SUM(AV45:BG45) | I45: =SUM(BH45:BS45) | J45: =SUM(L45:BS45) | L45: ='06_Деньги'!L23 | M45: ='06_Деньги'!M23 | N45: ='06_Деньги'!N23 | O45: ='06_Деньги'!O23 | P45: ='06_Деньги'!P23 | Q45: ='06_Деньги'!Q23 | R45: ='06_Деньги'!R23 | S45: ='06_Деньги'!S23 | ... BY45: ='06_Деньги'!BY23
B46: Оплата: логистика мерча | C46: ₽ | E46: =SUM(L46:W46) | F46: =SUM(X46:AI46) | G46: =SUM(AJ46:AU46) | H46: =SUM(AV46:BG46) | I46: =SUM(BH46:BS46) | J46: =SUM(L46:BS46) | L46: ='04_Доходы'!L134 | M46: ='04_Доходы'!M134 | N46: ='04_Доходы'!N134 | O46: ='04_Доходы'!O134 | P46: ='04_Доходы'!P134 | Q46: ='04_Доходы'!Q134 | R46: ='04_Доходы'!R134 | S46: ='04_Доходы'!S134 | ... BY46: ='04_Доходы'!BY134
B47: Оплата: поставщики и OPEX | C47: ₽ | D47: Кроме ФОТ: он платится сразу. Половина в текущем месяце, половина в следующем | E47: =SUM(L47:W47) | F47: =SUM(X47:AI47) | G47: =SUM(AJ47:AU47) | H47: =SUM(AV47:BG47) | I47: =SUM(BH47:BS47) | J47: =SUM(L47:BS47) | L47: =ДоляОплатыТек*('05_Расходы'!$L44-'05_Расходы'!$L30+'06_Деньги'!$L10) | M47: =ДоляОплатыТек*('05_Расходы'!M44-'05_Расходы'!M30+'06_Деньги'!M10)+(1-ДоляОплатыТек)*('05_Расходы'!L44-'05_Расходы'!L30+'06_Деньги'!L10) | N47: =ДоляОплатыТек*('05_Расходы'!N44-'05_Расходы'!N30+'06_Деньги'!N10)+(1-ДоляОплатыТек)*('05_Расходы'!M44-'05_Расходы'!M30+'06_Деньги'!M10) | O47: =ДоляОплатыТек*('05_Расходы'!O44-'05_Расходы'!O30+'06_Деньги'!O10)+(1-ДоляОплатыТек)*('05_Расходы'!N44-'05_Расходы'!N30+'06_Деньги'!N10) | P47: =ДоляОплатыТек*('05_Расходы'!P44-'05_Расходы'!P30+'06_Деньги'!P10)+(1-ДоляОплатыТек)*('05_Расходы'!O44-'05_Расходы'!O30+'06_Деньги'!O10) | Q47: =ДоляОплатыТек*('05_Расходы'!Q44-'05_Расходы'!Q30+'06_Деньги'!Q10)+(1-ДоляОплатыТек)*('05_Расходы'!P44-'05_Расходы'!P30+'06_Деньги'!P10) | R47: =ДоляОплатыТек*('05_Расходы'!R44-'05_Расходы'!R30+'06_Деньги'!R10)+(1-ДоляОплатыТек)*('05_Расходы'!Q44-'05_Расходы'!Q30+'06_Деньги'!Q10) | S47: =ДоляОплатыТек*('05_Расходы'!S44-'05_Расходы'!S30+'06_Деньги'!S10)+(1-ДоляОплатыТек)*('05_Расходы'!R44-'05_Расходы'!R30+'06_Деньги'!R10) | T47: =ДоляОплатыТек*('05_Расходы'!T44-'05_Расходы'!T30+'06_Деньги'!T10)+(1-ДоляОплатыТек)*('05_Расходы'!S44-'05_Расходы'!S30+'06_Деньги'!S10) | ... BY47: =ДоляОплатыТек*('05_Расходы'!BY44-'05_Расходы'!BY30+'06_Деньги'!BY10)+(1-ДоляОплатыТек)*('05_Расходы'!BX44-'05_Расходы'!BX30+'06_Деньги'!BX10)
B48: Оплата: ФОТ | C48: ₽ | D48: Зарплата платится в месяц начисления | E48: =SUM(L48:W48) | F48: =SUM(X48:AI48) | G48: =SUM(AJ48:AU48) | H48: =SUM(AV48:BG48) | I48: =SUM(BH48:BS48) | J48: =SUM(L48:BS48) | L48: ='05_Расходы'!L30 | M48: ='05_Расходы'!M30 | N48: ='05_Расходы'!N30 | O48: ='05_Расходы'!O30 | P48: ='05_Расходы'!P30 | Q48: ='05_Расходы'!Q30 | R48: ='05_Расходы'!R30 | S48: ='05_Расходы'!S30 | ... BY48: ='05_Расходы'!BY30
B49: Оплата: клубу | C49: ₽ | D49: Роялти клубу — с поступивших денег, остальное сразу | E49: =SUM(L49:W49) | F49: =SUM(X49:AI49) | G49: =SUM(AJ49:AU49) | H49: =SUM(AV49:BG49) | I49: =SUM(BH49:BS49) | J49: =SUM(L49:BS49) | L49: =IF(ЛагОплатыФК=0,'05_Расходы'!L47+'05_Расходы'!L49+L41/(1+НДС)*IF(L$5>=ДатаФКСтупень3,ДоляФКРоялти3,IF(L$5>=ДатаФКСтупень2,ДоляФКРоялти2,ДоляФКРоялти)),0) | M49: =IF(ЛагОплатыФК=0,'05_Расходы'!M47+'05_Расходы'!M49+M41/(1+НДС)*IF(M$5>=ДатаФКСтупень3,ДоляФКРоялти3,IF(M$5>=ДатаФКСтупень2,ДоляФКРоялти2,ДоляФКРоялти)),'05_Расходы'!L47+'05_Расходы'!L49+L41/(1+НДС)*IF(L$5>=ДатаФКСтупень3,ДоляФКРоялти3,IF(L$5>=ДатаФКСтупень2,ДоляФКРоялти2,ДоляФКРоялти))) | N49: =IF(ЛагОплатыФК=0,'05_Расходы'!N47+'05_Расходы'!N49+N41/(1+НДС)*IF(N$5>=ДатаФКСтупень3,ДоляФКРоялти3,IF(N$5>=ДатаФКСтупень2,ДоляФКРоялти2,ДоляФКРоялти)),'05_Расходы'!M47+'05_Расходы'!M49+M41/(1+НДС)*IF(M$5>=ДатаФКСтупень3,ДоляФКРоялти3,IF(M$5>=ДатаФКСтупень2,ДоляФКРоялти2,ДоляФКРоялти))) | O49: =IF(ЛагОплатыФК=0,'05_Расходы'!O47+'05_Расходы'!O49+O41/(1+НДС)*IF(O$5>=ДатаФКСтупень3,ДоляФКРоялти3,IF(O$5>=ДатаФКСтупень2,ДоляФКРоялти2,ДоляФКРоялти)),'05_Расходы'!N47+'05_Расходы'!N49+N41/(1+НДС)*IF(N$5>=ДатаФКСтупень3,ДоляФКРоялти3,IF(N$5>=ДатаФКСтупень2,ДоляФКРоялти2,ДоляФКРоялти))) | P49: =IF(ЛагОплатыФК=0,'05_Расходы'!P47+'05_Расходы'!P49+P41/(1+НДС)*IF(P$5>=ДатаФКСтупень3,ДоляФКРоялти3,IF(P$5>=ДатаФКСтупень2,ДоляФКРоялти2,ДоляФКРоялти)),'05_Расходы'!O47+'05_Расходы'!O49+O41/(1+НДС)*IF(O$5>=ДатаФКСтупень3,ДоляФКРоялти3,IF(O$5>=ДатаФКСтупень2,ДоляФКРоялти2,ДоляФКРоялти))) | Q49: =IF(ЛагОплатыФК=0,'05_Расходы'!Q47+'05_Расходы'!Q49+Q41/(1+НДС)*IF(Q$5>=ДатаФКСтупень3,ДоляФКРоялти3,IF(Q$5>=ДатаФКСтупень2,ДоляФКРоялти2,ДоляФКРоялти)),'05_Расходы'!P47+'05_Расходы'!P49+P41/(1+НДС)*IF(P$5>=ДатаФКСтупень3,ДоляФКРоялти3,IF(P$5>=ДатаФКСтупень2,ДоляФКРоялти2,ДоляФКРоялти))) | R49: =IF(ЛагОплатыФК=0,'05_Расходы'!R47+'05_Расходы'!R49+R41/(1+НДС)*IF(R$5>=ДатаФКСтупень3,ДоляФКРоялти3,IF(R$5>=ДатаФКСтупень2,ДоляФКРоялти2,ДоляФКРоялти)),'05_Расходы'!Q47+'05_Расходы'!Q49+Q41/(1+НДС)*IF(Q$5>=ДатаФКСтупень3,ДоляФКРоялти3,IF(Q$5>=ДатаФКСтупень2,ДоляФКРоялти2,ДоляФКРоялти))) | S49: =IF(ЛагОплатыФК=0,'05_Расходы'!S47+'05_Расходы'!S49+S41/(1+НДС)*IF(S$5>=ДатаФКСтупень3,ДоляФКРоялти3,IF(S$5>=ДатаФКСтупень2,ДоляФКРоялти2,ДоляФКРоялти)),'05_Расходы'!R47+'05_Расходы'!R49+R41/(1+НДС)*IF(R$5>=ДатаФКСтупень3,ДоляФКРоялти3,IF(R$5>=ДатаФКСтупень2,ДоляФКРоялти2,ДоляФКРоялти))) | T49: =IF(ЛагОплатыФК=0,'05_Расходы'!T47+'05_Расходы'!T49+T41/(1+НДС)*IF(T$5>=ДатаФКСтупень3,ДоляФКРоялти3,IF(T$5>=ДатаФКСтупень2,ДоляФКРоялти2,ДоляФКРоялти)),'05_Расходы'!S47+'05_Расходы'!S49+S41/(1+НДС)*IF(S$5>=ДатаФКСтупень3,ДоляФКРоялти3,IF(S$5>=ДатаФКСтупень2,ДоляФКРоялти2,ДоляФКРоялти))) | ... BY49: =IF(ЛагОплатыФК=0,'05_Расходы'!BY47+'05_Расходы'!BY49+BY41/(1+НДС)*IF(BY$5>=ДатаФКСтупень3,ДоляФКРоялти3,IF(BY$5>=ДатаФКСтупень2,ДоляФКРоялти2,ДоляФКРоялти)),'05_Расходы'!BX47+'05_Расходы'!BX49+BX41/(1+НДС)*IF(BX$5>=ДатаФКСтупень3,ДоляФКРоялти3,IF(BX$5>=ДатаФКСтупень2,ДоляФКРоялти2,ДоляФКРоялти)))
B50: Оплата: НДС | C50: ₽ | E50: =SUM(L50:W50) | F50: =SUM(X50:AI50) | G50: =SUM(AJ50:AU50) | H50: =SUM(AV50:BG50) | I50: =SUM(BH50:BS50) | J50: =SUM(L50:BS50) | L50: ='06_Деньги'!L25 | M50: ='06_Деньги'!M25 | N50: ='06_Деньги'!N25 | O50: ='06_Деньги'!O25 | P50: ='06_Деньги'!P25 | Q50: ='06_Деньги'!Q25 | R50: ='06_Деньги'!R25 | S50: ='06_Деньги'!S25 | ... BY50: ='06_Деньги'!BY25
B51: Оплата: УСН | C51: ₽ | E51: =SUM(L51:W51) | F51: =SUM(X51:AI51) | G51: =SUM(AJ51:AU51) | H51: =SUM(AV51:BG51) | I51: =SUM(BH51:BS51) | J51: =SUM(L51:BS51) | L51: ='06_Деньги'!L24 | M51: ='06_Деньги'!M24 | N51: ='06_Деньги'!N24 | O51: ='06_Деньги'!O24 | P51: ='06_Деньги'!P24 | Q51: ='06_Деньги'!Q24 | R51: ='06_Деньги'!R24 | S51: ='06_Деньги'!S24 | ... BY51: ='06_Деньги'!BY24
B52: Оплата: лагеря | C52: ₽ | D52: Блок отключён | E52: =SUM(L52:W52) | F52: =SUM(X52:AI52) | G52: =SUM(AJ52:AU52) | H52: =SUM(AV52:BG52) | I52: =SUM(BH52:BS52) | J52: =SUM(L52:BS52) | L52: =0 | M52: =0 | N52: =0 | O52: =0 | P52: =0 | Q52: =0 | R52: =0 | S52: =0 | ... BY52: =0
B53: Расходы до займа — всего | C53: ₽ | E53: =SUM(L53:W53) | F53: =SUM(X53:AI53) | G53: =SUM(AJ53:AU53) | H53: =SUM(AV53:BG53) | I53: =SUM(BH53:BS53) | J53: =SUM(L53:BS53) | L53: =SUM(L45:L52) | M53: =SUM(M45:M52) | N53: =SUM(N45:N52) | O53: =SUM(O45:O52) | P53: =SUM(P45:P52) | Q53: =SUM(Q45:Q52) | R53: =SUM(R45:R52) | S53: =SUM(S45:S52) | ... BY53: =SUM(BY45:BY52)
B54: Справочно: закупка на склад | C54: ₽ | D54: Уже входит в оплату поставщикам выше | E54: =SUM(L54:W54) | F54: =SUM(X54:AI54) | G54: =SUM(AJ54:AU54) | H54: =SUM(AV54:BG54) | I54: =SUM(BH54:BS54) | J54: =SUM(L54:BS54) | L54: ='06_Деньги'!L10 | M54: ='06_Деньги'!M10 | N54: ='06_Деньги'!N10 | O54: ='06_Деньги'!O10 | P54: ='06_Деньги'!P10 | Q54: ='06_Деньги'!Q10 | R54: ='06_Деньги'!R10 | S54: ='06_Деньги'!S10 | ... BY54: ='06_Деньги'!BY10
B55: Поток до возврата займа | C55: ₽ | E55: =SUM(L55:W55) | F55: =SUM(X55:AI55) | G55: =SUM(AJ55:AU55) | H55: =SUM(AV55:BG55) | I55: =SUM(BH55:BS55) | J55: =SUM(L55:BS55) | L55: =L44-L53 | M55: =M44-M53 | N55: =N44-N53 | O55: =O44-O53 | P55: =P44-P53 | Q55: =Q44-Q53 | R55: =R44-R53 | S55: =S44-S53 | ... BY55: =BY44-BY53
B56: Остаток до возврата займа | C56: ₽ | E56: =SUM(L56:W56) | F56: =SUM(X56:AI56) | G56: =SUM(AJ56:AU56) | H56: =SUM(AV56:BG56) | I56: =SUM(BH56:BS56) | J56: =SUM(L56:BS56) | L56: =L39+L55 | M56: =M39+M55 | N56: =N39+N55 | O56: =O39+O55 | P56: =P39+P55 | Q56: =Q39+Q55 | R56: =R39+R55 | S56: =S39+S55 | ... BY56: =BY39+BY55
B57: Возврат займа клубу | C57: ₽ | E57: =SUM(L57:W57) | F57: =SUM(X57:AI57) | G57: =SUM(AJ57:AU57) | H57: =SUM(AV57:BG57) | I57: =SUM(BH57:BS57) | J57: =SUM(L57:BS57) | L57: ='06_Деньги'!L18 | M57: ='06_Деньги'!M18 | N57: ='06_Деньги'!N18 | O57: ='06_Деньги'!O18 | P57: ='06_Деньги'!P18 | Q57: ='06_Деньги'!Q18 | R57: ='06_Деньги'!R18 | S57: ='06_Деньги'!S18 | ... BY57: ='06_Деньги'!BY18
B58: Чистый денежный поток | C58: ₽ | E58: =SUM(L58:W58) | F58: =SUM(X58:AI58) | G58: =SUM(AJ58:AU58) | H58: =SUM(AV58:BG58) | I58: =SUM(BH58:BS58) | J58: =SUM(L58:BS58) | L58: =L55-L57 | M58: =M55-M57 | N58: =N55-N57 | O58: =O55-O57 | P58: =P55-P57 | Q58: =Q55-Q57 | R58: =R55-R57 | S58: =S55-S57 | ... BY58: =BY55-BY57
B59: Остаток на конец | C59: ₽ | D59: В колонках лет — значение на конец года, в «Итого» — на конец пятого года. Это остаток, а не сумма. | E59: =W59 | F59: =AI59 | G59: =AU59 | H59: =BG59 | I59: =BS59 | J59: =BS59 | L59: =L39+L58 | M59: =M39+M58 | N59: =N39+N58 | O59: =O39+O58 | P59: =P39+P58 | Q59: =Q39+Q58 | R59: =R39+R58 | S59: =S39+S58 | ... BY59: =BY39+BY58

Sheet 03_Сеть
B1: Сеть: продажи, школы и дети
B2: Расшифровка к «Результату». Считается слева направо: план продаж → открытия → когорты школ по месяцам жизни → дети.
B4: Показатель | C4: Ед. | D4: Как считается | E4: Год 1 | F4: Год 2 | G4: Год 3 | H4: Год 4 | I4: Год 5 | J4: Итого 5 лет | L4: М1 | M4: М2 | N4: М3 | O4: М4 | P4: М5 | Q4: М6 | R4: М7 | S4: М8 | T4: М9 | U4: М10 | V4: М11 | W4: М12 | X4: М13 | Y4: М14 | Z4: М15 | AA4: М16 | AB4: М17 | AC4: М18 | AD4: М19 | AE4: М20 | AF4: М21 | AG4: М22 | AH4: М23 | AI4: М24 | AJ4: М25 | AK4: М26 | AL4: М27 | AM4: М28 | AN4: М29 | AO4: М30 | AP4: М31 | AQ4: М32 | AR4: М33 | AS4: М34 | AT4: М35 | AU4: М36 | AV4: М37 | AW4: М38 | AX4: М39 | AY4: М40 | AZ4: М41 | BA4: М42 | BB4: М43 | BC4: М44 | BD4: М45 | BE4: М46 | BF4: М47 | BG4: М48 | BH4: М49 | BI4: М50 | BJ4: М51 | BK4: М52 | BL4: М53 | BM4: М54 | BN4: М55 | BO4: М56 | BP4: М57 | BQ4: М58 | BR4: М59 | BS4: М60 | BT4: тех. 1 | BU4: тех. 2 | BV4: тех. 3 | BW4: тех. 4 | BX4: тех. 5 | BY4: тех. 6
E5: =TEXT(MONTH(DATE(YEAR(СтартМодели),MONTH(СтартМодели)+0,1)),"00")&"."&YEAR(DATE(YEAR(СтартМодели),MONTH(СтартМодели)+0,1))&" – "&TEXT(MONTH(DATE(YEAR(СтартМодели),MONTH(СтартМодели)+11,1)),"00")&"."&YEAR(DATE(YEAR(СтартМодели),MONTH(СтартМодели)+11,1)) | F5: =TEXT(MONTH(DATE(YEAR(СтартМодели),MONTH(СтартМодели)+12,1)),"00")&"."&YEAR(DATE(YEAR(СтартМодели),MONTH(СтартМодели)+12,1))&" – "&TEXT(MONTH(DATE(YEAR(СтартМодели),MONTH(СтартМодели)+23,1)),"00")&"."&YEAR(DATE(YEAR(СтартМодели),MONTH(СтартМодели)+23,1)) | G5: =TEXT(MONTH(DATE(YEAR(СтартМодели),MONTH(СтартМодели)+24,1)),"00")&"."&YEAR(DATE(YEAR(СтартМодели),MONTH(СтартМодели)+24,1))&" – "&TEXT(MONTH(DATE(YEAR(СтартМодели),MONTH(СтартМодели)+35,1)),"00")&"."&YEAR(DATE(YEAR(СтартМодели),MONTH(СтартМодели)+35,1)) | H5: =TEXT(MONTH(DATE(YEAR(СтартМодели),MONTH(СтартМодели)+36,1)),"00")&"."&YEAR(DATE(YEAR(СтартМодели),MONTH(СтартМодели)+36,1))&" – "&TEXT(MONTH(DATE(YEAR(СтартМодели),MONTH(СтартМодели)+47,1)),"00")&"."&YEAR(DATE(YEAR(СтартМодели),MONTH(СтартМодели)+47,1)) | I5: =TEXT(MONTH(DATE(YEAR(СтартМодели),MONTH(СтартМодели)+48,1)),"00")&"."&YEAR(DATE(YEAR(СтартМодели),MONTH(СтартМодели)+48,1))&" – "&TEXT(MONTH(DATE(YEAR(СтартМодели),MONTH(СтартМодели)+59,1)),"00")&"."&YEAR(DATE(YEAR(СтартМодели),MONTH(СтартМодели)+59,1)) | J5: =TEXT(MONTH(DATE(YEAR(СтартМодели),MONTH(СтартМодели)+0,1)),"00")&"."&YEAR(DATE(YEAR(СтартМодели),MONTH(СтартМодели)+0,1))&" – "&TEXT(MONTH(DATE(YEAR(СтартМодели),MONTH(СтартМодели)+59,1)),"00")&"."&YEAR(DATE(YEAR(СтартМодели),MONTH(СтартМодели)+59,1)) | L5: =DATE(YEAR(СтартМодели),MONTH(СтартМодели)+1-1,1) | M5: =DATE(YEAR(СтартМодели),MONTH(СтартМодели)+2-1,1) | N5: =DATE(YEAR(СтартМодели),MONTH(СтартМодели)+3-1,1) | O5: =DATE(YEAR(СтартМодели),MONTH(СтартМодели)+4-1,1) | P5: =DATE(YEAR(СтартМодели),MONTH(СтартМодели)+5-1,1) | Q5: =DATE(YEAR(СтартМодели),MONTH(СтартМодели)+6-1,1) | R5: =DATE(YEAR(СтартМодели),MONTH(СтартМодели)+7-1,1) | S5: =DATE(YEAR(СтартМодели),MONTH(СтартМодели)+8-1,1) | T5: =DATE(YEAR(СтартМодели),MONTH(СтартМодели)+9-1,1) | U5: =DATE(YEAR(СтартМодели),MONTH(СтартМодели)+10-1,1) | V5: =DATE(YEAR(СтартМодели),MONTH(СтартМодели)+11-1,1) | W5: =DATE(YEAR(СтартМодели),MONTH(СтартМодели)+12-1,1) | X5: =DATE(YEAR(СтартМодели),MONTH(СтартМодели)+13-1,1) | Y5: =DATE(YEAR(СтартМодели),MONTH(СтартМодели)+14-1,1) | Z5: =DATE(YEAR(СтартМодели),MONTH(СтартМодели)+15-1,1) | AA5: =DATE(YEAR(СтартМодели),MONTH(СтартМодели)+16-1,1) | AB5: =DATE(YEAR(СтартМодели),MONTH(СтартМодели)+17-1,1) | AC5: =DATE(YEAR(СтартМодели),MONTH(СтартМодели)+18-1,1) | AD5: =DATE(YEAR(СтартМодели),MONTH(СтартМодели)+19-1,1) | AE5: =DATE(YEAR(СтартМодели),MONTH(СтартМодели)+20-1,1) | AF5: =DATE(YEAR(СтартМодели),MONTH(СтартМодели)+21-1,1) | AG5: =DATE(YEAR(СтартМодели),MONTH(СтартМодели)+22-1,1) | AH5: =DATE(YEAR(СтартМодели),MONTH(СтартМодели)+23-1,1) | AI5: =DATE(YEAR(СтартМодели),MONTH(СтартМодели)+24-1,1) | AJ5: =DATE(YEAR(СтартМодели),MONTH(СтартМодели)+25-1,1) | AK5: =DATE(YEAR(СтартМодели),MONTH(СтартМодели)+26-1,1) | AL5: =DATE(YEAR(СтартМодели),MONTH(СтартМодели)+27-1,1) | AM5: =DATE(YEAR(СтартМодели),MONTH(СтартМодели)+28-1,1) | AN5: =DATE(YEAR(СтартМодели),MONTH(СтартМодели)+29-1,1) | AO5: =DATE(YEAR(СтартМодели),MONTH(СтартМодели)+30-1,1) | AP5: =DATE(YEAR(СтартМодели),MONTH(СтартМодели)+31-1,1) | AQ5: =DATE(YEAR(СтартМодели),MONTH(СтартМодели)+32-1,1) | AR5: =DATE(YEAR(СтартМодели),MONTH(СтартМодели)+33-1,1) | AS5: =DATE(YEAR(СтартМодели),MONTH(СтартМодели)+34-1,1) | AT5: =DATE(YEAR(СтартМодели),MONTH(СтартМодели)+35-1,1) | AU5: =DATE(YEAR(СтартМодели),MONTH(СтартМодели)+36-1,1) | AV5: =DATE(YEAR(СтартМодели),MONTH(СтартМодели)+37-1,1) | AW5: =DATE(YEAR(СтартМодели),MONTH(СтартМодели)+38-1,1) | AX5: =DATE(YEAR(СтартМодели),MONTH(СтартМодели)+39-1,1) | AY5: =DATE(YEAR(СтартМодели),MONTH(СтартМодели)+40-1,1) | AZ5: =DATE(YEAR(СтартМодели),MONTH(СтартМодели)+41-1,1) | BA5: =DATE(YEAR(СтартМодели),MONTH(СтартМодели)+42-1,1) | BB5: =DATE(YEAR(СтартМодели),MONTH(СтартМодели)+43-1,1) | BC5: =DATE(YEAR(СтартМодели),MONTH(СтартМодели)+44-1,1) | BD5: =DATE(YEAR(СтартМодели),MONTH(СтартМодели)+45-1,1) | BE5: =DATE(YEAR(СтартМодели),MONTH(СтартМодели)+46-1,1) | BF5: =DATE(YEAR(СтартМодели),MONTH(СтартМодели)+47-1,1) | BG5: =DATE(YEAR(СтартМодели),MONTH(СтартМодели)+48-1,1) | BH5: =DATE(YEAR(СтартМодели),MONTH(СтартМодели)+49-1,1) | BI5: =DATE(YEAR(СтартМодели),MONTH(СтартМодели)+50-1,1) | BJ5: =DATE(YEAR(СтартМодели),MONTH(СтартМодели)+51-1,1) | BK5: =DATE(YEAR(СтартМодели),MONTH(СтартМодели)+52-1,1) | BL5: =DATE(YEAR(СтартМодели),MONTH(СтартМодели)+53-1,1) | BM5: =DATE(YEAR(СтартМодели),MONTH(СтартМодели)+54-1,1) | BN5: =DATE(YEAR(СтартМодели),MONTH(СтартМодели)+55-1,1) | BO5: =DATE(YEAR(СтартМодели),MONTH(СтартМодели)+56-1,1) | BP5: =DATE(YEAR(СтартМодели),MONTH(СтартМодели)+57-1,1) | BQ5: =DATE(YEAR(СтартМодели),MONTH(СтартМодели)+58-1,1) | BR5: =DATE(YEAR(СтартМодели),MONTH(СтартМодели)+59-1,1) | BS5: =DATE(YEAR(СтартМодели),MONTH(СтартМодели)+60-1,1) | BT5: =DATE(YEAR(СтартМодели),MONTH(СтартМодели)+61-1,1) | BU5: =DATE(YEAR(СтартМодели),MONTH(СтартМодели)+62-1,1) | BV5: =DATE(YEAR(СтартМодели),MONTH(СтартМодели)+63-1,1) | BW5: =DATE(YEAR(СтартМодели),MONTH(СтартМодели)+64-1,1) | BX5: =DATE(YEAR(СтартМодели),MONTH(СтартМодели)+65-1,1) | BY5: =DATE(YEAR(СтартМодели),MONTH(СтартМодели)+66-1,1)
B6: Календарь
B7: Месяц | C7: дата | D7: Отсчёт от даты старта на листе вводных Внутренняя механика расчёта: годового итога у этой строки нет, смотрите итоговые строки блока ниже. | L7: =DATE(YEAR(СтартМодели),MONTH(СтартМодели)+1-1,1) | M7: =DATE(YEAR(СтартМодели),MONTH(СтартМодели)+2-1,1) | N7: =DATE(YEAR(СтартМодели),MONTH(СтартМодели)+3-1,1) | O7: =DATE(YEAR(СтартМодели),MONTH(СтартМодели)+4-1,1) | P7: =DATE(YEAR(СтартМодели),MONTH(СтартМодели)+5-1,1) | Q7: =DATE(YEAR(СтартМодели),MONTH(СтартМодели)+6-1,1) | R7: =DATE(YEAR(СтартМодели),MONTH(СтартМодели)+7-1,1) | S7: =DATE(YEAR(СтартМодели),MONTH(СтартМодели)+8-1,1) | T7: =DATE(YEAR(СтартМодели),MONTH(СтартМодели)+9-1,1) | U7: =DATE(YEAR(СтартМодели),MONTH(СтартМодели)+10-1,1) | V7: =DATE(YEAR(СтартМодели),MONTH(СтартМодели)+11-1,1) | W7: =DATE(YEAR(СтартМодели),MONTH(СтартМодели)+12-1,1) | X7: =DATE(YEAR(СтартМодели),MONTH(СтартМодели)+13-1,1) | Y7: =DATE(YEAR(СтартМодели),MONTH(СтартМодели)+14-1,1) | Z7: =DATE(YEAR(СтартМодели),MONTH(СтартМодели)+15-1,1) | AA7: =DATE(YEAR(СтартМодели),MONTH(СтартМодели)+16-1,1) | AB7: =DATE(YEAR(СтартМодели),MONTH(СтартМодели)+17-1,1) | AC7: =DATE(YEAR(СтартМодели),MONTH(СтартМодели)+18-1,1) | AD7: =DATE(YEAR(СтартМодели),MONTH(СтартМодели)+19-1,1) | AE7: =DATE(YEAR(СтартМодели),MONTH(СтартМодели)+20-1,1) | AF7: =DATE(YEAR(СтартМодели),MONTH(СтартМодели)+21-1,1) | AG7: =DATE(YEAR(СтартМодели),MONTH(СтартМодели)+22-1,1) | AH7: =DATE(YEAR(СтартМодели),MONTH(СтартМодели)+23-1,1) | AI7: =DATE(YEAR(СтартМодели),MONTH(СтартМодели)+24-1,1) | AJ7: =DATE(YEAR(СтартМодели),MONTH(СтартМодели)+25-1,1) | AK7: =DATE(YEAR(СтартМодели),MONTH(СтартМодели)+26-1,1) | AL7: =DATE(YEAR(СтартМодели),MONTH(СтартМодели)+27-1,1) | AM7: =DATE(YEAR(СтартМодели),MONTH(СтартМодели)+28-1,1) | AN7: =DATE(YEAR(СтартМодели),MONTH(СтартМодели)+29-1,1) | AO7: =DATE(YEAR(СтартМодели),MONTH(СтартМодели)+30-1,1) | AP7: =DATE(YEAR(СтартМодели),MONTH(СтартМодели)+31-1,1) | AQ7: =DATE(YEAR(СтартМодели),MONTH(СтартМодели)+32-1,1) | AR7: =DATE(YEAR(СтартМодели),MONTH(СтартМодели)+33-1,1) | AS7: =DATE(YEAR(СтартМодели),MONTH(СтартМодели)+34-1,1) | AT7: =DATE(YEAR(СтартМодели),MONTH(СтартМодели)+35-1,1) | AU7: =DATE(YEAR(СтартМодели),MONTH(СтартМодели)+36-1,1) | AV7: =DATE(YEAR(СтартМодели),MONTH(СтартМодели)+37-1,1) | AW7: =DATE(YEAR(СтартМодели),MONTH(СтартМодели)+38-1,1) | AX7: =DATE(YEAR(СтартМодели),MONTH(СтартМодели)+39-1,1) | AY7: =DATE(YEAR(СтартМодели),MONTH(СтартМодели)+40-1,1) | AZ7: =DATE(YEAR(СтартМодели),MONTH(СтартМодели)+41-1,1) | BA7: =DATE(YEAR(СтартМодели),MONTH(СтартМодели)+42-1,1) | BB7: =DATE(YEAR(СтартМодели),MONTH(СтартМодели)+43-1,1) | BC7: =DATE(YEAR(СтартМодели),MONTH(СтартМодели)+44-1,1) | BD7: =DATE(YEAR(СтартМодели),MONTH(СтартМодели)+45-1,1) | BE7: =DATE(YEAR(СтартМодели),MONTH(СтартМодели)+46-1,1) | BF7: =DATE(YEAR(СтартМодели),MONTH(СтартМодели)+47-1,1) | BG7: =DATE(YEAR(СтартМодели),MONTH(СтартМодели)+48-1,1) | BH7: =DATE(YEAR(СтартМодели),MONTH(СтартМодели)+49-1,1) | BI7: =DATE(YEAR(СтартМодели),MONTH(СтартМодели)+50-1,1) | BJ7: =DATE(YEAR(СтартМодели),MONTH(СтартМодели)+51-1,1) | BK7: =DATE(YEAR(СтартМодели),MONTH(СтартМодели)+52-1,1) | BL7: =DATE(YEAR(СтартМодели),MONTH(СтартМодели)+53-1,1) | BM7: =DATE(YEAR(СтартМодели),MONTH(СтартМодели)+54-1,1) | BN7: =DATE(YEAR(СтартМодели),MONTH(СтартМодели)+55-1,1) | BO7: =DATE(YEAR(СтартМодели),MONTH(СтартМодели)+56-1,1) | BP7: =DATE(YEAR(СтартМодели),MONTH(СтартМодели)+57-1,1) | BQ7: =DATE(YEAR(СтартМодели),MONTH(СтартМодели)+58-1,1) | BR7: =DATE(YEAR(СтартМодели),MONTH(СтартМодели)+59-1,1) | BS7: =DATE(YEAR(СтартМодели),MONTH(СтартМодели)+60-1,1) | BT7: =DATE(YEAR(СтартМодели),MONTH(СтартМодели)+61-1,1) | BU7: =DATE(YEAR(СтартМодели),MONTH(СтартМодели)+62-1,1) | BV7: =DATE(YEAR(СтартМодели),MONTH(СтартМодели)+63-1,1) | BW7: =DATE(YEAR(СтартМодели),MONTH(СтартМодели)+64-1,1) | BX7: =DATE(YEAR(СтартМодели),MONTH(СтартМодели)+65-1,1) | BY7: =DATE(YEAR(СтартМодели),MONTH(СтартМодели)+66-1,1)
B8: Год модели (сезон) | C8: № | D8: Сезон длится 12 месяцев от старта Внутренняя механика расчёта: годового итога у этой строки нет, смотрите итоговые строки блока ниже. | L8: =INT((1-1)/12)+1 | M8: =INT((2-1)/12)+1 | N8: =INT((3-1)/12)+1 | O8: =INT((4-1)/12)+1 | P8: =INT((5-1)/12)+1 | Q8: =INT((6-1)/12)+1 | R8: =INT((7-1)/12)+1 | S8: =INT((8-1)/12)+1 | T8: =INT((9-1)/12)+1 | U8: =INT((10-1)/12)+1 | V8: =INT((11-1)/12)+1 | W8: =INT((12-1)/12)+1 | X8: =INT((13-1)/12)+1 | Y8: =INT((14-1)/12)+1 | Z8: =INT((15-1)/12)+1 | AA8: =INT((16-1)/12)+1 | AB8: =INT((17-1)/12)+1 | AC8: =INT((18-1)/12)+1 | AD8: =INT((19-1)/12)+1 | AE8: =INT((20-1)/12)+1 | AF8: =INT((21-1)/12)+1 | AG8: =INT((22-1)/12)+1 | AH8: =INT((23-1)/12)+1 | AI8: =INT((24-1)/12)+1 | AJ8: =INT((25-1)/12)+1 | AK8: =INT((26-1)/12)+1 | AL8: =INT((27-1)/12)+1 | AM8: =INT((28-1)/12)+1 | AN8: =INT((29-1)/12)+1 | AO8: =INT((30-1)/12)+1 | AP8: =INT((31-1)/12)+1 | AQ8: =INT((32-1)/12)+1 | AR8: =INT((33-1)/12)+1 | AS8: =INT((34-1)/12)+1 | AT8: =INT((35-1)/12)+1 | AU8: =INT((36-1)/12)+1 | AV8: =INT((37-1)/12)+1 | AW8: =INT((38-1)/12)+1 | AX8: =INT((39-1)/12)+1 | AY8: =INT((40-1)/12)+1 | AZ8: =INT((41-1)/12)+1 | BA8: =INT((42-1)/12)+1 | BB8: =INT((43-1)/12)+1 | BC8: =INT((44-1)/12)+1 | BD8: =INT((45-1)/12)+1 | BE8: =INT((46-1)/12)+1 | BF8: =INT((47-1)/12)+1 | BG8: =INT((48-1)/12)+1 | BH8: =INT((49-1)/12)+1 | BI8: =INT((50-1)/12)+1 | BJ8: =INT((51-1)/12)+1 | BK8: =INT((52-1)/12)+1 | BL8: =INT((53-1)/12)+1 | BM8: =INT((54-1)/12)+1 | BN8: =INT((55-1)/12)+1 | BO8: =INT((56-1)/12)+1 | BP8: =INT((57-1)/12)+1 | BQ8: =INT((58-1)/12)+1 | BR8: =INT((59-1)/12)+1 | BS8: =INT((60-1)/12)+1 | BT8: =INT((61-1)/12)+1 | BU8: =INT((62-1)/12)+1 | BV8: =INT((63-1)/12)+1 | BW8: =INT((64-1)/12)+1 | BX8: =INT((65-1)/12)+1 | BY8: =INT((66-1)/12)+1
B9: Месяц сезона | C9: № | D9: 1 = первый месяц сезона от даты старта Внутренняя механика расчёта: годового итога у этой строки нет, смотрите итоговые строки блока ниже. | L9: =MOD(1-1,12)+1 | M9: =MOD(2-1,12)+1 | N9: =MOD(3-1,12)+1 | O9: =MOD(4-1,12)+1 | P9: =MOD(5-1,12)+1 | Q9: =MOD(6-1,12)+1 | R9: =MOD(7-1,12)+1 | S9: =MOD(8-1,12)+1 | T9: =MOD(9-1,12)+1 | U9: =MOD(10-1,12)+1 | V9: =MOD(11-1,12)+1 | W9: =MOD(12-1,12)+1 | X9: =MOD(13-1,12)+1 | Y9: =MOD(14-1,12)+1 | Z9: =MOD(15-1,12)+1 | AA9: =MOD(16-1,12)+1 | AB9: =MOD(17-1,12)+1 | AC9: =MOD(18-1,12)+1 | AD9: =MOD(19-1,12)+1 | AE9: =MOD(20-1,12)+1 | AF9: =MOD(21-1,12)+1 | AG9: =MOD(22-1,12)+1 | AH9: =MOD(23-1,12)+1 | AI9: =MOD(24-1,12)+1 | AJ9: =MOD(25-1,12)+1 | AK9: =MOD(26-1,12)+1 | AL9: =MOD(27-1,12)+1 | AM9: =MOD(28-1,12)+1 | AN9: =MOD(29-1,12)+1 | AO9: =MOD(30-1,12)+1 | AP9: =MOD(31-1,12)+1 | AQ9: =MOD(32-1,12)+1 | AR9: =MOD(33-1,12)+1 | AS9: =MOD(34-1,12)+1 | AT9: =MOD(35-1,12)+1 | AU9: =MOD(36-1,12)+1 | AV9: =MOD(37-1,12)+1 | AW9: =MOD(38-1,12)+1 | AX9: =MOD(39-1,12)+1 | AY9: =MOD(40-1,12)+1 | AZ9: =MOD(41-1,12)+1 | BA9: =MOD(42-1,12)+1 | BB9: =MOD(43-1,12)+1 | BC9: =MOD(44-1,12)+1 | BD9: =MOD(45-1,12)+1 | BE9: =MOD(46-1,12)+1 | BF9: =MOD(47-1,12)+1 | BG9: =MOD(48-1,12)+1 | BH9: =MOD(49-1,12)+1 | BI9: =MOD(50-1,12)+1 | BJ9: =MOD(51-1,12)+1 | BK9: =MOD(52-1,12)+1 | BL9: =MOD(53-1,12)+1 | BM9: =MOD(54-1,12)+1 | BN9: =MOD(55-1,12)+1 | BO9: =MOD(56-1,12)+1 | BP9: =MOD(57-1,12)+1 | BQ9: =MOD(58-1,12)+1 | BR9: =MOD(59-1,12)+1 | BS9: =MOD(60-1,12)+1 | BT9: =MOD(61-1,12)+1 | BU9: =MOD(62-1,12)+1 | BV9: =MOD(63-1,12)+1 | BW9: =MOD(64-1,12)+1 | BX9: =MOD(65-1,12)+1 | BY9: =MOD(66-1,12)+1
B10: Сезонность посещаемости | C10: % | D10: Доля детей, посещающих занятия в этом календарном месяце В колонках лет — среднее за год, в «Итого» — среднее за все 60 месяцев. | E10: =AVERAGE(L10:W10) | F10: =AVERAGE(X10:AI10) | G10: =AVERAGE(AJ10:AU10) | H10: =AVERAGE(AV10:BG10) | I10: =AVERAGE(BH10:BS10) | J10: =AVERAGE(L10:BS10) | L10: {=INDEX('01_Вводные'!$B$44:$M$44,1,MONTH(L7))} | M10: {=INDEX('01_Вводные'!$B$44:$M$44,1,MONTH(M7))} | N10: {=INDEX('01_Вводные'!$B$44:$M$44,1,MONTH(N7))} | O10: {=INDEX('01_Вводные'!$B$44:$M$44,1,MONTH(O7))} | P10: {=INDEX('01_Вводные'!$B$44:$M$44,1,MONTH(P7))} | Q10: {=INDEX('01_Вводные'!$B$44:$M$44,1,MONTH(Q7))} | R10: {=INDEX('01_Вводные'!$B$44:$M$44,1,MONTH(R7))} | S10: {=INDEX('01_Вводные'!$B$44:$M$44,1,MONTH(S7))} | ... BY10: {=INDEX('01_Вводные'!$B$44:$M$44,1,MONTH(BY7))}
B12: Продажи франшиз и открытия
B13: Продажи франшиз, план | C13: шт. | D13: Годовой план сезона, разложенный по календарным месяцам весами из таблицы планов. Первый месяц — без продаж. За горизонтом продаж нет: технические месяцы нужны только для склада | E13: =SUM(L13:W13) | F13: =SUM(X13:AI13) | G13: =SUM(AJ13:AU13) | H13: =SUM(AV13:BG13) | I13: =SUM(BH13:BS13) | J13: =SUM(L13:BS13) | L13: {=IF(OR(1>60,1=1),0,INDEX('01_Вводные'!$B$36:$B$40,L8)*INDEX('01_Вводные'!$C$36:$N$40,L8,MOD(MONTH(L7)-9,12)+1)/(SUM(INDEX('01_Вводные'!$C$36:$N$40,L8,0))-IF(1<=12,INDEX('01_Вводные'!$C$36:$N$40,L8,MOD(MONTH(СтартМодели)-9,12)+1),0)))} | M13: {=IF(OR(2>60,2=1),0,INDEX('01_Вводные'!$B$36:$B$40,M8)*INDEX('01_Вводные'!$C$36:$N$40,M8,MOD(MONTH(M7)-9,12)+1)/(SUM(INDEX('01_Вводные'!$C$36:$N$40,M8,0))-IF(2<=12,INDEX('01_Вводные'!$C$36:$N$40,M8,MOD(MONTH(СтартМодели)-9,12)+1),0)))} | N13: {=IF(OR(3>60,3=1),0,INDEX('01_Вводные'!$B$36:$B$40,N8)*INDEX('01_Вводные'!$C$36:$N$40,N8,MOD(MONTH(N7)-9,12)+1)/(SUM(INDEX('01_Вводные'!$C$36:$N$40,N8,0))-IF(3<=12,INDEX('01_Вводные'!$C$36:$N$40,N8,MOD(MONTH(СтартМодели)-9,12)+1),0)))} | O13: {=IF(OR(4>60,4=1),0,INDEX('01_Вводные'!$B$36:$B$40,O8)*INDEX('01_Вводные'!$C$36:$N$40,O8,MOD(MONTH(O7)-9,12)+1)/(SUM(INDEX('01_Вводные'!$C$36:$N$40,O8,0))-IF(4<=12,INDEX('01_Вводные'!$C$36:$N$40,O8,MOD(MONTH(СтартМодели)-9,12)+1),0)))} | P13: {=IF(OR(5>60,5=1),0,INDEX('01_Вводные'!$B$36:$B$40,P8)*INDEX('01_Вводные'!$C$36:$N$40,P8,MOD(MONTH(P7)-9,12)+1)/(SUM(INDEX('01_Вводные'!$C$36:$N$40,P8,0))-IF(5<=12,INDEX('01_Вводные'!$C$36:$N$40,P8,MOD(MONTH(СтартМодели)-9,12)+1),0)))} | Q13: {=IF(OR(6>60,6=1),0,INDEX('01_Вводные'!$B$36:$B$40,Q8)*INDEX('01_Вводные'!$C$36:$N$40,Q8,MOD(MONTH(Q7)-9,12)+1)/(SUM(INDEX('01_Вводные'!$C$36:$N$40,Q8,0))-IF(6<=12,INDEX('01_Вводные'!$C$36:$N$40,Q8,MOD(MONTH(СтартМодели)-9,12)+1),0)))} | R13: {=IF(OR(7>60,7=1),0,INDEX('01_Вводные'!$B$36:$B$40,R8)*INDEX('01_Вводные'!$C$36:$N$40,R8,MOD(MONTH(R7)-9,12)+1)/(SUM(INDEX('01_Вводные'!$C$36:$N$40,R8,0))-IF(7<=12,INDEX('01_Вводные'!$C$36:$N$40,R8,MOD(MONTH(СтартМодели)-9,12)+1),0)))} | S13: {=IF(OR(8>60,8=1),0,INDEX('01_Вводные'!$B$36:$B$40,S8)*INDEX('01_Вводные'!$C$36:$N$40,S8,MOD(MONTH(S7)-9,12)+1)/(SUM(INDEX('01_Вводные'!$C$36:$N$40,S8,0))-IF(8<=12,INDEX('01_Вводные'!$C$36:$N$40,S8,MOD(MONTH(СтартМодели)-9,12)+1),0)))} | T13: {=IF(OR(9>60,9=1),0,INDEX('01_Вводные'!$B$36:$B$40,T8)*INDEX('01_Вводные'!$C$36:$N$40,T8,MOD(MONTH(T7)-9,12)+1)/(SUM(INDEX('01_Вводные'!$C$36:$N$40,T8,0))-IF(9<=12,INDEX('01_Вводные'!$C$36:$N$40,T8,MOD(MONTH(СтартМодели)-9,12)+1),0)))} | U13: {=IF(OR(10>60,10=1),0,INDEX('01_Вводные'!$B$36:$B$40,U8)*INDEX('01_Вводные'!$C$36:$N$40,U8,MOD(MONTH(U7)-9,12)+1)/(SUM(INDEX('01_Вводные'!$C$36:$N$40,U8,0))-IF(10<=12,INDEX('01_Вводные'!$C$36:$N$40,U8,MOD(MONTH(СтартМодели)-9,12)+1),0)))} | V13: {=IF(OR(11>60,11=1),0,INDEX('01_Вводные'!$B$36:$B$40,V8)*INDEX('01_Вводные'!$C$36:$N$40,V8,MOD(MONTH(V7)-9,12)+1)/(SUM(INDEX('01_Вводные'!$C$36:$N$40,V8,0))-IF(11<=12,INDEX('01_Вводные'!$C$36:$N$40,V8,MOD(MONTH(СтартМодели)-9,12)+1),0)))} | W13: {=IF(OR(12>60,12=1),0,INDEX('01_Вводные'!$B$36:$B$40,W8)*INDEX('01_Вводные'!$C$36:$N$40,W8,MOD(MONTH(W7)-9,12)+1)/(SUM(INDEX('01_Вводные'!$C$36:$N$40,W8,0))-IF(12<=12,INDEX('01_Вводные'!$C$36:$N$40,W8,MOD(MONTH(СтартМодели)-9,12)+1),0)))} | X13: {=IF(OR(13>60,13=1),0,INDEX('01_Вводные'!$B$36:$B$40,X8)*INDEX('01_Вводные'!$C$36:$N$40,X8,MOD(MONTH(X7)-9,12)+1)/(SUM(INDEX('01_Вводные'!$C$36:$N$40,X8,0))-IF(13<=12,INDEX('01_Вводные'!$C$36:$N$40,X8,MOD(MONTH(СтартМодели)-9,12)+1),0)))} | Y13: {=IF(OR(14>60,14=1),0,INDEX('01_Вводные'!$B$36:$B$40,Y8)*INDEX('01_Вводные'!$C$36:$N$40,Y8,MOD(MONTH(Y7)-9,12)+1)/(SUM(INDEX('01_Вводные'!$C$36:$N$40,Y8,0))-IF(14<=12,INDEX('01_Вводные'!$C$36:$N$40,Y8,MOD(MONTH(СтартМодели)-9,12)+1),0)))} | Z13: {=IF(OR(15>60,15=1),0,INDEX('01_Вводные'!$B$36:$B$40,Z8)*INDEX('01_Вводные'!$C$36:$N$40,Z8,MOD(MONTH(Z7)-9,12)+1)/(SUM(INDEX('01_Вводные'!$C$36:$N$40,Z8,0))-IF(15<=12,INDEX('01_Вводные'!$C$36:$N$40,Z8,MOD(MONTH(СтартМодели)-9,12)+1),0)))} | AA13: {=IF(OR(16>60,16=1),0,INDEX('01_Вводные'!$B$36:$B$40,AA8)*INDEX('01_Вводные'!$C$36:$N$40,AA8,MOD(MONTH(AA7)-9,12)+1)/(SUM(INDEX('01_Вводные'!$C$36:$N$40,AA8,0))-IF(16<=12,INDEX('01_Вводные'!$C$36:$N$40,AA8,MOD(MONTH(СтартМодели)-9,12)+1),0)))} | AB13: {=IF(OR(17>60,17=1),0,INDEX('01_Вводные'!$B$36:$B$40,AB8)*INDEX('01_Вводные'!$C$36:$N$40,AB8,MOD(MONTH(AB7)-9,12)+1)/(SUM(INDEX('01_Вводные'!$C$36:$N$40,AB8,0))-IF(17<=12,INDEX('01_Вводные'!$C$36:$N$40,AB8,MOD(MONTH(СтартМодели)-9,12)+1),0)))} | AC13: {=IF(OR(18>60,18=1),0,INDEX('01_Вводные'!$B$36:$B$40,AC8)*INDEX('01_Вводные'!$C$36:$N$40,AC8,MOD(MONTH(AC7)-9,12)+1)/(SUM(INDEX('01_Вводные'!$C$36:$N$40,AC8,0))-IF(18<=12,INDEX('01_Вводные'!$C$36:$N$40,AC8,MOD(MONTH(СтартМодели)-9,12)+1),0)))} | AD13: {=IF(OR(19>60,19=1),0,INDEX('01_Вводные'!$B$36:$B$40,AD8)*INDEX('01_Вводные'!$C$36:$N$40,AD8,MOD(MONTH(AD7)-9,12)+1)/(SUM(INDEX('01_Вводные'!$C$36:$N$40,AD8,0))-IF(19<=12,INDEX('01_Вводные'!$C$36:$N$40,AD8,MOD(MONTH(СтартМодели)-9,12)+1),0)))} | AE13: {=IF(OR(20>60,20=1),0,INDEX('01_Вводные'!$B$36:$B$40,AE8)*INDEX('01_Вводные'!$C$36:$N$40,AE8,MOD(MONTH(AE7)-9,12)+1)/(SUM(INDEX('01_Вводные'!$C$36:$N$40,AE8,0))-IF(20<=12,INDEX('01_Вводные'!$C$36:$N$40,AE8,MOD(MONTH(СтартМодели)-9,12)+1),0)))} | AF13: {=IF(OR(21>60,21=1),0,INDEX('01_Вводные'!$B$36:$B$40,AF8)*INDEX('01_Вводные'!$C$36:$N$40,AF8,MOD(MONTH(AF7)-9,12)+1)/(SUM(INDEX('01_Вводные'!$C$36:$N$40,AF8,0))-IF(21<=12,INDEX('01_Вводные'!$C$36:$N$40,AF8,MOD(MONTH(СтартМодели)-9,12)+1),0)))} | AG13: {=IF(OR(22>60,22=1),0,INDEX('01_Вводные'!$B$36:$B$40,AG8)*INDEX('01_Вводные'!$C$36:$N$40,AG8,MOD(MONTH(AG7)-9,12)+1)/(SUM(INDEX('01_Вводные'!$C$36:$N$40,AG8,0))-IF(22<=12,INDEX('01_Вводные'!$C$36:$N$40,AG8,MOD(MONTH(СтартМодели)-9,12)+1),0)))} | AH13: {=IF(OR(23>60,23=1),0,INDEX('01_Вводные'!$B$36:$B$40,AH8)*INDEX('01_Вводные'!$C$36:$N$40,AH8,MOD(MONTH(AH7)-9,12)+1)/(SUM(INDEX('01_Вводные'!$C$36:$N$40,AH8,0))-IF(23<=12,INDEX('01_Вводные'!$C$36:$N$40,AH8,MOD(MONTH(СтартМодели)-9,12)+1),0)))} | AI13: {=IF(OR(24>60,24=1),0,INDEX('01_Вводные'!$B$36:$B$40,AI8)*INDEX('01_Вводные'!$C$36:$N$40,AI8,MOD(MONTH(AI7)-9,12)+1)/(SUM(INDEX('01_Вводные'!$C$36:$N$40,AI8,0))-IF(24<=12,INDEX('01_Вводные'!$C$36:$N$40,AI8,MOD(MONTH(СтартМодели)-9,12)+1),0)))} | AJ13: {=IF(OR(25>60,25=1),0,INDEX('01_Вводные'!$B$36:$B$40,AJ8)*INDEX('01_Вводные'!$C$36:$N$40,AJ8,MOD(MONTH(AJ7)-9,12)+1)/(SUM(INDEX('01_Вводные'!$C$36:$N$40,AJ8,0))-IF(25<=12,INDEX('01_Вводные'!$C$36:$N$40,AJ8,MOD(MONTH(СтартМодели)-9,12)+1),0)))} | AK13: {=IF(OR(26>60,26=1),0,INDEX('01_Вводные'!$B$36:$B$40,AK8)*INDEX('01_Вводные'!$C$36:$N$40,AK8,MOD(MONTH(AK7)-9,12)+1)/(SUM(INDEX('01_Вводные'!$C$36:$N$40,AK8,0))-IF(26<=12,INDEX('01_Вводные'!$C$36:$N$40,AK8,MOD(MONTH(СтартМодели)-9,12)+1),0)))} | AL13: {=IF(OR(27>60,27=1),0,INDEX('01_Вводные'!$B$36:$B$40,AL8)*INDEX('01_Вводные'!$C$36:$N$40,AL8,MOD(MONTH(AL7)-9,12)+1)/(SUM(INDEX('01_Вводные'!$C$36:$N$40,AL8,0))-IF(27<=12,INDEX('01_Вводные'!$C$36:$N$40,AL8,MOD(MONTH(СтартМодели)-9,12)+1),0)))} | AM13: {=IF(OR(28>60,28=1),0,INDEX('01_Вводные'!$B$36:$B$40,AM8)*INDEX('01_Вводные'!$C$36:$N$40,AM8,MOD(MONTH(AM7)-9,12)+1)/(SUM(INDEX('01_Вводные'!$C$36:$N$40,AM8,0))-IF(28<=12,INDEX('01_Вводные'!$C$36:$N$40,AM8,MOD(MONTH(СтартМодели)-9,12)+1),0)))} | AN13: {=IF(OR(29>60,29=1),0,INDEX('01_Вводные'!$B$36:$B$40,AN8)*INDEX('01_Вводные'!$C$36:$N$40,AN8,MOD(MONTH(AN7)-9,12)+1)/(SUM(INDEX('01_Вводные'!$C$36:$N$40,AN8,0))-IF(29<=12,INDEX('01_Вводные'!$C$36:$N$40,AN8,MOD(MONTH(СтартМодели)-9,12)+1),0)))} | AO13: {=IF(OR(30>60,30=1),0,INDEX('01_Вводные'!$B$36:$B$40,AO8)*INDEX('01_Вводные'!$C$36:$N$40,AO8,MOD(MONTH(AO7)-9,12)+1)/(SUM(INDEX('01_Вводные'!$C$36:$N$40,AO8,0))-IF(30<=12,INDEX('01_Вводные'!$C$36:$N$40,AO8,MOD(MONTH(СтартМодели)-9,12)+1),0)))} | AP13: {=IF(OR(31>60,31=1),0,INDEX('01_Вводные'!$B$36:$B$40,AP8)*INDEX('01_Вводные'!$C$36:$N$40,AP8,MOD(MONTH(AP7)-9,12)+1)/(SUM(INDEX('01_Вводные'!$C$36:$N$40,AP8,0))-IF(31<=12,INDEX('01_Вводные'!$C$36:$N$40,AP8,MOD(MONTH(СтартМодели)-9,12)+1),0)))} | AQ13: {=IF(OR(32>60,32=1),0,INDEX('01_Вводные'!$B$36:$B$40,AQ8)*INDEX('01_Вводные'!$C$36:$N$40,AQ8,MOD(MONTH(AQ7)-9,12)+1)/(SUM(INDEX('01_Вводные'!$C$36:$N$40,AQ8,0))-IF(32<=12,INDEX('01_Вводные'!$C$36:$N$40,AQ8,MOD(MONTH(СтартМодели)-9,12)+1),0)))} | AR13: {=IF(OR(33>60,33=1),0,INDEX('01_Вводные'!$B$36:$B$40,AR8)*INDEX('01_Вводные'!$C$36:$N$40,AR8,MOD(MONTH(AR7)-9,12)+1)/(SUM(INDEX('01_Вводные'!$C$36:$N$40,AR8,0))-IF(33<=12,INDEX('01_Вводные'!$C$36:$N$40,AR8,MOD(MONTH(СтартМодели)-9,12)+1),0)))} | AS13: {=IF(OR(34>60,34=1),0,INDEX('01_Вводные'!$B$36:$B$40,AS8)*INDEX('01_Вводные'!$C$36:$N$40,AS8,MOD(MONTH(AS7)-9,12)+1)/(SUM(INDEX('01_Вводные'!$C$36:$N$40,AS8,0))-IF(34<=12,INDEX('01_Вводные'!$C$36:$N$40,AS8,MOD(MONTH(СтартМодели)-9,12)+1),0)))} | AT13: {=IF(OR(35>60,35=1),0,INDEX('01_Вводные'!$B$36:$B$40,AT8)*INDEX('01_Вводные'!$C$36:$N$40,AT8,MOD(MONTH(AT7)-9,12)+1)/(SUM(INDEX('01_Вводные'!$C$36:$N$40,AT8,0))-IF(35<=12,INDEX('01_Вводные'!$C$36:$N$40,AT8,MOD(MONTH(СтартМодели)-9,12)+1),0)))} | AU13: {=IF(OR(36>60,36=1),0,INDEX('01_Вводные'!$B$36:$B$40,AU8)*INDEX('01_Вводные'!$C$36:$N$40,AU8,MOD(MONTH(AU7)-9,12)+1)/(SUM(INDEX('01_Вводные'!$C$36:$N$40,AU8,0))-IF(36<=12,INDEX('01_Вводные'!$C$36:$N$40,AU8,MOD(MONTH(СтартМодели)-9,12)+1),0)))} | AV13: {=IF(OR(37>60,37=1),0,INDEX('01_Вводные'!$B$36:$B$40,AV8)*INDEX('01_Вводные'!$C$36:$N$40,AV8,MOD(MONTH(AV7)-9,12)+1)/(SUM(INDEX('01_Вводные'!$C$36:$N$40,AV8,0))-IF(37<=12,INDEX('01_Вводные'!$C$36:$N$40,AV8,MOD(MONTH(СтартМодели)-9,12)+1),0)))} | AW13: {=IF(OR(38>60,38=1),0,INDEX('01_Вводные'!$B$36:$B$40,AW8)*INDEX('01_Вводные'!$C$36:$N$40,AW8,MOD(MONTH(AW7)-9,12)+1)/(SUM(INDEX('01_Вводные'!$C$36:$N$40,AW8,0))-IF(38<=12,INDEX('01_Вводные'!$C$36:$N$40,AW8,MOD(MONTH(СтартМодели)-9,12)+1),0)))} | AX13: {=IF(OR(39>60,39=1),0,INDEX('01_Вводные'!$B$36:$B$40,AX8)*INDEX('01_Вводные'!$C$36:$N$40,AX8,MOD(MONTH(AX7)-9,12)+1)/(SUM(INDEX('01_Вводные'!$C$36:$N$40,AX8,0))-IF(39<=12,INDEX('01_Вводные'!$C$36:$N$40,AX8,MOD(MONTH(СтартМодели)-9,12)+1),0)))} | AY13: {=IF(OR(40>60,40=1),0,INDEX('01_Вводные'!$B$36:$B$40,AY8)*INDEX('01_Вводные'!$C$36:$N$40,AY8,MOD(MONTH(AY7)-9,12)+1)/(SUM(INDEX('01_Вводные'!$C$36:$N$40,AY8,0))-IF(40<=12,INDEX('01_Вводные'!$C$36:$N$40,AY8,MOD(MONTH(СтартМодели)-9,12)+1),0)))} | AZ13: {=IF(OR(41>60,41=1),0,INDEX('01_Вводные'!$B$36:$B$40,AZ8)*INDEX('01_Вводные'!$C$36:$N$40,AZ8,MOD(MONTH(AZ7)-9,12)+1)/(SUM(INDEX('01_Вводные'!$C$36:$N$40,AZ8,0))-IF(41<=12,INDEX('01_Вводные'!$C$36:$N$40,AZ8,MOD(MONTH(СтартМодели)-9,12)+1),0)))} | BA13: {=IF(OR(42>60,42=1),0,INDEX('01_Вводные'!$B$36:$B$40,BA8)*INDEX('01_Вводные'!$C$36:$N$40,BA8,MOD(MONTH(BA7)-9,12)+1)/(SUM(INDEX('01_Вводные'!$C$36:$N$40,BA8,0))-IF(42<=12,INDEX('01_Вводные'!$C$36:$N$40,BA8,MOD(MONTH(СтартМодели)-9,12)+1),0)))} | BB13: {=IF(OR(43>60,43=1),0,INDEX('01_Вводные'!$B$36:$B$40,BB8)*INDEX('01_Вводные'!$C$36:$N$40,BB8,MOD(MONTH(BB7)-9,12)+1)/(SUM(INDEX('01_Вводные'!$C$36:$N$40,BB8,0))-IF(43<=12,INDEX('01_Вводные'!$C$36:$N$40,BB8,MOD(MONTH(СтартМодели)-9,12)+1),0)))} | BC13: {=IF(OR(44>60,44=1),0,INDEX('01_Вводные'!$B$36:$B$40,BC8)*INDEX('01_Вводные'!$C$36:$N$40,BC8,MOD(MONTH(BC7)-9,12)+1)/(SUM(INDEX('01_Вводные'!$C$36:$N$40,BC8,0))-IF(44<=12,INDEX('01_Вводные'!$C$36:$N$40,BC8,MOD(MONTH(СтартМодели)-9,12)+1),0)))} | BD13: {=IF(OR(45>60,45=1),0,INDEX('01_Вводные'!$B$36:$B$40,BD8)*INDEX('01_Вводные'!$C$36:$N$40,BD8,MOD(MONTH(BD7)-9,12)+1)/(SUM(INDEX('01_Вводные'!$C$36:$N$40,BD8,0))-IF(45<=12,INDEX('01_Вводные'!$C$36:$N$40,BD8,MOD(MONTH(СтартМодели)-9,12)+1),0)))} | BE13: {=IF(OR(46>60,46=1),0,INDEX('01_Вводные'!$B$36:$B$40,BE8)*INDEX('01_Вводные'!$C$36:$N$40,BE8,MOD(MONTH(BE7)-9,12)+1)/(SUM(INDEX('01_Вводные'!$C$36:$N$40,BE8,0))-IF(46<=12,INDEX('01_Вводные'!$C$36:$N$40,BE8,MOD(MONTH(СтартМодели)-9,12)+1),0)))} | BF13: {=IF(OR(47>60,47=1),0,INDEX('01_Вводные'!$B$36:$B$40,BF8)*INDEX('01_Вводные'!$C$36:$N$40,BF8,MOD(MONTH(BF7)-9,12)+1)/(SUM(INDEX('01_Вводные'!$C$36:$N$40,BF8,0))-IF(47<=12,INDEX('01_Вводные'!$C$36:$N$40,BF8,MOD(MONTH(СтартМодели)-9,12)+1),0)))} | BG13: {=IF(OR(48>60,48=1),0,INDEX('01_Вводные'!$B$36:$B$40,BG8)*INDEX('01_Вводные'!$C$36:$N$40,BG8,MOD(MONTH(BG7)-9,12)+1)/(SUM(INDEX('01_Вводные'!$C$36:$N$40,BG8,0))-IF(48<=12,INDEX('01_Вводные'!$C$36:$N$40,BG8,MOD(MONTH(СтартМодели)-9,12)+1),0)))} | BH13: {=IF(OR(49>60,49=1),0,INDEX('01_Вводные'!$B$36:$B$40,BH8)*INDEX('01_Вводные'!$C$36:$N$40,BH8,MOD(MONTH(BH7)-9,12)+1)/(SUM(INDEX('01_Вводные'!$C$36:$N$40,BH8,0))-IF(49<=12,INDEX('01_Вводные'!$C$36:$N$40,BH8,MOD(MONTH(СтартМодели)-9,12)+1),0)))} | BI13: {=IF(OR(50>60,50=1),0,INDEX('01_Вводные'!$B$36:$B$40,BI8)*INDEX('01_Вводные'!$C$36:$N$40,BI8,MOD(MONTH(BI7)-9,12)+1)/(SUM(INDEX('01_Вводные'!$C$36:$N$40,BI8,0))-IF(50<=12,INDEX('01_Вводные'!$C$36:$N$40,BI8,MOD(MONTH(СтартМодели)-9,12)+1),0)))} | BJ13: {=IF(OR(51>60,51=1),0,INDEX('01_Вводные'!$B$36:$B$40,BJ8)*INDEX('01_Вводные'!$C$36:$N$40,BJ8,MOD(MONTH(BJ7)-9,12)+1)/(SUM(INDEX('01_Вводные'!$C$36:$N$40,BJ8,0))-IF(51<=12,INDEX('01_Вводные'!$C$36:$N$40,BJ8,MOD(MONTH(СтартМодели)-9,12)+1),0)))} | BK13: {=IF(OR(52>60,52=1),0,INDEX('01_Вводные'!$B$36:$B$40,BK8)*INDEX('01_Вводные'!$C$36:$N$40,BK8,MOD(MONTH(BK7)-9,12)+1)/(SUM(INDEX('01_Вводные'!$C$36:$N$40,BK8,0))-IF(52<=12,INDEX('01_Вводные'!$C$36:$N$40,BK8,MOD(MONTH(СтартМодели)-9,12)+1),0)))} | BL13: {=IF(OR(53>60,53=1),0,INDEX('01_Вводные'!$B$36:$B$40,BL8)*INDEX('01_Вводные'!$C$36:$N$40,BL8,MOD(MONTH(BL7)-9,12)+1)/(SUM(INDEX('01_Вводные'!$C$36:$N$40,BL8,0))-IF(53<=12,INDEX('01_Вводные'!$C$36:$N$40,BL8,MOD(MONTH(СтартМодели)-9,12)+1),0)))} | BM13: {=IF(OR(54>60,54=1),0,INDEX('01_Вводные'!$B$36:$B$40,BM8)*INDEX('01_Вводные'!$C$36:$N$40,BM8,MOD(MONTH(BM7)-9,12)+1)/(SUM(INDEX('01_Вводные'!$C$36:$N$40,BM8,0))-IF(54<=12,INDEX('01_Вводные'!$C$36:$N$40,BM8,MOD(MONTH(СтартМодели)-9,12)+1),0)))} | BN13: {=IF(OR(55>60,55=1),0,INDEX('01_Вводные'!$B$36:$B$40,BN8)*INDEX('01_Вводные'!$C$36:$N$40,BN8,MOD(MONTH(BN7)-9,12)+1)/(SUM(INDEX('01_Вводные'!$C$36:$N$40,BN8,0))-IF(55<=12,INDEX('01_Вводные'!$C$36:$N$40,BN8,MOD(MONTH(СтартМодели)-9,12)+1),0)))} | BO13: {=IF(OR(56>60,56=1),0,INDEX('01_Вводные'!$B$36:$B$40,BO8)*INDEX('01_Вводные'!$C$36:$N$40,BO8,MOD(MONTH(BO7)-9,12)+1)/(SUM(INDEX('01_Вводные'!$C$36:$N$40,BO8,0))-IF(56<=12,INDEX('01_Вводные'!$C$36:$N$40,BO8,MOD(MONTH(СтартМодели)-9,12)+1),0)))} | BP13: {=IF(OR(57>60,57=1),0,INDEX('01_Вводные'!$B$36:$B$40,BP8)*INDEX('01_Вводные'!$C$36:$N$40,BP8,MOD(MONTH(BP7)-9,12)+1)/(SUM(INDEX('01_Вводные'!$C$36:$N$40,BP8,0))-IF(57<=12,INDEX('01_Вводные'!$C$36:$N$40,BP8,MOD(MONTH(СтартМодели)-9,12)+1),0)))} | BQ13: {=IF(OR(58>60,58=1),0,INDEX('01_Вводные'!$B$36:$B$40,BQ8)*INDEX('01_Вводные'!$C$36:$N$40,BQ8,MOD(MONTH(BQ7)-9,12)+1)/(SUM(INDEX('01_Вводные'!$C$36:$N$40,BQ8,0))-IF(58<=12,INDEX('01_Вводные'!$C$36:$N$40,BQ8,MOD(MONTH(СтартМодели)-9,12)+1),0)))} | BR13: {=IF(OR(59>60,59=1),0,INDEX('01_Вводные'!$B$36:$B$40,BR8)*INDEX('01_Вводные'!$C$36:$N$40,BR8,MOD(MONTH(BR7)-9,12)+1)/(SUM(INDEX('01_Вводные'!$C$36:$N$40,BR8,0))-IF(59<=12,INDEX('01_Вводные'!$C$36:$N$40,BR8,MOD(MONTH(СтартМодели)-9,12)+1),0)))} | BS13: {=IF(OR(60>60,60=1),0,INDEX('01_Вводные'!$B$36:$B$40,BS8)*INDEX('01_Вводные'!$C$36:$N$40,BS8,MOD(MONTH(BS7)-9,12)+1)/(SUM(INDEX('01_Вводные'!$C$36:$N$40,BS8,0))-IF(60<=12,INDEX('01_Вводные'!$C$36:$N$40,BS8,MOD(MONTH(СтартМодели)-9,12)+1),0)))} | BT13: {=IF(OR(61>60,61=1),0,INDEX('01_Вводные'!$B$36:$B$40,BT8)*INDEX('01_Вводные'!$C$36:$N$40,BT8,MOD(MONTH(BT7)-9,12)+1)/(SUM(INDEX('01_Вводные'!$C$36:$N$40,BT8,0))-IF(61<=12,INDEX('01_Вводные'!$C$36:$N$40,BT8,MOD(MONTH(СтартМодели)-9,12)+1),0)))} | BU13: {=IF(OR(62>60,62=1),0,INDEX('01_Вводные'!$B$36:$B$40,BU8)*INDEX('01_Вводные'!$C$36:$N$40,BU8,MOD(MONTH(BU7)-9,12)+1)/(SUM(INDEX('01_Вводные'!$C$36:$N$40,BU8,0))-IF(62<=12,INDEX('01_Вводные'!$C$36:$N$40,BU8,MOD(MONTH(СтартМодели)-9,12)+1),0)))} | BV13: {=IF(OR(63>60,63=1),0,INDEX('01_Вводные'!$B$36:$B$40,BV8)*INDEX('01_Вводные'!$C$36:$N$40,BV8,MOD(MONTH(BV7)-9,12)+1)/(SUM(INDEX('01_Вводные'!$C$36:$N$40,BV8,0))-IF(63<=12,INDEX('01_Вводные'!$C$36:$N$40,BV8,MOD(MONTH(СтартМодели)-9,12)+1),0)))} | BW13: {=IF(OR(64>60,64=1),0,INDEX('01_Вводные'!$B$36:$B$40,BW8)*INDEX('01_Вводные'!$C$36:$N$40,BW8,MOD(MONTH(BW7)-9,12)+1)/(SUM(INDEX('01_Вводные'!$C$36:$N$40,BW8,0))-IF(64<=12,INDEX('01_Вводные'!$C$36:$N$40,BW8,MOD(MONTH(СтартМодели)-9,12)+1),0)))} | BX13: {=IF(OR(65>60,65=1),0,INDEX('01_Вводные'!$B$36:$B$40,BX8)*INDEX('01_Вводные'!$C$36:$N$40,BX8,MOD(MONTH(BX7)-9,12)+1)/(SUM(INDEX('01_Вводные'!$C$36:$N$40,BX8,0))-IF(65<=12,INDEX('01_Вводные'!$C$36:$N$40,BX8,MOD(MONTH(СтартМодели)-9,12)+1),0)))} | BY13: {=IF(OR(66>60,66=1),0,INDEX('01_Вводные'!$B$36:$B$40,BY8)*INDEX('01_Вводные'!$C$36:$N$40,BY8,MOD(MONTH(BY7)-9,12)+1)/(SUM(INDEX('01_Вводные'!$C$36:$N$40,BY8,0))-IF(66<=12,INDEX('01_Вводные'!$C$36:$N$40,BY8,MOD(MONTH(СтартМодели)-9,12)+1),0)))}
B14: Открытия школ | C14: шт. | D14: Первая школа партнёра — через лаг открытия, следующие — ещё через лаг B311. Обе ветки с поправкой на конверсию продажи в открытие | E14: =SUM(L14:W14) | F14: =SUM(X14:AI14) | G14: =SUM(AJ14:AU14) | H14: =SUM(AV14:BG14) | I14: =SUM(BH14:BS14) | J14: =SUM(L14:BS14) | L14: {=IF(1-ЛагОткрытия<1,0,INDEX($L13:$BY13,1,1-ЛагОткрытия))*КонверсияОткрытия*MIN(1,ШколНаПродажу)+IF(1-(ЛагОткрытия+ЛагСледующихШкол)<1,0,INDEX($L13:$BY13,1,1-(ЛагОткрытия+ЛагСледующихШкол)))*КонверсияОткрытия*MAX(0,ШколНаПродажу-1)} | M14: {=IF(2-ЛагОткрытия<1,0,INDEX($L13:$BY13,1,2-ЛагОткрытия))*КонверсияОткрытия*MIN(1,ШколНаПродажу)+IF(2-(ЛагОткрытия+ЛагСледующихШкол)<1,0,INDEX($L13:$BY13,1,2-(ЛагОткрытия+ЛагСледующихШкол)))*КонверсияОткрытия*MAX(0,ШколНаПродажу-1)} | N14: {=IF(3-ЛагОткрытия<1,0,INDEX($L13:$BY13,1,3-ЛагОткрытия))*КонверсияОткрытия*MIN(1,ШколНаПродажу)+IF(3-(ЛагОткрытия+ЛагСледующихШкол)<1,0,INDEX($L13:$BY13,1,3-(ЛагОткрытия+ЛагСледующихШкол)))*КонверсияОткрытия*MAX(0,ШколНаПродажу-1)} | O14: {=IF(4-ЛагОткрытия<1,0,INDEX($L13:$BY13,1,4-ЛагОткрытия))*КонверсияОткрытия*MIN(1,ШколНаПродажу)+IF(4-(ЛагОткрытия+ЛагСледующихШкол)<1,0,INDEX($L13:$BY13,1,4-(ЛагОткрытия+ЛагСледующихШкол)))*КонверсияОткрытия*MAX(0,ШколНаПродажу-1)} | P14: {=IF(5-ЛагОткрытия<1,0,INDEX($L13:$BY13,1,5-ЛагОткрытия))*КонверсияОткрытия*MIN(1,ШколНаПродажу)+IF(5-(ЛагОткрытия+ЛагСледующихШкол)<1,0,INDEX($L13:$BY13,1,5-(ЛагОткрытия+ЛагСледующихШкол)))*КонверсияОткрытия*MAX(0,ШколНаПродажу-1)} | Q14: {=IF(6-ЛагОткрытия<1,0,INDEX($L13:$BY13,1,6-ЛагОткрытия))*КонверсияОткрытия*MIN(1,ШколНаПродажу)+IF(6-(ЛагОткрытия+ЛагСледующихШкол)<1,0,INDEX($L13:$BY13,1,6-(ЛагОткрытия+ЛагСледующихШкол)))*КонверсияОткрытия*MAX(0,ШколНаПродажу-1)} | R14: {=IF(7-ЛагОткрытия<1,0,INDEX($L13:$BY13,1,7-ЛагОткрытия))*КонверсияОткрытия*MIN(1,ШколНаПродажу)+IF(7-(ЛагОткрытия+ЛагСледующихШкол)<1,0,INDEX($L13:$BY13,1,7-(ЛагОткрытия+ЛагСледующихШкол)))*КонверсияОткрытия*MAX(0,ШколНаПродажу-1)} | S14: {=IF(8-ЛагОткрытия<1,0,INDEX($L13:$BY13,1,8-ЛагОткрытия))*КонверсияОткрытия*MIN(1,ШколНаПродажу)+IF(8-(ЛагОткрытия+ЛагСледующихШкол)<1,0,INDEX($L13:$BY13,1,8-(ЛагОткрытия+ЛагСледующихШкол)))*КонверсияОткрытия*MAX(0,ШколНаПродажу-1)} | T14: {=IF(9-ЛагОткрытия<1,0,INDEX($L13:$BY13,1,9-ЛагОткрытия))*КонверсияОткрытия*MIN(1,ШколНаПродажу)+IF(9-(ЛагОткрытия+ЛагСледующихШкол)<1,0,INDEX($L13:$BY13,1,9-(ЛагОткрытия+ЛагСледующихШкол)))*КонверсияОткрытия*MAX(0,ШколНаПродажу-1)} | U14: {=IF(10-ЛагОткрытия<1,0,INDEX($L13:$BY13,1,10-ЛагОткрытия))*КонверсияОткрытия*MIN(1,ШколНаПродажу)+IF(10-(ЛагОткрытия+ЛагСледующихШкол)<1,0,INDEX($L13:$BY13,1,10-(ЛагОткрытия+ЛагСледующихШкол)))*КонверсияОткрытия*MAX(0,ШколНаПродажу-1)} | V14: {=IF(11-ЛагОткрытия<1,0,INDEX($L13:$BY13,1,11-ЛагОткрытия))*КонверсияОткрытия*MIN(1,ШколНаПродажу)+IF(11-(ЛагОткрытия+ЛагСледующихШкол)<1,0,INDEX($L13:$BY13,1,11-(ЛагОткрытия+ЛагСледующихШкол)))*КонверсияОткрытия*MAX(0,ШколНаПродажу-1)} | W14: {=IF(12-ЛагОткрытия<1,0,INDEX($L13:$BY13,1,12-ЛагОткрытия))*КонверсияОткрытия*MIN(1,ШколНаПродажу)+IF(12-(ЛагОткрытия+ЛагСледующихШкол)<1,0,INDEX($L13:$BY13,1,12-(ЛагОткрытия+ЛагСледующихШкол)))*КонверсияОткрытия*MAX(0,ШколНаПродажу-1)} | X14: {=IF(13-ЛагОткрытия<1,0,INDEX($L13:$BY13,1,13-ЛагОткрытия))*КонверсияОткрытия*MIN(1,ШколНаПродажу)+IF(13-(ЛагОткрытия+ЛагСледующихШкол)<1,0,INDEX($L13:$BY13,1,13-(ЛагОткрытия+ЛагСледующихШкол)))*КонверсияОткрытия*MAX(0,ШколНаПродажу-1)} | Y14: {=IF(14-ЛагОткрытия<1,0,INDEX($L13:$BY13,1,14-ЛагОткрытия))*КонверсияОткрытия*MIN(1,ШколНаПродажу)+IF(14-(ЛагОткрытия+ЛагСледующихШкол)<1,0,INDEX($L13:$BY13,1,14-(ЛагОткрытия+ЛагСледующихШкол)))*КонверсияОткрытия*MAX(0,ШколНаПродажу-1)} | Z14: {=IF(15-ЛагОткрытия<1,0,INDEX($L13:$BY13,1,15-ЛагОткрытия))*КонверсияОткрытия*MIN(1,ШколНаПродажу)+IF(15-(ЛагОткрытия+ЛагСледующихШкол)<1,0,INDEX($L13:$BY13,1,15-(ЛагОткрытия+ЛагСледующихШкол)))*КонверсияОткрытия*MAX(0,ШколНаПродажу-1)} | AA14: {=IF(16-ЛагОткрытия<1,0,INDEX($L13:$BY13,1,16-ЛагОткрытия))*КонверсияОткрытия*MIN(1,ШколНаПродажу)+IF(16-(ЛагОткрытия+ЛагСледующихШкол)<1,0,INDEX($L13:$BY13,1,16-(ЛагОткрытия+ЛагСледующихШкол)))*КонверсияОткрытия*MAX(0,ШколНаПродажу-1)} | AB14: {=IF(17-ЛагОткрытия<1,0,INDEX($L13:$BY13,1,17-ЛагОткрытия))*КонверсияОткрытия*MIN(1,ШколНаПродажу)+IF(17-(ЛагОткрытия+ЛагСледующихШкол)<1,0,INDEX($L13:$BY13,1,17-(ЛагОткрытия+ЛагСледующихШкол)))*КонверсияОткрытия*MAX(0,ШколНаПродажу-1)} | AC14: {=IF(18-ЛагОткрытия<1,0,INDEX($L13:$BY13,1,18-ЛагОткрытия))*КонверсияОткрытия*MIN(1,ШколНаПродажу)+IF(18-(ЛагОткрытия+ЛагСледующихШкол)<1,0,INDEX($L13:$BY13,1,18-(ЛагОткрытия+ЛагСледующихШкол)))*КонверсияОткрытия*MAX(0,ШколНаПродажу-1)} | AD14: {=IF(19-ЛагОткрытия<1,0,INDEX($L13:$BY13,1,19-ЛагОткрытия))*КонверсияОткрытия*MIN(1,ШколНаПродажу)+IF(19-(ЛагОткрытия+ЛагСледующихШкол)<1,0,INDEX($L13:$BY13,1,19-(ЛагОткрытия+ЛагСледующихШкол)))*КонверсияОткрытия*MAX(0,ШколНаПродажу-1)} | AE14: {=IF(20-ЛагОткрытия<1,0,INDEX($L13:$BY13,1,20-ЛагОткрытия))*КонверсияОткрытия*MIN(1,ШколНаПродажу)+IF(20-(ЛагОткрытия+ЛагСледующихШкол)<1,0,INDEX($L13:$BY13,1,20-(ЛагОткрытия+ЛагСледующихШкол)))*КонверсияОткрытия*MAX(0,ШколНаПродажу-1)} | AF14: {=IF(21-ЛагОткрытия<1,0,INDEX($L13:$BY13,1,21-ЛагОткрытия))*КонверсияОткрытия*MIN(1,ШколНаПродажу)+IF(21-(ЛагОткрытия+ЛагСледующихШкол)<1,0,INDEX($L13:$BY13,1,21-(ЛагОткрытия+ЛагСледующихШкол)))*КонверсияОткрытия*MAX(0,ШколНаПродажу-1)} | AG14: {=IF(22-ЛагОткрытия<1,0,INDEX($L13:$BY13,1,22-ЛагОткрытия))*КонверсияОткрытия*MIN(1,ШколНаПродажу)+IF(22-(ЛагОткрытия+ЛагСледующихШкол)<1,0,INDEX($L13:$BY13,1,22-(ЛагОткрытия+ЛагСледующихШкол)))*КонверсияОткрытия*MAX(0,ШколНаПродажу-1)} | AH14: {=IF(23-ЛагОткрытия<1,0,INDEX($L13:$BY13,1,23-ЛагОткрытия))*КонверсияОткрытия*MIN(1,ШколНаПродажу)+IF(23-(ЛагОткрытия+ЛагСледующихШкол)<1,0,INDEX($L13:$BY13,1,23-(ЛагОткрытия+ЛагСледующихШкол)))*КонверсияОткрытия*MAX(0,ШколНаПродажу-1)} | AI14: {=IF(24-ЛагОткрытия<1,0,INDEX($L13:$BY13,1,24-ЛагОткрытия))*КонверсияОткрытия*MIN(1,ШколНаПродажу)+IF(24-(ЛагОткрытия+ЛагСледующихШкол)<1,0,INDEX($L13:$BY13,1,24-(ЛагОткрытия+ЛагСледующихШкол)))*КонверсияОткрытия*MAX(0,ШколНаПродажу-1)} | AJ14: {=IF(25-ЛагОткрытия<1,0,INDEX($L13:$BY13,1,25-ЛагОткрытия))*КонверсияОткрытия*MIN(1,ШколНаПродажу)+IF(25-(ЛагОткрытия+ЛагСледующихШкол)<1,0,INDEX($L13:$BY13,1,25-(ЛагОткрытия+ЛагСледующихШкол)))*КонверсияОткрытия*MAX(0,ШколНаПродажу-1)} | AK14: {=IF(26-ЛагОткрытия<1,0,INDEX($L13:$BY13,1,26-ЛагОткрытия))*КонверсияОткрытия*MIN(1,ШколНаПродажу)+IF(26-(ЛагОткрытия+ЛагСледующихШкол)<1,0,INDEX($L13:$BY13,1,26-(ЛагОткрытия+ЛагСледующихШкол)))*КонверсияОткрытия*MAX(0,ШколНаПродажу-1)} | AL14: {=IF(27-ЛагОткрытия<1,0,INDEX($L13:$BY13,1,27-ЛагОткрытия))*КонверсияОткрытия*MIN(1,ШколНаПродажу)+IF(27-(ЛагОткрытия+ЛагСледующихШкол)<1,0,INDEX($L13:$BY13,1,27-(ЛагОткрытия+ЛагСледующихШкол)))*КонверсияОткрытия*MAX(0,ШколНаПродажу-1)} | AM14: {=IF(28-ЛагОткрытия<1,0,INDEX($L13:$BY13,1,28-ЛагОткрытия))*КонверсияОткрытия*MIN(1,ШколНаПродажу)+IF(28-(ЛагОткрытия+ЛагСледующихШкол)<1,0,INDEX($L13:$BY13,1,28-(ЛагОткрытия+ЛагСледующихШкол)))*КонверсияОткрытия*MAX(0,ШколНаПродажу-1)} | AN14: {=IF(29-ЛагОткрытия<1,0,INDEX($L13:$BY13,1,29-ЛагОткрытия))*КонверсияОткрытия*MIN(1,ШколНаПродажу)+IF(29-(ЛагОткрытия+ЛагСледующихШкол)<1,0,INDEX($L13:$BY13,1,29-(ЛагОткрытия+ЛагСледующихШкол)))*КонверсияОткрытия*MAX(0,ШколНаПродажу-1)} | AO14: {=IF(30-ЛагОткрытия<1,0,INDEX($L13:$BY13,1,30-ЛагОткрытия))*КонверсияОткрытия*MIN(1,ШколНаПродажу)+IF(30-(ЛагОткрытия+ЛагСледующихШкол)<1,0,INDEX($L13:$BY13,1,30-(ЛагОткрытия+ЛагСледующихШкол)))*КонверсияОткрытия*MAX(0,ШколНаПродажу-1)} | AP14: {=IF(31-ЛагОткрытия<1,0,INDEX($L13:$BY13,1,31-ЛагОткрытия))*КонверсияОткрытия*MIN(1,ШколНаПродажу)+IF(31-(ЛагОткрытия+ЛагСледующихШкол)<1,0,INDEX($L13:$BY13,1,31-(ЛагОткрытия+ЛагСледующихШкол)))*КонверсияОткрытия*MAX(0,ШколНаПродажу-1)} | AQ14: {=IF(32-ЛагОткрытия<1,0,INDEX($L13:$BY13,1,32-ЛагОткрытия))*КонверсияОткрытия*MIN(1,ШколНаПродажу)+IF(32-(ЛагОткрытия+ЛагСледующихШкол)<1,0,INDEX($L13:$BY13,1,32-(ЛагОткрытия+ЛагСледующихШкол)))*КонверсияОткрытия*MAX(0,ШколНаПродажу-1)} | AR14: {=IF(33-ЛагОткрытия<1,0,INDEX($L13:$BY13,1,33-ЛагОткрытия))*КонверсияОткрытия*MIN(1,ШколНаПродажу)+IF(33-(ЛагОткрытия+ЛагСледующихШкол)<1,0,INDEX($L13:$BY13,1,33-(ЛагОткрытия+ЛагСледующихШкол)))*КонверсияОткрытия*MAX(0,ШколНаПродажу-1)} | AS14: {=IF(34-ЛагОткрытия<1,0,INDEX($L13:$BY13,1,34-ЛагОткрытия))*КонверсияОткрытия*MIN(1,ШколНаПродажу)+IF(34-(ЛагОткрытия+ЛагСледующихШкол)<1,0,INDEX($L13:$BY13,1,34-(ЛагОткрытия+ЛагСледующихШкол)))*КонверсияОткрытия*MAX(0,ШколНаПродажу-1)} | AT14: {=IF(35-ЛагОткрытия<1,0,INDEX($L13:$BY13,1,35-ЛагОткрытия))*КонверсияОткрытия*MIN(1,ШколНаПродажу)+IF(35-(ЛагОткрытия+ЛагСледующихШкол)<1,0,INDEX($L13:$BY13,1,35-(ЛагОткрытия+ЛагСледующихШкол)))*КонверсияОткрытия*MAX(0,ШколНаПродажу-1)} | AU14: {=IF(36-ЛагОткрытия<1,0,INDEX($L13:$BY13,1,36-ЛагОткрытия))*КонверсияОткрытия*MIN(1,ШколНаПродажу)+IF(36-(ЛагОткрытия+ЛагСледующихШкол)<1,0,INDEX($L13:$BY13,1,36-(ЛагОткрытия+ЛагСледующихШкол)))*КонверсияОткрытия*MAX(0,ШколНаПродажу-1)} | AV14: {=IF(37-ЛагОткрытия<1,0,INDEX($L13:$BY13,1,37-ЛагОткрытия))*КонверсияОткрытия*MIN(1,ШколНаПродажу)+IF(37-(ЛагОткрытия+ЛагСледующихШкол)<1,0,INDEX($L13:$BY13,1,37-(ЛагОткрытия+ЛагСледующихШкол)))*КонверсияОткрытия*MAX(0,ШколНаПродажу-1)} | AW14: {=IF(38-ЛагОткрытия<1,0,INDEX($L13:$BY13,1,38-ЛагОткрытия))*КонверсияОткрытия*MIN(1,ШколНаПродажу)+IF(38-(ЛагОткрытия+ЛагСледующихШкол)<1,0,INDEX($L13:$BY13,1,38-(ЛагОткрытия+ЛагСледующихШкол)))*КонверсияОткрытия*MAX(0,ШколНаПродажу-1)} | AX14: {=IF(39-ЛагОткрытия<1,0,INDEX($L13:$BY13,1,39-ЛагОткрытия))*КонверсияОткрытия*MIN(1,ШколНаПродажу)+IF(39-(ЛагОткрытия+ЛагСледующихШкол)<1,0,INDEX($L13:$BY13,1,39-(ЛагОткрытия+ЛагСледующихШкол)))*КонверсияОткрытия*MAX(0,ШколНаПродажу-1)} | AY14: {=IF(40-ЛагОткрытия<1,0,INDEX($L13:$BY13,1,40-ЛагОткрытия))*КонверсияОткрытия*MIN(1,ШколНаПродажу)+IF(40-(ЛагОткрытия+ЛагСледующихШкол)<1,0,INDEX($L13:$BY13,1,40-(ЛагОткрытия+ЛагСледующихШкол)))*КонверсияОткрытия*MAX(0,ШколНаПродажу-1)} | AZ14: {=IF(41-ЛагОткрытия<1,0,INDEX($L13:$BY13,1,41-ЛагОткрытия))*КонверсияОткрытия*MIN(1,ШколНаПродажу)+IF(41-(ЛагОткрытия+ЛагСледующихШкол)<1,0,INDEX($L13:$BY13,1,41-(ЛагОткрытия+ЛагСледующихШкол)))*КонверсияОткрытия*MAX(0,ШколНаПродажу-1)} | BA14: {=IF(42-ЛагОткрытия<1,0,INDEX($L13:$BY13,1,42-ЛагОткрытия))*КонверсияОткрытия*MIN(1,ШколНаПродажу)+IF(42-(ЛагОткрытия+ЛагСледующихШкол)<1,0,INDEX($L13:$BY13,1,42-(ЛагОткрытия+ЛагСледующихШкол)))*КонверсияОткрытия*MAX(0,ШколНаПродажу-1)} | BB14: {=IF(43-ЛагОткрытия<1,0,INDEX($L13:$BY13,1,43-ЛагОткрытия))*КонверсияОткрытия*MIN(1,ШколНаПродажу)+IF(43-(ЛагОткрытия+ЛагСледующихШкол)<1,0,INDEX($L13:$BY13,1,43-(ЛагОткрытия+ЛагСледующихШкол)))*КонверсияОткрытия*MAX(0,ШколНаПродажу-1)} | BC14: {=IF(44-ЛагОткрытия<1,0,INDEX($L13:$BY13,1,44-ЛагОткрытия))*КонверсияОткрытия*MIN(1,ШколНаПродажу)+IF(44-(ЛагОткрытия+ЛагСледующихШкол)<1,0,INDEX($L13:$BY13,1,44-(ЛагОткрытия+ЛагСледующихШкол)))*КонверсияОткрытия*MAX(0,ШколНаПродажу-1)} | BD14: {=IF(45-ЛагОткрытия<1,0,INDEX($L13:$BY13,1,45-ЛагОткрытия))*КонверсияОткрытия*MIN(1,ШколНаПродажу)+IF(45-(ЛагОткрытия+ЛагСледующихШкол)<1,0,INDEX($L13:$BY13,1,45-(ЛагОткрытия+ЛагСледующихШкол)))*КонверсияОткрытия*MAX(0,ШколНаПродажу-1)} | BE14: {=IF(46-ЛагОткрытия<1,0,INDEX($L13:$BY13,1,46-ЛагОткрытия))*КонверсияОткрытия*MIN(1,ШколНаПродажу)+IF(46-(ЛагОткрытия+ЛагСледующихШкол)<1,0,INDEX($L13:$BY13,1,46-(ЛагОткрытия+ЛагСледующихШкол)))*КонверсияОткрытия*MAX(0,ШколНаПродажу-1)} | BF14: {=IF(47-ЛагОткрытия<1,0,INDEX($L13:$BY13,1,47-ЛагОткрытия))*КонверсияОткрытия*MIN(1,ШколНаПродажу)+IF(47-(ЛагОткрытия+ЛагСледующихШкол)<1,0,INDEX($L13:$BY13,1,47-(ЛагОткрытия+ЛагСледующихШкол)))*КонверсияОткрытия*MAX(0,ШколНаПродажу-1)} | BG14: {=IF(48-ЛагОткрытия<1,0,INDEX($L13:$BY13,1,48-ЛагОткрытия))*КонверсияОткрытия*MIN(1,ШколНаПродажу)+IF(48-(ЛагОткрытия+ЛагСледующихШкол)<1,0,INDEX($L13:$BY13,1,48-(ЛагОткрытия+ЛагСледующихШкол)))*КонверсияОткрытия*MAX(0,ШколНаПродажу-1)} | BH14: {=IF(49-ЛагОткрытия<1,0,INDEX($L13:$BY13,1,49-ЛагОткрытия))*КонверсияОткрытия*MIN(1,ШколНаПродажу)+IF(49-(ЛагОткрытия+ЛагСледующихШкол)<1,0,INDEX($L13:$BY13,1,49-(ЛагОткрытия+ЛагСледующихШкол)))*КонверсияОткрытия*MAX(0,ШколНаПродажу-1)} | BI14: {=IF(50-ЛагОткрытия<1,0,INDEX($L13:$BY13,1,50-ЛагОткрытия))*КонверсияОткрытия*MIN(1,ШколНаПродажу)+IF(50-(ЛагОткрытия+ЛагСледующихШкол)<1,0,INDEX($L13:$BY13,1,50-(ЛагОткрытия+ЛагСледующихШкол)))*КонверсияОткрытия*MAX(0,ШколНаПродажу-1)} | BJ14: {=IF(51-ЛагОткрытия<1,0,INDEX($L13:$BY13,1,51-ЛагОткрытия))*КонверсияОткрытия*MIN(1,ШколНаПродажу)+IF(51-(ЛагОткрытия+ЛагСледующихШкол)<1,0,INDEX($L13:$BY13,1,51-(ЛагОткрытия+ЛагСледующихШкол)))*КонверсияОткрытия*MAX(0,ШколНаПродажу-1)} | BK14: {=IF(52-ЛагОткрытия<1,0,INDEX($L13:$BY13,1,52-ЛагОткрытия))*КонверсияОткрытия*MIN(1,ШколНаПродажу)+IF(52-(ЛагОткрытия+ЛагСледующихШкол)<1,0,INDEX($L13:$BY13,1,52-(ЛагОткрытия+ЛагСледующихШкол)))*КонверсияОткрытия*MAX(0,ШколНаПродажу-1)} | BL14: {=IF(53-ЛагОткрытия<1,0,INDEX($L13:$BY13,1,53-ЛагОткрытия))*КонверсияОткрытия*MIN(1,ШколНаПродажу)+IF(53-(ЛагОткрытия+ЛагСледующихШкол)<1,0,INDEX($L13:$BY13,1,53-(ЛагОткрытия+ЛагСледующихШкол)))*КонверсияОткрытия*MAX(0,ШколНаПродажу-1)} | BM14: {=IF(54-ЛагОткрытия<1,0,INDEX($L13:$BY13,1,54-ЛагОткрытия))*КонверсияОткрытия*MIN(1,ШколНаПродажу)+IF(54-(ЛагОткрытия+ЛагСледующихШкол)<1,0,INDEX($L13:$BY13,1,54-(ЛагОткрытия+ЛагСледующихШкол)))*КонверсияОткрытия*MAX(0,ШколНаПродажу-1)} | BN14: {=IF(55-ЛагОткрытия<1,0,INDEX($L13:$BY13,1,55-ЛагОткрытия))*КонверсияОткрытия*MIN(1,ШколНаПродажу)+IF(55-(ЛагОткрытия+ЛагСледующихШкол)<1,0,INDEX($L13:$BY13,1,55-(ЛагОткрытия+ЛагСледующихШкол)))*КонверсияОткрытия*MAX(0,ШколНаПродажу-1)} | BO14: {=IF(56-ЛагОткрытия<1,0,INDEX($L13:$BY13,1,56-ЛагОткрытия))*КонверсияОткрытия*MIN(1,ШколНаПродажу)+IF(56-(ЛагОткрытия+ЛагСледующихШкол)<1,0,INDEX($L13:$BY13,1,56-(ЛагОткрытия+ЛагСледующихШкол)))*КонверсияОткрытия*MAX(0,ШколНаПродажу-1)} | BP14: {=IF(57-ЛагОткрытия<1,0,INDEX($L13:$BY13,1,57-ЛагОткрытия))*КонверсияОткрытия*MIN(1,ШколНаПродажу)+IF(57-(ЛагОткрытия+ЛагСледующихШкол)<1,0,INDEX($L13:$BY13,1,57-(ЛагОткрытия+ЛагСледующихШкол)))*КонверсияОткрытия*MAX(0,ШколНаПродажу-1)} | BQ14: {=IF(58-ЛагОткрытия<1,0,INDEX($L13:$BY13,1,58-ЛагОткрытия))*КонверсияОткрытия*MIN(1,ШколНаПродажу)+IF(58-(ЛагОткрытия+ЛагСледующихШкол)<1,0,INDEX($L13:$BY13,1,58-(ЛагОткрытия+ЛагСледующихШкол)))*КонверсияОткрытия*MAX(0,ШколНаПродажу-1)} | BR14: {=IF(59-ЛагОткрытия<1,0,INDEX($L13:$BY13,1,59-ЛагОткрытия))*КонверсияОткрытия*MIN(1,ШколНаПродажу)+IF(59-(ЛагОткрытия+ЛагСледующихШкол)<1,0,INDEX($L13:$BY13,1,59-(ЛагОткрытия+ЛагСледующихШкол)))*КонверсияОткрытия*MAX(0,ШколНаПродажу-1)} | BS14: {=IF(60-ЛагОткрытия<1,0,INDEX($L13:$BY13,1,60-ЛагОткрытия))*КонверсияОткрытия*MIN(1,ШколНаПродажу)+IF(60-(ЛагОткрытия+ЛагСледующихШкол)<1,0,INDEX($L13:$BY13,1,60-(ЛагОткрытия+ЛагСледующихШкол)))*КонверсияОткрытия*MAX(0,ШколНаПродажу-1)} | BT14: {=IF(61-ЛагОткрытия<1,0,INDEX($L13:$BY13,1,61-ЛагОткрытия))*КонверсияОткрытия*MIN(1,ШколНаПродажу)+IF(61-(ЛагОткрытия+ЛагСледующихШкол)<1,0,INDEX($L13:$BY13,1,61-(ЛагОткрытия+ЛагСледующихШкол)))*КонверсияОткрытия*MAX(0,ШколНаПродажу-1)} | BU14: {=IF(62-ЛагОткрытия<1,0,INDEX($L13:$BY13,1,62-ЛагОткрытия))*КонверсияОткрытия*MIN(1,ШколНаПродажу)+IF(62-(ЛагОткрытия+ЛагСледующихШкол)<1,0,INDEX($L13:$BY13,1,62-(ЛагОткрытия+ЛагСледующихШкол)))*КонверсияОткрытия*MAX(0,ШколНаПродажу-1)} | BV14: {=IF(63-ЛагОткрытия<1,0,INDEX($L13:$BY13,1,63-ЛагОткрытия))*КонверсияОткрытия*MIN(1,ШколНаПродажу)+IF(63-(ЛагОткрытия+ЛагСледующихШкол)<1,0,INDEX($L13:$BY13,1,63-(ЛагОткрытия+ЛагСледующихШкол)))*КонверсияОткрытия*MAX(0,ШколНаПродажу-1)} | BW14: {=IF(64-ЛагОткрытия<1,0,INDEX($L13:$BY13,1,64-ЛагОткрытия))*КонверсияОткрытия*MIN(1,ШколНаПродажу)+IF(64-(ЛагОткрытия+ЛагСледующихШкол)<1,0,INDEX($L13:$BY13,1,64-(ЛагОткрытия+ЛагСледующихШкол)))*КонверсияОткрытия*MAX(0,ШколНаПродажу-1)} | BX14: {=IF(65-ЛагОткрытия<1,0,INDEX($L13:$BY13,1,65-ЛагОткрытия))*КонверсияОткрытия*MIN(1,ШколНаПродажу)+IF(65-(ЛагОткрытия+ЛагСледующихШкол)<1,0,INDEX($L13:$BY13,1,65-(ЛагОткрытия+ЛагСледующихШкол)))*КонверсияОткрытия*MAX(0,ШколНаПродажу-1)} | BY14: {=IF(66-ЛагОткрытия<1,0,INDEX($L13:$BY13,1,66-ЛагОткрытия))*КонверсияОткрытия*MIN(1,ШколНаПродажу)+IF(66-(ЛагОткрытия+ЛагСледующихШкол)<1,0,INDEX($L13:$BY13,1,66-(ЛагОткрытия+ЛагСледующихШкол)))*КонверсияОткрытия*MAX(0,ШколНаПродажу-1)}
B15: Новые юрлица (партнёры) | C15: шт. | D15: Партнёр появляется в месяц покупки франшизы — без лага: лаг нужен школе, а не договору | E15: =SUM(L15:W15) | F15: =SUM(X15:AI15) | G15: =SUM(AJ15:AU15) | H15: =SUM(AV15:BG15) | I15: =SUM(BH15:BS15) | J15: =SUM(L15:BS15) | L15: =L13*ЮрлицНаПродажу | M15: =M13*ЮрлицНаПродажу | N15: =N13*ЮрлицНаПродажу | O15: =O13*ЮрлицНаПродажу | P15: =P13*ЮрлицНаПродажу | Q15: =Q13*ЮрлицНаПродажу | R15: =R13*ЮрлицНаПродажу | S15: =S13*ЮрлицНаПродажу | ... BY15: =BY13*ЮрлицНаПродажу
B17: Действующая сеть (та, что была на старте)
B18: Школы действующей сети | C18: шт. | D18: Каждый месяц убывает на коэффициент закрытия В колонках лет — значение на конец года, в «Итого» — на конец пятого года. Это остаток, а не сумма. | E18: =W18 | F18: =AI18 | G18: =AU18 | H18: =BG18 | I18: =BS18 | J18: =BS18 | L18: =ШколыСтарт*КоэффСохранения | M18: =L18*КоэффСохранения | N18: =M18*КоэффСохранения | O18: =N18*КоэффСохранения | P18: =O18*КоэффСохранения | Q18: =P18*КоэффСохранения | R18: =Q18*КоэффСохранения | S18: =R18*КоэффСохранения | T18: =S18*КоэффСохранения | ... BY18: =BX18*КоэффСохранения
B19: Дети действующей сети, 100% база | C19: чел. | D19: База растёт по сезонам и уменьшается вместе с числом школ В колонках лет — значение на конец года, в «Итого» — на конец пятого года. Это остаток, а не сумма. | E19: =W19 | F19: =AI19 | G19: =AU19 | H19: =BG19 | I19: =BS19 | J19: =BS19 | L19: =ДетиСтарт*(1+РостДетей)^(L8-1)*IF(ШколыСтарт=0,0,L18/ШколыСтарт) | M19: =ДетиСтарт*(1+РостДетей)^(M8-1)*IF(ШколыСтарт=0,0,M18/ШколыСтарт) | N19: =ДетиСтарт*(1+РостДетей)^(N8-1)*IF(ШколыСтарт=0,0,N18/ШколыСтарт) | O19: =ДетиСтарт*(1+РостДетей)^(O8-1)*IF(ШколыСтарт=0,0,O18/ШколыСтарт) | P19: =ДетиСтарт*(1+РостДетей)^(P8-1)*IF(ШколыСтарт=0,0,P18/ШколыСтарт) | Q19: =ДетиСтарт*(1+РостДетей)^(Q8-1)*IF(ШколыСтарт=0,0,Q18/ШколыСтарт) | R19: =ДетиСтарт*(1+РостДетей)^(R8-1)*IF(ШколыСтарт=0,0,R18/ШколыСтарт) | S19: =ДетиСтарт*(1+РостДетей)^(S8-1)*IF(ШколыСтарт=0,0,S18/ШколыСтарт) | ... BY19: =ДетиСтарт*(1+РостДетей)^(BY8-1)*IF(ШколыСтарт=0,0,BY18/ШколыСтарт)
B20: Дети действующей сети, активные | C20: чел. | D20: База, умноженная на сезонность посещаемости В колонках лет — значение на конец года, в «Итого» — на конец пятого года. Это остаток, а не сумма. | E20: =W20 | F20: =AI20 | G20: =AU20 | H20: =BG20 | I20: =BS20 | J20: =BS20 | L20: =L19*L10 | M20: =M19*M10 | N20: =N19*N10 | O20: =O19*O10 | P20: =P19*P10 | Q20: =Q19*Q10 | R20: =R19*R10 | S20: =S19*S10 | ... BY20: =BY19*BY10
B22: Новые школы по месяцам жизни
B23: 1 мес. | C23: шт. | D23: Школы, открывшиеся в этом месяце Внутренняя механика расчёта: годового итога у этой строки нет, смотрите итоговые строки блока ниже. | L23: =L14 | M23: =M14 | N23: =N14 | O23: =O14 | P23: =P14 | Q23: =Q14 | R23: =R14 | S23: =S14 | ... BY23: =BY14
B24: 2 мес. | C24: шт. | D24: Внутренняя механика расчёта: годового итога у этой строки нет, смотрите итоговые строки блока ниже. | L24: =0 | M24: =L23*КоэффСохранения | N24: =M23*КоэффСохранения | O24: =N23*КоэффСохранения | P24: =O23*КоэффСохранения | Q24: =P23*КоэффСохранения | R24: =Q23*КоэффСохранения | S24: =R23*КоэффСохранения | T24: =S23*КоэффСохранения | ... BY24: =BX23*КоэффСохранения
B25: 3 мес. | C25: шт. | D25: Внутренняя механика расчёта: годового итога у этой строки нет, смотрите итоговые строки блока ниже. | L25: =0 | M25: =L24*КоэффСохранения | N25: =M24*КоэффСохранения | O25: =N24*КоэффСохранения | P25: =O24*КоэффСохранения | Q25: =P24*КоэффСохранения | R25: =Q24*КоэффСохранения | S25: =R24*КоэффСохранения | T25: =S24*КоэффСохранения | ... BY25: =BX24*КоэффСохранения
B26: 4 мес. | C26: шт. | D26: Внутренняя механика расчёта: годового итога у этой строки нет, смотрите итоговые строки блока ниже. | L26: =0 | M26: =L25*КоэффСохранения | N26: =M25*КоэффСохранения | O26: =N25*КоэффСохранения | P26: =O25*КоэффСохранения | Q26: =P25*КоэффСохранения | R26: =Q25*КоэффСохранения | S26: =R25*КоэффСохранения | T26: =S25*КоэффСохранения | ... BY26: =BX25*КоэффСохранения
B27: 5 мес. | C27: шт. | D27: Внутренняя механика расчёта: годового итога у этой строки нет, смотрите итоговые строки блока ниже. | L27: =0 | M27: =L26*КоэффСохранения | N27: =M26*КоэффСохранения | O27: =N26*КоэффСохранения | P27: =O26*КоэффСохранения | Q27: =P26*КоэффСохранения | R27: =Q26*КоэффСохранения | S27: =R26*КоэффСохранения | T27: =S26*КоэффСохранения | ... BY27: =BX26*КоэффСохранения
B28: 6 мес. | C28: шт. | D28: Внутренняя механика расчёта: годового итога у этой строки нет, смотрите итоговые строки блока ниже. | L28: =0 | M28: =L27*КоэффСохранения | N28: =M27*КоэффСохранения | O28: =N27*КоэффСохранения | P28: =O27*КоэффСохранения | Q28: =P27*КоэффСохранения | R28: =Q27*КоэффСохранения | S28: =R27*КоэффСохранения | T28: =S27*КоэффСохранения | ... BY28: =BX27*КоэффСохранения
B29: 7 мес. | C29: шт. | D29: Внутренняя механика расчёта: годового итога у этой строки нет, смотрите итоговые строки блока ниже. | L29: =0 | M29: =L28*КоэффСохранения | N29: =M28*КоэффСохранения | O29: =N28*КоэффСохранения | P29: =O28*КоэффСохранения | Q29: =P28*КоэффСохранения | R29: =Q28*КоэффСохранения | S29: =R28*КоэффСохранения | T29: =S28*КоэффСохранения | ... BY29: =BX28*КоэффСохранения
B30: 8 мес. | C30: шт. | D30: Внутренняя механика расчёта: годового итога у этой строки нет, смотрите итоговые строки блока ниже. | L30: =0 | M30: =L29*КоэффСохранения | N30: =M29*КоэффСохранения | O30: =N29*КоэффСохранения | P30: =O29*КоэффСохранения | Q30: =P29*КоэффСохранения | R30: =Q29*КоэффСохранения | S30: =R29*КоэффСохранения | T30: =S29*КоэффСохранения | ... BY30: =BX29*КоэффСохранения
B31: 9 мес. | C31: шт. | D31: Внутренняя механика расчёта: годового итога у этой строки нет, смотрите итоговые строки блока ниже. | L31: =0 | M31: =L30*КоэффСохранения | N31: =M30*КоэффСохранения | O31: =N30*КоэффСохранения | P31: =O30*КоэффСохранения | Q31: =P30*КоэффСохранения | R31: =Q30*КоэффСохранения | S31: =R30*КоэффСохранения | T31: =S30*КоэффСохранения | ... BY31: =BX30*КоэффСохранения
B32: 10 мес. | C32: шт. | D32: Внутренняя механика расчёта: годового итога у этой строки нет, смотрите итоговые строки блока ниже. | L32: =0 | M32: =L31*КоэффСохранения | N32: =M31*КоэффСохранения | O32: =N31*КоэффСохранения | P32: =O31*КоэффСохранения | Q32: =P31*КоэффСохранения | R32: =Q31*КоэффСохранения | S32: =R31*КоэффСохранения | T32: =S31*КоэффСохранения | ... BY32: =BX31*КоэффСохранения
B33: 11 мес. | C33: шт. | D33: Внутренняя механика расчёта: годового итога у этой строки нет, смотрите итоговые строки блока ниже. | L33: =0 | M33: =L32*КоэффСохранения | N33: =M32*КоэффСохранения | O33: =N32*КоэффСохранения | P33: =O32*КоэффСохранения | Q33: =P32*КоэффСохранения | R33: =Q32*КоэффСохранения | S33: =R32*КоэффСохранения | T33: =S32*КоэффСохранения | ... BY33: =BX32*КоэффСохранения
B34: 12 мес. | C34: шт. | D34: Внутренняя механика расчёта: годового итога у этой строки нет, смотрите итоговые строки блока ниже. | L34: =0 | M34: =L33*КоэффСохранения | N34: =M33*КоэффСохранения | O34: =N33*КоэффСохранения | P34: =O33*КоэффСохранения | Q34: =P33*КоэффСохранения | R34: =Q33*КоэффСохранения | S34: =R33*КоэффСохранения | T34: =S33*КоэффСохранения | ... BY34: =BX33*КоэффСохранения
B35: 13 мес. | C35: шт. | D35: Внутренняя механика расчёта: годового итога у этой строки нет, смотрите итоговые строки блока ниже. | L35: =0 | M35: =L34*КоэффСохранения | N35: =M34*КоэффСохранения | O35: =N34*КоэффСохранения | P35: =O34*КоэффСохранения | Q35: =P34*КоэффСохранения | R35: =Q34*КоэффСохранения | S35: =R34*КоэффСохранения | T35: =S34*КоэффСохранения | ... BY35: =BX34*КоэффСохранения
... B46: 24 мес. | C46: шт. | D46: Внутренняя механика расчёта: годового итога у этой строки нет, смотрите итоговые строки блока ниже. | L46: =0 | M46: =L45*КоэффСохранения | N46: =M45*КоэффСохранения | O46: =N45*КоэффСохранения | P46: =O45*КоэффСохранения | Q46: =P45*КоэффСохранения | R46: =Q45*КоэффСохранения | S46: =R45*КоэффСохранения | T46: =S45*КоэффСохранения | ... BY46: =BX45*КоэффСохранения
B47: 25+ мес. (зрелые) | C47: шт. | D47: Школы старше двух лет копятся здесь Внутренняя механика расчёта: годового итога у этой строки нет, смотрите итоговые строки блока ниже. | L47: =0 | M47: =(L46+L47)*КоэффСохранения | N47: =(M46+M47)*КоэффСохранения | O47: =(N46+N47)*КоэффСохранения | P47: =(O46+O47)*КоэффСохранения | Q47: =(P46+P47)*КоэффСохранения | R47: =(Q46+Q47)*КоэффСохранения | S47: =(R46+R47)*КоэффСохранения | T47: =(S46+S47)*КоэффСохранения | ... BY47: =(BX46+BX47)*КоэффСохранения
B49: Новые школы и их дети
B50: Новые школы 1–12 мес. | C50: шт. | D50: Сумма первых двенадцати когорт В колонках лет — значение на конец года, в «Итого» — на конец пятого года. Это остаток, а не сумма. | E50: =W50 | F50: =AI50 | G50: =AU50 | H50: =BG50 | I50: =BS50 | J50: =BS50 | L50: =SUM(L23:L34) | M50: =SUM(M23:M34) | N50: =SUM(N23:N34) | O50: =SUM(O23:O34) | P50: =SUM(P23:P34) | Q50: =SUM(Q23:Q34) | R50: =SUM(R23:R34) | S50: =SUM(S23:S34) | ... BY50: =SUM(BY23:BY34)
B51: Новые школы 13–24 мес. | C51: шт. | D51: Второй год жизни В колонках лет — значение на конец года, в «Итого» — на конец пятого года. Это остаток, а не сумма. | E51: =W51 | F51: =AI51 | G51: =AU51 | H51: =BG51 | I51: =BS51 | J51: =BS51 | L51: =SUM(L35:L46) | M51: =SUM(M35:M46) | N51: =SUM(N35:N46) | O51: =SUM(O35:O46) | P51: =SUM(P35:P46) | Q51: =SUM(Q35:Q46) | R51: =SUM(R35:R46) | S51: =SUM(S35:S46) | ... BY51: =SUM(BY35:BY46)
B52: Новые школы зрелые | C52: шт. | D52: Старше двух лет В колонках лет — значение на конец года, в «Итого» — на конец пятого года. Это остаток, а не сумма. | E52: =W52 | F52: =AI52 | G52: =AU52 | H52: =BG52 | I52: =BS52 | J52: =BS52 | L52: =L47 | M52: =M47 | N52: =N47 | O52: =O47 | P52: =P47 | Q52: =Q47 | R52: =R47 | S52: =S47 | ... BY52: =BY47
B53: Новые школы — всего | C53: шт. | D53: В колонках лет — значение на конец года, в «Итого» — на конец пятого года. Это остаток, а не сумма. | E53: =W53 | F53: =AI53 | G53: =AU53 | H53: =BG53 | I53: =BS53 | J53: =BS53 | L53: =SUM(L50:L52) | M53: =SUM(M50:M52) | N53: =SUM(N50:N52) | O53: =SUM(O50:O52) | P53: =SUM(P50:P52) | Q53: =SUM(Q50:Q52) | R53: =SUM(R50:R52) | S53: =SUM(S50:S52) | ... BY53: =SUM(BY50:BY52)
B54: Дети новых школ, 1–12 мес. | C54: чел. | D54: Каждая когорта умножается на ёмкость своего возраста из справочника тарифов В колонках лет — значение на конец года, в «Итого» — на конец пятого года. Это остаток, а не сумма. | E54: =W54 | F54: =AI54 | G54: =AU54 | H54: =BG54 | I54: =BS54 | J54: =BS54 | L54: =SUMPRODUCT(L23:L34,CapacityYear1)*МножительДетей*L10 | M54: =SUMPRODUCT(M23:M34,CapacityYear1)*МножительДетей*M10 | N54: =SUMPRODUCT(N23:N34,CapacityYear1)*МножительДетей*N10 | O54: =SUMPRODUCT(O23:O34,CapacityYear1)*МножительДетей*O10 | P54: =SUMPRODUCT(P23:P34,CapacityYear1)*МножительДетей*P10 | Q54: =SUMPRODUCT(Q23:Q34,CapacityYear1)*МножительДетей*Q10 | R54: =SUMPRODUCT(R23:R34,CapacityYear1)*МножительДетей*R10 | S54: =SUMPRODUCT(S23:S34,CapacityYear1)*МножительДетей*S10 | ... BY54: =SUMPRODUCT(BY23:BY34,CapacityYear1)*МножительДетей*BY10
B55: Дети новых школ, 13–24 мес. | C55: чел. | D55: В колонках лет — значение на конец года, в «Итого» — на конец пятого года. Это остаток, а не сумма. | E55: =W55 | F55: =AI55 | G55: =AU55 | H55: =BG55 | I55: =BS55 | J55: =BS55 | L55: =SUMPRODUCT(L35:L46,CapacityYear2)*МножительДетей*L10 | M55: =SUMPRODUCT(M35:M46,CapacityYear2)*МножительДетей*M10 | N55: =SUMPRODUCT(N35:N46,CapacityYear2)*МножительДетей*N10 | O55: =SUMPRODUCT(O35:O46,CapacityYear2)*МножительДетей*O10 | P55: =SUMPRODUCT(P35:P46,CapacityYear2)*МножительДетей*P10 | Q55: =SUMPRODUCT(Q35:Q46,CapacityYear2)*МножительДетей*Q10 | R55: =SUMPRODUCT(R35:R46,CapacityYear2)*МножительДетей*R10 | S55: =SUMPRODUCT(S35:S46,CapacityYear2)*МножительДетей*S10 | ... BY55: =SUMPRODUCT(BY35:BY46,CapacityYear2)*МножительДетей*BY10
B56: Дети новых школ, зрелые | C56: чел. | D56: В колонках лет — значение на конец года, в «Итого» — на конец пятого года. Это остаток, а не сумма. | E56: =W56 | F56: =AI56 | G56: =AU56 | H56: =BG56 | I56: =BS56 | J56: =BS56 | L56: =L47*CapacityAge25*МножительДетей*L10 | M56: =M47*CapacityAge25*МножительДетей*M10 | N56: =N47*CapacityAge25*МножительДетей*N10 | O56: =O47*CapacityAge25*МножительДетей*O10 | P56: =P47*CapacityAge25*МножительДетей*P10 | Q56: =Q47*CapacityAge25*МножительДетей*Q10 | R56: =R47*CapacityAge25*МножительДетей*R10 | S56: =S47*CapacityAge25*МножительДетей*S10 | ... BY56: =BY47*CapacityAge25*МножительДетей*BY10
B57: Дети новых школ — всего | C57: чел. | D57: В колонках лет — значение на конец года, в «Итого» — на конец пятого года. Это остаток, а не сумма. | E57: =W57 | F57: =AI57 | G57: =AU57 | H57: =BG57 | I57: =BS57 | J57: =BS57 | L57: =SUM(L54:L56) | M57: =SUM(M54:M56) | N57: =SUM(N54:N56) | O57: =SUM(O54:O56) | P57: =SUM(P54:P56) | Q57: =SUM(Q54:Q56) | R57: =SUM(R54:R56) | S57: =SUM(S54:S56) | ... BY57: =SUM(BY54:BY56)
B59: Итог по сети
B60: Школы всего | C60: шт. | D60: Действующая сеть плюс новые школы В колонках лет — значение на конец года, в «Итого» — на конец пятого года. Это остаток, а не сумма. | E60: =W60 | F60: =AI60 | G60: =AU60 | H60: =BG60 | I60: =BS60 | J60: =BS60 | L60: =L18+L53 | M60: =M18+M53 | N60: =N18+N53 | O60: =O18+O53 | P60: =P18+P53 | Q60: =Q18+Q53 | R60: =R18+R53 | S60: =S18+S53 | ... BY60: =BY18+BY53
B61: Юрлица (партнёры) всего | C61: шт. | D61: Накопленные партнёры за вычетом закрытий В колонках лет — значение на конец года, в «Итого» — на конец пятого года. Это остаток, а не сумма. | E61: =W61 | F61: =AI61 | G61: =AU61 | H61: =BG61 | I61: =BS61 | J61: =BS61 | L61: =ЮрлицаСтарт*КоэффСохранения+$L15 | M61: =L61*КоэффСохранения+M15 | N61: =M61*КоэффСохранения+N15 | O61: =N61*КоэффСохранения+O15 | P61: =O61*КоэффСохранения+P15 | Q61: =P61*КоэффСохранения+Q15 | R61: =Q61*КоэффСохранения+R15 | S61: =R61*КоэффСохранения+S15 | T61: =S61*КоэффСохранения+T15 | ... BY61: =BX61*КоэффСохранения+BY15
B62: Дети всего, активные | C62: чел. | D62: Действующая сеть плюс новые школы В колонках лет — значение на конец года, в «Итого» — на конец пятого года. Это остаток, а не сумма. | E62: =W62 | F62: =AI62 | G62: =AU62 | H62: =BG62 | I62: =BS62 | J62: =BS62 | L62: =L20+L57 | M62: =M20+M57 | N62: =N20+N57 | O62: =O20+O57 | P62: =P20+P57 | Q62: =Q20+Q57 | R62: =R20+R57 | S62: =S20+S57 | ... BY62: =BY20+BY57

Sheet 04_Доходы
B1: Доходы: паушальные, роялти, мерч
B2: Расшифровка к «Результату». Роялти новых школ разложено по возрасту школы: чем старше школа, тем больше в ней детей.
B4: Показатель | C4: Ед. | D4: Как считается | E4: Год 1 | F4: Год 2 | G4: Год 3 | H4: Год 4 | I4: Год 5 | J4: Итого 5 лет | L4: М1 | M4: М2 | N4: М3 | O4: М4 | P4: М5 | Q4: М6 | R4: М7 | S4: М8 | T4: М9 | U4: М10 | V4: М11 | W4: М12 | X4: М13 | Y4: М14 | Z4: М15 | AA4: М16 | AB4: М17 | AC4: М18 | AD4: М19 | AE4: М20 | AF4: М21 | AG4: М22 | AH4: М23 | AI4: М24 | AJ4: М25 | AK4: М26 | AL4: М27 | AM4: М28 | AN4: М29 | AO4: М30 | AP4: М31 | AQ4: М32 | AR4: М33 | AS4: М34 | AT4: М35 | AU4: М36 | AV4: М37 | AW4: М38 | AX4: М39 | AY4: М40 | AZ4: М41 | BA4: М42 | BB4: М43 | BC4: М44 | BD4: М45 | BE4: М46 | BF4: М47 | BG4: М48 | BH4: М49 | BI4: М50 | BJ4: М51 | BK4: М52 | BL4: М53 | BM4: М54 | BN4: М55 | BO4: М56 | BP4: М57 | BQ4: М58 | BR4: М59 | BS4: М60 | BT4: тех. 1 | BU4: тех. 2 | BV4: тех. 3 | BW4: тех. 4 | BX4: тех. 5 | BY4: тех. 6
E5: =TEXT(MONTH(DATE(YEAR(СтартМодели),MONTH(СтартМодели)+0,1)),"00")&"."&YEAR(DATE(YEAR(СтартМодели),MONTH(СтартМодели)+0,1))&" – "&TEXT(MONTH(DATE(YEAR(СтартМодели),MONTH(СтартМодели)+11,1)),"00")&"."&YEAR(DATE(YEAR(СтартМодели),MONTH(СтартМодели)+11,1)) | F5: =TEXT(MONTH(DATE(YEAR(СтартМодели),MONTH(СтартМодели)+12,1)),"00")&"."&YEAR(DATE(YEAR(СтартМодели),MONTH(СтартМодели)+12,1))&" – "&TEXT(MONTH(DATE(YEAR(СтартМодели),MONTH(СтартМодели)+23,1)),"00")&"."&YEAR(DATE(YEAR(СтартМодели),MONTH(СтартМодели)+23,1)) | G5: =TEXT(MONTH(DATE(YEAR(СтартМодели),MONTH(СтартМодели)+24,1)),"00")&"."&YEAR(DATE(YEAR(СтартМодели),MONTH(СтартМодели)+24,1))&" – "&TEXT(MONTH(DATE(YEAR(СтартМодели),MONTH(СтартМодели)+35,1)),"00")&"."&YEAR(DATE(YEAR(СтартМодели),MONTH(СтартМодели)+35,1)) | H5: =TEXT(MONTH(DATE(YEAR(СтартМодели),MONTH(СтартМодели)+36,1)),"00")&"."&YEAR(DATE(YEAR(СтартМодели),MONTH(СтартМодели)+36,1))&" – "&TEXT(MONTH(DATE(YEAR(СтартМодели),MONTH(СтартМодели)+47,1)),"00")&"."&YEAR(DATE(YEAR(СтартМодели),MONTH(СтартМодели)+47,1)) | I5: =TEXT(MONTH(DATE(YEAR(СтартМодели),MONTH(СтартМодели)+48,1)),"00")&"."&YEAR(DATE(YEAR(СтартМодели),MONTH(СтартМодели)+48,1))&" – "&TEXT(MONTH(DATE(YEAR(СтартМодели),MONTH(СтартМодели)+59,1)),"00")&"."&YEAR(DATE(YEAR(СтартМодели),MONTH(СтартМодели)+59,1)) | J5: =TEXT(MONTH(DATE(YEAR(СтартМодели),MONTH(СтартМодели)+0,1)),"00")&"."&YEAR(DATE(YEAR(СтартМодели),MONTH(СтартМодели)+0,1))&" – "&TEXT(MONTH(DATE(YEAR(СтартМодели),MONTH(СтартМодели)+59,1)),"00")&"."&YEAR(DATE(YEAR(СтартМодели),MONTH(СтартМодели)+59,1)) | L5: =DATE(YEAR(СтартМодели),MONTH(СтартМодели)+1-1,1) | M5: =DATE(YEAR(СтартМодели),MONTH(СтартМодели)+2-1,1) | N5: =DATE(YEAR(СтартМодели),MONTH(СтартМодели)+3-1,1) | O5: =DATE(YEAR(СтартМодели),MONTH(СтартМодели)+4-1,1) | P5: =DATE(YEAR(СтартМодели),MONTH(СтартМодели)+5-1,1) | Q5: =DATE(YEAR(СтартМодели),MONTH(СтартМодели)+6-1,1) | R5: =DATE(YEAR(СтартМодели),MONTH(СтартМодели)+7-1,1) | S5: =DATE(YEAR(СтартМодели),MONTH(СтартМодели)+8-1,1) | T5: =DATE(YEAR(СтартМодели),MONTH(СтартМодели)+9-1,1) | U5: =DATE(YEAR(СтартМодели),MONTH(СтартМодели)+10-1,1) | V5: =DATE(YEAR(СтартМодели),MONTH(СтартМодели)+11-1,1) | W5: =DATE(YEAR(СтартМодели),MONTH(СтартМодели)+12-1,1) | X5: =DATE(YEAR(СтартМодели),MONTH(СтартМодели)+13-1,1) | Y5: =DATE(YEAR(СтартМодели),MONTH(СтартМодели)+14-1,1) | Z5: =DATE(YEAR(СтартМодели),MONTH(СтартМодели)+15-1,1) | AA5: =DATE(YEAR(СтартМодели),MONTH(СтартМодели)+16-1,1) | AB5: =DATE(YEAR(СтартМодели),MONTH(СтартМодели)+17-1,1) | AC5: =DATE(YEAR(СтартМодели),MONTH(СтартМодели)+18-1,1) | AD5: =DATE(YEAR(СтартМодели),MONTH(СтартМодели)+19-1,1) | AE5: =DATE(YEAR(СтартМодели),MONTH(СтартМодели)+20-1,1) | AF5: =DATE(YEAR(СтартМодели),MONTH(СтартМодели)+21-1,1) | AG5: =DATE(YEAR(СтартМодели),MONTH(СтартМодели)+22-1,1) | AH5: =DATE(YEAR(СтартМодели),MONTH(СтартМодели)+23-1,1) | AI5: =DATE(YEAR(СтартМодели),MONTH(СтартМодели)+24-1,1) | AJ5: =DATE(YEAR(СтартМодели),MONTH(СтартМодели)+25-1,1) | AK5: =DATE(YEAR(СтартМодели),MONTH(СтартМодели)+26-1,1) | AL5: =DATE(YEAR(СтартМодели),MONTH(СтартМодели)+27-1,1) | AM5: =DATE(YEAR(СтартМодели),MONTH(СтартМодели)+28-1,1) | AN5: =DATE(YEAR(СтартМодели),MONTH(СтартМодели)+29-1,1) | AO5: =DATE(YEAR(СтартМодели),MONTH(СтартМодели)+30-1,1) | AP5: =DATE(YEAR(СтартМодели),MONTH(СтартМодели)+31-1,1) | AQ5: =DATE(YEAR(СтартМодели),MONTH(СтартМодели)+32-1,1) | AR5: =DATE(YEAR(СтартМодели),MONTH(СтартМодели)+33-1,1) | AS5: =DATE(YEAR(СтартМодели),MONTH(СтартМодели)+34-1,1) | AT5: =DATE(YEAR(СтартМодели),MONTH(СтартМодели)+35-1,1) | AU5: =DATE(YEAR(СтартМодели),MONTH(СтартМодели)+36-1,1) | AV5: =DATE(YEAR(СтартМодели),MONTH(СтартМодели)+37-1,1) | AW5: =DATE(YEAR(СтартМодели),MONTH(СтартМодели)+38-1,1) | AX5: =DATE(YEAR(СтартМодели),MONTH(СтартМодели)+39-1,1) | AY5: =DATE(YEAR(СтартМодели),MONTH(СтартМодели)+40-1,1) | AZ5: =DATE(YEAR(СтартМодели),MONTH(СтартМодели)+41-1,1) | BA5: =DATE(YEAR(СтартМодели),MONTH(СтартМодели)+42-1,1) | BB5: =DATE(YEAR(СтартМодели),MONTH(СтартМодели)+43-1,1) | BC5: =DATE(YEAR(СтартМодели),MONTH(СтартМодели)+44-1,1) | BD5: =DATE(YEAR(СтартМодели),MONTH(СтартМодели)+45-1,1) | BE5: =DATE(YEAR(СтартМодели),MONTH(СтартМодели)+46-1,1) | BF5: =DATE(YEAR(СтартМодели),MONTH(СтартМодели)+47-1,1) | BG5: =DATE(YEAR(СтартМодели),MONTH(СтартМодели)+48-1,1) | BH5: =DATE(YEAR(СтартМодели),MONTH(СтартМодели)+49-1,1) | BI5: =DATE(YEAR(СтартМодели),MONTH(СтартМодели)+50-1,1) | BJ5: =DATE(YEAR(СтартМодели),MONTH(СтартМодели)+51-1,1) | BK5: =DATE(YEAR(СтартМодели),MONTH(СтартМодели)+52-1,1) | BL5: =DATE(YEAR(СтартМодели),MONTH(СтартМодели)+53-1,1) | BM5: =DATE(YEAR(СтартМодели),MONTH(СтартМодели)+54-1,1) | BN5: =DATE(YEAR(СтартМодели),MONTH(СтартМодели)+55-1,1) | BO5: =DATE(YEAR(СтартМодели),MONTH(СтартМодели)+56-1,1) | BP5: =DATE(YEAR(СтартМодели),MONTH(СтартМодели)+57-1,1) | BQ5: =DATE(YEAR(СтартМодели),MONTH(СтартМодели)+58-1,1) | BR5: =DATE(YEAR(СтартМодели),MONTH(СтартМодели)+59-1,1) | BS5: =DATE(YEAR(СтартМодели),MONTH(СтартМодели)+60-1,1) | BT5: =DATE(YEAR(СтартМодели),MONTH(СтартМодели)+61-1,1) | BU5: =DATE(YEAR(СтартМодели),MONTH(СтартМодели)+62-1,1) | BV5: =DATE(YEAR(СтартМодели),MONTH(СтартМодели)+63-1,1) | BW5: =DATE(YEAR(СтартМодели),MONTH(СтартМодели)+64-1,1) | BX5: =DATE(YEAR(СтартМодели),MONTH(СтартМодели)+65-1,1) | BY5: =DATE(YEAR(СтартМодели),MONTH(СтартМодели)+66-1,1)
B6: Множители периода
B7: Индекс цен | C7: коэфф. | D7: Накопленная индексация из справочника тарифов В колонках лет — значение на конец года, в «Итого» — на конец пятого года. Это остаток, а не сумма. | E7: =W7 | F7: =AI7 | G7: =AU7 | H7: =BG7 | I7: =BS7 | J7: =BS7 | L7: ='07_Тарифы'!B$4 | M7: ='07_Тарифы'!C$4 | N7: ='07_Тарифы'!D$4 | O7: ='07_Тарифы'!E$4 | P7: ='07_Тарифы'!F$4 | Q7: ='07_Тарифы'!G$4 | R7: ='07_Тарифы'!H$4 | S7: ='07_Тарифы'!I$4 | ... BY7: ='07_Тарифы'!BO$4
B8: Множитель оборота | C8: коэфф. | D8: Сезонность, сценарные множители и индексация в одном числе В колонках лет — среднее за год, в «Итого» — среднее за все 60 месяцев. | E8: =AVERAGE(L8:W8) | F8: =AVERAGE(X8:AI8) | G8: =AVERAGE(AJ8:AU8) | H8: =AVERAGE(AV8:BG8) | I8: =AVERAGE(BH8:BS8) | J8: =AVERAGE(L8:BS8) | L8: ='03_Сеть'!L10*МножительДетей*МножительЦен*L7 | M8: ='03_Сеть'!M10*МножительДетей*МножительЦен*M7 | N8: ='03_Сеть'!N10*МножительДетей*МножительЦен*N7 | O8: ='03_Сеть'!O10*МножительДетей*МножительЦен*O7 | P8: ='03_Сеть'!P10*МножительДетей*МножительЦен*P7 | Q8: ='03_Сеть'!Q10*МножительДетей*МножительЦен*Q7 | R8: ='03_Сеть'!R10*МножительДетей*МножительЦен*R7 | S8: ='03_Сеть'!S10*МножительДетей*МножительЦен*S7 | ... BY8: ='03_Сеть'!BY10*МножительДетей*МножительЦен*BY7
B9: Ставка роялти: договоры до перехода | C9: коэфф. | D9: После общей даты все переходят на единую ставку В колонках лет — среднее за год, в «Итого» — среднее за все 60 месяцев. | E9: =AVERAGE(L9:W9) | F9: =AVERAGE(X9:AI9) | G9: =AVERAGE(AJ9:AU9) | H9: =AVERAGE(AV9:BG9) | I9: =AVERAGE(BH9:BS9) | J9: =AVERAGE(L9:BS9) | L9: =L8*IF('03_Сеть'!L7>=ДатаПереходаСтавки,СтавкаРоялтиВсех,СтавкаРоялтиСтарых) | M9: =M8*IF('03_Сеть'!M7>=ДатаПереходаСтавки,СтавкаРоялтиВсех,СтавкаРоялтиСтарых) | N9: =N8*IF('03_Сеть'!N7>=ДатаПереходаСтавки,СтавкаРоялтиВсех,СтавкаРоялтиСтарых) | O9: =O8*IF('03_Сеть'!O7>=ДатаПереходаСтавки,СтавкаРоялтиВсех,СтавкаРоялтиСтарых) | P9: =P8*IF('03_Сеть'!P7>=ДатаПереходаСтавки,СтавкаРоялтиВсех,СтавкаРоялтиСтарых) | Q9: =Q8*IF('03_Сеть'!Q7>=ДатаПереходаСтавки,СтавкаРоялтиВсех,СтавкаРоялтиСтарых) | R9: =R8*IF('03_Сеть'!R7>=ДатаПереходаСтавки,СтавкаРоялтиВсех,СтавкаРоялтиСтарых) | S9: =S8*IF('03_Сеть'!S7>=ДатаПереходаСтавки,СтавкаРоялтиВсех,СтавкаРоялтиСтарых) | ... BY9: =BY8*IF('03_Сеть'!BY7>=ДатаПереходаСтавки,СтавкаРоялтиВсех,СтавкаРоялтиСтарых)
B10: Ставка роялти: договоры после перехода | C10: коэфф. | D10: В колонках лет — среднее за год, в «Итого» — среднее за все 60 месяцев. | E10: =AVERAGE(L10:W10) | F10: =AVERAGE(X10:AI10) | G10: =AVERAGE(AJ10:AU10) | H10: =AVERAGE(AV10:BG10) | I10: =AVERAGE(BH10:BS10) | J10: =AVERAGE(L10:BS10) | L10: =L8*IF('03_Сеть'!L7>=ДатаПереходаСтавки,СтавкаРоялтиВсех,СтавкаРоялтиНовых) | M10: =M8*IF('03_Сеть'!M7>=ДатаПереходаСтавки,СтавкаРоялтиВсех,СтавкаРоялтиНовых) | N10: =N8*IF('03_Сеть'!N7>=ДатаПереходаСтавки,СтавкаРоялтиВсех,СтавкаРоялтиНовых) | O10: =O8*IF('03_Сеть'!O7>=ДатаПереходаСтавки,СтавкаРоялтиВсех,СтавкаРоялтиНовых) | P10: =P8*IF('03_Сеть'!P7>=ДатаПереходаСтавки,СтавкаРоялтиВсех,СтавкаРоялтиНовых) | Q10: =Q8*IF('03_Сеть'!Q7>=ДатаПереходаСтавки,СтавкаРоялтиВсех,СтавкаРоялтиНовых) | R10: =R8*IF('03_Сеть'!R7>=ДатаПереходаСтавки,СтавкаРоялтиВсех,СтавкаРоялтиНовых) | S10: =S8*IF('03_Сеть'!S7>=ДатаПереходаСтавки,СтавкаРоялтиВсех,СтавкаРоялтиНовых) | ... BY10: =BY8*IF('03_Сеть'!BY7>=ДатаПереходаСтавки,СтавкаРоялтиВсех,СтавкаРоялтиНовых)
B12: Паушальные взносы
B13: Паушальные взносы, с НДС | C13: ₽ | D13: Продажи месяца по тарифу из справочника | E13: =SUM(L13:W13) | F13: =SUM(X13:AI13) | G13: =SUM(AJ13:AU13) | H13: =SUM(AV13:BG13) | I13: =SUM(BH13:BS13) | J13: =SUM(L13:BS13) | L13: ='03_Сеть'!L13*'07_Тарифы'!B$6 | M13: ='03_Сеть'!M13*'07_Тарифы'!C$6 | N13: ='03_Сеть'!N13*'07_Тарифы'!D$6 | O13: ='03_Сеть'!O13*'07_Тарифы'!E$6 | P13: ='03_Сеть'!P13*'07_Тарифы'!F$6 | Q13: ='03_Сеть'!Q13*'07_Тарифы'!G$6 | R13: ='03_Сеть'!R13*'07_Тарифы'!H$6 | S13: ='03_Сеть'!S13*'07_Тарифы'!I$6 | ... BY13: ='03_Сеть'!BY13*'07_Тарифы'!BO$6
B14: Паушальные взносы, без НДС | C14: ₽ | E14: =SUM(L14:W14) | F14: =SUM(X14:AI14) | G14: =SUM(AJ14:AU14) | H14: =SUM(AV14:BG14) | I14: =SUM(BH14:BS14) | J14: =SUM(L14:BS14) | L14: =L13/(1+НДС) | M14: =M13/(1+НДС) | N14: =N13/(1+НДС) | O14: =O13/(1+НДС) | P14: =P13/(1+НДС) | Q14: =Q13/(1+НДС) | R14: =R13/(1+НДС) | S14: =S13/(1+НДС) | ... BY14: =BY13/(1+НДС)
B16: Роялти действующей сети
B17: Роялти действующей сети, с НДС | C17: ₽ | D17: По каждой группе точек начисления: процент с выручки группы, но не меньше суммы фиксов этой группы. Профиль групп — раздел 16 вводных. | E17: =SUM(L17:W17) | F17: =SUM(X17:AI17) | G17: =SUM(AJ17:AU17) | H17: =SUM(AV17:BG17) | I17: =SUM(BH17:BS17) | J17: =SUM(L17:BS17) | L17: =SUMPRODUCT((ГруппыФикс*ГруппыТочек*IF(ШколыСтарт=0,0,'03_Сеть'!L18/ШколыСтарт)+('03_Сеть'!L20*'07_Тарифы'!B$8)*ГруппыДоля*(ГруппыСтавка*('03_Сеть'!L7<ДатаПереходаСтавки)+СтавкаРоялтиВсех*('03_Сеть'!L7>=ДатаПереходаСтавки))+ABS(ГруппыФикс*ГруппыТочек*IF(ШколыСтарт=0,0,'03_Сеть'!L18/ШколыСтарт)-('03_Сеть'!L20*'07_Тарифы'!B$8)*ГруппыДоля*(ГруппыСтавка*('03_Сеть'!L7<ДатаПереходаСтавки)+СтавкаРоялтиВсех*('03_Сеть'!L7>=ДатаПереходаСтавки))))/2) | M17: =SUMPRODUCT((ГруппыФикс*ГруппыТочек*IF(ШколыСтарт=0,0,'03_Сеть'!M18/ШколыСтарт)+('03_Сеть'!M20*'07_Тарифы'!C$8)*ГруппыДоля*(ГруппыСтавка*('03_Сеть'!M7<ДатаПереходаСтавки)+СтавкаРоялтиВсех*('03_Сеть'!M7>=ДатаПереходаСтавки))+ABS(ГруппыФикс*ГруппыТочек*IF(ШколыСтарт=0,0,'03_Сеть'!M18/ШколыСтарт)-('03_Сеть'!M20*'07_Тарифы'!C$8)*ГруппыДоля*(ГруппыСтавка*('03_Сеть'!M7<ДатаПереходаСтавки)+СтавкаРоялтиВсех*('03_Сеть'!M7>=ДатаПереходаСтавки))))/2) | N17: =SUMPRODUCT((ГруппыФикс*ГруппыТочек*IF(ШколыСтарт=0,0,'03_Сеть'!N18/ШколыСтарт)+('03_Сеть'!N20*'07_Тарифы'!D$8)*ГруппыДоля*(ГруппыСтавка*('03_Сеть'!N7<ДатаПереходаСтавки)+СтавкаРоялтиВсех*('03_Сеть'!N7>=ДатаПереходаСтавки))+ABS(ГруппыФикс*ГруппыТочек*IF(ШколыСтарт=0,0,'03_Сеть'!N18/ШколыСтарт)-('03_Сеть'!N20*'07_Тарифы'!D$8)*ГруппыДоля*(ГруппыСтавка*('03_Сеть'!N7<ДатаПереходаСтавки)+СтавкаРоялтиВсех*('03_Сеть'!N7>=ДатаПереходаСтавки))))/2) | O17: =SUMPRODUCT((ГруппыФикс*ГруппыТочек*IF(ШколыСтарт=0,0,'03_Сеть'!O18/ШколыСтарт)+('03_Сеть'!O20*'07_Тарифы'!E$8)*ГруппыДоля*(ГруппыСтавка*('03_Сеть'!O7<ДатаПереходаСтавки)+СтавкаРоялтиВсех*('03_Сеть'!O7>=ДатаПереходаСтавки))+ABS(ГруппыФикс*ГруппыТочек*IF(ШколыСтарт=0,0,'03_Сеть'!O18/ШколыСтарт)-('03_Сеть'!O20*'07_Тарифы'!E$8)*ГруппыДоля*(ГруппыСтавка*('03_Сеть'!O7<ДатаПереходаСтавки)+СтавкаРоялтиВсех*('03_Сеть'!O7>=ДатаПереходаСтавки))))/2) | P17: =SUMPRODUCT((ГруппыФикс*ГруппыТочек*IF(ШколыСтарт=0,0,'03_Сеть'!P18/ШколыСтарт)+('03_Сеть'!P20*'07_Тарифы'!F$8)*ГруппыДоля*(ГруппыСтавка*('03_Сеть'!P7<ДатаПереходаСтавки)+СтавкаРоялтиВсех*('03_Сеть'!P7>=ДатаПереходаСтавки))+ABS(ГруппыФикс*ГруппыТочек*IF(ШколыСтарт=0,0,'03_Сеть'!P18/ШколыСтарт)-('03_Сеть'!P20*'07_Тарифы'!F$8)*ГруппыДоля*(ГруппыСтавка*('03_Сеть'!P7<ДатаПереходаСтавки)+СтавкаРоялтиВсех*('03_Сеть'!P7>=ДатаПереходаСтавки))))/2) | Q17: =SUMPRODUCT((ГруппыФикс*ГруппыТочек*IF(ШколыСтарт=0,0,'03_Сеть'!Q18/ШколыСтарт)+('03_Сеть'!Q20*'07_Тарифы'!G$8)*ГруппыДоля*(ГруппыСтавка*('03_Сеть'!Q7<ДатаПереходаСтавки)+СтавкаРоялтиВсех*('03_Сеть'!Q7>=ДатаПереходаСтавки))+ABS(ГруппыФикс*ГруппыТочек*IF(ШколыСтарт=0,0,'03_Сеть'!Q18/ШколыСтарт)-('03_Сеть'!Q20*'07_Тарифы'!G$8)*ГруппыДоля*(ГруппыСтавка*('03_Сеть'!Q7<ДатаПереходаСтавки)+СтавкаРоялтиВсех*('03_Сеть'!Q7>=ДатаПереходаСтавки))))/2) | R17: =SUMPRODUCT((ГруппыФикс*ГруппыТочек*IF(ШколыСтарт=0,0,'03_Сеть'!R18/ШколыСтарт)+('03_Сеть'!R20*'07_Тарифы'!H$8)*ГруппыДоля*(ГруппыСтавка*('03_Сеть'!R7<ДатаПереходаСтавки)+СтавкаРоялтиВсех*('03_Сеть'!R7>=ДатаПереходаСтавки))+ABS(ГруппыФикс*ГруппыТочек*IF(ШколыСтарт=0,0,'03_Сеть'!R18/ШколыСтарт)-('03_Сеть'!R20*'07_Тарифы'!H$8)*ГруппыДоля*(ГруппыСтавка*('03_Сеть'!R7<ДатаПереходаСтавки)+СтавкаРоялтиВсех*('03_Сеть'!R7>=ДатаПереходаСтавки))))/2) | S17: =SUMPRODUCT((ГруппыФикс*ГруппыТочек*IF(ШколыСтарт=0,0,'03_Сеть'!S18/ШколыСтарт)+('03_Сеть'!S20*'07_Тарифы'!I$8)*ГруппыДоля*(ГруппыСтавка*('03_Сеть'!S7<ДатаПереходаСтавки)+СтавкаРоялтиВсех*('03_Сеть'!S7>=ДатаПереходаСтавки))+ABS(ГруппыФикс*ГруппыТочек*IF(ШколыСтарт=0,0,'03_Сеть'!S18/ШколыСтарт)-('03_Сеть'!S20*'07_Тарифы'!I$8)*ГруппыДоля*(ГруппыСтавка*('03_Сеть'!S7<ДатаПереходаСтавки)+СтавкаРоялтиВсех*('03_Сеть'!S7>=ДатаПереходаСтавки))))/2) | ... BY17: =SUMPRODUCT((ГруппыФикс*ГруппыТочек*IF(ШколыСтарт=0,0,'03_Сеть'!BY18/ШколыСтарт)+('03_Сеть'!BY20*'07_Тарифы'!BO$8)*ГруппыДоля*(ГруппыСтавка*('03_Сеть'!BY7<ДатаПереходаСтавки)+СтавкаРоялтиВсех*('03_Сеть'!BY7>=ДатаПереходаСтавки))+ABS(ГруппыФикс*ГруппыТочек*IF(ШколыСтарт=0,0,'03_Сеть'!BY18/ШколыСтарт)-('03_Сеть'!BY20*'07_Тарифы'!BO$8)*ГруппыДоля*(ГруппыСтавка*('03_Сеть'!BY7<ДатаПереходаСтавки)+СтавкаРоялтиВсех*('03_Сеть'!BY7>=ДатаПереходаСтавки))))/2)
B19: Школы по возрасту: договоры до перехода на новую ставку
B20: Открытия по старым договорам | C20: шт. | D20: Школа считается «старой», если франшизу купили до граничной даты | E20: =SUM(L20:W20) | F20: =SUM(X20:AI20) | G20: =SUM(AJ20:AU20) | H20: =SUM(AV20:BG20) | I20: =SUM(BH20:BS20) | J20: =SUM(L20:BS20) | L20: {=IF(1-ЛагОткрытия<1,0,IF(INDEX('03_Сеть'!$L7:$BY7,1,1-ЛагОткрытия)<=ДатаLegacy,'03_Сеть'!L14,0))} | M20: {=IF(2-ЛагОткрытия<1,0,IF(INDEX('03_Сеть'!$L7:$BY7,1,2-ЛагОткрытия)<=ДатаLegacy,'03_Сеть'!M14,0))} | N20: {=IF(3-ЛагОткрытия<1,0,IF(INDEX('03_Сеть'!$L7:$BY7,1,3-ЛагОткрытия)<=ДатаLegacy,'03_Сеть'!N14,0))} | O20: {=IF(4-ЛагОткрытия<1,0,IF(INDEX('03_Сеть'!$L7:$BY7,1,4-ЛагОткрытия)<=ДатаLegacy,'03_Сеть'!O14,0))} | P20: {=IF(5-ЛагОткрытия<1,0,IF(INDEX('03_Сеть'!$L7:$BY7,1,5-ЛагОткрытия)<=ДатаLegacy,'03_Сеть'!P14,0))} | Q20: {=IF(6-ЛагОткрытия<1,0,IF(INDEX('03_Сеть'!$L7:$BY7,1,6-ЛагОткрытия)<=ДатаLegacy,'03_Сеть'!Q14,0))} | R20: {=IF(7-ЛагОткрытия<1,0,IF(INDEX('03_Сеть'!$L7:$BY7,1,7-ЛагОткрытия)<=ДатаLegacy,'03_Сеть'!R14,0))} | S20: {=IF(8-ЛагОткрытия<1,0,IF(INDEX('03_Сеть'!$L7:$BY7,1,8-ЛагОткрытия)<=ДатаLegacy,'03_Сеть'!S14,0))} | T20: {=IF(9-ЛагОткрытия<1,0,IF(INDEX('03_Сеть'!$L7:$BY7,1,9-ЛагОткрытия)<=ДатаLegacy,'03_Сеть'!T14,0))} | U20: {=IF(10-ЛагОткрытия<1,0,IF(INDEX('03_Сеть'!$L7:$BY7,1,10-ЛагОткрытия)<=ДатаLegacy,'03_Сеть'!U14,0))} | V20: {=IF(11-ЛагОткрытия<1,0,IF(INDEX('03_Сеть'!$L7:$BY7,1,11-ЛагОткрытия)<=ДатаLegacy,'03_Сеть'!V14,0))} | W20: {=IF(12-ЛагОткрытия<1,0,IF(INDEX('03_Сеть'!$L7:$BY7,1,12-ЛагОткрытия)<=ДатаLegacy,'03_Сеть'!W14,0))} | X20: {=IF(13-ЛагОткрытия<1,0,IF(INDEX('03_Сеть'!$L7:$BY7,1,13-ЛагОткрытия)<=ДатаLegacy,'03_Сеть'!X14,0))} | Y20: {=IF(14-ЛагОткрытия<1,0,IF(INDEX('03_Сеть'!$L7:$BY7,1,14-ЛагОткрытия)<=ДатаLegacy,'03_Сеть'!Y14,0))} | Z20: {=IF(15-ЛагОткрытия<1,0,IF(INDEX('03_Сеть'!$L7:$BY7,1,15-ЛагОткрытия)<=ДатаLegacy,'03_Сеть'!Z14,0))} | AA20: {=IF(16-ЛагОткрытия<1,0,IF(INDEX('03_Сеть'!$L7:$BY7,1,16-ЛагОткрытия)<=ДатаLegacy,'03_Сеть'!AA14,0))} | AB20: {=IF(17-ЛагОткрытия<1,0,IF(INDEX('03_Сеть'!$L7:$BY7,1,17-ЛагОткрытия)<=ДатаLegacy,'03_Сеть'!AB14,0))} | AC20: {=IF(18-ЛагОткрытия<1,0,IF(INDEX('03_Сеть'!$L7:$BY7,1,18-ЛагОткрытия)<=ДатаLegacy,'03_Сеть'!AC14,0))} | AD20: {=IF(19-ЛагОткрытия<1,0,IF(INDEX('03_Сеть'!$L7:$BY7,1,19-ЛагОткрытия)<=ДатаLegacy,'03_Сеть'!AD14,0))} | AE20: {=IF(20-ЛагОткрытия<1,0,IF(INDEX('03_Сеть'!$L7:$BY7,1,20-ЛагОткрытия)<=ДатаLegacy,'03_Сеть'!AE14,0))} | AF20: {=IF(21-ЛагОткрытия<1,0,IF(INDEX('03_Сеть'!$L7:$BY7,1,21-ЛагОткрытия)<=ДатаLegacy,'03_Сеть'!AF14,0))} | AG20: {=IF(22-ЛагОткрытия<1,0,IF(INDEX('03_Сеть'!$L7:$BY7,1,22-ЛагОткрытия)<=ДатаLegacy,'03_Сеть'!AG14,0))} | AH20: {=IF(23-ЛагОткрытия<1,0,IF(INDEX('03_Сеть'!$L7:$BY7,1,23-ЛагОткрытия)<=ДатаLegacy,'03_Сеть'!AH14,0))} | AI20: {=IF(24-ЛагОткрытия<1,0,IF(INDEX('03_Сеть'!$L7:$BY7,1,24-ЛагОткрытия)<=ДатаLegacy,'03_Сеть'!AI14,0))} | AJ20: {=IF(25-ЛагОткрытия<1,0,IF(INDEX('03_Сеть'!$L7:$BY7,1,25-ЛагОткрытия)<=ДатаLegacy,'03_Сеть'!AJ14,0))} | AK20: {=IF(26-ЛагОткрытия<1,0,IF(INDEX('03_Сеть'!$L7:$BY7,1,26-ЛагОткрытия)<=ДатаLegacy,'03_Сеть'!AK14,0))} | AL20: {=IF(27-ЛагОткрытия<1,0,IF(INDEX('03_Сеть'!$L7:$BY7,1,27-ЛагОткрытия)<=ДатаLegacy,'03_Сеть'!AL14,0))} | AM20: {=IF(28-ЛагОткрытия<1,0,IF(INDEX('03_Сеть'!$L7:$BY7,1,28-ЛагОткрытия)<=ДатаLegacy,'03_Сеть'!AM14,0))} | AN20: {=IF(29-ЛагОткрытия<1,0,IF(INDEX('03_Сеть'!$L7:$BY7,1,29-ЛагОткрытия)<=ДатаLegacy,'03_Сеть'!AN14,0))} | AO20: {=IF(30-ЛагОткрытия<1,0,IF(INDEX('03_Сеть'!$L7:$BY7,1,30-ЛагОткрытия)<=ДатаLegacy,'03_Сеть'!AO14,0))} | AP20: {=IF(31-ЛагОткрытия<1,0,IF(INDEX('03_Сеть'!$L7:$BY7,1,31-ЛагОткрытия)<=ДатаLegacy,'03_Сеть'!AP14,0))} | AQ20: {=IF(32-ЛагОткрытия<1,0,IF(INDEX('03_Сеть'!$L7:$BY7,1,32-ЛагОткрытия)<=ДатаLegacy,'03_Сеть'!AQ14,0))} | AR20: {=IF(33-ЛагОткрытия<1,0,IF(INDEX('03_Сеть'!$L7:$BY7,1,33-ЛагОткрытия)<=ДатаLegacy,'03_Сеть'!AR14,0))} | AS20: {=IF(34-ЛагОткрытия<1,0,IF(INDEX('03_Сеть'!$L7:$BY7,1,34-ЛагОткрытия)<=ДатаLegacy,'03_Сеть'!AS14,0))} | AT20: {=IF(35-ЛагОткрытия<1,0,IF(INDEX('03_Сеть'!$L7:$BY7,1,35-ЛагОткрытия)<=ДатаLegacy,'03_Сеть'!AT14,0))} | AU20: {=IF(36-ЛагОткрытия<1,0,IF(INDEX('03_Сеть'!$L7:$BY7,1,36-ЛагОткрытия)<=ДатаLegacy,'03_Сеть'!AU14,0))} | AV20: {=IF(37-ЛагОткрытия<1,0,IF(INDEX('03_Сеть'!$L7:$BY7,1,37-ЛагОткрытия)<=ДатаLegacy,'03_Сеть'!AV14,0))} | AW20: {=IF(38-ЛагОткрытия<1,0,IF(INDEX('03_Сеть'!$L7:$BY7,1,38-ЛагОткрытия)<=ДатаLegacy,'03_Сеть'!AW14,0))} | AX20: {=IF(39-ЛагОткрытия<1,0,IF(INDEX('03_Сеть'!$L7:$BY7,1,39-ЛагОткрытия)<=ДатаLegacy,'03_Сеть'!AX14,0))} | AY20: {=IF(40-ЛагОткрытия<1,0,IF(INDEX('03_Сеть'!$L7:$BY7,1,40-ЛагОткрытия)<=ДатаLegacy,'03_Сеть'!AY14,0))} | AZ20: {=IF(41-ЛагОткрытия<1,0,IF(INDEX('03_Сеть'!$L7:$BY7,1,41-ЛагОткрытия)<=ДатаLegacy,'03_Сеть'!AZ14,0))} | BA20: {=IF(42-ЛагОткрытия<1,0,IF(INDEX('03_Сеть'!$L7:$BY7,1,42-ЛагОткрытия)<=ДатаLegacy,'03_Сеть'!BA14,0))} | BB20: {=IF(43-ЛагОткрытия<1,0,IF(INDEX('03_Сеть'!$L7:$BY7,1,43-ЛагОткрытия)<=ДатаLegacy,'03_Сеть'!BB14,0))} | BC20: {=IF(44-ЛагОткрытия<1,0,IF(INDEX('03_Сеть'!$L7:$BY7,1,44-ЛагОткрытия)<=ДатаLegacy,'03_Сеть'!BC14,0))} | BD20: {=IF(45-ЛагОткрытия<1,0,IF(INDEX('03_Сеть'!$L7:$BY7,1,45-ЛагОткрытия)<=ДатаLegacy,'03_Сеть'!BD14,0))} | BE20: {=IF(46-ЛагОткрытия<1,0,IF(INDEX('03_Сеть'!$L7:$BY7,1,46-ЛагОткрытия)<=ДатаLegacy,'03_Сеть'!BE14,0))} | BF20: {=IF(47-ЛагОткрытия<1,0,IF(INDEX('03_Сеть'!$L7:$BY7,1,47-ЛагОткрытия)<=ДатаLegacy,'03_Сеть'!BF14,0))} | BG20: {=IF(48-ЛагОткрытия<1,0,IF(INDEX('03_Сеть'!$L7:$BY7,1,48-ЛагОткрытия)<=ДатаLegacy,'03_Сеть'!BG14,0))} | BH20: {=IF(49-ЛагОткрытия<1,0,IF(INDEX('03_Сеть'!$L7:$BY7,1,49-ЛагОткрытия)<=ДатаLegacy,'03_Сеть'!BH14,0))} | BI20: {=IF(50-ЛагОткрытия<1,0,IF(INDEX('03_Сеть'!$L7:$BY7,1,50-ЛагОткрытия)<=ДатаLegacy,'03_Сеть'!BI14,0))} | BJ20: {=IF(51-ЛагОткрытия<1,0,IF(INDEX('03_Сеть'!$L7:$BY7,1,51-ЛагОткрытия)<=ДатаLegacy,'03_Сеть'!BJ14,0))} | BK20: {=IF(52-ЛагОткрытия<1,0,IF(INDEX('03_Сеть'!$L7:$BY7,1,52-ЛагОткрытия)<=ДатаLegacy,'03_Сеть'!BK14,0))} | BL20: {=IF(53-ЛагОткрытия<1,0,IF(INDEX('03_Сеть'!$L7:$BY7,1,53-ЛагОткрытия)<=ДатаLegacy,'03_Сеть'!BL14,0))} | BM20: {=IF(54-ЛагОткрытия<1,0,IF(INDEX('03_Сеть'!$L7:$BY7,1,54-ЛагОткрытия)<=ДатаLegacy,'03_Сеть'!BM14,0))} | BN20: {=IF(55-ЛагОткрытия<1,0,IF(INDEX('03_Сеть'!$L7:$BY7,1,55-ЛагОткрытия)<=ДатаLegacy,'03_Сеть'!BN14,0))} | BO20: {=IF(56-ЛагОткрытия<1,0,IF(INDEX('03_Сеть'!$L7:$BY7,1,56-ЛагОткрытия)<=ДатаLegacy,'03_Сеть'!BO14,0))} | BP20: {=IF(57-ЛагОткрытия<1,0,IF(INDEX('03_Сеть'!$L7:$BY7,1,57-ЛагОткрытия)<=ДатаLegacy,'03_Сеть'!BP14,0))} | BQ20: {=IF(58-ЛагОткрытия<1,0,IF(INDEX('03_Сеть'!$L7:$BY7,1,58-ЛагОткрытия)<=ДатаLegacy,'03_Сеть'!BQ14,0))} | BR20: {=IF(59-ЛагОткрытия<1,0,IF(INDEX('03_Сеть'!$L7:$BY7,1,59-ЛагОткрытия)<=ДатаLegacy,'03_Сеть'!BR14,0))} | BS20: {=IF(60-ЛагОткрытия<1,0,IF(INDEX('03_Сеть'!$L7:$BY7,1,60-ЛагОткрытия)<=ДатаLegacy,'03_Сеть'!BS14,0))} | BT20: {=IF(61-ЛагОткрытия<1,0,IF(INDEX('03_Сеть'!$L7:$BY7,1,61-ЛагОткрытия)<=ДатаLegacy,'03_Сеть'!BT14,0))} | BU20: {=IF(62-ЛагОткрытия<1,0,IF(INDEX('03_Сеть'!$L7:$BY7,1,62-ЛагОткрытия)<=ДатаLegacy,'03_Сеть'!BU14,0))} | BV20: {=IF(63-ЛагОткрытия<1,0,IF(INDEX('03_Сеть'!$L7:$BY7,1,63-ЛагОткрытия)<=ДатаLegacy,'03_Сеть'!BV14,0))} | BW20: {=IF(64-ЛагОткрытия<1,0,IF(INDEX('03_Сеть'!$L7:$BY7,1,64-ЛагОткрытия)<=ДатаLegacy,'03_Сеть'!BW14,0))} | BX20: {=IF(65-ЛагОткрытия<1,0,IF(INDEX('03_Сеть'!$L7:$BY7,1,65-ЛагОткрытия)<=ДатаLegacy,'03_Сеть'!BX14,0))} | BY20: {=IF(66-ЛагОткрытия<1,0,IF(INDEX('03_Сеть'!$L7:$BY7,1,66-ЛагОткрытия)<=ДатаLegacy,'03_Сеть'!BY14,0))}
B21: 1 мес. | C21: шт. | D21: В колонках лет — значение на конец года, в «Итого» — на конец пятого года. Это остаток, а не сумма. | E21: =W21 | F21: =AI21 | G21: =AU21 | H21: =BG21 | I21: =BS21 | J21: =BS21 | L21: =L20 | M21: =M20 | N21: =N20 | O21: =O20 | P21: =P20 | Q21: =Q20 | R21: =R20 | S21: =S20 | ... BY21: =BY20
B22: 2 мес. | C22: шт. | D22: В колонках лет — значение на конец года, в «Итого» — на конец пятого года. Это остаток, а не сумма. | E22: =W22 | F22: =AI22 | G22: =AU22 | H22: =BG22 | I22: =BS22 | J22: =BS22 | L22: =0 | M22: =L21*КоэффСохранения | N22: =M21*КоэффСохранения | O22: =N21*КоэффСохранения | P22: =O21*КоэффСохранения | Q22: =P21*КоэффСохранения | R22: =Q21*КоэффСохранения | S22: =R21*КоэффСохранения | T22: =S21*КоэффСохранения | ... BY22: =BX21*КоэффСохранения
B23: 3 мес. | C23: шт. | D23: В колонках лет — значение на конец года, в «Итого» — на конец пятого года. Это остаток, а не сумма. | E23: =W23 | F23: =AI23 | G23: =AU23 | H23: =BG23 | I23: =BS23 | J23: =BS23 | L23: =0 | M23: =L22*КоэффСохранения | N23: =M22*КоэффСохранения | O23: =N22*КоэффСохранения | P23: =O22*КоэффСохранения | Q23: =P22*КоэффСохранения | R23: =Q22*КоэффСохранения | S23: =R22*КоэффСохранения | T23: =S22*КоэффСохранения | ... BY23: =BX22*КоэффСохранения
B24: 4 мес. | C24: шт. | D24: В колонках лет — значение на конец года, в «Итого» — на конец пятого года. Это остаток, а не сумма. | E24: =W24 | F24: =AI24 | G24: =AU24 | H24: =BG24 | I24: =BS24 | J24: =BS24 | L24: =0 | M24: =L23*КоэффСохранения | N24: =M23*КоэффСохранения | O24: =N23*КоэффСохранения | P24: =O23*КоэффСохранения | Q24: =P23*КоэффСохранения | R24: =Q23*КоэффСохранения | S24: =R23*КоэффСохранения | T24: =S23*КоэффСохранения | ... BY24: =BX23*КоэффСохранения
B25: 5 мес. | C25: шт. | D25: В колонках лет — значение на конец года, в «Итого» — на конец пятого года. Это остаток, а не сумма. | E25: =W25 | F25: =AI25 | G25: =AU25 | H25: =BG25 | I25: =BS25 | J25: =BS25 | L25: =0 | M25: =L24*КоэффСохранения | N25: =M24*КоэффСохранения | O25: =N24*КоэффСохранения | P25: =O24*КоэффСохранения | Q25: =P24*КоэффСохранения | R25: =Q24*КоэффСохранения | S25: =R24*КоэффСохранения | T25: =S24*КоэффСохранения | ... BY25: =BX24*КоэффСохранения
B26: 6 мес. | C26: шт. | D26: В колонках лет — значение на конец года, в «Итого» — на конец пятого года. Это остаток, а не сумма. | E26: =W26 | F26: =AI26 | G26: =AU26 | H26: =BG26 | I26: =BS26 | J26: =BS26 | L26: =0 | M26: =L25*КоэффСохранения | N26: =M25*КоэффСохранения | O26: =N25*КоэффСохранения | P26: =O25*КоэффСохранения | Q26: =P25*КоэффСохранения | R26: =Q25*КоэффСохранения | S26: =R25*КоэффСохранения | T26: =S25*КоэффСохранения | ... BY26: =BX25*КоэффСохранения
B27: 7 мес. | C27: шт. | D27: В колонках лет — значение на конец года, в «Итого» — на конец пятого года. Это остаток, а не сумма. | E27: =W27 | F27: =AI27 | G27: =AU27 | H27: =BG27 | I27: =BS27 | J27: =BS27 | L27: =0 | M27: =L26*КоэффСохранения | N27: =M26*КоэффСохранения | O27: =N26*КоэффСохранения | P27: =O26*КоэффСохранения | Q27: =P26*КоэффСохранения | R27: =Q26*КоэффСохранения | S27: =R26*КоэффСохранения | T27: =S26*КоэффСохранения | ... BY27: =BX26*КоэффСохранения
B28: 8 мес. | C28: шт. | D28: В колонках лет — значение на конец года, в «Итого» — на конец пятого года. Это остаток, а не сумма. | E28: =W28 | F28: =AI28 | G28: =AU28 | H28: =BG28 | I28: =BS28 | J28: =BS28 | L28: =0 | M28: =L27*КоэффСохранения | N28: =M27*КоэффСохранения | O28: =N27*КоэффСохранения | P28: =O27*КоэффСохранения | Q28: =P27*КоэффСохранения | R28: =Q27*КоэффСохранения | S28: =R27*КоэффСохранения | T28: =S27*КоэффСохранения | ... BY28: =BX27*КоэффСохранения
B29: 9 мес. | C29: шт. | D29: В колонках лет — значение на конец года, в «Итого» — на конец пятого года. Это остаток, а не сумма. | E29: =W29 | F29: =AI29 | G29: =AU29 | H29: =BG29 | I29: =BS29 | J29: =BS29 | L29: =0 | M29: =L28*КоэффСохранения | N29: =M28*КоэффСохранения | O29: =N28*КоэффСохранения | P29: =O28*КоэффСохранения | Q29: =P28*КоэффСохранения | R29: =Q28*КоэффСохранения | S29: =R28*КоэффСохранения | T29: =S28*КоэффСохранения | ... BY29: =BX28*КоэффСохранения
B30: 10 мес. | C30: шт. | D30: В колонках лет — значение на конец года, в «Итого» — на конец пятого года. Это остаток, а не сумма. | E30: =W30 | F30: =AI30 | G30: =AU30 | H30: =BG30 | I30: =BS30 | J30: =BS30 | L30: =0 | M30: =L29*КоэффСохранения | N30: =M29*КоэффСохранения | O30: =N29*КоэффСохранения | P30: =O29*КоэффСохранения | Q30: =P29*КоэффСохранения | R30: =Q29*КоэффСохранения | S30: =R29*КоэффСохранения | T30: =S29*КоэффСохранения | ... BY30: =BX29*КоэффСохранения
B31: 11 мес. | C31: шт. | D31: В колонках лет — значение на конец года, в «Итого» — на конец пятого года. Это остаток, а не сумма. | E31: =W31 | F31: =AI31 | G31: =AU31 | H31: =BG31 | I31: =BS31 | J31: =BS31 | L31: =0 | M31: =L30*КоэффСохранения | N31: =M30*КоэффСохранения | O31: =N30*КоэффСохранения | P31: =O30*КоэффСохранения | Q31: =P30*КоэффСохранения | R31: =Q30*КоэффСохранения | S31: =R30*КоэффСохранения | T31: =S30*КоэффСохранения | ... BY31: =BX30*КоэффСохранения
B32: 12 мес. | C32: шт. | D32: В колонках лет — значение на конец года, в «Итого» — на конец пятого года. Это остаток, а не сумма. | E32: =W32 | F32: =AI32 | G32: =AU32 | H32: =BG32 | I32: =BS32 | J32: =BS32 | L32: =0 | M32: =L31*КоэффСохранения | N32: =M31*КоэффСохранения | O32: =N31*КоэффСохранения | P32: =O31*КоэффСохранения | Q32: =P31*КоэффСохранения | R32: =Q31*КоэффСохранения | S32: =R31*КоэффСохранения | T32: =S31*КоэффСохранения | ... BY32: =BX31*КоэффСохранения
B33: 13 мес. | C33: шт. | D33: В колонках лет — значение на конец года, в «Итого» — на конец пятого года. Это остаток, а не сумма. | E33: =W33 | F33: =AI33 | G33: =AU33 | H33: =BG33 | I33: =BS33 | J33: =BS33 | L33: =0 | M33: =L32*КоэффСохранения | N33: =M32*КоэффСохранения | O33: =N32*КоэффСохранения | P33: =O32*КоэффСохранения | Q33: =P32*КоэффСохранения | R33: =Q32*КоэффСохранения | S33: =R32*КоэффСохранения | T33: =S32*КоэффСохранения | ... BY33: =BX32*КоэффСохранения
... B44: 24 мес. | C44: шт. | D44: В колонках лет — значение на конец года, в «Итого» — на конец пятого года. Это остаток, а не сумма. | E44: =W44 | F44: =AI44 | G44: =AU44 | H44: =BG44 | I44: =BS44 | J44: =BS44 | L44: =0 | M44: =L43*КоэффСохранения | N44: =M43*КоэффСохранения | O44: =N43*КоэффСохранения | P44: =O43*КоэффСохранения | Q44: =P43*КоэффСохранения | R44: =Q43*КоэффСохранения | S44: =R43*КоэффСохранения | T44: =S43*КоэффСохранения | ... BY44: =BX43*КоэффСохранения
B45: 25+ мес. | C45: шт. | D45: В колонках лет — значение на конец года, в «Итого» — на конец пятого года. Это остаток, а не сумма. | E45: =W45 | F45: =AI45 | G45: =AU45 | H45: =BG45 | I45: =BS45 | J45: =BS45 | L45: =0 | M45: =(L44+L45)*КоэффСохранения | N45: =(M44+M45)*КоэффСохранения | O45: =(N44+N45)*КоэффСохранения | P45: =(O44+O45)*КоэффСохранения | Q45: =(P44+P45)*КоэффСохранения | R45: =(Q44+Q45)*КоэффСохранения | S45: =(R44+R45)*КоэффСохранения | T45: =(S44+S45)*КоэффСохранения | ... BY45: =(BX44+BX45)*КоэффСохранения
B47: Роялти новых школ по возрасту — старая ставка
B48: 1 мес. | C48: ₽ | E48: =SUM(L48:W48) | F48: =SUM(X48:AI48) | G48: =SUM(AJ48:AU48) | H48: =SUM(AV48:BG48) | I48: =SUM(BH48:BS48) | J48: =SUM(L48:BS48) | L48: =IF(OR(L21=0,1<=КаникулыРоялти),0,L21*IF(РоялтиПоГруппам="Да",MeanMinAge01+L9*SUMIF(ThresholdAge01,"<"&L9,WeightedRevAge01)-SUMIF(ThresholdAge01,"<"&L9,WeightedMinAge01),MAX(CapacityAge01*АбонементНовых*L9,MeanMinAge01))) | M48: =IF(OR(M21=0,1<=КаникулыРоялти),0,M21*IF(РоялтиПоГруппам="Да",MeanMinAge01+M9*SUMIF(ThresholdAge01,"<"&M9,WeightedRevAge01)-SUMIF(ThresholdAge01,"<"&M9,WeightedMinAge01),MAX(CapacityAge01*АбонементНовых*M9,MeanMinAge01))) | N48: =IF(OR(N21=0,1<=КаникулыРоялти),0,N21*IF(РоялтиПоГруппам="Да",MeanMinAge01+N9*SUMIF(ThresholdAge01,"<"&N9,WeightedRevAge01)-SUMIF(ThresholdAge01,"<"&N9,WeightedMinAge01),MAX(CapacityAge01*АбонементНовых*N9,MeanMinAge01))) | O48: =IF(OR(O21=0,1<=КаникулыРоялти),0,O21*IF(РоялтиПоГруппам="Да",MeanMinAge01+O9*SUMIF(ThresholdAge01,"<"&O9,WeightedRevAge01)-SUMIF(ThresholdAge01,"<"&O9,WeightedMinAge01),MAX(CapacityAge01*АбонементНовых*O9,MeanMinAge01))) | P48: =IF(OR(P21=0,1<=КаникулыРоялти),0,P21*IF(РоялтиПоГруппам="Да",MeanMinAge01+P9*SUMIF(ThresholdAge01,"<"&P9,WeightedRevAge01)-SUMIF(ThresholdAge01,"<"&P9,WeightedMinAge01),MAX(CapacityAge01*АбонементНовых*P9,MeanMinAge01))) | Q48: =IF(OR(Q21=0,1<=КаникулыРоялти),0,Q21*IF(РоялтиПоГруппам="Да",MeanMinAge01+Q9*SUMIF(ThresholdAge01,"<"&Q9,WeightedRevAge01)-SUMIF(ThresholdAge01,"<"&Q9,WeightedMinAge01),MAX(CapacityAge01*АбонементНовых*Q9,MeanMinAge01))) | R48: =IF(OR(R21=0,1<=КаникулыРоялти),0,R21*IF(РоялтиПоГруппам="Да",MeanMinAge01+R9*SUMIF(ThresholdAge01,"<"&R9,WeightedRevAge01)-SUMIF(ThresholdAge01,"<"&R9,WeightedMinAge01),MAX(CapacityAge01*АбонементНовых*R9,MeanMinAge01))) | S48: =IF(OR(S21=0,1<=КаникулыРоялти),0,S21*IF(РоялтиПоГруппам="Да",MeanMinAge01+S9*SUMIF(ThresholdAge01,"<"&S9,WeightedRevAge01)-SUMIF(ThresholdAge01,"<"&S9,WeightedMinAge01),MAX(CapacityAge01*АбонементНовых*S9,MeanMinAge01))) | ... BY48: =IF(OR(BY21=0,1<=КаникулыРоялти),0,BY21*IF(РоялтиПоГруппам="Да",MeanMinAge01+BY9*SUMIF(ThresholdAge01,"<"&BY9,WeightedRevAge01)-SUMIF(ThresholdAge01,"<"&BY9,WeightedMinAge01),MAX(CapacityAge01*АбонементНовых*BY9,MeanMinAge01)))
B49: 2 мес. | C49: ₽ | E49: =SUM(L49:W49) | F49: =SUM(X49:AI49) | G49: =SUM(AJ49:AU49) | H49: =SUM(AV49:BG49) | I49: =SUM(BH49:BS49) | J49: =SUM(L49:BS49) | L49: =IF(OR(L22=0,2<=КаникулыРоялти),0,L22*IF(РоялтиПоГруппам="Да",MeanMinAge02+L9*SUMIF(ThresholdAge02,"<"&L9,WeightedRevAge02)-SUMIF(ThresholdAge02,"<"&L9,WeightedMinAge02),MAX(CapacityAge02*АбонементНовых*L9,MeanMinAge02))) | M49: =IF(OR(M22=0,2<=КаникулыРоялти),0,M22*IF(РоялтиПоГруппам="Да",MeanMinAge02+M9*SUMIF(ThresholdAge02,"<"&M9,WeightedRevAge02)-SUMIF(ThresholdAge02,"<"&M9,WeightedMinAge02),MAX(CapacityAge02*АбонементНовых*M9,MeanMinAge02))) | N49: =IF(OR(N22=0,2<=КаникулыРоялти),0,N22*IF(РоялтиПоГруппам="Да",MeanMinAge02+N9*SUMIF(ThresholdAge02,"<"&N9,WeightedRevAge02)-SUMIF(ThresholdAge02,"<"&N9,WeightedMinAge02),MAX(CapacityAge02*АбонементНовых*N9,MeanMinAge02))) | O49: =IF(OR(O22=0,2<=КаникулыРоялти),0,O22*IF(РоялтиПоГруппам="Да",MeanMinAge02+O9*SUMIF(ThresholdAge02,"<"&O9,WeightedRevAge02)-SUMIF(ThresholdAge02,"<"&O9,WeightedMinAge02),MAX(CapacityAge02*АбонементНовых*O9,MeanMinAge02))) | P49: =IF(OR(P22=0,2<=КаникулыРоялти),0,P22*IF(РоялтиПоГруппам="Да",MeanMinAge02+P9*SUMIF(ThresholdAge02,"<"&P9,WeightedRevAge02)-SUMIF(ThresholdAge02,"<"&P9,WeightedMinAge02),MAX(CapacityAge02*АбонементНовых*P9,MeanMinAge02))) | Q49: =IF(OR(Q22=0,2<=КаникулыРоялти),0,Q22*IF(РоялтиПоГруппам="Да",MeanMinAge02+Q9*SUMIF(ThresholdAge02,"<"&Q9,WeightedRevAge02)-SUMIF(ThresholdAge02,"<"&Q9,WeightedMinAge02),MAX(CapacityAge02*АбонементНовых*Q9,MeanMinAge02))) | R49: =IF(OR(R22=0,2<=КаникулыРоялти),0,R22*IF(РоялтиПоГруппам="Да",MeanMinAge02+R9*SUMIF(ThresholdAge02,"<"&R9,WeightedRevAge02)-SUMIF(ThresholdAge02,"<"&R9,WeightedMinAge02),MAX(CapacityAge02*АбонементНовых*R9,MeanMinAge02))) | S49: =IF(OR(S22=0,2<=КаникулыРоялти),0,S22*IF(РоялтиПоГруппам="Да",MeanMinAge02+S9*SUMIF(ThresholdAge02,"<"&S9,WeightedRevAge02)-SUMIF(ThresholdAge02,"<"&S9,WeightedMinAge02),MAX(CapacityAge02*АбонементНовых*S9,MeanMinAge02))) | ... BY49: =IF(OR(BY22=0,2<=КаникулыРоялти),0,BY22*IF(РоялтиПоГруппам="Да",MeanMinAge02+BY9*SUMIF(ThresholdAge02,"<"&BY9,WeightedRevAge02)-SUMIF(ThresholdAge02,"<"&BY9,WeightedMinAge02),MAX(CapacityAge02*АбонементНовых*BY9,MeanMinAge02)))
B50: 3 мес. | C50: ₽ | E50: =SUM(L50:W50) | F50: =SUM(X50:AI50) | G50: =SUM(AJ50:AU50) | H50: =SUM(AV50:BG50) | I50: =SUM(BH50:BS50) | J50: =SUM(L50:BS50) | L50: =IF(OR(L23=0,3<=КаникулыРоялти),0,L23*IF(РоялтиПоГруппам="Да",MeanMinAge03+L9*SUMIF(ThresholdAge03,"<"&L9,WeightedRevAge03)-SUMIF(ThresholdAge03,"<"&L9,WeightedMinAge03),MAX(CapacityAge03*АбонементНовых*L9,MeanMinAge03))) | M50: =IF(OR(M23=0,3<=КаникулыРоялти),0,M23*IF(РоялтиПоГруппам="Да",MeanMinAge03+M9*SUMIF(ThresholdAge03,"<"&M9,WeightedRevAge03)-SUMIF(ThresholdAge03,"<"&M9,WeightedMinAge03),MAX(CapacityAge03*АбонементНовых*M9,MeanMinAge03))) | N50: =IF(OR(N23=0,3<=КаникулыРоялти),0,N23*IF(РоялтиПоГруппам="Да",MeanMinAge03+N9*SUMIF(ThresholdAge03,"<"&N9,WeightedRevAge03)-SUMIF(ThresholdAge03,"<"&N9,WeightedMinAge03),MAX(CapacityAge03*АбонементНовых*N9,MeanMinAge03))) | O50: =IF(OR(O23=0,3<=КаникулыРоялти),0,O23*IF(РоялтиПоГруппам="Да",MeanMinAge03+O9*SUMIF(ThresholdAge03,"<"&O9,WeightedRevAge03)-SUMIF(ThresholdAge03,"<"&O9,WeightedMinAge03),MAX(CapacityAge03*АбонементНовых*O9,MeanMinAge03))) | P50: =IF(OR(P23=0,3<=КаникулыРоялти),0,P23*IF(РоялтиПоГруппам="Да",MeanMinAge03+P9*SUMIF(ThresholdAge03,"<"&P9,WeightedRevAge03)-SUMIF(ThresholdAge03,"<"&P9,WeightedMinAge03),MAX(CapacityAge03*АбонементНовых*P9,MeanMinAge03))) | Q50: =IF(OR(Q23=0,3<=КаникулыРоялти),0,Q23*IF(РоялтиПоГруппам="Да",MeanMinAge03+Q9*SUMIF(ThresholdAge03,"<"&Q9,WeightedRevAge03)-SUMIF(ThresholdAge03,"<"&Q9,WeightedMinAge03),MAX(CapacityAge03*АбонементНовых*Q9,MeanMinAge03))) | R50: =IF(OR(R23=0,3<=КаникулыРоялти),0,R23*IF(РоялтиПоГруппам="Да",MeanMinAge03+R9*SUMIF(ThresholdAge03,"<"&R9,WeightedRevAge03)-SUMIF(ThresholdAge03,"<"&R9,WeightedMinAge03),MAX(CapacityAge03*АбонементНовых*R9,MeanMinAge03))) | S50: =IF(OR(S23=0,3<=КаникулыРоялти),0,S23*IF(РоялтиПоГруппам="Да",MeanMinAge03+S9*SUMIF(ThresholdAge03,"<"&S9,WeightedRevAge03)-SUMIF(ThresholdAge03,"<"&S9,WeightedMinAge03),MAX(CapacityAge03*АбонементНовых*S9,MeanMinAge03))) | ... BY50: =IF(OR(BY23=0,3<=КаникулыРоялти),0,BY23*IF(РоялтиПоГруппам="Да",MeanMinAge03+BY9*SUMIF(ThresholdAge03,"<"&BY9,WeightedRevAge03)-SUMIF(ThresholdAge03,"<"&BY9,WeightedMinAge03),MAX(CapacityAge03*АбонементНовых*BY9,MeanMinAge03)))
B51: 4 мес. | C51: ₽ | E51: =SUM(L51:W51) | F51: =SUM(X51:AI51) | G51: =SUM(AJ51:AU51) | H51: =SUM(AV51:BG51) | I51: =SUM(BH51:BS51) | J51: =SUM(L51:BS51) | L51: =IF(OR(L24=0,4<=КаникулыРоялти),0,L24*IF(РоялтиПоГруппам="Да",MeanMinAge04+L9*SUMIF(ThresholdAge04,"<"&L9,WeightedRevAge04)-SUMIF(ThresholdAge04,"<"&L9,WeightedMinAge04),MAX(CapacityAge04*АбонементНовых*L9,MeanMinAge04))) | M51: =IF(OR(M24=0,4<=КаникулыРоялти),0,M24*IF(РоялтиПоГруппам="Да",MeanMinAge04+M9*SUMIF(ThresholdAge04,"<"&M9,WeightedRevAge04)-SUMIF(ThresholdAge04,"<"&M9,WeightedMinAge04),MAX(CapacityAge04*АбонементНовых*M9,MeanMinAge04))) | N51: =IF(OR(N24=0,4<=КаникулыРоялти),0,N24*IF(РоялтиПоГруппам="Да",MeanMinAge04+N9*SUMIF(ThresholdAge04,"<"&N9,WeightedRevAge04)-SUMIF(ThresholdAge04,"<"&N9,WeightedMinAge04),MAX(CapacityAge04*АбонементНовых*N9,MeanMinAge04))) | O51: =IF(OR(O24=0,4<=КаникулыРоялти),0,O24*IF(РоялтиПоГруппам="Да",MeanMinAge04+O9*SUMIF(ThresholdAge04,"<"&O9,WeightedRevAge04)-SUMIF(ThresholdAge04,"<"&O9,WeightedMinAge04),MAX(CapacityAge04*АбонементНовых*O9,MeanMinAge04))) | P51: =IF(OR(P24=0,4<=КаникулыРоялти),0,P24*IF(РоялтиПоГруппам="Да",MeanMinAge04+P9*SUMIF(ThresholdAge04,"<"&P9,WeightedRevAge04)-SUMIF(ThresholdAge04,"<"&P9,WeightedMinAge04),MAX(CapacityAge04*АбонементНовых*P9,MeanMinAge04))) | Q51: =IF(OR(Q24=0,4<=КаникулыРоялти),0,Q24*IF(РоялтиПоГруппам="Да",MeanMinAge04+Q9*SUMIF(ThresholdAge04,"<"&Q9,WeightedRevAge04)-SUMIF(ThresholdAge04,"<"&Q9,WeightedMinAge04),MAX(CapacityAge04*АбонементНовых*Q9,MeanMinAge04))) | R51: =IF(OR(R24=0,4<=КаникулыРоялти),0,R24*IF(РоялтиПоГруппам="Да",MeanMinAge04+R9*SUMIF(ThresholdAge04,"<"&R9,WeightedRevAge04)-SUMIF(ThresholdAge04,"<"&R9,WeightedMinAge04),MAX(CapacityAge04*АбонементНовых*R9,MeanMinAge04))) | S51: =IF(OR(S24=0,4<=КаникулыРоялти),0,S24*IF(РоялтиПоГруппам="Да",MeanMinAge04+S9*SUMIF(ThresholdAge04,"<"&S9,WeightedRevAge04)-SUMIF(ThresholdAge04,"<"&S9,WeightedMinAge04),MAX(CapacityAge04*АбонементНовых*S9,MeanMinAge04))) | ... BY51: =IF(OR(BY24=0,4<=КаникулыРоялти),0,BY24*IF(РоялтиПоГруппам="Да",MeanMinAge04+BY9*SUMIF(ThresholdAge04,"<"&BY9,WeightedRevAge04)-SUMIF(ThresholdAge04,"<"&BY9,WeightedMinAge04),MAX(CapacityAge04*АбонементНовых*BY9,MeanMinAge04)))
B52: 5 мес. | C52: ₽ | E52: =SUM(L52:W52) | F52: =SUM(X52:AI52) | G52: =SUM(AJ52:AU52) | H52: =SUM(AV52:BG52) | I52: =SUM(BH52:BS52) | J52: =SUM(L52:BS52) | L52: =IF(OR(L25=0,5<=КаникулыРоялти),0,L25*IF(РоялтиПоГруппам="Да",MeanMinAge05+L9*SUMIF(ThresholdAge05,"<"&L9,WeightedRevAge05)-SUMIF(ThresholdAge05,"<"&L9,WeightedMinAge05),MAX(CapacityAge05*АбонементНовых*L9,MeanMinAge05))) | M52: =IF(OR(M25=0,5<=КаникулыРоялти),0,M25*IF(РоялтиПоГруппам="Да",MeanMinAge05+M9*SUMIF(ThresholdAge05,"<"&M9,WeightedRevAge05)-SUMIF(ThresholdAge05,"<"&M9,WeightedMinAge05),MAX(CapacityAge05*АбонементНовых*M9,MeanMinAge05))) | N52: =IF(OR(N25=0,5<=КаникулыРоялти),0,N25*IF(РоялтиПоГруппам="Да",MeanMinAge05+N9*SUMIF(ThresholdAge05,"<"&N9,WeightedRevAge05)-SUMIF(ThresholdAge05,"<"&N9,WeightedMinAge05),MAX(CapacityAge05*АбонементНовых*N9,MeanMinAge05))) | O52: =IF(OR(O25=0,5<=КаникулыРоялти),0,O25*IF(РоялтиПоГруппам="Да",MeanMinAge05+O9*SUMIF(ThresholdAge05,"<"&O9,WeightedRevAge05)-SUMIF(ThresholdAge05,"<"&O9,WeightedMinAge05),MAX(CapacityAge05*АбонементНовых*O9,MeanMinAge05))) | P52: =IF(OR(P25=0,5<=КаникулыРоялти),0,P25*IF(РоялтиПоГруппам="Да",MeanMinAge05+P9*SUMIF(ThresholdAge05,"<"&P9,WeightedRevAge05)-SUMIF(ThresholdAge05,"<"&P9,WeightedMinAge05),MAX(CapacityAge05*АбонементНовых*P9,MeanMinAge05))) | Q52: =IF(OR(Q25=0,5<=КаникулыРоялти),0,Q25*IF(РоялтиПоГруппам="Да",MeanMinAge05+Q9*SUMIF(ThresholdAge05,"<"&Q9,WeightedRevAge05)-SUMIF(ThresholdAge05,"<"&Q9,WeightedMinAge05),MAX(CapacityAge05*АбонементНовых*Q9,MeanMinAge05))) | R52: =IF(OR(R25=0,5<=КаникулыРоялти),0,R25*IF(РоялтиПоГруппам="Да",MeanMinAge05+R9*SUMIF(ThresholdAge05,"<"&R9,WeightedRevAge05)-SUMIF(ThresholdAge05,"<"&R9,WeightedMinAge05),MAX(CapacityAge05*АбонементНовых*R9,MeanMinAge05))) | S52: =IF(OR(S25=0,5<=КаникулыРоялти),0,S25*IF(РоялтиПоГруппам="Да",MeanMinAge05+S9*SUMIF(ThresholdAge05,"<"&S9,WeightedRevAge05)-SUMIF(ThresholdAge05,"<"&S9,WeightedMinAge05),MAX(CapacityAge05*АбонементНовых*S9,MeanMinAge05))) | ... BY52: =IF(OR(BY25=0,5<=КаникулыРоялти),0,BY25*IF(РоялтиПоГруппам="Да",MeanMinAge05+BY9*SUMIF(ThresholdAge05,"<"&BY9,WeightedRevAge05)-SUMIF(ThresholdAge05,"<"&BY9,WeightedMinAge05),MAX(CapacityAge05*АбонементНовых*BY9,MeanMinAge05)))
B53: 6 мес. | C53: ₽ | E53: =SUM(L53:W53) | F53: =SUM(X53:AI53) | G53: =SUM(AJ53:AU53) | H53: =SUM(AV53:BG53) | I53: =SUM(BH53:BS53) | J53: =SUM(L53:BS53) | L53: =IF(OR(L26=0,6<=КаникулыРоялти),0,L26*IF(РоялтиПоГруппам="Да",MeanMinAge06+L9*SUMIF(ThresholdAge06,"<"&L9,WeightedRevAge06)-SUMIF(ThresholdAge06,"<"&L9,WeightedMinAge06),MAX(CapacityAge06*АбонементНовых*L9,MeanMinAge06))) | M53: =IF(OR(M26=0,6<=КаникулыРоялти),0,M26*IF(РоялтиПоГруппам="Да",MeanMinAge06+M9*SUMIF(ThresholdAge06,"<"&M9,WeightedRevAge06)-SUMIF(ThresholdAge06,"<"&M9,WeightedMinAge06),MAX(CapacityAge06*АбонементНовых*M9,MeanMinAge06))) | N53: =IF(OR(N26=0,6<=КаникулыРоялти),0,N26*IF(РоялтиПоГруппам="Да",MeanMinAge06+N9*SUMIF(ThresholdAge06,"<"&N9,WeightedRevAge06)-SUMIF(ThresholdAge06,"<"&N9,WeightedMinAge06),MAX(CapacityAge06*АбонементНовых*N9,MeanMinAge06))) | O53: =IF(OR(O26=0,6<=КаникулыРоялти),0,O26*IF(РоялтиПоГруппам="Да",MeanMinAge06+O9*SUMIF(ThresholdAge06,"<"&O9,WeightedRevAge06)-SUMIF(ThresholdAge06,"<"&O9,WeightedMinAge06),MAX(CapacityAge06*АбонементНовых*O9,MeanMinAge06))) | P53: =IF(OR(P26=0,6<=КаникулыРоялти),0,P26*IF(РоялтиПоГруппам="Да",MeanMinAge06+P9*SUMIF(ThresholdAge06,"<"&P9,WeightedRevAge06)-SUMIF(ThresholdAge06,"<"&P9,WeightedMinAge06),MAX(CapacityAge06*АбонементНовых*P9,MeanMinAge06))) | Q53: =IF(OR(Q26=0,6<=КаникулыРоялти),0,Q26*IF(РоялтиПоГруппам="Да",MeanMinAge06+Q9*SUMIF(ThresholdAge06,"<"&Q9,WeightedRevAge06)-SUMIF(ThresholdAge06,"<"&Q9,WeightedMinAge06),MAX(CapacityAge06*АбонементНовых*Q9,MeanMinAge06))) | R53: =IF(OR(R26=0,6<=КаникулыРоялти),0,R26*IF(РоялтиПоГруппам="Да",MeanMinAge06+R9*SUMIF(ThresholdAge06,"<"&R9,WeightedRevAge06)-SUMIF(ThresholdAge06,"<"&R9,WeightedMinAge06),MAX(CapacityAge06*АбонементНовых*R9,MeanMinAge06))) | S53: =IF(OR(S26=0,6<=КаникулыРоялти),0,S26*IF(РоялтиПоГруппам="Да",MeanMinAge06+S9*SUMIF(ThresholdAge06,"<"&S9,WeightedRevAge06)-SUMIF(ThresholdAge06,"<"&S9,WeightedMinAge06),MAX(CapacityAge06*АбонементНовых*S9,MeanMinAge06))) | ... BY53: =IF(OR(BY26=0,6<=КаникулыРоялти),0,BY26*IF(РоялтиПоГруппам="Да",MeanMinAge06+BY9*SUMIF(ThresholdAge06,"<"&BY9,WeightedRevAge06)-SUMIF(ThresholdAge06,"<"&BY9,WeightedMinAge06),MAX(CapacityAge06*АбонементНовых*BY9,MeanMinAge06)))
B54: 7 мес. | C54: ₽ | E54: =SUM(L54:W54) | F54: =SUM(X54:AI54) | G54: =SUM(AJ54:AU54) | H54: =SUM(AV54:BG54) | I54: =SUM(BH54:BS54) | J54: =SUM(L54:BS54) | L54: =IF(OR(L27=0,7<=КаникулыРоялти),0,L27*IF(РоялтиПоГруппам="Да",MeanMinAge07+L9*SUMIF(ThresholdAge07,"<"&L9,WeightedRevAge07)-SUMIF(ThresholdAge07,"<"&L9,WeightedMinAge07),MAX(CapacityAge07*АбонементНовых*L9,MeanMinAge07))) | M54: =IF(OR(M27=0,7<=КаникулыРоялти),0,M27*IF(РоялтиПоГруппам="Да",MeanMinAge07+M9*SUMIF(ThresholdAge07,"<"&M9,WeightedRevAge07)-SUMIF(ThresholdAge07,"<"&M9,WeightedMinAge07),MAX(CapacityAge07*АбонементНовых*M9,MeanMinAge07))) | N54: =IF(OR(N27=0,7<=КаникулыРоялти),0,N27*IF(РоялтиПоГруппам="Да",MeanMinAge07+N9*SUMIF(ThresholdAge07,"<"&N9,WeightedRevAge07)-SUMIF(ThresholdAge07,"<"&N9,WeightedMinAge07),MAX(CapacityAge07*АбонементНовых*N9,MeanMinAge07))) | O54: =IF(OR(O27=0,7<=КаникулыРоялти),0,O27*IF(РоялтиПоГруппам="Да",MeanMinAge07+O9*SUMIF(ThresholdAge07,"<"&O9,WeightedRevAge07)-SUMIF(ThresholdAge07,"<"&O9,WeightedMinAge07),MAX(CapacityAge07*АбонементНовых*O9,MeanMinAge07))) | P54: =IF(OR(P27=0,7<=КаникулыРоялти),0,P27*IF(РоялтиПоГруппам="Да",MeanMinAge07+P9*SUMIF(ThresholdAge07,"<"&P9,WeightedRevAge07)-SUMIF(ThresholdAge07,"<"&P9,WeightedMinAge07),MAX(CapacityAge07*АбонементНовых*P9,MeanMinAge07))) | Q54: =IF(OR(Q27=0,7<=КаникулыРоялти),0,Q27*IF(РоялтиПоГруппам="Да",MeanMinAge07+Q9*SUMIF(ThresholdAge07,"<"&Q9,WeightedRevAge07)-SUMIF(ThresholdAge07,"<"&Q9,WeightedMinAge07),MAX(CapacityAge07*АбонементНовых*Q9,MeanMinAge07))) | R54: =IF(OR(R27=0,7<=КаникулыРоялти),0,R27*IF(РоялтиПоГруппам="Да",MeanMinAge07+R9*SUMIF(ThresholdAge07,"<"&R9,WeightedRevAge07)-SUMIF(ThresholdAge07,"<"&R9,WeightedMinAge07),MAX(CapacityAge07*АбонементНовых*R9,MeanMinAge07))) | S54: =IF(OR(S27=0,7<=КаникулыРоялти),0,S27*IF(РоялтиПоГруппам="Да",MeanMinAge07+S9*SUMIF(ThresholdAge07,"<"&S9,WeightedRevAge07)-SUMIF(ThresholdAge07,"<"&S9,WeightedMinAge07),MAX(CapacityAge07*АбонементНовых*S9,MeanMinAge07))) | ... BY54: =IF(OR(BY27=0,7<=КаникулыРоялти),0,BY27*IF(РоялтиПоГруппам="Да",MeanMinAge07+BY9*SUMIF(ThresholdAge07,"<"&BY9,WeightedRevAge07)-SUMIF(ThresholdAge07,"<"&BY9,WeightedMinAge07),MAX(CapacityAge07*АбонементНовых*BY9,MeanMinAge07)))
B55: 8 мес. | C55: ₽ | E55: =SUM(L55:W55) | F55: =SUM(X55:AI55) | G55: =SUM(AJ55:AU55) | H55: =SUM(AV55:BG55) | I55: =SUM(BH55:BS55) | J55: =SUM(L55:BS55) | L55: =IF(OR(L28=0,8<=КаникулыРоялти),0,L28*IF(РоялтиПоГруппам="Да",MeanMinAge08+L9*SUMIF(ThresholdAge08,"<"&L9,WeightedRevAge08)-SUMIF(ThresholdAge08,"<"&L9,WeightedMinAge08),MAX(CapacityAge08*АбонементНовых*L9,MeanMinAge08))) | M55: =IF(OR(M28=0,8<=КаникулыРоялти),0,M28*IF(РоялтиПоГруппам="Да",MeanMinAge08+M9*SUMIF(ThresholdAge08,"<"&M9,WeightedRevAge08)-SUMIF(ThresholdAge08,"<"&M9,WeightedMinAge08),MAX(CapacityAge08*АбонементНовых*M9,MeanMinAge08))) | N55: =IF(OR(N28=0,8<=КаникулыРоялти),0,N28*IF(РоялтиПоГруппам="Да",MeanMinAge08+N9*SUMIF(ThresholdAge08,"<"&N9,WeightedRevAge08)-SUMIF(ThresholdAge08,"<"&N9,WeightedMinAge08),MAX(CapacityAge08*АбонементНовых*N9,MeanMinAge08))) | O55: =IF(OR(O28=0,8<=КаникулыРоялти),0,O28*IF(РоялтиПоГруппам="Да",MeanMinAge08+O9*SUMIF(ThresholdAge08,"<"&O9,WeightedRevAge08)-SUMIF(ThresholdAge08,"<"&O9,WeightedMinAge08),MAX(CapacityAge08*АбонементНовых*O9,MeanMinAge08))) | P55: =IF(OR(P28=0,8<=КаникулыРоялти),0,P28*IF(РоялтиПоГруппам="Да",MeanMinAge08+P9*SUMIF(ThresholdAge08,"<"&P9,WeightedRevAge08)-SUMIF(ThresholdAge08,"<"&P9,WeightedMinAge08),MAX(CapacityAge08*АбонементНовых*P9,MeanMinAge08))) | Q55: =IF(OR(Q28=0,8<=КаникулыРоялти),0,Q28*IF(РоялтиПоГруппам="Да",MeanMinAge08+Q9*SUMIF(ThresholdAge08,"<"&Q9,WeightedRevAge08)-SUMIF(ThresholdAge08,"<"&Q9,WeightedMinAge08),MAX(CapacityAge08*АбонементНовых*Q9,MeanMinAge08))) | R55: =IF(OR(R28=0,8<=КаникулыРоялти),0,R28*IF(РоялтиПоГруппам="Да",MeanMinAge08+R9*SUMIF(ThresholdAge08,"<"&R9,WeightedRevAge08)-SUMIF(ThresholdAge08,"<"&R9,WeightedMinAge08),MAX(CapacityAge08*АбонементНовых*R9,MeanMinAge08))) | S55: =IF(OR(S28=0,8<=КаникулыРоялти),0,S28*IF(РоялтиПоГруппам="Да",MeanMinAge08+S9*SUMIF(ThresholdAge08,"<"&S9,WeightedRevAge08)-SUMIF(ThresholdAge08,"<"&S9,WeightedMinAge08),MAX(CapacityAge08*АбонементНовых*S9,MeanMinAge08))) | ... BY55: =IF(OR(BY28=0,8<=КаникулыРоялти),0,BY28*IF(РоялтиПоГруппам="Да",MeanMinAge08+BY9*SUMIF(ThresholdAge08,"<"&BY9,WeightedRevAge08)-SUMIF(ThresholdAge08,"<"&BY9,WeightedMinAge08),MAX(CapacityAge08*АбонементНовых*BY9,MeanMinAge08)))
B56: 9 мес. | C56: ₽ | E56: =SUM(L56:W56) | F56: =SUM(X56:AI56) | G56: =SUM(AJ56:AU56) | H56: =SUM(AV56:BG56) | I56: =SUM(BH56:BS56) | J56: =SUM(L56:BS56) | L56: =IF(OR(L29=0,9<=КаникулыРоялти),0,L29*IF(РоялтиПоГруппам="Да",MeanMinAge09+L9*SUMIF(ThresholdAge09,"<"&L9,WeightedRevAge09)-SUMIF(ThresholdAge09,"<"&L9,WeightedMinAge09),MAX(CapacityAge09*АбонементНовых*L9,MeanMinAge09))) | M56: =IF(OR(M29=0,9<=КаникулыРоялти),0,M29*IF(РоялтиПоГруппам="Да",MeanMinAge09+M9*SUMIF(ThresholdAge09,"<"&M9,WeightedRevAge09)-SUMIF(ThresholdAge09,"<"&M9,WeightedMinAge09),MAX(CapacityAge09*АбонементНовых*M9,MeanMinAge09))) | N56: =IF(OR(N29=0,9<=КаникулыРоялти),0,N29*IF(РоялтиПоГруппам="Да",MeanMinAge09+N9*SUMIF(ThresholdAge09,"<"&N9,WeightedRevAge09)-SUMIF(ThresholdAge09,"<"&N9,WeightedMinAge09),MAX(CapacityAge09*АбонементНовых*N9,MeanMinAge09))) | O56: =IF(OR(O29=0,9<=КаникулыРоялти),0,O29*IF(РоялтиПоГруппам="Да",MeanMinAge09+O9*SUMIF(ThresholdAge09,"<"&O9,WeightedRevAge09)-SUMIF(ThresholdAge09,"<"&O9,WeightedMinAge09),MAX(CapacityAge09*АбонементНовых*O9,MeanMinAge09))) | P56: =IF(OR(P29=0,9<=КаникулыРоялти),0,P29*IF(РоялтиПоГруппам="Да",MeanMinAge09+P9*SUMIF(ThresholdAge09,"<"&P9,WeightedRevAge09)-SUMIF(ThresholdAge09,"<"&P9,WeightedMinAge09),MAX(CapacityAge09*АбонементНовых*P9,MeanMinAge09))) | Q56: =IF(OR(Q29=0,9<=КаникулыРоялти),0,Q29*IF(РоялтиПоГруппам="Да",MeanMinAge09+Q9*SUMIF(ThresholdAge09,"<"&Q9,WeightedRevAge09)-SUMIF(ThresholdAge09,"<"&Q9,WeightedMinAge09),MAX(CapacityAge09*АбонементНовых*Q9,MeanMinAge09))) | R56: =IF(OR(R29=0,9<=КаникулыРоялти),0,R29*IF(РоялтиПоГруппам="Да",MeanMinAge09+R9*SUMIF(ThresholdAge09,"<"&R9,WeightedRevAge09)-SUMIF(ThresholdAge09,"<"&R9,WeightedMinAge09),MAX(CapacityAge09*АбонементНовых*R9,MeanMinAge09))) | S56: =IF(OR(S29=0,9<=КаникулыРоялти),0,S29*IF(РоялтиПоГруппам="Да",MeanMinAge09+S9*SUMIF(ThresholdAge09,"<"&S9,WeightedRevAge09)-SUMIF(ThresholdAge09,"<"&S9,WeightedMinAge09),MAX(CapacityAge09*АбонементНовых*S9,MeanMinAge09))) | ... BY56: =IF(OR(BY29=0,9<=КаникулыРоялти),0,BY29*IF(РоялтиПоГруппам="Да",MeanMinAge09+BY9*SUMIF(ThresholdAge09,"<"&BY9,WeightedRevAge09)-SUMIF(ThresholdAge09,"<"&BY9,WeightedMinAge09),MAX(CapacityAge09*АбонементНовых*BY9,MeanMinAge09)))
B57: 10 мес. | C57: ₽ | E57: =SUM(L57:W57) | F57: =SUM(X57:AI57) | G57: =SUM(AJ57:AU57) | H57: =SUM(AV57:BG57) | I57: =SUM(BH57:BS57) | J57: =SUM(L57:BS57) | L57: =IF(OR(L30=0,10<=КаникулыРоялти),0,L30*IF(РоялтиПоГруппам="Да",MeanMinAge10+L9*SUMIF(ThresholdAge10,"<"&L9,WeightedRevAge10)-SUMIF(ThresholdAge10,"<"&L9,WeightedMinAge10),MAX(CapacityAge10*АбонементНовых*L9,MeanMinAge10))) | M57: =IF(OR(M30=0,10<=КаникулыРоялти),0,M30*IF(РоялтиПоГруппам="Да",MeanMinAge10+M9*SUMIF(ThresholdAge10,"<"&M9,WeightedRevAge10)-SUMIF(ThresholdAge10,"<"&M9,WeightedMinAge10),MAX(CapacityAge10*АбонементНовых*M9,MeanMinAge10))) | N57: =IF(OR(N30=0,10<=КаникулыРоялти),0,N30*IF(РоялтиПоГруппам="Да",MeanMinAge10+N9*SUMIF(ThresholdAge10,"<"&N9,WeightedRevAge10)-SUMIF(ThresholdAge10,"<"&N9,WeightedMinAge10),MAX(CapacityAge10*АбонементНовых*N9,MeanMinAge10))) | O57: =IF(OR(O30=0,10<=КаникулыРоялти),0,O30*IF(РоялтиПоГруппам="Да",MeanMinAge10+O9*SUMIF(ThresholdAge10,"<"&O9,WeightedRevAge10)-SUMIF(ThresholdAge10,"<"&O9,WeightedMinAge10),MAX(CapacityAge10*АбонементНовых*O9,MeanMinAge10))) | P57: =IF(OR(P30=0,10<=КаникулыРоялти),0,P30*IF(РоялтиПоГруппам="Да",MeanMinAge10+P9*SUMIF(ThresholdAge10,"<"&P9,WeightedRevAge10)-SUMIF(ThresholdAge10,"<"&P9,WeightedMinAge10),MAX(CapacityAge10*АбонементНовых*P9,MeanMinAge10))) | Q57: =IF(OR(Q30=0,10<=КаникулыРоялти),0,Q30*IF(РоялтиПоГруппам="Да",MeanMinAge10+Q9*SUMIF(ThresholdAge10,"<"&Q9,WeightedRevAge10)-SUMIF(ThresholdAge10,"<"&Q9,WeightedMinAge10),MAX(CapacityAge10*АбонементНовых*Q9,MeanMinAge10))) | R57: =IF(OR(R30=0,10<=КаникулыРоялти),0,R30*IF(РоялтиПоГруппам="Да",MeanMinAge10+R9*SUMIF(ThresholdAge10,"<"&R9,WeightedRevAge10)-SUMIF(ThresholdAge10,"<"&R9,WeightedMinAge10),MAX(CapacityAge10*АбонементНовых*R9,MeanMinAge10))) | S57: =IF(OR(S30=0,10<=КаникулыРоялти),0,S30*IF(РоялтиПоГруппам="Да",MeanMinAge10+S9*SUMIF(ThresholdAge10,"<"&S9,WeightedRevAge10)-SUMIF(ThresholdAge10,"<"&S9,WeightedMinAge10),MAX(CapacityAge10*АбонементНовых*S9,MeanMinAge10))) | ... BY57: =IF(OR(BY30=0,10<=КаникулыРоялти),0,BY30*IF(РоялтиПоГруппам="Да",MeanMinAge10+BY9*SUMIF(ThresholdAge10,"<"&BY9,WeightedRevAge10)-SUMIF(ThresholdAge10,"<"&BY9,WeightedMinAge10),MAX(CapacityAge10*АбонементНовых*BY9,MeanMinAge10)))
B58: 11 мес. | C58: ₽ | E58: =SUM(L58:W58) | F58: =SUM(X58:AI58) | G58: =SUM(AJ58:AU58) | H58: =SUM(AV58:BG58) | I58: =SUM(BH58:BS58) | J58: =SUM(L58:BS58) | L58: =IF(OR(L31=0,11<=КаникулыРоялти),0,L31*IF(РоялтиПоГруппам="Да",MeanMinAge11+L9*SUMIF(ThresholdAge11,"<"&L9,WeightedRevAge11)-SUMIF(ThresholdAge11,"<"&L9,WeightedMinAge11),MAX(CapacityAge11*АбонементНовых*L9,MeanMinAge11))) | M58: =IF(OR(M31=0,11<=КаникулыРоялти),0,M31*IF(РоялтиПоГруппам="Да",MeanMinAge11+M9*SUMIF(ThresholdAge11,"<"&M9,WeightedRevAge11)-SUMIF(ThresholdAge11,"<"&M9,WeightedMinAge11),MAX(CapacityAge11*АбонементНовых*M9,MeanMinAge11))) | N58: =IF(OR(N31=0,11<=КаникулыРоялти),0,N31*IF(РоялтиПоГруппам="Да",MeanMinAge11+N9*SUMIF(ThresholdAge11,"<"&N9,WeightedRevAge11)-SUMIF(ThresholdAge11,"<"&N9,WeightedMinAge11),MAX(CapacityAge11*АбонементНовых*N9,MeanMinAge11))) | O58: =IF(OR(O31=0,11<=КаникулыРоялти),0,O31*IF(РоялтиПоГруппам="Да",MeanMinAge11+O9*SUMIF(ThresholdAge11,"<"&O9,WeightedRevAge11)-SUMIF(ThresholdAge11,"<"&O9,WeightedMinAge11),MAX(CapacityAge11*АбонементНовых*O9,MeanMinAge11))) | P58: =IF(OR(P31=0,11<=КаникулыРоялти),0,P31*IF(РоялтиПоГруппам="Да",MeanMinAge11+P9*SUMIF(ThresholdAge11,"<"&P9,WeightedRevAge11)-SUMIF(ThresholdAge11,"<"&P9,WeightedMinAge11),MAX(CapacityAge11*АбонементНовых*P9,MeanMinAge11))) | Q58: =IF(OR(Q31=0,11<=КаникулыРоялти),0,Q31*IF(РоялтиПоГруппам="Да",MeanMinAge11+Q9*SUMIF(ThresholdAge11,"<"&Q9,WeightedRevAge11)-SUMIF(ThresholdAge11,"<"&Q9,WeightedMinAge11),MAX(CapacityAge11*АбонементНовых*Q9,MeanMinAge11))) | R58: =IF(OR(R31=0,11<=КаникулыРоялти),0,R31*IF(РоялтиПоГруппам="Да",MeanMinAge11+R9*SUMIF(ThresholdAge11,"<"&R9,WeightedRevAge11)-SUMIF(ThresholdAge11,"<"&R9,WeightedMinAge11),MAX(CapacityAge11*АбонементНовых*R9,MeanMinAge11))) | S58: =IF(OR(S31=0,11<=КаникулыРоялти),0,S31*IF(РоялтиПоГруппам="Да",MeanMinAge11+S9*SUMIF(ThresholdAge11,"<"&S9,WeightedRevAge11)-SUMIF(ThresholdAge11,"<"&S9,WeightedMinAge11),MAX(CapacityAge11*АбонементНовых*S9,MeanMinAge11))) | ... BY58: =IF(OR(BY31=0,11<=КаникулыРоялти),0,BY31*IF(РоялтиПоГруппам="Да",MeanMinAge11+BY9*SUMIF(ThresholdAge11,"<"&BY9,WeightedRevAge11)-SUMIF(ThresholdAge11,"<"&BY9,WeightedMinAge11),MAX(CapacityAge11*АбонементНовых*BY9,MeanMinAge11)))
B59: 12 мес. | C59: ₽ | E59: =SUM(L59:W59) | F59: =SUM(X59:AI59) | G59: =SUM(AJ59:AU59) | H59: =SUM(AV59:BG59) | I59: =SUM(BH59:BS59) | J59: =SUM(L59:BS59) | L59: =IF(OR(L32=0,12<=КаникулыРоялти),0,L32*IF(РоялтиПоГруппам="Да",MeanMinAge12+L9*SUMIF(ThresholdAge12,"<"&L9,WeightedRevAge12)-SUMIF(ThresholdAge12,"<"&L9,WeightedMinAge12),MAX(CapacityAge12*АбонементНовых*L9,MeanMinAge12))) | M59: =IF(OR(M32=0,12<=КаникулыРоялти),0,M32*IF(РоялтиПоГруппам="Да",MeanMinAge12+M9*SUMIF(ThresholdAge12,"<"&M9,WeightedRevAge12)-SUMIF(ThresholdAge12,"<"&M9,WeightedMinAge12),MAX(CapacityAge12*АбонементНовых*M9,MeanMinAge12))) | N59: =IF(OR(N32=0,12<=КаникулыРоялти),0,N32*IF(РоялтиПоГруппам="Да",MeanMinAge12+N9*SUMIF(ThresholdAge12,"<"&N9,WeightedRevAge12)-SUMIF(ThresholdAge12,"<"&N9,WeightedMinAge12),MAX(CapacityAge12*АбонементНовых*N9,MeanMinAge12))) | O59: =IF(OR(O32=0,12<=КаникулыРоялти),0,O32*IF(РоялтиПоГруппам="Да",MeanMinAge12+O9*SUMIF(ThresholdAge12,"<"&O9,WeightedRevAge12)-SUMIF(ThresholdAge12,"<"&O9,WeightedMinAge12),MAX(CapacityAge12*АбонементНовых*O9,MeanMinAge12))) | P59: =IF(OR(P32=0,12<=КаникулыРоялти),0,P32*IF(РоялтиПоГруппам="Да",MeanMinAge12+P9*SUMIF(ThresholdAge12,"<"&P9,WeightedRevAge12)-SUMIF(ThresholdAge12,"<"&P9,WeightedMinAge12),MAX(CapacityAge12*АбонементНовых*P9,MeanMinAge12))) | Q59: =IF(OR(Q32=0,12<=КаникулыРоялти),0,Q32*IF(РоялтиПоГруппам="Да",MeanMinAge12+Q9*SUMIF(ThresholdAge12,"<"&Q9,WeightedRevAge12)-SUMIF(ThresholdAge12,"<"&Q9,WeightedMinAge12),MAX(CapacityAge12*АбонементНовых*Q9,MeanMinAge12))) | R59: =IF(OR(R32=0,12<=КаникулыРоялти),0,R32*IF(РоялтиПоГруппам="Да",MeanMinAge12+R9*SUMIF(ThresholdAge12,"<"&R9,WeightedRevAge12)-SUMIF(ThresholdAge12,"<"&R9,WeightedMinAge12),MAX(CapacityAge12*АбонементНовых*R9,MeanMinAge12))) | S59: =IF(OR(S32=0,12<=КаникулыРоялти),0,S32*IF(РоялтиПоГруппам="Да",MeanMinAge12+S9*SUMIF(ThresholdAge12,"<"&S9,WeightedRevAge12)-SUMIF(ThresholdAge12,"<"&S9,WeightedMinAge12),MAX(CapacityAge12*АбонементНовых*S9,MeanMinAge12))) | ... BY59: =IF(OR(BY32=0,12<=КаникулыРоялти),0,BY32*IF(РоялтиПоГруппам="Да",MeanMinAge12+BY9*SUMIF(ThresholdAge12,"<"&BY9,WeightedRevAge12)-SUMIF(ThresholdAge12,"<"&BY9,WeightedMinAge12),MAX(CapacityAge12*АбонементНовых*BY9,MeanMinAge12)))
B60: 13 мес. | C60: ₽ | E60: =SUM(L60:W60) | F60: =SUM(X60:AI60) | G60: =SUM(AJ60:AU60) | H60: =SUM(AV60:BG60) | I60: =SUM(BH60:BS60) | J60: =SUM(L60:BS60) | L60: =IF(OR(L33=0,13<=КаникулыРоялти),0,L33*IF(РоялтиПоГруппам="Да",MeanMinAge13+L9*SUMIF(ThresholdAge13,"<"&L9,WeightedRevAge13)-SUMIF(ThresholdAge13,"<"&L9,WeightedMinAge13),MAX(CapacityAge13*АбонементНовых*L9,MeanMinAge13))) | M60: =IF(OR(M33=0,13<=КаникулыРоялти),0,M33*IF(РоялтиПоГруппам="Да",MeanMinAge13+M9*SUMIF(ThresholdAge13,"<"&M9,WeightedRevAge13)-SUMIF(ThresholdAge13,"<"&M9,WeightedMinAge13),MAX(CapacityAge13*АбонементНовых*M9,MeanMinAge13))) | N60: =IF(OR(N33=0,13<=КаникулыРоялти),0,N33*IF(РоялтиПоГруппам="Да",MeanMinAge13+N9*SUMIF(ThresholdAge13,"<"&N9,WeightedRevAge13)-SUMIF(ThresholdAge13,"<"&N9,WeightedMinAge13),MAX(CapacityAge13*АбонементНовых*N9,MeanMinAge13))) | O60: =IF(OR(O33=0,13<=КаникулыРоялти),0,O33*IF(РоялтиПоГруппам="Да",MeanMinAge13+O9*SUMIF(ThresholdAge13,"<"&O9,WeightedRevAge13)-SUMIF(ThresholdAge13,"<"&O9,WeightedMinAge13),MAX(CapacityAge13*АбонементНовых*O9,MeanMinAge13))) | P60: =IF(OR(P33=0,13<=КаникулыРоялти),0,P33*IF(РоялтиПоГруппам="Да",MeanMinAge13+P9*SUMIF(ThresholdAge13,"<"&P9,WeightedRevAge13)-SUMIF(ThresholdAge13,"<"&P9,WeightedMinAge13),MAX(CapacityAge13*АбонементНовых*P9,MeanMinAge13))) | Q60: =IF(OR(Q33=0,13<=КаникулыРоялти),0,Q33*IF(РоялтиПоГруппам="Да",MeanMinAge13+Q9*SUMIF(ThresholdAge13,"<"&Q9,WeightedRevAge13)-SUMIF(ThresholdAge13,"<"&Q9,WeightedMinAge13),MAX(CapacityAge13*АбонементНовых*Q9,MeanMinAge13))) | R60: =IF(OR(R33=0,13<=КаникулыРоялти),0,R33*IF(РоялтиПоГруппам="Да",MeanMinAge13+R9*SUMIF(ThresholdAge13,"<"&R9,WeightedRevAge13)-SUMIF(ThresholdAge13,"<"&R9,WeightedMinAge13),MAX(CapacityAge13*АбонементНовых*R9,MeanMinAge13))) | S60: =IF(OR(S33=0,13<=КаникулыРоялти),0,S33*IF(РоялтиПоГруппам="Да",MeanMinAge13+S9*SUMIF(ThresholdAge13,"<"&S9,WeightedRevAge13)-SUMIF(ThresholdAge13,"<"&S9,WeightedMinAge13),MAX(CapacityAge13*АбонементНовых*S9,MeanMinAge13))) | ... BY60: =IF(OR(BY33=0,13<=КаникулыРоялти),0,BY33*IF(РоялтиПоГруппам="Да",MeanMinAge13+BY9*SUMIF(ThresholdAge13,"<"&BY9,WeightedRevAge13)-SUMIF(ThresholdAge13,"<"&BY9,WeightedMinAge13),MAX(CapacityAge13*АбонементНовых*BY9,MeanMinAge13)))
B61: 14 мес. | C61: ₽ | E61: =SUM(L61:W61) | F61: =SUM(X61:AI61) | G61: =SUM(AJ61:AU61) | H61: =SUM(AV61:BG61) | I61: =SUM(BH61:BS61) | J61: =SUM(L61:BS61) | L61: =IF(OR(L34=0,14<=КаникулыРоялти),0,L34*IF(РоялтиПоГруппам="Да",MeanMinAge14+L9*SUMIF(ThresholdAge14,"<"&L9,WeightedRevAge14)-SUMIF(ThresholdAge14,"<"&L9,WeightedMinAge14),MAX(CapacityAge14*АбонементНовых*L9,MeanMinAge14))) | M61: =IF(OR(M34=0,14<=КаникулыРоялти),0,M34*IF(РоялтиПоГруппам="Да",MeanMinAge14+M9*SUMIF(ThresholdAge14,"<"&M9,WeightedRevAge14)-SUMIF(ThresholdAge14,"<"&M9,WeightedMinAge14),MAX(CapacityAge14*АбонементНовых*M9,MeanMinAge14))) | N61: =IF(OR(N34=0,14<=КаникулыРоялти),0,N34*IF(РоялтиПоГруппам="Да",MeanMinAge14+N9*SUMIF(ThresholdAge14,"<"&N9,WeightedRevAge14)-SUMIF(ThresholdAge14,"<"&N9,WeightedMinAge14),MAX(CapacityAge14*АбонементНовых*N9,MeanMinAge14))) | O61: =IF(OR(O34=0,14<=КаникулыРоялти),0,O34*IF(РоялтиПоГруппам="Да",MeanMinAge14+O9*SUMIF(ThresholdAge14,"<"&O9,WeightedRevAge14)-SUMIF(ThresholdAge14,"<"&O9,WeightedMinAge14),MAX(CapacityAge14*АбонементНовых*O9,MeanMinAge14))) | P61: =IF(OR(P34=0,14<=КаникулыРоялти),0,P34*IF(РоялтиПоГруппам="Да",MeanMinAge14+P9*SUMIF(ThresholdAge14,"<"&P9,WeightedRevAge14)-SUMIF(ThresholdAge14,"<"&P9,WeightedMinAge14),MAX(CapacityAge14*АбонементНовых*P9,MeanMinAge14))) | Q61: =IF(OR(Q34=0,14<=КаникулыРоялти),0,Q34*IF(РоялтиПоГруппам="Да",MeanMinAge14+Q9*SUMIF(ThresholdAge14,"<"&Q9,WeightedRevAge14)-SUMIF(ThresholdAge14,"<"&Q9,WeightedMinAge14),MAX(CapacityAge14*АбонементНовых*Q9,MeanMinAge14))) | R61: =IF(OR(R34=0,14<=КаникулыРоялти),0,R34*IF(РоялтиПоГруппам="Да",MeanMinAge14+R9*SUMIF(ThresholdAge14,"<"&R9,WeightedRevAge14)-SUMIF(ThresholdAge14,"<"&R9,WeightedMinAge14),MAX(CapacityAge14*АбонементНовых*R9,MeanMinAge14))) | S61: =IF(OR(S34=0,14<=КаникулыРоялти),0,S34*IF(РоялтиПоГруппам="Да",MeanMinAge14+S9*SUMIF(ThresholdAge14,"<"&S9,WeightedRevAge14)-SUMIF(ThresholdAge14,"<"&S9,WeightedMinAge14),MAX(CapacityAge14*АбонементНовых*S9,MeanMinAge14))) | ... BY61: =IF(OR(BY34=0,14<=КаникулыРоялти),0,BY34*IF(РоялтиПоГруппам="Да",MeanMinAge14+BY9*SUMIF(ThresholdAge14,"<"&BY9,WeightedRevAge14)-SUMIF(ThresholdAge14,"<"&BY9,WeightedMinAge14),MAX(CapacityAge14*АбонементНовых*BY9,MeanMinAge14)))
B62: 15 мес. | C62: ₽ | E62: =SUM(L62:W62) | F62: =SUM(X62:AI62) | G62: =SUM(AJ62:AU62) | H62: =SUM(AV62:BG62) | I62: =SUM(BH62:BS62) | J62: =SUM(L62:BS62) | L62: =IF(OR(L35=0,15<=КаникулыРоялти),0,L35*IF(РоялтиПоГруппам="Да",MeanMinAge15+L9*SUMIF(ThresholdAge15,"<"&L9,WeightedRevAge15)-SUMIF(ThresholdAge15,"<"&L9,WeightedMinAge15),MAX(CapacityAge15*АбонементНовых*L9,MeanMinAge15))) | M62: =IF(OR(M35=0,15<=КаникулыРоялти),0,M35*IF(РоялтиПоГруппам="Да",MeanMinAge15+M9*SUMIF(ThresholdAge15,"<"&M9,WeightedRevAge15)-SUMIF(ThresholdAge15,"<"&M9,WeightedMinAge15),MAX(CapacityAge15*АбонементНовых*M9,MeanMinAge15))) | N62: =IF(OR(N35=0,15<=КаникулыРоялти),0,N35*IF(РоялтиПоГруппам="Да",MeanMinAge15+N9*SUMIF(ThresholdAge15,"<"&N9,WeightedRevAge15)-SUMIF(ThresholdAge15,"<"&N9,WeightedMinAge15),MAX(CapacityAge15*АбонементНовых*N9,MeanMinAge15))) | O62: =IF(OR(O35=0,15<=КаникулыРоялти),0,O35*IF(РоялтиПоГруппам="Да",MeanMinAge15+O9*SUMIF(ThresholdAge15,"<"&O9,WeightedRevAge15)-SUMIF(ThresholdAge15,"<"&O9,WeightedMinAge15),MAX(CapacityAge15*АбонементНовых*O9,MeanMinAge15))) | P62: =IF(OR(P35=0,15<=КаникулыРоялти),0,P35*IF(РоялтиПоГруппам="Да",MeanMinAge15+P9*SUMIF(ThresholdAge15,"<"&P9,WeightedRevAge15)-SUMIF(ThresholdAge15,"<"&P9,WeightedMinAge15),MAX(CapacityAge15*АбонементНовых*P9,MeanMinAge15))) | Q62: =IF(OR(Q35=0,15<=КаникулыРоялти),0,Q35*IF(РоялтиПоГруппам="Да",MeanMinAge15+Q9*SUMIF(ThresholdAge15,"<"&Q9,WeightedRevAge15)-SUMIF(ThresholdAge15,"<"&Q9,WeightedMinAge15),MAX(CapacityAge15*АбонементНовых*Q9,MeanMinAge15))) | R62: =IF(OR(R35=0,15<=КаникулыРоялти),0,R35*IF(РоялтиПоГруппам="Да",MeanMinAge15+R9*SUMIF(ThresholdAge15,"<"&R9,WeightedRevAge15)-SUMIF(ThresholdAge15,"<"&R9,WeightedMinAge15),MAX(CapacityAge15*АбонементНовых*R9,MeanMinAge15))) | S62: =IF(OR(S35=0,15<=КаникулыРоялти),0,S35*IF(РоялтиПоГруппам="Да",MeanMinAge15+S9*SUMIF(ThresholdAge15,"<"&S9,WeightedRevAge15)-SUMIF(ThresholdAge15,"<"&S9,WeightedMinAge15),MAX(CapacityAge15*АбонементНовых*S9,MeanMinAge15))) | ... BY62: =IF(OR(BY35=0,15<=КаникулыРоялти),0,BY35*IF(РоялтиПоГруппам="Да",MeanMinAge15+BY9*SUMIF(ThresholdAge15,"<"&BY9,WeightedRevAge15)-SUMIF(ThresholdAge15,"<"&BY9,WeightedMinAge15),MAX(CapacityAge15*АбонементНовых*BY9,MeanMinAge15)))
B63: 16 мес. | C63: ₽ | E63: =SUM(L63:W63) | F63: =SUM(X63:AI63) | G63: =SUM(AJ63:AU63) | H63: =SUM(AV63:BG63) | I63: =SUM(BH63:BS63) | J63: =SUM(L63:BS63) | L63: =IF(OR(L36=0,16<=КаникулыРоялти),0,L36*IF(РоялтиПоГруппам="Да",MeanMinAge16+L9*SUMIF(ThresholdAge16,"<"&L9,WeightedRevAge16)-SUMIF(ThresholdAge16,"<"&L9,WeightedMinAge16),MAX(CapacityAge16*АбонементНовых*L9,MeanMinAge16))) | M63: =IF(OR(M36=0,16<=КаникулыРоялти),0,M36*IF(РоялтиПоГруппам="Да",MeanMinAge16+M9*SUMIF(ThresholdAge16,"<"&M9,WeightedRevAge16)-SUMIF(ThresholdAge16,"<"&M9,WeightedMinAge16),MAX(CapacityAge16*АбонементНовых*M9,MeanMinAge16))) | N63: =IF(OR(N36=0,16<=КаникулыРоялти),0,N36*IF(РоялтиПоГруппам="Да",MeanMinAge16+N9*SUMIF(ThresholdAge16,"<"&N9,WeightedRevAge16)-SUMIF(ThresholdAge16,"<"&N9,WeightedMinAge16),MAX(CapacityAge16*АбонементНовых*N9,MeanMinAge16))) | O63: =IF(OR(O36=0,16<=КаникулыРоялти),0,O36*IF(РоялтиПоГруппам="Да",MeanMinAge16+O9*SUMIF(ThresholdAge16,"<"&O9,WeightedRevAge16)-SUMIF(ThresholdAge16,"<"&O9,WeightedMinAge16),MAX(CapacityAge16*АбонементНовых*O9,MeanMinAge16))) | P63: =IF(OR(P36=0,16<=КаникулыРоялти),0,P36*IF(РоялтиПоГруппам="Да",MeanMinAge16+P9*SUMIF(ThresholdAge16,"<"&P9,WeightedRevAge16)-SUMIF(ThresholdAge16,"<"&P9,WeightedMinAge16),MAX(CapacityAge16*АбонементНовых*P9,MeanMinAge16))) | Q63: =IF(OR(Q36=0,16<=КаникулыРоялти),0,Q36*IF(РоялтиПоГруппам="Да",MeanMinAge16+Q9*SUMIF(ThresholdAge16,"<"&Q9,WeightedRevAge16)-SUMIF(ThresholdAge16,"<"&Q9,WeightedMinAge16),MAX(CapacityAge16*АбонементНовых*Q9,MeanMinAge16))) | R63: =IF(OR(R36=0,16<=КаникулыРоялти),0,R36*IF(РоялтиПоГруппам="Да",MeanMinAge16+R9*SUMIF(ThresholdAge16,"<"&R9,WeightedRevAge16)-SUMIF(ThresholdAge16,"<"&R9,WeightedMinAge16),MAX(CapacityAge16*АбонементНовых*R9,MeanMinAge16))) | S63: =IF(OR(S36=0,16<=КаникулыРоялти),0,S36*IF(РоялтиПоГруппам="Да",MeanMinAge16+S9*SUMIF(ThresholdAge16,"<"&S9,WeightedRevAge16)-SUMIF(ThresholdAge16,"<"&S9,WeightedMinAge16),MAX(CapacityAge16*АбонементНовых*S9,MeanMinAge16))) | ... BY63: =IF(OR(BY36=0,16<=КаникулыРоялти),0,BY36*IF(РоялтиПоГруппам="Да",MeanMinAge16+BY9*SUMIF(ThresholdAge16,"<"&BY9,WeightedRevAge16)-SUMIF(ThresholdAge16,"<"&BY9,WeightedMinAge16),MAX(CapacityAge16*АбонементНовых*BY9,MeanMinAge16)))
B64: 17 мес. | C64: ₽ | E64: =SUM(L64:W64) | F64: =SUM(X64:AI64) | G64: =SUM(AJ64:AU64) | H64: =SUM(AV64:BG64) | I64: =SUM(BH64:BS64) | J64: =SUM(L64:BS64) | L64: =IF(OR(L37=0,17<=КаникулыРоялти),0,L37*IF(РоялтиПоГруппам="Да",MeanMinAge17+L9*SUMIF(ThresholdAge17,"<"&L9,WeightedRevAge17)-SUMIF(ThresholdAge17,"<"&L9,WeightedMinAge17),MAX(CapacityAge17*АбонементНовых*L9,MeanMinAge17))) | M64: =IF(OR(M37=0,17<=КаникулыРоялти),0,M37*IF(РоялтиПоГруппам="Да",MeanMinAge17+M9*SUMIF(ThresholdAge17,"<"&M9,WeightedRevAge17)-SUMIF(ThresholdAge17,"<"&M9,WeightedMinAge17),MAX(CapacityAge17*АбонементНовых*M9,MeanMinAge17))) | N64: =IF(OR(N37=0,17<=КаникулыРоялти),0,N37*IF(РоялтиПоГруппам="Да",MeanMinAge17+N9*SUMIF(ThresholdAge17,"<"&N9,WeightedRevAge17)-SUMIF(ThresholdAge17,"<"&N9,WeightedMinAge17),MAX(CapacityAge17*АбонементНовых*N9,MeanMinAge17))) | O64: =IF(OR(O37=0,17<=КаникулыРоялти),0,O37*IF(РоялтиПоГруппам="Да",MeanMinAge17+O9*SUMIF(ThresholdAge17,"<"&O9,WeightedRevAge17)-SUMIF(ThresholdAge17,"<"&O9,WeightedMinAge17),MAX(CapacityAge17*АбонементНовых*O9,MeanMinAge17))) | P64: =IF(OR(P37=0,17<=КаникулыРоялти),0,P37*IF(РоялтиПоГруппам="Да",MeanMinAge17+P9*SUMIF(ThresholdAge17,"<"&P9,WeightedRevAge17)-SUMIF(ThresholdAge17,"<"&P9,WeightedMinAge17),MAX(CapacityAge17*АбонементНовых*P9,MeanMinAge17))) | Q64: =IF(OR(Q37=0,17<=КаникулыРоялти),0,Q37*IF(РоялтиПоГруппам="Да",MeanMinAge17+Q9*SUMIF(ThresholdAge17,"<"&Q9,WeightedRevAge17)-SUMIF(ThresholdAge17,"<"&Q9,WeightedMinAge17),MAX(CapacityAge17*АбонементНовых*Q9,MeanMinAge17))) | R64: =IF(OR(R37=0,17<=КаникулыРоялти),0,R37*IF(РоялтиПоГруппам="Да",MeanMinAge17+R9*SUMIF(ThresholdAge17,"<"&R9,WeightedRevAge17)-SUMIF(ThresholdAge17,"<"&R9,WeightedMinAge17),MAX(CapacityAge17*АбонементНовых*R9,MeanMinAge17))) | S64: =IF(OR(S37=0,17<=КаникулыРоялти),0,S37*IF(РоялтиПоГруппам="Да",MeanMinAge17+S9*SUMIF(ThresholdAge17,"<"&S9,WeightedRevAge17)-SUMIF(ThresholdAge17,"<"&S9,WeightedMinAge17),MAX(CapacityAge17*АбонементНовых*S9,MeanMinAge17))) | ... BY64: =IF(OR(BY37=0,17<=КаникулыРоялти),0,BY37*IF(РоялтиПоГруппам="Да",MeanMinAge17+BY9*SUMIF(ThresholdAge17,"<"&BY9,WeightedRevAge17)-SUMIF(ThresholdAge17,"<"&BY9,WeightedMinAge17),MAX(CapacityAge17*АбонементНовых*BY9,MeanMinAge17)))
B65: 18 мес. | C65: ₽ | E65: =SUM(L65:W65) | F65: =SUM(X65:AI65) | G65: =SUM(AJ65:AU65) | H65: =SUM(AV65:BG65) | I65: =SUM(BH65:BS65) | J65: =SUM(L65:BS65) | L65: =IF(OR(L38=0,18<=КаникулыРоялти),0,L38*IF(РоялтиПоГруппам="Да",MeanMinAge18+L9*SUMIF(ThresholdAge18,"<"&L9,WeightedRevAge18)-SUMIF(ThresholdAge18,"<"&L9,WeightedMinAge18),MAX(CapacityAge18*АбонементНовых*L9,MeanMinAge18))) | M65: =IF(OR(M38=0,18<=КаникулыРоялти),0,M38*IF(РоялтиПоГруппам="Да",MeanMinAge18+M9*SUMIF(ThresholdAge18,"<"&M9,WeightedRevAge18)-SUMIF(ThresholdAge18,"<"&M9,WeightedMinAge18),MAX(CapacityAge18*АбонементНовых*M9,MeanMinAge18))) | N65: =IF(OR(N38=0,18<=КаникулыРоялти),0,N38*IF(РоялтиПоГруппам="Да",MeanMinAge18+N9*SUMIF(ThresholdAge18,"<"&N9,WeightedRevAge18)-SUMIF(ThresholdAge18,"<"&N9,WeightedMinAge18),MAX(CapacityAge18*АбонементНовых*N9,MeanMinAge18))) | O65: =IF(OR(O38=0,18<=КаникулыРоялти),0,O38*IF(РоялтиПоГруппам="Да",MeanMinAge18+O9*SUMIF(ThresholdAge18,"<"&O9,WeightedRevAge18)-SUMIF(ThresholdAge18,"<"&O9,WeightedMinAge18),MAX(CapacityAge18*АбонементНовых*O9,MeanMinAge18))) | P65: =IF(OR(P38=0,18<=КаникулыРоялти),0,P38*IF(РоялтиПоГруппам="Да",MeanMinAge18+P9*SUMIF(ThresholdAge18,"<"&P9,WeightedRevAge18)-SUMIF(ThresholdAge18,"<"&P9,WeightedMinAge18),MAX(CapacityAge18*АбонементНовых*P9,MeanMinAge18))) | Q65: =IF(OR(Q38=0,18<=КаникулыРоялти),0,Q38*IF(РоялтиПоГруппам="Да",MeanMinAge18+Q9*SUMIF(ThresholdAge18,"<"&Q9,WeightedRevAge18)-SUMIF(ThresholdAge18,"<"&Q9,WeightedMinAge18),MAX(CapacityAge18*АбонементНовых*Q9,MeanMinAge18))) | R65: =IF(OR(R38=0,18<=КаникулыРоялти),0,R38*IF(РоялтиПоГруппам="Да",MeanMinAge18+R9*SUMIF(ThresholdAge18,"<"&R9,WeightedRevAge18)-SUMIF(ThresholdAge18,"<"&R9,WeightedMinAge18),MAX(CapacityAge18*АбонементНовых*R9,MeanMinAge18))) | S65: =IF(OR(S38=0,18<=КаникулыРоялти),0,S38*IF(РоялтиПоГруппам="Да",MeanMinAge18+S9*SUMIF(ThresholdAge18,"<"&S9,WeightedRevAge18)-SUMIF(ThresholdAge18,"<"&S9,WeightedMinAge18),MAX(CapacityAge18*АбонементНовых*S9,MeanMinAge18))) | ... BY65: =IF(OR(BY38=0,18<=КаникулыРоялти),0,BY38*IF(РоялтиПоГруппам="Да",MeanMinAge18+BY9*SUMIF(ThresholdAge18,"<"&BY9,WeightedRevAge18)-SUMIF(ThresholdAge18,"<"&BY9,WeightedMinAge18),MAX(CapacityAge18*АбонементНовых*BY9,MeanMinAge18)))
B66: 19 мес. | C66: ₽ | E66: =SUM(L66:W66) | F66: =SUM(X66:AI66) | G66: =SUM(AJ66:AU66) | H66: =SUM(AV66:BG66) | I66: =SUM(BH66:BS66) | J66: =SUM(L66:BS66) | L66: =IF(OR(L39=0,19<=КаникулыРоялти),0,L39*IF(РоялтиПоГруппам="Да",MeanMinAge19+L9*SUMIF(ThresholdAge19,"<"&L9,WeightedRevAge19)-SUMIF(ThresholdAge19,"<"&L9,WeightedMinAge19),MAX(CapacityAge19*АбонементНовых*L9,MeanMinAge19))) | M66: =IF(OR(M39=0,19<=КаникулыРоялти),0,M39*IF(РоялтиПоГруппам="Да",MeanMinAge19+M9*SUMIF(ThresholdAge19,"<"&M9,WeightedRevAge19)-SUMIF(ThresholdAge19,"<"&M9,WeightedMinAge19),MAX(CapacityAge19*АбонементНовых*M9,MeanMinAge19))) | N66: =IF(OR(N39=0,19<=КаникулыРоялти),0,N39*IF(РоялтиПоГруппам="Да",MeanMinAge19+N9*SUMIF(ThresholdAge19,"<"&N9,WeightedRevAge19)-SUMIF(ThresholdAge19,"<"&N9,WeightedMinAge19),MAX(CapacityAge19*АбонементНовых*N9,MeanMinAge19))) | O66: =IF(OR(O39=0,19<=КаникулыРоялти),0,O39*IF(РоялтиПоГруппам="Да",MeanMinAge19+O9*SUMIF(ThresholdAge19,"<"&O9,WeightedRevAge19)-SUMIF(ThresholdAge19,"<"&O9,WeightedMinAge19),MAX(CapacityAge19*АбонементНовых*O9,MeanMinAge19))) | P66: =IF(OR(P39=0,19<=КаникулыРоялти),0,P39*IF(РоялтиПоГруппам="Да",MeanMinAge19+P9*SUMIF(ThresholdAge19,"<"&P9,WeightedRevAge19)-SUMIF(ThresholdAge19,"<"&P9,WeightedMinAge19),MAX(CapacityAge19*АбонементНовых*P9,MeanMinAge19))) | Q66: =IF(OR(Q39=0,19<=КаникулыРоялти),0,Q39*IF(РоялтиПоГруппам="Да",MeanMinAge19+Q9*SUMIF(ThresholdAge19,"<"&Q9,WeightedRevAge19)-SUMIF(ThresholdAge19,"<"&Q9,WeightedMinAge19),MAX(CapacityAge19*АбонементНовых*Q9,MeanMinAge19))) | R66: =IF(OR(R39=0,19<=КаникулыРоялти),0,R39*IF(РоялтиПоГруппам="Да",MeanMinAge19+R9*SUMIF(ThresholdAge19,"<"&R9,WeightedRevAge19)-SUMIF(ThresholdAge19,"<"&R9,WeightedMinAge19),MAX(CapacityAge19*АбонементНовых*R9,MeanMinAge19))) | S66: =IF(OR(S39=0,19<=КаникулыРоялти),0,S39*IF(РоялтиПоГруппам="Да",MeanMinAge19+S9*SUMIF(ThresholdAge19,"<"&S9,WeightedRevAge19)-SUMIF(ThresholdAge19,"<"&S9,WeightedMinAge19),MAX(CapacityAge19*АбонементНовых*S9,MeanMinAge19))) | ... BY66: =IF(OR(BY39=0,19<=КаникулыРоялти),0,BY39*IF(РоялтиПоГруппам="Да",MeanMinAge19+BY9*SUMIF(ThresholdAge19,"<"&BY9,WeightedRevAge19)-SUMIF(ThresholdAge19,"<"&BY9,WeightedMinAge19),MAX(CapacityAge19*АбонементНовых*BY9,MeanMinAge19)))
B67: 20 мес. | C67: ₽ | E67: =SUM(L67:W67) | F67: =SUM(X67:AI67) | G67: =SUM(AJ67:AU67) | H67: =SUM(AV67:BG67) | I67: =SUM(BH67:BS67) | J67: =SUM(L67:BS67) | L67: =IF(OR(L40=0,20<=КаникулыРоялти),0,L40*IF(РоялтиПоГруппам="Да",MeanMinAge20+L9*SUMIF(ThresholdAge20,"<"&L9,WeightedRevAge20)-SUMIF(ThresholdAge20,"<"&L9,WeightedMinAge20),MAX(CapacityAge20*АбонементНовых*L9,MeanMinAge20))) | M67: =IF(OR(M40=0,20<=КаникулыРоялти),0,M40*IF(РоялтиПоГруппам="Да",MeanMinAge20+M9*SUMIF(ThresholdAge20,"<"&M9,WeightedRevAge20)-SUMIF(ThresholdAge20,"<"&M9,WeightedMinAge20),MAX(CapacityAge20*АбонементНовых*M9,MeanMinAge20))) | N67: =IF(OR(N40=0,20<=КаникулыРоялти),0,N40*IF(РоялтиПоГруппам="Да",MeanMinAge20+N9*SUMIF(ThresholdAge20,"<"&N9,WeightedRevAge20)-SUMIF(ThresholdAge20,"<"&N9,WeightedMinAge20),MAX(CapacityAge20*АбонементНовых*N9,MeanMinAge20))) | O67: =IF(OR(O40=0,20<=КаникулыРоялти),0,O40*IF(РоялтиПоГруппам="Да",MeanMinAge20+O9*SUMIF(ThresholdAge20,"<"&O9,WeightedRevAge20)-SUMIF(ThresholdAge20,"<"&O9,WeightedMinAge20),MAX(CapacityAge20*АбонементНовых*O9,MeanMinAge20))) | P67: =IF(OR(P40=0,20<=КаникулыРоялти),0,P40*IF(РоялтиПоГруппам="Да",MeanMinAge20+P9*SUMIF(ThresholdAge20,"<"&P9,WeightedRevAge20)-SUMIF(ThresholdAge20,"<"&P9,WeightedMinAge20),MAX(CapacityAge20*АбонементНовых*P9,MeanMinAge20))) | Q67: =IF(OR(Q40=0,20<=КаникулыРоялти),0,Q40*IF(РоялтиПоГруппам="Да",MeanMinAge20+Q9*SUMIF(ThresholdAge20,"<"&Q9,WeightedRevAge20)-SUMIF(ThresholdAge20,"<"&Q9,WeightedMinAge20),MAX(CapacityAge20*АбонементНовых*Q9,MeanMinAge20))) | R67: =IF(OR(R40=0,20<=КаникулыРоялти),0,R40*IF(РоялтиПоГруппам="Да",MeanMinAge20+R9*SUMIF(ThresholdAge20,"<"&R9,WeightedRevAge20)-SUMIF(ThresholdAge20,"<"&R9,WeightedMinAge20),MAX(CapacityAge20*АбонементНовых*R9,MeanMinAge20))) | S67: =IF(OR(S40=0,20<=КаникулыРоялти),0,S40*IF(РоялтиПоГруппам="Да",MeanMinAge20+S9*SUMIF(ThresholdAge20,"<"&S9,WeightedRevAge20)-SUMIF(ThresholdAge20,"<"&S9,WeightedMinAge20),MAX(CapacityAge20*АбонементНовых*S9,MeanMinAge20))) | ... BY67: =IF(OR(BY40=0,20<=КаникулыРоялти),0,BY40*IF(РоялтиПоГруппам="Да",MeanMinAge20+BY9*SUMIF(ThresholdAge20,"<"&BY9,WeightedRevAge20)-SUMIF(ThresholdAge20,"<"&BY9,WeightedMinAge20),MAX(CapacityAge20*АбонементНовых*BY9,MeanMinAge20)))
B68: 21 мес. | C68: ₽ | E68: =SUM(L68:W68) | F68: =SUM(X68:AI68) | G68: =SUM(AJ68:AU68) | H68: =SUM(AV68:BG68) | I68: =SUM(BH68:BS68) | J68: =SUM(L68:BS68) | L68: =IF(OR(L41=0,21<=КаникулыРоялти),0,L41*IF(РоялтиПоГруппам="Да",MeanMinAge21+L9*SUMIF(ThresholdAge21,"<"&L9,WeightedRevAge21)-SUMIF(ThresholdAge21,"<"&L9,WeightedMinAge21),MAX(CapacityAge21*АбонементНовых*L9,MeanMinAge21))) | M68: =IF(OR(M41=0,21<=КаникулыРоялти),0,M41*IF(РоялтиПоГруппам="Да",MeanMinAge21+M9*SUMIF(ThresholdAge21,"<"&M9,WeightedRevAge21)-SUMIF(ThresholdAge21,"<"&M9,WeightedMinAge21),MAX(CapacityAge21*АбонементНовых*M9,MeanMinAge21))) | N68: =IF(OR(N41=0,21<=КаникулыРоялти),0,N41*IF(РоялтиПоГруппам="Да",MeanMinAge21+N9*SUMIF(ThresholdAge21,"<"&N9,WeightedRevAge21)-SUMIF(ThresholdAge21,"<"&N9,WeightedMinAge21),MAX(CapacityAge21*АбонементНовых*N9,MeanMinAge21))) | O68: =IF(OR(O41=0,21<=КаникулыРоялти),0,O41*IF(РоялтиПоГруппам="Да",MeanMinAge21+O9*SUMIF(ThresholdAge21,"<"&O9,WeightedRevAge21)-SUMIF(ThresholdAge21,"<"&O9,WeightedMinAge21),MAX(CapacityAge21*АбонементНовых*O9,MeanMinAge21))) | P68: =IF(OR(P41=0,21<=КаникулыРоялти),0,P41*IF(РоялтиПоГруппам="Да",MeanMinAge21+P9*SUMIF(ThresholdAge21,"<"&P9,WeightedRevAge21)-SUMIF(ThresholdAge21,"<"&P9,WeightedMinAge21),MAX(CapacityAge21*АбонементНовых*P9,MeanMinAge21))) | Q68: =IF(OR(Q41=0,21<=КаникулыРоялти),0,Q41*IF(РоялтиПоГруппам="Да",MeanMinAge21+Q9*SUMIF(ThresholdAge21,"<"&Q9,WeightedRevAge21)-SUMIF(ThresholdAge21,"<"&Q9,WeightedMinAge21),MAX(CapacityAge21*АбонементНовых*Q9,MeanMinAge21))) | R68: =IF(OR(R41=0,21<=КаникулыРоялти),0,R41*IF(РоялтиПоГруппам="Да",MeanMinAge21+R9*SUMIF(ThresholdAge21,"<"&R9,WeightedRevAge21)-SUMIF(ThresholdAge21,"<"&R9,WeightedMinAge21),MAX(CapacityAge21*АбонементНовых*R9,MeanMinAge21))) | S68: =IF(OR(S41=0,21<=КаникулыРоялти),0,S41*IF(РоялтиПоГруппам="Да",MeanMinAge21+S9*SUMIF(ThresholdAge21,"<"&S9,WeightedRevAge21)-SUMIF(ThresholdAge21,"<"&S9,WeightedMinAge21),MAX(CapacityAge21*АбонементНовых*S9,MeanMinAge21))) | ... BY68: =IF(OR(BY41=0,21<=КаникулыРоялти),0,BY41*IF(РоялтиПоГруппам="Да",MeanMinAge21+BY9*SUMIF(ThresholdAge21,"<"&BY9,WeightedRevAge21)-SUMIF(ThresholdAge21,"<"&BY9,WeightedMinAge21),MAX(CapacityAge21*АбонементНовых*BY9,MeanMinAge21)))
B69: 22 мес. | C69: ₽ | E69: =SUM(L69:W69) | F69: =SUM(X69:AI69) | G69: =SUM(AJ69:AU69) | H69: =SUM(AV69:BG69) | I69: =SUM(BH69:BS69) | J69: =SUM(L69:BS69) | L69: =IF(OR(L42=0,22<=КаникулыРоялти),0,L42*IF(РоялтиПоГруппам="Да",MeanMinAge22+L9*SUMIF(ThresholdAge22,"<"&L9,WeightedRevAge22)-SUMIF(ThresholdAge22,"<"&L9,WeightedMinAge22),MAX(CapacityAge22*АбонементНовых*L9,MeanMinAge22))) | M69: =IF(OR(M42=0,22<=КаникулыРоялти),0,M42*IF(РоялтиПоГруппам="Да",MeanMinAge22+M9*SUMIF(ThresholdAge22,"<"&M9,WeightedRevAge22)-SUMIF(ThresholdAge22,"<"&M9,WeightedMinAge22),MAX(CapacityAge22*АбонементНовых*M9,MeanMinAge22))) | N69: =IF(OR(N42=0,22<=КаникулыРоялти),0,N42*IF(РоялтиПоГруппам="Да",MeanMinAge22+N9*SUMIF(ThresholdAge22,"<"&N9,WeightedRevAge22)-SUMIF(ThresholdAge22,"<"&N9,WeightedMinAge22),MAX(CapacityAge22*АбонементНовых*N9,MeanMinAge22))) | O69: =IF(OR(O42=0,22<=КаникулыРоялти),0,O42*IF(РоялтиПоГруппам="Да",MeanMinAge22+O9*SUMIF(ThresholdAge22,"<"&O9,WeightedRevAge22)-SUMIF(ThresholdAge22,"<"&O9,WeightedMinAge22),MAX(CapacityAge22*АбонементНовых*O9,MeanMinAge22))) | P69: =IF(OR(P42=0,22<=КаникулыРоялти),0,P42*IF(РоялтиПоГруппам="Да",MeanMinAge22+P9*SUMIF(ThresholdAge22,"<"&P9,WeightedRevAge22)-SUMIF(ThresholdAge22,"<"&P9,WeightedMinAge22),MAX(CapacityAge22*АбонементНовых*P9,MeanMinAge22))) | Q69: =IF(OR(Q42=0,22<=КаникулыРоялти),0,Q42*IF(РоялтиПоГруппам="Да",MeanMinAge22+Q9*SUMIF(ThresholdAge22,"<"&Q9,WeightedRevAge22)-SUMIF(ThresholdAge22,"<"&Q9,WeightedMinAge22),MAX(CapacityAge22*АбонементНовых*Q9,MeanMinAge22))) | R69: =IF(OR(R42=0,22<=КаникулыРоялти),0,R42*IF(РоялтиПоГруппам="Да",MeanMinAge22+R9*SUMIF(ThresholdAge22,"<"&R9,WeightedRevAge22)-SUMIF(ThresholdAge22,"<"&R9,WeightedMinAge22),MAX(CapacityAge22*АбонементНовых*R9,MeanMinAge22))) | S69: =IF(OR(S42=0,22<=КаникулыРоялти),0,S42*IF(РоялтиПоГруппам="Да",MeanMinAge22+S9*SUMIF(ThresholdAge22,"<"&S9,WeightedRevAge22)-SUMIF(ThresholdAge22,"<"&S9,WeightedMinAge22),MAX(CapacityAge22*АбонементНовых*S9,MeanMinAge22))) | ... BY69: =IF(OR(BY42=0,22<=КаникулыРоялти),0,BY42*IF(РоялтиПоГруппам="Да",MeanMinAge22+BY9*SUMIF(ThresholdAge22,"<"&BY9,WeightedRevAge22)-SUMIF(ThresholdAge22,"<"&BY9,WeightedMinAge22),MAX(CapacityAge22*АбонементНовых*BY9,MeanMinAge22)))
