Workbook
Name RevenueAge01: '18_Календарь_тарифы'!$B$24:$U$24
Name MinimumAge01: '18_Календарь_тарифы'!$B$54:$U$54
Name CapacityAge01: '18_Календарь_тарифы'!$W$24
Name MeanMinAge01: '18_Календарь_тарифы'!$X$24
Name RevenueAge02: '18_Календарь_тарифы'!$B$25:$U$25
Name MinimumAge02: '18_Календарь_тарифы'!$B$55:$U$55
Name CapacityAge02: '18_Календарь_тарифы'!$W$25
Name MeanMinAge02: '18_Календарь_тарифы'!$X$25
Name RevenueAge03: '18_Календарь_тарифы'!$B$26:$U$26
Name MinimumAge03: '18_Календарь_тарифы'!$B$56:$U$56
Name CapacityAge03: '18_Календарь_тарифы'!$W$26
Name MeanMinAge03: '18_Календарь_тарифы'!$X$26
Name RevenueAge04: '18_Календарь_тарифы'!$B$27:$U$27
Name MinimumAge04: '18_Календарь_тарифы'!$B$57:$U$57
Name CapacityAge04: '18_Календарь_тарифы'!$W$27
Name MeanMinAge04: '18_Календарь_тарифы'!$X$27
Name RevenueAge05: '18_Календарь_тарифы'!$B$28:$U$28
Name MinimumAge05: '18_Календарь_тарифы'!$B$58:$U$58
Name CapacityAge05: '18_Календарь_тарифы'!$W$28
Name MeanMinAge05: '18_Календарь_тарифы'!$X$28
Name RevenueAge06: '18_Календарь_тарифы'!$B$29:$U$29
Name MinimumAge06: '18_Календарь_тарифы'!$B$59:$U$59
Name CapacityAge06: '18_Календарь_тарифы'!$W$29
Name MeanMinAge06: '18_Календарь_тарифы'!$X$29
Name RevenueAge07: '18_Календарь_тарифы'!$B$30:$U$30
Name MinimumAge07: '18_Календарь_тарифы'!$B$60:$U$60
Name CapacityAge07: '18_Календарь_тарифы'!$W$30
Name MeanMinAge07: '18_Календарь_тарифы'!$X$30
Name RevenueAge08: '18_Календарь_тарифы'!$B$31:$U$31
Name MinimumAge08: '18_Календарь_тарифы'!$B$61:$U$61
Name CapacityAge08: '18_Календарь_тарифы'!$W$31
Name MeanMinAge08: '18_Календарь_тарифы'!$X$31
Name RevenueAge09: '18_Календарь_тарифы'!$B$32:$U$32
Name MinimumAge09: '18_Календарь_тарифы'!$B$62:$U$62
Name CapacityAge09: '18_Календарь_тарифы'!$W$32
Name MeanMinAge09: '18_Календарь_тарифы'!$X$32
Name RevenueAge10: '18_Календарь_тарифы'!$B$33:$U$33
Name MinimumAge10: '18_Календарь_тарифы'!$B$63:$U$63
Name CapacityAge10: '18_Календарь_тарифы'!$W$33
Name MeanMinAge10: '18_Календарь_тарифы'!$X$33
Name RevenueAge11: '18_Календарь_тарифы'!$B$34:$U$34
Name MinimumAge11: '18_Календарь_тарифы'!$B$64:$U$64
Name CapacityAge11: '18_Календарь_тарифы'!$W$34
Name MeanMinAge11: '18_Календарь_тарифы'!$X$34
Name RevenueAge12: '18_Календарь_тарифы'!$B$35:$U$35
Name MinimumAge12: '18_Календарь_тарифы'!$B$65:$U$65
Name CapacityAge12: '18_Календарь_тарифы'!$W$35
Name MeanMinAge12: '18_Календарь_тарифы'!$X$35
Name RevenueAge13: '18_Календарь_тарифы'!$B$36:$U$36
Name MinimumAge13: '18_Календарь_тарифы'!$B$66:$U$66
Name CapacityAge13: '18_Календарь_тарифы'!$W$36
Name MeanMinAge13: '18_Календарь_тарифы'!$X$36
Name RevenueAge14: '18_Календарь_тарифы'!$B$37:$U$37
Name MinimumAge14: '18_Календарь_тарифы'!$B$67:$U$67
Name CapacityAge14: '18_Календарь_тарифы'!$W$37
Name MeanMinAge14: '18_Календарь_тарифы'!$X$37
Name RevenueAge15: '18_Календарь_тарифы'!$B$38:$U$38
Name MinimumAge15: '18_Календарь_тарифы'!$B$68:$U$68
Name CapacityAge15: '18_Календарь_тарифы'!$W$38
Name MeanMinAge15: '18_Календарь_тарифы'!$X$38

Sheet 00_Старт
A1: СПАРТАК · финансовая модель — с чего начать
A2: Три действия: посмотреть результат → поменять вводные → проверить сходимость. Считать вручную ничего не нужно.
A4: ШАГ 1 · Что уже посчитано | D4: все суммы в млн ₽, если не указано иное
A5: Показатель | B5: Значение | C5: Ед. | D5: Что это значит
A6: Активный сценарий | B6: ='01_Вводные'!$B$192 | D6: Меняется на 01_Вводные!B192. Пересчитывает всю книгу.
A7: Старт горизонта | B7: ='01_Вводные'!$B$7 | D7: Дальше 60 месяцев. Сезон = сентябрь–август.
A8: Выручка без НДС, 5 сезонов | B8: ='00_Дашборд'!$H$24/1000000 | C8: млн ₽ | D8: Паушальные + роялти + мерч + лагеря.
A9: EBITDA, 5 сезонов | B9: ='00_Дашборд'!$H$29/1000000 | C9: млн ₽ | D9: До налога УСН, до CAPEX и до возврата займа.
A10: Рентабельность EBITDA | B10: ='00_Дашборд'!$H$30 | C10: % | D10: EBITDA / выручка без НДС за весь горизонт.
A11: Деньги на конец горизонта | B11: ='00_Дашборд'!$H$32/1000000 | C11: млн ₽ | D11: Остаток на счёте в последнем месяце.
A12: Пиковый кассовый дефицит | B12: ='00_Дашборд'!$H$38/1000000 | C12: млн ₽ | D12: Максимальный минус на счёте. Кредит на его покрытие в модель НЕ заложен.
A13: Нехватка товара (по COGS) | B13: ='13_Проверки'!$B$41/1000000 | C13: млн ₽ | D13: Если > 0 — план продаж не обеспечен запасом формы.
A14: Операционные выплаты ФК | B14: ='00_Дашборд'!$H$37/1000000 | C14: млн ₽ | D14: Деньгами: доли от паушальных, роялти и прибыли мерча.
A15: Возврат займа ФК | B15: ='00_Дашборд'!$H$34/1000000 | C15: млн ₽ | D15: Тело займа на мерч, отдельно от операционных выплат.
A16: Займ на конец | B16: ='00_Дашборд'!$H$35/1000000 | C16: млн ₽ | D16: Непогашенный остаток стартового займа 50 млн ₽.
A17: CAPEX за горизонт | B17: ='00_Дашборд'!$H$39/1000000 | C17: млн ₽ | D17: 1% выручки с НДС + разовый CAPEX.
A18: Активные школы на конец | B18: ='00_Дашборд'!$G$20 | D18: Действующая сеть + новые школы.
A19: Продано франшиз за 5 сезонов | B19: ='00_Дашборд'!$H$17 | D19: Финансовый план; целые продажи — на 04_Продажи.
A21: ШАГ 2 · Что можно менять | D21: правим ТОЛЬКО жёлтые ячейки на 01_Вводные
A22: Переключатель | B22: Сейчас | C22: Где | D22: Что произойдёт
A23: Сценарий | B23: ='01_Вводные'!$B$192 | C23: B192 | D23: Меняет 6 драйверов сразу: план продаж, детей, цену абонемента, мерч, таргет, срок роялти.
A24: Режим просмотра итога | B24: ='01_Вводные'!$B$188 | C24: B188 | D24: Добавляет к прогнозу фактический сезон 25/26. На формулы прогноза не влияет.
A25: Драйвер чувствительности | B25: ='01_Вводные'!$B$233 | C25: B233 | D25: Что именно тестируем на 12_Чувствительность.
A26: Чувствительность включена | B26: ='01_Вводные'!$B$234 | C26: B234 | D26: «Нет» отключает два дополнительных прогона — книга считается быстрее.
A27: Лагеря включены | B27: ='01_Вводные'!$B$241 | C27: B241 | D27: «Нет» обнуляет продажи, начисления и оплаты лагерей.
A28: CAPEX включён | B28: ='01_Вводные'!$B$290 | C28: B290 | D28: «Нет» убирает CAPEX из денег до погашения займа.
A29: Индексация вне ФОТ | B29: ='01_Вводные'!$B$294 | C29: B294 | D29: Абонемент, паушальный, форма, ERP, IT, юристы, реклама. Офис и мин. роялти не индексируются.
A30: Постепенный набор детей | B30: ='01_Вводные'!$B$295 | C30: B295 | D30: Школа выходит на план за 12 месяцев, потом на план 2-го года за 13–24.
A31: Роялти по тарифным группам | B31: ='01_Вводные'!$B$239 | C31: B239 | D31: «Да» — минимум проверяется по каждой школе своего тарифа. «Нет» — прежнее усреднение, только для сверки.
A32: Возврат займа ограничен запасом | B32: ='01_Вводные'!$B$238 | C32: B238 | D32: п.27 ТЗ: гасим займ только если склад не ниже цели будущих месяцев.
A34: Числовые вводные (цены, оклады, ставки, планы продаж) — там же, на 01_Вводные, по разделам 1–16.
A35: Базы сценарных драйверов (план продаж, мощность школы, абонемент, мерч, таргет, дебиторка) — 01_Вводные!B210:B225.
A37: ШАГ 3 · Проверить, что модель сошлась
A38: Пройдено автопроверок | B38: =COUNTIF('13_Проверки'!$C$4:$C$68,"OK") | D38: Тесты сходимости БДР↔БДДС, склада, займа, сценариев.
A39: Требует проверки | B39: =COUNTIF('13_Проверки'!$C$4:$C$68,"ПРОВЕРИТЬ") | D39: Должно быть 0. Если больше — открой 13_Проверки.
A40: Риск плана | B40: =COUNTIF('13_Проверки'!$C$4:$C$68,"РИСК ПЛАНА") | D40: Не ошибка формул: нехватка денег или товара показана честно.
A41: Сознательное упрощение | B41: =COUNTIF('13_Проверки'!$C$4:$C$68,"УПРОЩЕНИЕ") | D41: Включён упрощённый режим расчёта (например, роялти без тарифов).
A42: Итог | B42: =IF(COUNTIF('13_Проверки'!$C$4:$C$68,"ПРОВЕРИТЬ")=0,"Модель сходится","Есть расхождения") | C42: 13_Проверки
A44: Цвета ячеек
A45: Жёлтая | D45: Обычная вводная. Можно и нужно менять.
A46: Жёлтая с оттенком | D46: Вводная, которую ещё надо подтвердить (см. 14_Ревизия).
A47: Переключатель | D47: Выбор из списка: Да/Нет, сценарий, режим.
A48: Блок v4 / ревизии | D48: CAPEX, индексация, набор детей — правила из первоначальной модели.
A49: Серая курсивная | D49: Формула. Вписать сюда число = сломать связь.
A50: Зелёная | D50: Формула, исправленная при ревизии. Не трогать.
A52: Куда идти за деталями
A53: Лист | D53: Зачем нужен / кто смотрит
A54: 00_Дашборд | D54: Итоги по сезонам, 5 графиков, KPI · Собственник, ФК
A55: 01_Вводные | D55: ЕДИНСТВЕННЫЙ лист для ручной правки · Аналитик
A56: 01а_Действующая_сеть | D56: Реестр 51/104, отток, сверка роялти с фактом · Собственник, аналитик
A57: 02_Модель | D57: БДР и БДДС помесячно: выручка → EBITDA → деньги · Финансист
A58: 03_Сценарии | D58: Негативный / базовый / позитивный рядом · Собственник
A59: 04_Продажи | D59: План продаж, сезонность, лиды, открытия, маркетинг · Коммерция
A60: 05_Воронка | D60: Лиды → продажи → открытия → ERP · Коммерция
A61: 06_Сеть_и_дети | D61: Юрлица, школы, набор детей по возрасту, роялти · Операции
A62: 07_Мерч | D62: Форма: продажи, COGS, склад, закупки, возврат займа · Операции
A63: 08_ФОТ | D63: Штат, найм, индексация, премии, взносы · HR / финансы
A64: 09_Лагеря | D64: Экономика лагерей и график оплат · Операции
... A73: 16а_Логика_модели | D73: Как из вводных получается EBITDA — цепочка расчёта · Все
A75: Скрытые служебные листы 17–19 содержат общие расчёты (сценарии, календарь тарифов, аналитика). Для работы они не нужны.

Sheet 00_Дашборд
A1: Финмодель Спартак — управленческий дашборд
A3: Как работать | B3: Все ручные вводные находятся только на листе 01_Вводные. Остальные листы — расчётные. Жёлтый = ввод, чёрный/зелёный = формулы и связи. | J3: Быстрая навигация
J4: → Вводные
A5: Ключевые вводные | J5: → Основная модель
A6: Старт модели | B6: ='01_Вводные'!$B$7 | D6: Сценарий | E6: ='01_Вводные'!B192 | G6: Контроль модели | J6: → Сценарии
A7: Стартовые юрлица | B7: ='01_Вводные'!$B$10 | D7: Сравнение | E7: 03_Сценарии | G7: Провалено автопроверок | H7: =COUNTIF('13_Проверки'!C4:C68,"ПРОВЕРИТЬ") | J7: → Продажи / воронка
A8: Стартовые школы | B8: ='01_Вводные'!$B$9 | D8: Чувствительность | E8: 12_Чувствительность | G8: Статус | H8: =IF(COUNTIF('13_Проверки'!C4:C68,"ПРОВЕРИТЬ")=0,"Сходится","Открой 13_Проверки") | J8: → Сеть и дети
A9: Дети действующей сети, 100% | B9: ='01_Вводные'!$B$11 | G9: Пиковый кассовый дефицит, ₽ | H9: =E12 | J9: → Мерч / склад
A10: Лаг открытия | B10: ='01_Вводные'!$B$15 | D10: Проверки | E10: 13_Проверки | G10: Нехватка товара, ₽ COGS | H10: =E11 | J10: → ФОТ
A11: Стартовый склад | B11: ='01_Вводные'!$B$77 | D11: Дефицит товара | E11: =MAX('07_Мерч'!B27:BI27) | G11: → Начать здесь: 00_Старт | J11: → Выплаты ФК
A12: Стартовый займ | B12: ='01_Вводные'!$B$78 | D12: Кассовый дефицит | E12: =MAX(0,-MIN('02_Модель'!B72:BI72)) | J12: → Проверки
A15: Итоги по сезонам
A16: Показатель | B16: 25/26 факт* | C16: 26/27 | D16: 27/28 | E16: 28/29 | F16: 29/30 | G16: 30/31 | H16: Итого прогноз
A17: Продажи франшиз | C17: =SUM('04_Продажи'!B15:M15) | D17: =SUM('04_Продажи'!N15:Y15) | E17: =SUM('04_Продажи'!Z15:AK15) | F17: =SUM('04_Продажи'!AL15:AW15) | G17: =SUM('04_Продажи'!AX15:BI15) | H17: =SUM(C17:G17)
A18: Открытия школ | C18: =SUM('04_Продажи'!B18:M18) | D18: =SUM('04_Продажи'!N18:Y18) | E18: =SUM('04_Продажи'!Z18:AK18) | F18: =SUM('04_Продажи'!AL18:AW18) | G18: =SUM('04_Продажи'!AX18:BI18) | H18: =SUM(C18:G18)
A19: Активные юрлица, конец | C19: ='02_Модель'!M13 | D19: ='02_Модель'!Y13 | E19: ='02_Модель'!AK13 | F19: ='02_Модель'!AW13 | G19: ='02_Модель'!BI13 | H19: =G19
A20: Активные школы, конец | C20: ='02_Модель'!M9+'02_Модель'!M12 | D20: ='02_Модель'!Y9+'02_Модель'!Y12 | E20: ='02_Модель'!AK9+'02_Модель'!AK12 | F20: ='02_Модель'!AW9+'02_Модель'!AW12 | G20: ='02_Модель'!BI9+'02_Модель'!BI12 | H20: =G20
A21: Дети действующей сети, среднее | C21: =AVERAGE('02_Модель'!B11:M11) | D21: =AVERAGE('02_Модель'!N11:Y11) | E21: =AVERAGE('02_Модель'!Z11:AK11) | F21: =AVERAGE('02_Модель'!AL11:AW11) | G21: =AVERAGE('02_Модель'!AX11:BI11) | H21: =AVERAGE('02_Модель'!B11:BI11)
A22: Дети новых школ, среднее | C22: =AVERAGE('02_Модель'!B14:M14) | D22: =AVERAGE('02_Модель'!N14:Y14) | E22: =AVERAGE('02_Модель'!Z14:AK14) | F22: =AVERAGE('02_Модель'!AL14:AW14) | G22: =AVERAGE('02_Модель'!AX14:BI14) | H22: =AVERAGE('02_Модель'!B14:BI14)
A23: Дети всего, среднее | C23: =AVERAGE('02_Модель'!B15:M15) | D23: =AVERAGE('02_Модель'!N15:Y15) | E23: =AVERAGE('02_Модель'!Z15:AK15) | F23: =AVERAGE('02_Модель'!AL15:AW15) | G23: =AVERAGE('02_Модель'!AX15:BI15) | H23: =AVERAGE('02_Модель'!B15:BI15)
A24: Выручка без НДС | B24: ='11_История_25_26'!N4 | C24: =SUM('02_Модель'!B23:M23) | D24: =SUM('02_Модель'!N23:Y23) | E24: =SUM('02_Модель'!Z23:AK23) | F24: =SUM('02_Модель'!AL23:AW23) | G24: =SUM('02_Модель'!AX23:BI23) | H24: =SUM(C24:G24)
A25: Паушальные взносы | C25: =SUM('02_Модель'!B18:M18) | D25: =SUM('02_Модель'!N18:Y18) | E25: =SUM('02_Модель'!Z18:AK18) | F25: =SUM('02_Модель'!AL18:AW18) | G25: =SUM('02_Модель'!AX18:BI18) | H25: =SUM(C25:G25)
A26: Роялти | C26: =SUM('02_Модель'!B19:M20) | D26: =SUM('02_Модель'!N19:Y20) | E26: =SUM('02_Модель'!Z19:AK20) | F26: =SUM('02_Модель'!AL19:AW20) | G26: =SUM('02_Модель'!AX19:BI20) | H26: =SUM(C26:G26)
A27: Мерч | C27: =SUM('02_Модель'!B21:M21) | D27: =SUM('02_Модель'!N21:Y21) | E27: =SUM('02_Модель'!Z21:AK21) | F27: =SUM('02_Модель'!AL21:AW21) | G27: =SUM('02_Модель'!AX21:BI21) | H27: =SUM(C27:G27)
A28: Лагеря | C28: =SUM('02_Модель'!B22:M22) | D28: =SUM('02_Модель'!N22:Y22) | E28: =SUM('02_Модель'!Z22:AK22) | F28: =SUM('02_Модель'!AL22:AW22) | G28: =SUM('02_Модель'!AX22:BI22) | H28: =SUM(C28:G28)
A29: EBITDA | B29: ='11_История_25_26'!N9 | C29: =SUM('02_Модель'!B44:M44) | D29: =SUM('02_Модель'!N44:Y44) | E29: =SUM('02_Модель'!Z44:AK44) | F29: =SUM('02_Модель'!AL44:AW44) | G29: =SUM('02_Модель'!AX44:BI44) | H29: =SUM(C29:G29)
A30: EBITDA margin | C30: =IF(SUM('02_Модель'!B23:M23)=0,0,SUM('02_Модель'!B44:M44)/SUM('02_Модель'!B23:M23)) | D30: =IF(SUM('02_Модель'!N23:Y23)=0,0,SUM('02_Модель'!N44:Y44)/SUM('02_Модель'!N23:Y23)) | E30: =IF(SUM('02_Модель'!Z23:AK23)=0,0,SUM('02_Модель'!Z44:AK44)/SUM('02_Модель'!Z23:AK23)) | F30: =IF(SUM('02_Модель'!AL23:AW23)=0,0,SUM('02_Модель'!AL44:AW44)/SUM('02_Модель'!AL23:AW23)) | G30: =IF(SUM('02_Модель'!AX23:BI23)=0,0,SUM('02_Модель'!AX44:BI44)/SUM('02_Модель'!AX23:BI23)) | H30: =IF(H24=0,0,H29/H24)
A31: Чистый денежный поток | C31: =SUM('02_Модель'!B71:M71) | D31: =SUM('02_Модель'!N71:Y71) | E31: =SUM('02_Модель'!Z71:AK71) | F31: =SUM('02_Модель'!AL71:AW71) | G31: =SUM('02_Модель'!AX71:BI71) | H31: =SUM(C31:G31)
A32: Деньги на конец | C32: ='02_Модель'!M72 | D32: ='02_Модель'!Y72 | E32: ='02_Модель'!AK72 | F32: ='02_Модель'!AW72 | G32: ='02_Модель'!BI72 | H32: =G32
A33: Закупки на склад | C33: =SUM('02_Модель'!B65:M65) | D33: =SUM('02_Модель'!N65:Y65) | E33: =SUM('02_Модель'!Z65:AK65) | F33: =SUM('02_Модель'!AL65:AW65) | G33: =SUM('02_Модель'!AX65:BI65) | H33: =SUM(C33:G33)
A34: Погашение займа | C34: =SUM('02_Модель'!B70:M70) | D34: =SUM('02_Модель'!N70:Y70) | E34: =SUM('02_Модель'!Z70:AK70) | F34: =SUM('02_Модель'!AL70:AW70) | G34: =SUM('02_Модель'!AX70:BI70) | H34: =SUM(C34:G34)
A35: Конечный займ | C35: ='02_Модель'!M75 | D35: ='02_Модель'!Y75 | E35: ='02_Модель'!AK75 | F35: ='02_Модель'!AW75 | G35: ='02_Модель'!BI75 | H35: =G35
A36: Конечный склад | C36: ='02_Модель'!M76 | D36: ='02_Модель'!Y76 | E36: ='02_Модель'!AK76 | F36: ='02_Модель'!AW76 | G36: ='02_Модель'!BI76 | H36: =G36
A37: Операционные выплаты ФК, деньги | C37: =SUM('02_Модель'!B61:M61) | D37: =SUM('02_Модель'!N61:Y61) | E37: =SUM('02_Модель'!Z61:AK61) | F37: =SUM('02_Модель'!AL61:AW61) | G37: =SUM('02_Модель'!AX61:BI61) | H37: =SUM(C37:G37)
A38: Пиковый кассовый дефицит | C38: =MAX(0,-MIN('02_Модель'!B72:M72)) | D38: =MAX(0,-MIN('02_Модель'!N72:Y72)) | E38: =MAX(0,-MIN('02_Модель'!Z72:AK72)) | F38: =MAX(0,-MIN('02_Модель'!AL72:AW72)) | G38: =MAX(0,-MIN('02_Модель'!AX72:BI72)) | H38: =MAX(0,-MIN('02_Модель'!B72:BI72))
A39: CAPEX — всего | C39: =SUM('02_Модель'!B57:M57) | D39: =SUM('02_Модель'!N57:Y57) | E39: =SUM('02_Модель'!Z57:AK57) | F39: =SUM('02_Модель'!AL57:AW57) | G39: =SUM('02_Модель'!AX57:BI57) | H39: =SUM(C39:G39)
A40: Результат с историей / без истории
A41: Режим просмотра | B41: ='01_Вводные'!B188
A42: Выручка, выбранный период | B42: =IF('01_Вводные'!B188="С историей",B24+H24,H24)
A43: EBITDA, выбранный период | B43: =IF('01_Вводные'!B188="С историей",B29+H29,H29)
A44: Что включено | B44: =IF('01_Вводные'!B188="С историей","Доступный факт 25/26 + прогноз 26/27–30/31","Только прогноз 26/27–30/31")
A45: 15_Изменения
A46: Что упрощено и почему
A47: • | B47: Все ручные вводные собраны на одном листе 01_Вводные — больше не нужно искать параметры по разным расчётным вкладкам.
A48: • | B48: Постепенный набор детей сохранён: месяцы 1–12 и 13–24, затем зрелая школа. Расчёт разделён на понятные возрастные группы.
A49: • | B49: Для новых школ сохранены 20 тарифных групп: минимальный роялти проверяется по школе соответствующего тарифа до суммирования. Действующая сеть пока считается агрегированно из-за отсутствия пошкольной базы детей.
A50: • | B50: Три сценария работают на одной логике. Чувствительность считает только два отклонения выбранного драйвера.
A51: • | B51: Выплаты ФК раскрыты отдельно на 10_Выплаты_ФК, воронка — на 05_Воронка. На дашборде 5 графиков: сеть, дети, продажи/открытия, EBITDA, cash/займ/выплаты ФК.
A52: • | B52: Индексация и CAPEX предусмотрены, как в v4. Прямое сравнение с первоначальной моделью — лист 17; порядок работы — лист 19.
A53: • | B53: Все формулы используют обычные функции Excel/Google Sheets без LET/FILTER/XLOOKUP/динамических массивов и внешних ссылок.
A54: 05_Воронка | E54: 10_Выплаты_ФК
A55: 15_Изменения | E55: 14_Ревизия
A56: 16_Инструкция
A60: Динамика сети: школы и активные дети
A103: Месяц | B103: Школы всего | C103: Юрлица | D103: Дети действующей сети | E103: Дети новых школ | F103: Дети всего | G103: Сезон | H103: Месяц для графика | I103: Продажи | J103: Открытия | K103: EBITDA | L103: Cash | M103: Остаток займа | N103: Выплаты ФК
A104: ='06_Сеть_и_дети'!B3 | B104: ='06_Сеть_и_дети'!B17 | C104: ='06_Сеть_и_дети'!B10 | D104: ='06_Сеть_и_дети'!B20 | E104: ='06_Сеть_и_дети'!B24 | F104: ='06_Сеть_и_дети'!B25 | G104: ='06_Сеть_и_дети'!B4 | H104: =CHOOSE(MONTH(A104),"янв","фев","мар","апр","май","июн","июл","авг","сен","окт","ноя","дек")&" "&YEAR(A104) | I104: ='04_Продажи'!B15 | J104: ='04_Продажи'!B18 | K104: ='02_Модель'!B44 | L104: ='02_Модель'!B72 | M104: ='02_Модель'!B75 | N104: ='10_Выплаты_ФК'!B34
A105: ='06_Сеть_и_дети'!C3 | B105: ='06_Сеть_и_дети'!C17 | C105: ='06_Сеть_и_дети'!C10 | D105: ='06_Сеть_и_дети'!C20 | E105: ='06_Сеть_и_дети'!C24 | F105: ='06_Сеть_и_дети'!C25 | G105: ='06_Сеть_и_дети'!C4 | H105: =CHOOSE(MONTH(A105),"янв","фев","мар","апр","май","июн","июл","авг","сен","окт","ноя","дек")&" "&YEAR(A105) | I105: ='04_Продажи'!C15 | J105: ='04_Продажи'!C18 | K105: ='02_Модель'!C44 | L105: ='02_Модель'!C72 | M105: ='02_Модель'!C75 | N105: ='10_Выплаты_ФК'!C34
A106: ='06_Сеть_и_дети'!D3 | B106: ='06_Сеть_и_дети'!D17 | C106: ='06_Сеть_и_дети'!D10 | D106: ='06_Сеть_и_дети'!D20 | E106: ='06_Сеть_и_дети'!D24 | F106: ='06_Сеть_и_дети'!D25 | G106: ='06_Сеть_и_дети'!D4 | H106: =CHOOSE(MONTH(A106),"янв","фев","мар","апр","май","июн","июл","авг","сен","окт","ноя","дек")&" "&YEAR(A106) | I106: ='04_Продажи'!D15 | J106: ='04_Продажи'!D18 | K106: ='02_Модель'!D44 | L106: ='02_Модель'!D72 | M106: ='02_Модель'!D75 | N106: ='10_Выплаты_ФК'!D34
A107: ='06_Сеть_и_дети'!E3 | B107: ='06_Сеть_и_дети'!E17 | C107: ='06_Сеть_и_дети'!E10 | D107: ='06_Сеть_и_дети'!E20 | E107: ='06_Сеть_и_дети'!E24 | F107: ='06_Сеть_и_дети'!E25 | G107: ='06_Сеть_и_дети'!E4 | H107: =CHOOSE(MONTH(A107),"янв","фев","мар","апр","май","июн","июл","авг","сен","окт","ноя","дек")&" "&YEAR(A107) | I107: ='04_Продажи'!E15 | J107: ='04_Продажи'!E18 | K107: ='02_Модель'!E44 | L107: ='02_Модель'!E72 | M107: ='02_Модель'!E75 | N107: ='10_Выплаты_ФК'!E34
A108: ='06_Сеть_и_дети'!F3 | B108: ='06_Сеть_и_дети'!F17 | C108: ='06_Сеть_и_дети'!F10 | D108: ='06_Сеть_и_дети'!F20 | E108: ='06_Сеть_и_дети'!F24 | F108: ='06_Сеть_и_дети'!F25 | G108: ='06_Сеть_и_дети'!F4 | H108: =CHOOSE(MONTH(A108),"янв","фев","мар","апр","май","июн","июл","авг","сен","окт","ноя","дек")&" "&YEAR(A108) | I108: ='04_Продажи'!F15 | J108: ='04_Продажи'!F18 | K108: ='02_Модель'!F44 | L108: ='02_Модель'!F72 | M108: ='02_Модель'!F75 | N108: ='10_Выплаты_ФК'!F34
A109: ='06_Сеть_и_дети'!G3 | B109: ='06_Сеть_и_дети'!G17 | C109: ='06_Сеть_и_дети'!G10 | D109: ='06_Сеть_и_дети'!G20 | E109: ='06_Сеть_и_дети'!G24 | F109: ='06_Сеть_и_дети'!G25 | G109: ='06_Сеть_и_дети'!G4 | H109: =CHOOSE(MONTH(A109),"янв","фев","мар","апр","май","июн","июл","авг","сен","окт","ноя","дек")&" "&YEAR(A109) | I109: ='04_Продажи'!G15 | J109: ='04_Продажи'!G18 | K109: ='02_Модель'!G44 | L109: ='02_Модель'!G72 | M109: ='02_Модель'!G75 | N109: ='10_Выплаты_ФК'!G34
A110: ='06_Сеть_и_дети'!H3 | B110: ='06_Сеть_и_дети'!H17 | C110: ='06_Сеть_и_дети'!H10 | D110: ='06_Сеть_и_дети'!H20 | E110: ='06_Сеть_и_дети'!H24 | F110: ='06_Сеть_и_дети'!H25 | G110: ='06_Сеть_и_дети'!H4 | H110: =CHOOSE(MONTH(A110),"янв","фев","мар","апр","май","июн","июл","авг","сен","окт","ноя","дек")&" "&YEAR(A110) | I110: ='04_Продажи'!H15 | J110: ='04_Продажи'!H18 | K110: ='02_Модель'!H44 | L110: ='02_Модель'!H72 | M110: ='02_Модель'!H75 | N110: ='10_Выплаты_ФК'!H34
A111: ='06_Сеть_и_дети'!I3 | B111: ='06_Сеть_и_дети'!I17 | C111: ='06_Сеть_и_дети'!I10 | D111: ='06_Сеть_и_дети'!I20 | E111: ='06_Сеть_и_дети'!I24 | F111: ='06_Сеть_и_дети'!I25 | G111: ='06_Сеть_и_дети'!I4 | H111: =CHOOSE(MONTH(A111),"янв","фев","мар","апр","май","июн","июл","авг","сен","окт","ноя","дек")&" "&YEAR(A111) | I111: ='04_Продажи'!I15 | J111: ='04_Продажи'!I18 | K111: ='02_Модель'!I44 | L111: ='02_Модель'!I72 | M111: ='02_Модель'!I75 | N111: ='10_Выплаты_ФК'!I34
A112: ='06_Сеть_и_дети'!J3 | B112: ='06_Сеть_и_дети'!J17 | C112: ='06_Сеть_и_дети'!J10 | D112: ='06_Сеть_и_дети'!J20 | E112: ='06_Сеть_и_дети'!J24 | F112: ='06_Сеть_и_дети'!J25 | G112: ='06_Сеть_и_дети'!J4 | H112: =CHOOSE(MONTH(A112),"янв","фев","мар","апр","май","июн","июл","авг","сен","окт","ноя","дек")&" "&YEAR(A112) | I112: ='04_Продажи'!J15 | J112: ='04_Продажи'!J18 | K112: ='02_Модель'!J44 | L112: ='02_Модель'!J72 | M112: ='02_Модель'!J75 | N112: ='10_Выплаты_ФК'!J34
A113: ='06_Сеть_и_дети'!K3 | B113: ='06_Сеть_и_дети'!K17 | C113: ='06_Сеть_и_дети'!K10 | D113: ='06_Сеть_и_дети'!K20 | E113: ='06_Сеть_и_дети'!K24 | F113: ='06_Сеть_и_дети'!K25 | G113: ='06_Сеть_и_дети'!K4 | H113: =CHOOSE(MONTH(A113),"янв","фев","мар","апр","май","июн","июл","авг","сен","окт","ноя","дек")&" "&YEAR(A113) | I113: ='04_Продажи'!K15 | J113: ='04_Продажи'!K18 | K113: ='02_Модель'!K44 | L113: ='02_Модель'!K72 | M113: ='02_Модель'!K75 | N113: ='10_Выплаты_ФК'!K34
A114: ='06_Сеть_и_дети'!L3 | B114: ='06_Сеть_и_дети'!L17 | C114: ='06_Сеть_и_дети'!L10 | D114: ='06_Сеть_и_дети'!L20 | E114: ='06_Сеть_и_дети'!L24 | F114: ='06_Сеть_и_дети'!L25 | G114: ='06_Сеть_и_дети'!L4 | H114: =CHOOSE(MONTH(A114),"янв","фев","мар","апр","май","июн","июл","авг","сен","окт","ноя","дек")&" "&YEAR(A114) | I114: ='04_Продажи'!L15 | J114: ='04_Продажи'!L18 | K114: ='02_Модель'!L44 | L114: ='02_Модель'!L72 | M114: ='02_Модель'!L75 | N114: ='10_Выплаты_ФК'!L34
A115: ='06_Сеть_и_дети'!M3 | B115: ='06_Сеть_и_дети'!M17 | C115: ='06_Сеть_и_дети'!M10 | D115: ='06_Сеть_и_дети'!M20 | E115: ='06_Сеть_и_дети'!M24 | F115: ='06_Сеть_и_дети'!M25 | G115: ='06_Сеть_и_дети'!M4 | H115: =CHOOSE(MONTH(A115),"янв","фев","мар","апр","май","июн","июл","авг","сен","окт","ноя","дек")&" "&YEAR(A115) | I115: ='04_Продажи'!M15 | J115: ='04_Продажи'!M18 | K115: ='02_Модель'!M44 | L115: ='02_Модель'!M72 | M115: ='02_Модель'!M75 | N115: ='10_Выплаты_ФК'!M34
A116: ='06_Сеть_и_дети'!N3 | B116: ='06_Сеть_и_дети'!N17 | C116: ='06_Сеть_и_дети'!N10 | D116: ='06_Сеть_и_дети'!N20 | E116: ='06_Сеть_и_дети'!N24 | F116: ='06_Сеть_и_дети'!N25 | G116: ='06_Сеть_и_дети'!N4 | H116: =CHOOSE(MONTH(A116),"янв","фев","мар","апр","май","июн","июл","авг","сен","окт","ноя","дек")&" "&YEAR(A116) | I116: ='04_Продажи'!N15 | J116: ='04_Продажи'!N18 | K116: ='02_Модель'!N44 | L116: ='02_Модель'!N72 | M116: ='02_Модель'!N75 | N116: ='10_Выплаты_ФК'!N34
A117: ='06_Сеть_и_дети'!O3 | B117: ='06_Сеть_и_дети'!O17 | C117: ='06_Сеть_и_дети'!O10 | D117: ='06_Сеть_и_дети'!O20 | E117: ='06_Сеть_и_дети'!O24 | F117: ='06_Сеть_и_дети'!O25 | G117: ='06_Сеть_и_дети'!O4 | H117: =CHOOSE(MONTH(A117),"янв","фев","мар","апр","май","июн","июл","авг","сен","окт","ноя","дек")&" "&YEAR(A117) | I117: ='04_Продажи'!O15 | J117: ='04_Продажи'!O18 | K117: ='02_Модель'!O44 | L117: ='02_Модель'!O72 | M117: ='02_Модель'!O75 | N117: ='10_Выплаты_ФК'!O34
A118: ='06_Сеть_и_дети'!P3 | B118: ='06_Сеть_и_дети'!P17 | C118: ='06_Сеть_и_дети'!P10 | D118: ='06_Сеть_и_дети'!P20 | E118: ='06_Сеть_и_дети'!P24 | F118: ='06_Сеть_и_дети'!P25 | G118: ='06_Сеть_и_дети'!P4 | H118: =CHOOSE(MONTH(A118),"янв","фев","мар","апр","май","июн","июл","авг","сен","окт","ноя","дек")&" "&YEAR(A118) | I118: ='04_Продажи'!P15 | J118: ='04_Продажи'!P18 | K118: ='02_Модель'!P44 | L118: ='02_Модель'!P72 | M118: ='02_Модель'!P75 | N118: ='10_Выплаты_ФК'!P34
A119: ='06_Сеть_и_дети'!Q3 | B119: ='06_Сеть_и_дети'!Q17 | C119: ='06_Сеть_и_дети'!Q10 | D119: ='06_Сеть_и_дети'!Q20 | E119: ='06_Сеть_и_дети'!Q24 | F119: ='06_Сеть_и_дети'!Q25 | G119: ='06_Сеть_и_дети'!Q4 | H119: =CHOOSE(MONTH(A119),"янв","фев","мар","апр","май","июн","июл","авг","сен","окт","ноя","дек")&" "&YEAR(A119) | I119: ='04_Продажи'!Q15 | J119: ='04_Продажи'!Q18 | K119: ='02_Модель'!Q44 | L119: ='02_Модель'!Q72 | M119: ='02_Модель'!Q75 | N119: ='10_Выплаты_ФК'!Q34
A120: ='06_Сеть_и_дети'!R3 | B120: ='06_Сеть_и_дети'!R17 | C120: ='06_Сеть_и_дети'!R10 | D120: ='06_Сеть_и_дети'!R20 | E120: ='06_Сеть_и_дети'!R24 | F120: ='06_Сеть_и_дети'!R25 | G120: ='06_Сеть_и_дети'!R4 | H120: =CHOOSE(MONTH(A120),"янв","фев","мар","апр","май","июн","июл","авг","сен","окт","ноя","дек")&" "&YEAR(A120) | I120: ='04_Продажи'!R15 | J120: ='04_Продажи'!R18 | K120: ='02_Модель'!R44 | L120: ='02_Модель'!R72 | M120: ='02_Модель'!R75 | N120: ='10_Выплаты_ФК'!R34
A121: ='06_Сеть_и_дети'!S3 | B121: ='06_Сеть_и_дети'!S17 | C121: ='06_Сеть_и_дети'!S10 | D121: ='06_Сеть_и_дети'!S20 | E121: ='06_Сеть_и_дети'!S24 | F121: ='06_Сеть_и_дети'!S25 | G121: ='06_Сеть_и_дети'!S4 | H121: =CHOOSE(MONTH(A121),"янв","фев","мар","апр","май","июн","июл","авг","сен","окт","ноя","дек")&" "&YEAR(A121) | I121: ='04_Продажи'!S15 | J121: ='04_Продажи'!S18 | K121: ='02_Модель'!S44 | L121: ='02_Модель'!S72 | M121: ='02_Модель'!S75 | N121: ='10_Выплаты_ФК'!S34
A122: ='06_Сеть_и_дети'!T3 | B122: ='06_Сеть_и_дети'!T17 | C122: ='06_Сеть_и_дети'!T10 | D122: ='06_Сеть_и_дети'!T20 | E122: ='06_Сеть_и_дети'!T24 | F122: ='06_Сеть_и_дети'!T25 | G122: ='06_Сеть_и_дети'!T4 | H122: =CHOOSE(MONTH(A122),"янв","фев","мар","апр","май","июн","июл","авг","сен","окт","ноя","дек")&" "&YEAR(A122) | I122: ='04_Продажи'!T15 | J122: ='04_Продажи'!T18 | K122: ='02_Модель'!T44 | L122: ='02_Модель'!T72 | M122: ='02_Модель'!T75 | N122: ='10_Выплаты_ФК'!T34
A123: ='06_Сеть_и_дети'!U3 | B123: ='06_Сеть_и_дети'!U17 | C123: ='06_Сеть_и_дети'!U10 | D123: ='06_Сеть_и_дети'!U20 | E123: ='06_Сеть_и_дети'!U24 | F123: ='06_Сеть_и_дети'!U25 | G123: ='06_Сеть_и_дети'!U4 | H123: =CHOOSE(MONTH(A123),"янв","фев","мар","апр","май","июн","июл","авг","сен","окт","ноя","дек")&" "&YEAR(A123) | I123: ='04_Продажи'!U15 | J123: ='04_Продажи'!U18 | K123: ='02_Модель'!U44 | L123: ='02_Модель'!U72 | M123: ='02_Модель'!U75 | N123: ='10_Выплаты_ФК'!U34
A124: ='06_Сеть_и_дети'!V3 | B124: ='06_Сеть_и_дети'!V17 | C124: ='06_Сеть_и_дети'!V10 | D124: ='06_Сеть_и_дети'!V20 | E124: ='06_Сеть_и_дети'!V24 | F124: ='06_Сеть_и_дети'!V25 | G124: ='06_Сеть_и_дети'!V4 | H124: =CHOOSE(MONTH(A124),"янв","фев","мар","апр","май","июн","июл","авг","сен","окт","ноя","дек")&" "&YEAR(A124) | I124: ='04_Продажи'!V15 | J124: ='04_Продажи'!V18 | K124: ='02_Модель'!V44 | L124: ='02_Модель'!V72 | M124: ='02_Модель'!V75 | N124: ='10_Выплаты_ФК'!V34
A125: ='06_Сеть_и_дети'!W3 | B125: ='06_Сеть_и_дети'!W17 | C125: ='06_Сеть_и_дети'!W10 | D125: ='06_Сеть_и_дети'!W20 | E125: ='06_Сеть_и_дети'!W24 | F125: ='06_Сеть_и_дети'!W25 | G125: ='06_Сеть_и_дети'!W4 | H125: =CHOOSE(MONTH(A125),"янв","фев","мар","апр","май","июн","июл","авг","сен","окт","ноя","дек")&" "&YEAR(A125) | I125: ='04_Продажи'!W15 | J125: ='04_Продажи'!W18 | K125: ='02_Модель'!W44 | L125: ='02_Модель'!W72 | M125: ='02_Модель'!W75 | N125: ='10_Выплаты_ФК'!W34
A126: ='06_Сеть_и_дети'!X3 | B126: ='06_Сеть_и_дети'!X17 | C126: ='06_Сеть_и_дети'!X10 | D126: ='06_Сеть_и_дети'!X20 | E126: ='06_Сеть_и_дети'!X24 | F126: ='06_Сеть_и_дети'!X25 | G126: ='06_Сеть_и_дети'!X4 | H126: =CHOOSE(MONTH(A126),"янв","фев","мар","апр","май","июн","июл","авг","сен","окт","ноя","дек")&" "&YEAR(A126) | I126: ='04_Продажи'!X15 | J126: ='04_Продажи'!X18 | K126: ='02_Модель'!X44 | L126: ='02_Модель'!X72 | M126: ='02_Модель'!X75 | N126: ='10_Выплаты_ФК'!X34
A127: ='06_Сеть_и_дети'!Y3 | B127: ='06_Сеть_и_дети'!Y17 | C127: ='06_Сеть_и_дети'!Y10 | D127: ='06_Сеть_и_дети'!Y20 | E127: ='06_Сеть_и_дети'!Y24 | F127: ='06_Сеть_и_дети'!Y25 | G127: ='06_Сеть_и_дети'!Y4 | H127: =CHOOSE(MONTH(A127),"янв","фев","мар","апр","май","июн","июл","авг","сен","окт","ноя","дек")&" "&YEAR(A127) | I127: ='04_Продажи'!Y15 | J127: ='04_Продажи'!Y18 | K127: ='02_Модель'!Y44 | L127: ='02_Модель'!Y72 | M127: ='02_Модель'!Y75 | N127: ='10_Выплаты_ФК'!Y34
A128: ='06_Сеть_и_дети'!Z3 | B128: ='06_Сеть_и_дети'!Z17 | C128: ='06_Сеть_и_дети'!Z10 | D128: ='06_Сеть_и_дети'!Z20 | E128: ='06_Сеть_и_дети'!Z24 | F128: ='06_Сеть_и_дети'!Z25 | G128: ='06_Сеть_и_дети'!Z4 | H128: =CHOOSE(MONTH(A128),"янв","фев","мар","апр","май","июн","июл","авг","сен","окт","ноя","дек")&" "&YEAR(A128) | I128: ='04_Продажи'!Z15 | J128: ='04_Продажи'!Z18 | K128: ='02_Модель'!Z44 | L128: ='02_Модель'!Z72 | M128: ='02_Модель'!Z75 | N128: ='10_Выплаты_ФК'!Z34
A129: ='06_Сеть_и_дети'!AA3 | B129: ='06_Сеть_и_дети'!AA17 | C129: ='06_Сеть_и_дети'!AA10 | D129: ='06_Сеть_и_дети'!AA20 | E129: ='06_Сеть_и_дети'!AA24 | F129: ='06_Сеть_и_дети'!AA25 | G129: ='06_Сеть_и_дети'!AA4 | H129: =CHOOSE(MONTH(A129),"янв","фев","мар","апр","май","июн","июл","авг","сен","окт","ноя","дек")&" "&YEAR(A129) | I129: ='04_Продажи'!AA15 | J129: ='04_Продажи'!AA18 | K129: ='02_Модель'!AA44 | L129: ='02_Модель'!AA72 | M129: ='02_Модель'!AA75 | N129: ='10_Выплаты_ФК'!AA34
A130: ='06_Сеть_и_дети'!AB3 | B130: ='06_Сеть_и_дети'!AB17 | C130: ='06_Сеть_и_дети'!AB10 | D130: ='06_Сеть_и_дети'!AB20 | E130: ='06_Сеть_и_дети'!AB24 | F130: ='06_Сеть_и_дети'!AB25 | G130: ='06_Сеть_и_дети'!AB4 | H130: =CHOOSE(MONTH(A130),"янв","фев","мар","апр","май","июн","июл","авг","сен","окт","ноя","дек")&" "&YEAR(A130) | I130: ='04_Продажи'!AB15 | J130: ='04_Продажи'!AB18 | K130: ='02_Модель'!AB44 | L130: ='02_Модель'!AB72 | M130: ='02_Модель'!AB75 | N130: ='10_Выплаты_ФК'!AB34
A131: ='06_Сеть_и_дети'!AC3 | B131: ='06_Сеть_и_дети'!AC17 | C131: ='06_Сеть_и_дети'!AC10 | D131: ='06_Сеть_и_дети'!AC20 | E131: ='06_Сеть_и_дети'!AC24 | F131: ='06_Сеть_и_дети'!AC25 | G131: ='06_Сеть_и_дети'!AC4 | H131: =CHOOSE(MONTH(A131),"янв","фев","мар","апр","май","июн","июл","авг","сен","окт","ноя","дек")&" "&YEAR(A131) | I131: ='04_Продажи'!AC15 | J131: ='04_Продажи'!AC18 | K131: ='02_Модель'!AC44 | L131: ='02_Модель'!AC72 | M131: ='02_Модель'!AC75 | N131: ='10_Выплаты_ФК'!AC34
A132: ='06_Сеть_и_дети'!AD3 | B132: ='06_Сеть_и_дети'!AD17 | C132: ='06_Сеть_и_дети'!AD10 | D132: ='06_Сеть_и_дети'!AD20 | E132: ='06_Сеть_и_дети'!AD24 | F132: ='06_Сеть_и_дети'!AD25 | G132: ='06_Сеть_и_дети'!AD4 | H132: =CHOOSE(MONTH(A132),"янв","фев","мар","апр","май","июн","июл","авг","сен","окт","ноя","дек")&" "&YEAR(A132) | I132: ='04_Продажи'!AD15 | J132: ='04_Продажи'!AD18 | K132: ='02_Модель'!AD44 | L132: ='02_Модель'!AD72 | M132: ='02_Модель'!AD75 | N132: ='10_Выплаты_ФК'!AD34
A133: ='06_Сеть_и_дети'!AE3 | B133: ='06_Сеть_и_дети'!AE17 | C133: ='06_Сеть_и_дети'!AE10 | D133: ='06_Сеть_и_дети'!AE20 | E133: ='06_Сеть_и_дети'!AE24 | F133: ='06_Сеть_и_дети'!AE25 | G133: ='06_Сеть_и_дети'!AE4 | H133: =CHOOSE(MONTH(A133),"янв","фев","мар","апр","май","июн","июл","авг","сен","окт","ноя","дек")&" "&YEAR(A133) | I133: ='04_Продажи'!AE15 | J133: ='04_Продажи'!AE18 | K133: ='02_Модель'!AE44 | L133: ='02_Модель'!AE72 | M133: ='02_Модель'!AE75 | N133: ='10_Выплаты_ФК'!AE34
A134: ='06_Сеть_и_дети'!AF3 | B134: ='06_Сеть_и_дети'!AF17 | C134: ='06_Сеть_и_дети'!AF10 | D134: ='06_Сеть_и_дети'!AF20 | E134: ='06_Сеть_и_дети'!AF24 | F134: ='06_Сеть_и_дети'!AF25 | G134: ='06_Сеть_и_дети'!AF4 | H134: =CHOOSE(MONTH(A134),"янв","фев","мар","апр","май","июн","июл","авг","сен","окт","ноя","дек")&" "&YEAR(A134) | I134: ='04_Продажи'!AF15 | J134: ='04_Продажи'!AF18 | K134: ='02_Модель'!AF44 | L134: ='02_Модель'!AF72 | M134: ='02_Модель'!AF75 | N134: ='10_Выплаты_ФК'!AF34
A135: ='06_Сеть_и_дети'!AG3 | B135: ='06_Сеть_и_дети'!AG17 | C135: ='06_Сеть_и_дети'!AG10 | D135: ='06_Сеть_и_дети'!AG20 | E135: ='06_Сеть_и_дети'!AG24 | F135: ='06_Сеть_и_дети'!AG25 | G135: ='06_Сеть_и_дети'!AG4 | H135: =CHOOSE(MONTH(A135),"янв","фев","мар","апр","май","июн","июл","авг","сен","окт","ноя","дек")&" "&YEAR(A135) | I135: ='04_Продажи'!AG15 | J135: ='04_Продажи'!AG18 | K135: ='02_Модель'!AG44 | L135: ='02_Модель'!AG72 | M135: ='02_Модель'!AG75 | N135: ='10_Выплаты_ФК'!AG34
A136: ='06_Сеть_и_дети'!AH3 | B136: ='06_Сеть_и_дети'!AH17 | C136: ='06_Сеть_и_дети'!AH10 | D136: ='06_Сеть_и_дети'!AH20 | E136: ='06_Сеть_и_дети'!AH24 | F136: ='06_Сеть_и_дети'!AH25 | G136: ='06_Сеть_и_дети'!AH4 | H136: =CHOOSE(MONTH(A136),"янв","фев","мар","апр","май","июн","июл","авг","сен","окт","ноя","дек")&" "&YEAR(A136) | I136: ='04_Продажи'!AH15 | J136: ='04_Продажи'!AH18 | K136: ='02_Модель'!AH44 | L136: ='02_Модель'!AH72 | M136: ='02_Модель'!AH75 | N136: ='10_Выплаты_ФК'!AH34
A137: ='06_Сеть_и_дети'!AI3 | B137: ='06_Сеть_и_дети'!AI17 | C137: ='06_Сеть_и_дети'!AI10 | D137: ='06_Сеть_и_дети'!AI20 | E137: ='06_Сеть_и_дети'!AI24 | F137: ='06_Сеть_и_дети'!AI25 | G137: ='06_Сеть_и_дети'!AI4 | H137: =CHOOSE(MONTH(A137),"янв","фев","мар","апр","май","июн","июл","авг","сен","окт","ноя","дек")&" "&YEAR(A137) | I137: ='04_Продажи'!AI15 | J137: ='04_Продажи'!AI18 | K137: ='02_Модель'!AI44 | L137: ='02_Модель'!AI72 | M137: ='02_Модель'!AI75 | N137: ='10_Выплаты_ФК'!AI34
A138: ='06_Сеть_и_дети'!AJ3 | B138: ='06_Сеть_и_дети'!AJ17 | C138: ='06_Сеть_и_дети'!AJ10 | D138: ='06_Сеть_и_дети'!AJ20 | E138: ='06_Сеть_и_дети'!AJ24 | F138: ='06_Сеть_и_дети'!AJ25 | G138: ='06_Сеть_и_дети'!AJ4 | H138: =CHOOSE(MONTH(A138),"янв","фев","мар","апр","май","июн","июл","авг","сен","окт","ноя","дек")&" "&YEAR(A138) | I138: ='04_Продажи'!AJ15 | J138: ='04_Продажи'!AJ18 | K138: ='02_Модель'!AJ44 | L138: ='02_Модель'!AJ72 | M138: ='02_Модель'!AJ75 | N138: ='10_Выплаты_ФК'!AJ34
A139: ='06_Сеть_и_дети'!AK3 | B139: ='06_Сеть_и_дети'!AK17 | C139: ='06_Сеть_и_дети'!AK10 | D139: ='06_Сеть_и_дети'!AK20 | E139: ='06_Сеть_и_дети'!AK24 | F139: ='06_Сеть_и_дети'!AK25 | G139: ='06_Сеть_и_дети'!AK4 | H139: =CHOOSE(MONTH(A139),"янв","фев","мар","апр","май","июн","июл","авг","сен","окт","ноя","дек")&" "&YEAR(A139) | I139: ='04_Продажи'!AK15 | J139: ='04_Продажи'!AK18 | K139: ='02_Модель'!AK44 | L139: ='02_Модель'!AK72 | M139: ='02_Модель'!AK75 | N139: ='10_Выплаты_ФК'!AK34
A140: ='06_Сеть_и_дети'!AL3 | B140: ='06_Сеть_и_дети'!AL17 | C140: ='06_Сеть_и_дети'!AL10 | D140: ='06_Сеть_и_дети'!AL20 | E140: ='06_Сеть_и_дети'!AL24 | F140: ='06_Сеть_и_дети'!AL25 | G140: ='06_Сеть_и_дети'!AL4 | H140: =CHOOSE(MONTH(A140),"янв","фев","мар","апр","май","июн","июл","авг","сен","окт","ноя","дек")&" "&YEAR(A140) | I140: ='04_Продажи'!AL15 | J140: ='04_Продажи'!AL18 | K140: ='02_Модель'!AL44 | L140: ='02_Модель'!AL72 | M140: ='02_Модель'!AL75 | N140: ='10_Выплаты_ФК'!AL34
A141: ='06_Сеть_и_дети'!AM3 | B141: ='06_Сеть_и_дети'!AM17 | C141: ='06_Сеть_и_дети'!AM10 | D141: ='06_Сеть_и_дети'!AM20 | E141: ='06_Сеть_и_дети'!AM24 | F141: ='06_Сеть_и_дети'!AM25 | G141: ='06_Сеть_и_дети'!AM4 | H141: =CHOOSE(MONTH(A141),"янв","фев","мар","апр","май","июн","июл","авг","сен","окт","ноя","дек")&" "&YEAR(A141) | I141: ='04_Продажи'!AM15 | J141: ='04_Продажи'!AM18 | K141: ='02_Модель'!AM44 | L141: ='02_Модель'!AM72 | M141: ='02_Модель'!AM75 | N141: ='10_Выплаты_ФК'!AM34
A142: ='06_Сеть_и_дети'!AN3 | B142: ='06_Сеть_и_дети'!AN17 | C142: ='06_Сеть_и_дети'!AN10 | D142: ='06_Сеть_и_дети'!AN20 | E142: ='06_Сеть_и_дети'!AN24 | F142: ='06_Сеть_и_дети'!AN25 | G142: ='06_Сеть_и_дети'!AN4 | H142: =CHOOSE(MONTH(A142),"янв","фев","мар","апр","май","июн","июл","авг","сен","окт","ноя","дек")&" "&YEAR(A142) | I142: ='04_Продажи'!AN15 | J142: ='04_Продажи'!AN18 | K142: ='02_Модель'!AN44 | L142: ='02_Модель'!AN72 | M142: ='02_Модель'!AN75 | N142: ='10_Выплаты_ФК'!AN34
A143: ='06_Сеть_и_дети'!AO3 | B143: ='06_Сеть_и_дети'!AO17 | C143: ='06_Сеть_и_дети'!AO10 | D143: ='06_Сеть_и_дети'!AO20 | E143: ='06_Сеть_и_дети'!AO24 | F143: ='06_Сеть_и_дети'!AO25 | G143: ='06_Сеть_и_дети'!AO4 | H143: =CHOOSE(MONTH(A143),"янв","фев","мар","апр","май","июн","июл","авг","сен","окт","ноя","дек")&" "&YEAR(A143) | I143: ='04_Продажи'!AO15 | J143: ='04_Продажи'!AO18 | K143: ='02_Модель'!AO44 | L143: ='02_Модель'!AO72 | M143: ='02_Модель'!AO75 | N143: ='10_Выплаты_ФК'!AO34
A144: ='06_Сеть_и_дети'!AP3 | B144: ='06_Сеть_и_дети'!AP17 | C144: ='06_Сеть_и_дети'!AP10 | D144: ='06_Сеть_и_дети'!AP20 | E144: ='06_Сеть_и_дети'!AP24 | F144: ='06_Сеть_и_дети'!AP25 | G144: ='06_Сеть_и_дети'!AP4 | H144: =CHOOSE(MONTH(A144),"янв","фев","мар","апр","май","июн","июл","авг","сен","окт","ноя","дек")&" "&YEAR(A144) | I144: ='04_Продажи'!AP15 | J144: ='04_Продажи'!AP18 | K144: ='02_Модель'!AP44 | L144: ='02_Модель'!AP72 | M144: ='02_Модель'!AP75 | N144: ='10_Выплаты_ФК'!AP34
A145: ='06_Сеть_и_дети'!AQ3 | B145: ='06_Сеть_и_дети'!AQ17 | C145: ='06_Сеть_и_дети'!AQ10 | D145: ='06_Сеть_и_дети'!AQ20 | E145: ='06_Сеть_и_дети'!AQ24 | F145: ='06_Сеть_и_дети'!AQ25 | G145: ='06_Сеть_и_дети'!AQ4 | H145: =CHOOSE(MONTH(A145),"янв","фев","мар","апр","май","июн","июл","авг","сен","окт","ноя","дек")&" "&YEAR(A145) | I145: ='04_Продажи'!AQ15 | J145: ='04_Продажи'!AQ18 | K145: ='02_Модель'!AQ44 | L145: ='02_Модель'!AQ72 | M145: ='02_Модель'!AQ75 | N145: ='10_Выплаты_ФК'!AQ34
A146: ='06_Сеть_и_дети'!AR3 | B146: ='06_Сеть_и_дети'!AR17 | C146: ='06_Сеть_и_дети'!AR10 | D146: ='06_Сеть_и_дети'!AR20 | E146: ='06_Сеть_и_дети'!AR24 | F146: ='06_Сеть_и_дети'!AR25 | G146: ='06_Сеть_и_дети'!AR4 | H146: =CHOOSE(MONTH(A146),"янв","фев","мар","апр","май","июн","июл","авг","сен","окт","ноя","дек")&" "&YEAR(A146) | I146: ='04_Продажи'!AR15 | J146: ='04_Продажи'!AR18 | K146: ='02_Модель'!AR44 | L146: ='02_Модель'!AR72 | M146: ='02_Модель'!AR75 | N146: ='10_Выплаты_ФК'!AR34
A147: ='06_Сеть_и_дети'!AS3 | B147: ='06_Сеть_и_дети'!AS17 | C147: ='06_Сеть_и_дети'!AS10 | D147: ='06_Сеть_и_дети'!AS20 | E147: ='06_Сеть_и_дети'!AS24 | F147: ='06_Сеть_и_дети'!AS25 | G147: ='06_Сеть_и_дети'!AS4 | H147: =CHOOSE(MONTH(A147),"янв","фев","мар","апр","май","июн","июл","авг","сен","окт","ноя","дек")&" "&YEAR(A147) | I147: ='04_Продажи'!AS15 | J147: ='04_Продажи'!AS18 | K147: ='02_Модель'!AS44 | L147: ='02_Модель'!AS72 | M147: ='02_Модель'!AS75 | N147: ='10_Выплаты_ФК'!AS34
A148: ='06_Сеть_и_дети'!AT3 | B148: ='06_Сеть_и_дети'!AT17 | C148: ='06_Сеть_и_дети'!AT10 | D148: ='06_Сеть_и_дети'!AT20 | E148: ='06_Сеть_и_дети'!AT24 | F148: ='06_Сеть_и_дети'!AT25 | G148: ='06_Сеть_и_дети'!AT4 | H148: =CHOOSE(MONTH(A148),"янв","фев","мар","апр","май","июн","июл","авг","сен","окт","ноя","дек")&" "&YEAR(A148) | I148: ='04_Продажи'!AT15 | J148: ='04_Продажи'!AT18 | K148: ='02_Модель'!AT44 | L148: ='02_Модель'!AT72 | M148: ='02_Модель'!AT75 | N148: ='10_Выплаты_ФК'!AT34
...

Sheet 01_Вводные
A1: Финмодель Спартак — единый лист вводных
A2: Легенда: | B2: ввод | C2: уточнить | D2: переключатель | E2: блок ревизии | F2: формула — не трогать | G2: → 00_Старт: оглавление, переключатели, легенда | H2: → 14а_Сверка_с_ТЗ: пункт ТЗ → формула
A3: Правило работы | B3: Менять жёлтые ячейки только здесь. Сценарий: B192. Чувствительность: B233:B234. Параметры, микс и история собраны на одном листе.
A4: Сценарии и чувствительность | G4: → Раздел 11: сценарии и чувствительность | H4: → Раздел 13: тарифные группы
A5: 1. Календарь, стартовая сеть и оборотный капитал
A6: Параметр | B6: Значение | C6: Ед. | D6: Статус / источник | E6: Комментарий | G6: → Раздел 12: настройки ревизии | H6: → Раздел 14: CAPEX и индексация
A7: Дата старта модели | B7: 46266 | C7: дата | D7: ТЗ 5.1 | E7: Сезон считается от даты старта: 12 месяцев — один сезон. Сезонность посещаемости, веса плана продаж и согласованный мерч привязаны к календарю и не зависят от месяца старта.
A8: Горизонт прогноза | B8: 60 | C8: мес. | D8: Фиксированная структура | E8: Фиксированное окно 60 месяцев + 6 технических. Изменение длины требует расширения структуры. | G8: → Раздел 15–16: займ, открытие школ, роялти по группам | H8: → Раздел 17: история сезона 25/26
A9: Активные школы действующей сети на старте | B9: 104 | C9: шт. | D9: Фактический реестр на 09.09.2026 | E9: 104 действующие школы у 51 действующего партнёра; 3 новых партнёра пока без школ и в 104 не входят.
A10: Активные юрлица на старте | B10: 51 | C10: шт. | D10: Реестр сети 21.08.2026 | E10: 51 действующий партнёр: 48 подписали ДКК, 3 в переговорах. В ТЗ v6.011 указано 49 — цифра реестра точнее, подтверждена 11.09.2026.
A11: Дети действующей сети, 100% база | B11: 5200 | C11: чел. | D11: ТЗ 5.3 | E11: 100% загрузка; внутри сезона применяется посещаемость
A12: Рост детей действующей сети | B12: 0.1 | C12: %/год | D12: ТЗ 5.3 | E12: Сложный рост, пересчёт каждый сентябрь
A13: Закрытие школ / юрлиц | B13: 0.03 | C13: %/год | D13: Согласовано 11.09.2026 | E13: =IF($B$13=0,"Механика работает, пока 0%","Закрывается "&ROUND($B$13*100,1)&" % школ и юрлиц в год; помесячно через коэффициент B14")
A14: Месячный коэффициент сохранения | B14: =(1-B13)^(1/12) | C14: коэфф. | D14: Расчёт | E14: Технический коэффициент для закрытий
A15: Лаг продажа → открытие | B15: 2 | C15: мес. | D15: ТЗ 5.2 | E15: Продажа, открытие и ERP — разные события
A16: Новых юрлиц на 1 продажу | B16: 1 | C16: юрлиц/продажу | D16: Временно | E16: Связь продаж с новыми юрлицами. Пока 1:1; отдельно от количества школ на партнёра.
A17: Стартовый денежный остаток | B17: 187878 | C17: ₽ | D17: ДДС на 02.07.2026 | E17: Обновить на 31.08.2026
A18: Дебиторка | B18: =$B$225*$F$203 | C18: дней | D18: Расчет по сценарию | E18: Базовое допущение | G18: ← формула; база: B225
A19: Кредиторка | B19: 15 | C19: дней | D19: ТЗ 8 | E19: Базовое допущение
A20: Доля поступления в текущем месяце | B20: =MAX(0,MIN(1,(30-B18)/30)) | C20: % | D20: Расчёт | E20: 15 дней ≈ 50% текущий / 50% следующий месяц
A21: Доля оплаты в текущем месяце | B21: =MAX(0,MIN(1,(30-B19)/30)) | C21: % | D21: Расчёт | E21: 15 дней ≈ 50% текущий / 50% следующий месяц
A22: Новых школ на 1 продажу / нового партнёра | B22: 1.5 | C22: школ/продажу | D22: Согласовано 11.09.2026 | E22: ="Новый партнёр открывает "&ROUND($B$22,1)&" школы. Действующая сеть: 2,04 школы на партнёра (104 на 51)"
A23: 2. Продажи франшиз и маркетинг
A24: Параметр | B24: Значение | C24: Ед. | D24: Статус / источник | E24: Комментарий
A25: Конверсия лид → продажа | B25: 0.03 | C25: % | D25: ТЗ 7
A26: Таргет на будущую продажу | B26: =$B$224*$F$202 | C26: ₽/продажа | D26: Расчет по сценарию | E26: Обычно M-2; для октября 2026 исключение M-1 | G26: ← формула; база: B224
A27: Лаг таргета до продажи | B27: 2 | C27: мес. | D27: ТЗ 7 | E27: Октябрь 2026 — отдельное исключение
A28: БИБОСС — сумма | B28: 250000 | C28: ₽ | D28: ТЗ 7 | E28: Ежегодно
A29: БИБОСС — месяц | B29: 10 | C29: номер месяца | D29: ТЗ 7 | E29: Октябрь
A30: TopFranchise — сумма | B30: 250000 | C30: ₽ | D30: ТЗ 7 | E30: Ежегодно
A31: TopFranchise — месяц | B31: 11 | C31: номер месяца | D31: ТЗ 7 | E31: Ноябрь
A32: Forbes — сумма | B32: 250000 | C32: ₽ | D32: ТЗ 7 | E32: Ежегодно
A33: Forbes — месяц | B33: 12 | C33: номер месяца | D33: ТЗ 7 | E33: Декабрь
A34: 2а. Планы продаж и сезонность (веса — по календарным месяцам, первый месяц модели без продаж)
A35: Сезон | B35: Годовой план | C35: Сен | D35: Окт | E35: Ноя | F35: Дек | G35: Янв | H35: Фев | I35: Мар | J35: Апр | K35: Май | L35: Июн | M35: Июл | N35: Авг | O35: Контроль
A36: 1 | B36: =$B$210*$F$198 | C36: 0.18 | D36: 0.09 | E36: 0.03 | F36: 0.02 | G36: 0.08 | H36: 0.13 | I36: 0.05 | J36: 0.06 | K36: 0.08 | L36: 0.05 | M36: 0.09 | N36: 0.14 | O36: =SUM(C36:N36)
A37: 2 | B37: =$B$211*$F$198 | C37: 0.18 | D37: 0.09 | E37: 0.03 | F37: 0.02 | G37: 0.08 | H37: 0.13 | I37: 0.05 | J37: 0.06 | K37: 0.08 | L37: 0.05 | M37: 0.09 | N37: 0.14 | O37: =SUM(C37:N37)
A38: 3 | B38: =$B$212*$F$198 | C38: 0.18 | D38: 0.09 | E38: 0.03 | F38: 0.02 | G38: 0.08 | H38: 0.13 | I38: 0.05 | J38: 0.06 | K38: 0.08 | L38: 0.05 | M38: 0.09 | N38: 0.14 | O38: =SUM(C38:N38)
A39: 4 | B39: =$B$213*$F$198 | C39: 0.18 | D39: 0.09 | E39: 0.03 | F39: 0.02 | G39: 0.08 | H39: 0.13 | I39: 0.05 | J39: 0.06 | K39: 0.08 | L39: 0.05 | M39: 0.09 | N39: 0.14 | O39: =SUM(C39:N39)
A40: 5 | B40: =$B$214*$F$198 | C40: 0.18 | D40: 0.09 | E40: 0.03 | F40: 0.02 | G40: 0.08 | H40: 0.13 | I40: 0.05 | J40: 0.06 | K40: 0.08 | L40: 0.05 | M40: 0.09 | N40: 0.14 | O40: =SUM(C40:N40)
A42: 3. Дети и сезонность посещаемости
A43: Месяц | B43: Янв | C43: Фев | D43: Мар | E43: Апр | F43: Май | G43: Июн | H43: Июл | I43: Авг | J43: Сен | K43: Окт | L43: Ноя | M43: Дек
A44: Индекс посещаемости | B44: 0.96323529 | C44: 1 | D44: 0.99264706 | E44: 0.92647059 | F44: 0.82352941 | G44: 0.31617647 | H44: 0.13970588 | I44: 0.058823529 | J44: 0.79411765 | K44: 0.94117647 | L44: 0.94117647 | M44: 0.92647059
A46: Дети к концу 12-го месяца, 100% | B46: =$B$215*$F$199 | C46: чел. при 100% | D46: Расчет по сценарию | E46: Взвешенное среднее | G46: ← формула; база: B215
A47: Дети к концу 24-го месяца, 100% | B47: =$B$216*$F$199 | C47: чел. при 100% | D47: Роман 10.08.2026 / тарифный микс | E47: Не полный план с 13-го месяца: плавный рост за месяцы 13-24. | G47: ← формула; база: B216
A49: 4. Паушальный взнос и роялти
A50: Параметр | B50: Значение | C50: Ед. | D50: Статус / источник | E50: Комментарий
A51: Абонемент действующей сети | B51: =$B$217*$F$200 | C51: ₽/мес. | D51: Расчет по сценарию | G51: ← формула; база: B217
A52: Средний фикс на точку начисления | B52: =SUMPRODUCT(B314:B318,D314:D318)/SUM(B314:B318) | C52: ₽/точку/мес. | D52: Расчёт из групп | E52: Считается из таблицы групп в разделе 16. Руками не вводится: в роялти входят фиксы групп, а не это среднее.
A53: Мин. роялти новой школы — 1-й год | B53: =SUMPRODUCT($C$263:$C$282,$I$263:$I$282)/$C$283 | C53: ₽/школа/мес. | D53: Взвешенный микс | E53: Минимум применяется по каждой школе | G53: ← формула; база: I263:I282
A54: Мин. роялти новой школы — 2-й год+ | B54: =SUMPRODUCT($C$263:$C$282,$J$263:$J$282)/$C$283 | C54: ₽/школа/мес. | D54: Взвешенный микс | E54: Минимум применяется по каждой школе | G54: ← формула; база: J263:J282
A55: ="Роялти старых / продаж до "&TEXT(DAY($B$244),"00")&"."&TEXT(MONTH($B$244),"00")&"."&YEAR($B$244) | B55: 0.065 | C55: % | D55: ТЗ 5.4 | E55: До 31.12.2029
A56: ="Роялти новых с "&TEXT(DAY($B$244+1),"00")&"."&TEXT(MONTH($B$244+1),"00")&"."&YEAR($B$244+1) | B56: 0.085 | C56: % | D56: ТЗ 5.4 | E56: До 31.12.2029
A57: ="Роялти всех с "&TEXT(DAY($B$245),"00")&"."&TEXT(MONTH($B$245),"00")&"."&YEAR($B$245) | B57: 0.1 | C57: % | D57: ТЗ 5.4 | E57: Дата перехода задаётся в B245; подпись слева следует за ней.
A58: НДС основной деятельности | B58: 0.05 | C58: % | D58: Временно | E58: Требует налоговой сверки
A59: Доля ФК от паушального | B59: 0.35 | C59: % без НДС | D59: V5 | F59: 35% выручки. Не связано с B76: там 35% ПРИБЫЛИ мерча. Совпадение ставок случайно — пересмотр одной не двигает другую.
A60: Доля ФК от роялти | B60: 0.1 | C60: % без НДС | D60: V5
A61: Средние по взвешенному миксу продуктов — по сезонам
A62: Сезон | B62: Средний паушальный, ₽ с НДС | C62: Средний абонемент, ₽/мес.
A63: 1 | B63: =SUMPRODUCT($C$263:$C$282,$D$263:$D$282)/$C$283 | C63: =$B$218*$F$200 | G63: ← формула; база: D263:D282
A64: 2 | B64: =SUMPRODUCT($C$263:$C$282,$D$263:$D$282)/$C$283 | C64: =$B$219*$F$200 | G64: ← формула; база: D263:D282
A65: 3 | B65: =SUMPRODUCT($C$263:$C$282,$D$263:$D$282)/$C$283 | C65: =$B$220*$F$200 | G65: ← формула; база: D263:D282
A66: 4 | B66: =SUMPRODUCT($C$263:$C$282,$D$263:$D$282)/$C$283 | C66: =$B$221*$F$200 | G66: ← формула; база: D263:D282
A67: 5 | B67: =SUMPRODUCT($C$263:$C$282,$D$263:$D$282)/$C$283 | C67: =$B$222*$F$200 | G67: ← формула; база: D263:D282
A69: 5. Мерч, склад и займ
A70: Параметр | B70: Значение | C70: Ед. | D70: Статус / источник | E70: Комментарий
A71: Себестоимость комплекта | B71: 2100 | C71: ₽ | D71: ТЗ 5.5
A72: Наценка мерча | B72: 0.85 | C72: % к COGS | D72: ТЗ 5.5
A73: Цена комплекта | B73: =B71*(1+B72) | C73: ₽ | D73: Расчёт | E73: 2 100 × 1,85 = 3 885
A74: Коэффициент мерча | B74: =$B$223*$F$201 | C74: компл./ребёнок/сезон | D74: Расчет по сценарию | E74: Ежегодная докупка | G74: ← формула; база: B223
A75: Логистика/возвраты/брак | B75: 0.02 | C75: % выручки без НДС | D75: V5 | E75: До уточнения
A76: Доля ФК от прибыли мерча | B76: 0.35 | C76: % | D76: Подтверждено | E76: Отдельно от возврата займа | F76: 35% прибыли (выручка − COGS − логистика). Не связано с B59: там 35% ВЫРУЧКИ по паушальным. Базы разные.
A77: Стартовый товарный запас | B77: 50000000 | C77: ₽ по COGS | D77: ТЗ 5.6
A78: Стартовый займ на мерч | B78: 50000000 | C78: ₽ | D78: ТЗ 5.6
A79: Доля COGS на погашение займа | B79: 0.6 | C79: % | D79: ТЗ 5.6
A80: Целевой запас | B80: 3 | C80: мес. будущих продаж | D80: ТЗ 5.6 / уточнено 10.09.2026 | E80: ="При закупке доводим склад до будущих "&$B$80&" мес. продаж по себестоимости"
A81: Начало регулярного пополнения | B81: 46692 | C81: дата | D81: Комментарий Романа | E81: Стартовые ~50 млн распродаются около 2 лет
A82: Месяц проверки закупки 1 | B82: 2 | C82: номер месяца | D82: Рабочее | E82: Февраль; уточнить точные месяцы закупок
A83: Месяц проверки закупки 2 | B83: 5 | C83: номер месяца | D83: Рабочее | E83: Май; уточнить точные месяцы закупок
A84: Месяц проверки закупки 3 | B84: 8 | C84: номер месяца | D84: Рабочее | E84: Август; уточнить точные месяцы закупок
A85: Месяц проверки закупки 4 | B85: 11 | C85: номер месяца | D85: Рабочее | E85: Ноябрь; уточнить точные месяцы закупок
A86: Первичная закупка новой школы
A87: 1-й месяц после открытия | B87: 0.5
A88: 2-й месяц после открытия | B88: 0.3
A89: 3-й месяц после открытия | B89: 0.2
A90: Контроль | B90: =SUM(B87:B89)
A92: Сезонность повторной закупки мерча
B93: Янв | C93: Фев | D93: Мар | E93: Апр | F93: Май | G93: Июн | H93: Июл | I93: Авг | J93: Сен | K93: Окт | L93: Ноя | M93: Дек
A94: Доля годовых повторных продаж | B94: 0 | C94: 0 | D94: 0 | E94: 0 | F94: 0 | G94: 0 | H94: 0 | I94: 0.25 | J94: 0.4 | K94: 0.25 | L94: 0.1 | M94: 0
A95: Контроль | B95: =SUM(B94:M94)
A97: 5а. Согласованный мерч действующей сети — факт сентябрь–декабрь 2026
A98: Месяц (факт, ищется по дате) | B98: 46266 | C98: 46296 | D98: 46327 | E98: 46357
A99: Комплекты, шт. | B99: 5070 | C99: 2550 | D99: 1260 | E99: 720
A100: Выручка, ₽ с НДС | B100: 10022370 | C100: 4335000 | D100: 2142000 | E100: 1224000
A101: COGS, ₽ | B101: 5237418.6 | C101: 2167500 | D101: 1178100 | E101: 673200
A103: 6. ERP и операционные расходы
A104: Параметр | B104: Значение | C104: Ед. | D104: Статус / источник | E104: Комментарий
A105: ERP база | B105: 80000 | C105: ₽/мес. | D105: ТЗ 5.7
A106: Школ в ERP-базе | B106: 104 | C106: шт. | D106: Фактический реестр на 09.09.2026 | E106: Базовые 80 тыс. ₽ ERP покрывают 104 действующие школы на старте; доплата 3 тыс. ₽ применяется к новым подключённым школам сверх этой базы.
A107: ERP на новую активную школу | B107: 3000 | C107: ₽/мес. | D107: ТЗ 5.7 | E107: С месяца открытия
...

Sheet 02_Модель
A1: Помесячная модель — БДР и БДДС
B3: =DATE(YEAR('01_Вводные'!$B$7),MONTH('01_Вводные'!$B$7)+0,1) | C3: =DATE(YEAR('01_Вводные'!$B$7),MONTH('01_Вводные'!$B$7)+1,1) | D3: =DATE(YEAR('01_Вводные'!$B$7),MONTH('01_Вводные'!$B$7)+2,1) | E3: =DATE(YEAR('01_Вводные'!$B$7),MONTH('01_Вводные'!$B$7)+3,1) | F3: =DATE(YEAR('01_Вводные'!$B$7),MONTH('01_Вводные'!$B$7)+4,1) | G3: =DATE(YEAR('01_Вводные'!$B$7),MONTH('01_Вводные'!$B$7)+5,1) | H3: =DATE(YEAR('01_Вводные'!$B$7),MONTH('01_Вводные'!$B$7)+6,1) | I3: =DATE(YEAR('01_Вводные'!$B$7),MONTH('01_Вводные'!$B$7)+7,1) | J3: =DATE(YEAR('01_Вводные'!$B$7),MONTH('01_Вводные'!$B$7)+8,1) | K3: =DATE(YEAR('01_Вводные'!$B$7),MONTH('01_Вводные'!$B$7)+9,1) | L3: =DATE(YEAR('01_Вводные'!$B$7),MONTH('01_Вводные'!$B$7)+10,1) | M3: =DATE(YEAR('01_Вводные'!$B$7),MONTH('01_Вводные'!$B$7)+11,1) | N3: =DATE(YEAR('01_Вводные'!$B$7),MONTH('01_Вводные'!$B$7)+12,1) | O3: =DATE(YEAR('01_Вводные'!$B$7),MONTH('01_Вводные'!$B$7)+13,1) | P3: =DATE(YEAR('01_Вводные'!$B$7),MONTH('01_Вводные'!$B$7)+14,1) | Q3: =DATE(YEAR('01_Вводные'!$B$7),MONTH('01_Вводные'!$B$7)+15,1) | R3: =DATE(YEAR('01_Вводные'!$B$7),MONTH('01_Вводные'!$B$7)+16,1) | S3: =DATE(YEAR('01_Вводные'!$B$7),MONTH('01_Вводные'!$B$7)+17,1) | T3: =DATE(YEAR('01_Вводные'!$B$7),MONTH('01_Вводные'!$B$7)+18,1) | U3: =DATE(YEAR('01_Вводные'!$B$7),MONTH('01_Вводные'!$B$7)+19,1) | V3: =DATE(YEAR('01_Вводные'!$B$7),MONTH('01_Вводные'!$B$7)+20,1) | W3: =DATE(YEAR('01_Вводные'!$B$7),MONTH('01_Вводные'!$B$7)+21,1) | X3: =DATE(YEAR('01_Вводные'!$B$7),MONTH('01_Вводные'!$B$7)+22,1) | Y3: =DATE(YEAR('01_Вводные'!$B$7),MONTH('01_Вводные'!$B$7)+23,1) | Z3: =DATE(YEAR('01_Вводные'!$B$7),MONTH('01_Вводные'!$B$7)+24,1) | AA3: =DATE(YEAR('01_Вводные'!$B$7),MONTH('01_Вводные'!$B$7)+25,1) | AB3: =DATE(YEAR('01_Вводные'!$B$7),MONTH('01_Вводные'!$B$7)+26,1) | AC3: =DATE(YEAR('01_Вводные'!$B$7),MONTH('01_Вводные'!$B$7)+27,1) | AD3: =DATE(YEAR('01_Вводные'!$B$7),MONTH('01_Вводные'!$B$7)+28,1) | AE3: =DATE(YEAR('01_Вводные'!$B$7),MONTH('01_Вводные'!$B$7)+29,1) | AF3: =DATE(YEAR('01_Вводные'!$B$7),MONTH('01_Вводные'!$B$7)+30,1) | AG3: =DATE(YEAR('01_Вводные'!$B$7),MONTH('01_Вводные'!$B$7)+31,1) | AH3: =DATE(YEAR('01_Вводные'!$B$7),MONTH('01_Вводные'!$B$7)+32,1) | AI3: =DATE(YEAR('01_Вводные'!$B$7),MONTH('01_Вводные'!$B$7)+33,1) | AJ3: =DATE(YEAR('01_Вводные'!$B$7),MONTH('01_Вводные'!$B$7)+34,1) | AK3: =DATE(YEAR('01_Вводные'!$B$7),MONTH('01_Вводные'!$B$7)+35,1) | AL3: =DATE(YEAR('01_Вводные'!$B$7),MONTH('01_Вводные'!$B$7)+36,1) | AM3: =DATE(YEAR('01_Вводные'!$B$7),MONTH('01_Вводные'!$B$7)+37,1) | AN3: =DATE(YEAR('01_Вводные'!$B$7),MONTH('01_Вводные'!$B$7)+38,1) | AO3: =DATE(YEAR('01_Вводные'!$B$7),MONTH('01_Вводные'!$B$7)+39,1) | AP3: =DATE(YEAR('01_Вводные'!$B$7),MONTH('01_Вводные'!$B$7)+40,1) | AQ3: =DATE(YEAR('01_Вводные'!$B$7),MONTH('01_Вводные'!$B$7)+41,1) | AR3: =DATE(YEAR('01_Вводные'!$B$7),MONTH('01_Вводные'!$B$7)+42,1) | AS3: =DATE(YEAR('01_Вводные'!$B$7),MONTH('01_Вводные'!$B$7)+43,1) | AT3: =DATE(YEAR('01_Вводные'!$B$7),MONTH('01_Вводные'!$B$7)+44,1) | AU3: =DATE(YEAR('01_Вводные'!$B$7),MONTH('01_Вводные'!$B$7)+45,1) | AV3: =DATE(YEAR('01_Вводные'!$B$7),MONTH('01_Вводные'!$B$7)+46,1) | AW3: =DATE(YEAR('01_Вводные'!$B$7),MONTH('01_Вводные'!$B$7)+47,1) | AX3: =DATE(YEAR('01_Вводные'!$B$7),MONTH('01_Вводные'!$B$7)+48,1) | AY3: =DATE(YEAR('01_Вводные'!$B$7),MONTH('01_Вводные'!$B$7)+49,1) | AZ3: =DATE(YEAR('01_Вводные'!$B$7),MONTH('01_Вводные'!$B$7)+50,1) | BA3: =DATE(YEAR('01_Вводные'!$B$7),MONTH('01_Вводные'!$B$7)+51,1) | BB3: =DATE(YEAR('01_Вводные'!$B$7),MONTH('01_Вводные'!$B$7)+52,1) | BC3: =DATE(YEAR('01_Вводные'!$B$7),MONTH('01_Вводные'!$B$7)+53,1) | BD3: =DATE(YEAR('01_Вводные'!$B$7),MONTH('01_Вводные'!$B$7)+54,1) | BE3: =DATE(YEAR('01_Вводные'!$B$7),MONTH('01_Вводные'!$B$7)+55,1) | BF3: =DATE(YEAR('01_Вводные'!$B$7),MONTH('01_Вводные'!$B$7)+56,1) | BG3: =DATE(YEAR('01_Вводные'!$B$7),MONTH('01_Вводные'!$B$7)+57,1) | BH3: =DATE(YEAR('01_Вводные'!$B$7),MONTH('01_Вводные'!$B$7)+58,1) | BI3: =DATE(YEAR('01_Вводные'!$B$7),MONTH('01_Вводные'!$B$7)+59,1)
B4: =INT((0)/12)+1 | C4: =INT((1)/12)+1 | D4: =INT((2)/12)+1 | E4: =INT((3)/12)+1 | F4: =INT((4)/12)+1 | G4: =INT((5)/12)+1 | H4: =INT((6)/12)+1 | I4: =INT((7)/12)+1 | J4: =INT((8)/12)+1 | K4: =INT((9)/12)+1 | L4: =INT((10)/12)+1 | M4: =INT((11)/12)+1 | N4: =INT((12)/12)+1 | O4: =INT((13)/12)+1 | P4: =INT((14)/12)+1 | Q4: =INT((15)/12)+1 | R4: =INT((16)/12)+1 | S4: =INT((17)/12)+1 | T4: =INT((18)/12)+1 | U4: =INT((19)/12)+1 | V4: =INT((20)/12)+1 | W4: =INT((21)/12)+1 | X4: =INT((22)/12)+1 | Y4: =INT((23)/12)+1 | Z4: =INT((24)/12)+1 | AA4: =INT((25)/12)+1 | AB4: =INT((26)/12)+1 | AC4: =INT((27)/12)+1 | AD4: =INT((28)/12)+1 | AE4: =INT((29)/12)+1 | AF4: =INT((30)/12)+1 | AG4: =INT((31)/12)+1 | AH4: =INT((32)/12)+1 | AI4: =INT((33)/12)+1 | AJ4: =INT((34)/12)+1 | AK4: =INT((35)/12)+1 | AL4: =INT((36)/12)+1 | AM4: =INT((37)/12)+1 | AN4: =INT((38)/12)+1 | AO4: =INT((39)/12)+1 | AP4: =INT((40)/12)+1 | AQ4: =INT((41)/12)+1 | AR4: =INT((42)/12)+1 | AS4: =INT((43)/12)+1 | AT4: =INT((44)/12)+1 | AU4: =INT((45)/12)+1 | AV4: =INT((46)/12)+1 | AW4: =INT((47)/12)+1 | AX4: =INT((48)/12)+1 | AY4: =INT((49)/12)+1 | AZ4: =INT((50)/12)+1 | BA4: =INT((51)/12)+1 | BB4: =INT((52)/12)+1 | BC4: =INT((53)/12)+1 | BD4: =INT((54)/12)+1 | BE4: =INT((55)/12)+1 | BF4: =INT((56)/12)+1 | BG4: =INT((57)/12)+1 | BH4: =INT((58)/12)+1 | BI4: =INT((59)/12)+1
A5: Операционные драйверы
A6: Сезон | B6: ='06_Сеть_и_дети'!B4 | C6: ='06_Сеть_и_дети'!C4 | D6: ='06_Сеть_и_дети'!D4 | E6: ='06_Сеть_и_дети'!E4 | F6: ='06_Сеть_и_дети'!F4 | G6: ='06_Сеть_и_дети'!G4 | H6: ='06_Сеть_и_дети'!H4 | I6: ='06_Сеть_и_дети'!I4 | ... BI6: ='06_Сеть_и_дети'!BI4
A7: Сезонность посещаемости | B7: ='06_Сеть_и_дети'!B5 | C7: ='06_Сеть_и_дети'!C5 | D7: ='06_Сеть_и_дети'!D5 | E7: ='06_Сеть_и_дети'!E5 | F7: ='06_Сеть_и_дети'!F5 | G7: ='06_Сеть_и_дети'!G5 | H7: ='06_Сеть_и_дети'!H5 | I7: ='06_Сеть_и_дети'!I5 | ... BI7: ='06_Сеть_и_дети'!BI5
A9: Действующая сеть — школы | B9: ='06_Сеть_и_дети'!B11 | C9: ='06_Сеть_и_дети'!C11 | D9: ='06_Сеть_и_дети'!D11 | E9: ='06_Сеть_и_дети'!E11 | F9: ='06_Сеть_и_дети'!F11 | G9: ='06_Сеть_и_дети'!G11 | H9: ='06_Сеть_и_дети'!H11 | I9: ='06_Сеть_и_дети'!I11 | ... BI9: ='06_Сеть_и_дети'!BI11
A10: Действующая сеть — дети 100% база | B10: ='06_Сеть_и_дети'!B19 | C10: ='06_Сеть_и_дети'!C19 | D10: ='06_Сеть_и_дети'!D19 | E10: ='06_Сеть_и_дети'!E19 | F10: ='06_Сеть_и_дети'!F19 | G10: ='06_Сеть_и_дети'!G19 | H10: ='06_Сеть_и_дети'!H19 | I10: ='06_Сеть_и_дети'!I19 | ... BI10: ='06_Сеть_и_дети'!BI19
A11: Действующая сеть — активные дети | B11: ='06_Сеть_и_дети'!B20 | C11: ='06_Сеть_и_дети'!C20 | D11: ='06_Сеть_и_дети'!D20 | E11: ='06_Сеть_и_дети'!E20 | F11: ='06_Сеть_и_дети'!F20 | G11: ='06_Сеть_и_дети'!G20 | H11: ='06_Сеть_и_дети'!H20 | I11: ='06_Сеть_и_дети'!I20 | ... BI11: ='06_Сеть_и_дети'!BI20
A12: Новые школы — активные школы | B12: ='06_Сеть_и_дети'!B16 | C12: ='06_Сеть_и_дети'!C16 | D12: ='06_Сеть_и_дети'!D16 | E12: ='06_Сеть_и_дети'!E16 | F12: ='06_Сеть_и_дети'!F16 | G12: ='06_Сеть_и_дети'!G16 | H12: ='06_Сеть_и_дети'!H16 | I12: ='06_Сеть_и_дети'!I16 | ... BI12: ='06_Сеть_и_дети'!BI16
A13: Активные юрлица | B13: ='06_Сеть_и_дети'!B10 | C13: ='06_Сеть_и_дети'!C10 | D13: ='06_Сеть_и_дети'!D10 | E13: ='06_Сеть_и_дети'!E10 | F13: ='06_Сеть_и_дети'!F10 | G13: ='06_Сеть_и_дети'!G10 | H13: ='06_Сеть_и_дети'!H10 | I13: ='06_Сеть_и_дети'!I10 | ... BI13: ='06_Сеть_и_дети'!BI10
A14: Новые школы — дети | B14: ='06_Сеть_и_дети'!B24 | C14: ='06_Сеть_и_дети'!C24 | D14: ='06_Сеть_и_дети'!D24 | E14: ='06_Сеть_и_дети'!E24 | F14: ='06_Сеть_и_дети'!F24 | G14: ='06_Сеть_и_дети'!G24 | H14: ='06_Сеть_и_дети'!H24 | I14: ='06_Сеть_и_дети'!I24 | ... BI14: ='06_Сеть_и_дети'!BI24
A15: Всего активных детей | B15: ='06_Сеть_и_дети'!B25 | C15: ='06_Сеть_и_дети'!C25 | D15: ='06_Сеть_и_дети'!D25 | E15: ='06_Сеть_и_дети'!E25 | F15: ='06_Сеть_и_дети'!F25 | G15: ='06_Сеть_и_дети'!G25 | H15: ='06_Сеть_и_дети'!H25 | I15: ='06_Сеть_и_дети'!I25 | ... BI15: ='06_Сеть_и_дети'!BI25
A17: БДР — выручка
A18: Паушальные взносы, без НДС | B18: ='04_Продажи'!B26 | C18: ='04_Продажи'!C26 | D18: ='04_Продажи'!D26 | E18: ='04_Продажи'!E26 | F18: ='04_Продажи'!F26 | G18: ='04_Продажи'!G26 | H18: ='04_Продажи'!H26 | I18: ='04_Продажи'!I26 | ... BI18: ='04_Продажи'!BI26
A19: Роялти действующей сети, без НДС | B19: ='06_Сеть_и_дети'!B28/(1+'01_Вводные'!$B$58) | C19: ='06_Сеть_и_дети'!C28/(1+'01_Вводные'!$B$58) | D19: ='06_Сеть_и_дети'!D28/(1+'01_Вводные'!$B$58) | E19: ='06_Сеть_и_дети'!E28/(1+'01_Вводные'!$B$58) | F19: ='06_Сеть_и_дети'!F28/(1+'01_Вводные'!$B$58) | G19: ='06_Сеть_и_дети'!G28/(1+'01_Вводные'!$B$58) | H19: ='06_Сеть_и_дети'!H28/(1+'01_Вводные'!$B$58) | I19: ='06_Сеть_и_дети'!I28/(1+'01_Вводные'!$B$58) | ... BI19: ='06_Сеть_и_дети'!BI28/(1+'01_Вводные'!$B$58)
A20: Роялти новых школ, без НДС | B20: ='06_Сеть_и_дети'!B29/(1+'01_Вводные'!$B$58) | C20: ='06_Сеть_и_дети'!C29/(1+'01_Вводные'!$B$58) | D20: ='06_Сеть_и_дети'!D29/(1+'01_Вводные'!$B$58) | E20: ='06_Сеть_и_дети'!E29/(1+'01_Вводные'!$B$58) | F20: ='06_Сеть_и_дети'!F29/(1+'01_Вводные'!$B$58) | G20: ='06_Сеть_и_дети'!G29/(1+'01_Вводные'!$B$58) | H20: ='06_Сеть_и_дети'!H29/(1+'01_Вводные'!$B$58) | I20: ='06_Сеть_и_дети'!I29/(1+'01_Вводные'!$B$58) | ... BI20: ='06_Сеть_и_дети'!BI29/(1+'01_Вводные'!$B$58)
A21: Мерч, без НДС | B21: ='07_Мерч'!B15 | C21: ='07_Мерч'!C15 | D21: ='07_Мерч'!D15 | E21: ='07_Мерч'!E15 | F21: ='07_Мерч'!F15 | G21: ='07_Мерч'!G15 | H21: ='07_Мерч'!H15 | I21: ='07_Мерч'!I15 | ... BI21: ='07_Мерч'!BI15
A22: Лагеря, без НДС | B22: =('09_Лагеря'!B10-'09_Лагеря'!B11) | C22: =('09_Лагеря'!C10-'09_Лагеря'!C11) | D22: =('09_Лагеря'!D10-'09_Лагеря'!D11) | E22: =('09_Лагеря'!E10-'09_Лагеря'!E11) | F22: =('09_Лагеря'!F10-'09_Лагеря'!F11) | G22: =('09_Лагеря'!G10-'09_Лагеря'!G11) | H22: =('09_Лагеря'!H10-'09_Лагеря'!H11) | I22: =('09_Лагеря'!I10-'09_Лагеря'!I11) | ... BI22: =('09_Лагеря'!BI10-'09_Лагеря'!BI11)
A23: Выручка — всего, без НДС | B23: =SUM(B18:B22) | C23: =SUM(C18:C22) | D23: =SUM(D18:D22) | E23: =SUM(E18:E22) | F23: =SUM(F18:F22) | G23: =SUM(G18:G22) | H23: =SUM(H18:H22) | I23: =SUM(I18:I22) | ... BI23: =SUM(BI18:BI22)
A25: БДР — прямые расходы
A26: COGS мерча | B26: ='07_Мерч'!B16 | C26: ='07_Мерч'!C16 | D26: ='07_Мерч'!D16 | E26: ='07_Мерч'!E16 | F26: ='07_Мерч'!F16 | G26: ='07_Мерч'!G16 | H26: ='07_Мерч'!H16 | I26: ='07_Мерч'!I16 | ... BI26: ='07_Мерч'!BI16
A27: Логистика/возвраты/брак | B27: ='07_Мерч'!B17 | C27: ='07_Мерч'!C17 | D27: ='07_Мерч'!D17 | E27: ='07_Мерч'!E17 | F27: ='07_Мерч'!F17 | G27: ='07_Мерч'!G17 | H27: ='07_Мерч'!H17 | I27: ='07_Мерч'!I17 | ... BI27: ='07_Мерч'!BI17
A28: ФК — 35% прибыли мерча | B28: ='07_Мерч'!B19 | C28: ='07_Мерч'!C19 | D28: ='07_Мерч'!D19 | E28: ='07_Мерч'!E19 | F28: ='07_Мерч'!F19 | G28: ='07_Мерч'!G19 | H28: ='07_Мерч'!H19 | I28: ='07_Мерч'!I19 | ... BI28: ='07_Мерч'!BI19
A29: ФК — паушальные | B29: =B18*'01_Вводные'!$B$59 | C29: =C18*'01_Вводные'!$B$59 | D29: =D18*'01_Вводные'!$B$59 | E29: =E18*'01_Вводные'!$B$59 | F29: =F18*'01_Вводные'!$B$59 | G29: =G18*'01_Вводные'!$B$59 | H29: =H18*'01_Вводные'!$B$59 | I29: =I18*'01_Вводные'!$B$59 | ... BI29: =BI18*'01_Вводные'!$B$59
A30: ФК — роялти | B30: =(B19+B20)*'01_Вводные'!$B$60 | C30: =(C19+C20)*'01_Вводные'!$B$60 | D30: =(D19+D20)*'01_Вводные'!$B$60 | E30: =(E19+E20)*'01_Вводные'!$B$60 | F30: =(F19+F20)*'01_Вводные'!$B$60 | G30: =(G19+G20)*'01_Вводные'!$B$60 | H30: =(H19+H20)*'01_Вводные'!$B$60 | I30: =(I19+I20)*'01_Вводные'!$B$60 | ... BI30: =(BI19+BI20)*'01_Вводные'!$B$60
A31: Лагеря — расходы + партнёр | B31: ='09_Лагеря'!B12+'09_Лагеря'!B13 | C31: ='09_Лагеря'!C12+'09_Лагеря'!C13 | D31: ='09_Лагеря'!D12+'09_Лагеря'!D13 | E31: ='09_Лагеря'!E12+'09_Лагеря'!E13 | F31: ='09_Лагеря'!F12+'09_Лагеря'!F13 | G31: ='09_Лагеря'!G12+'09_Лагеря'!G13 | H31: ='09_Лагеря'!H12+'09_Лагеря'!H13 | I31: ='09_Лагеря'!I12+'09_Лагеря'!I13 | ... BI31: ='09_Лагеря'!BI12+'09_Лагеря'!BI13
A32: Прямые расходы — всего | B32: =SUM(B26:B31) | C32: =SUM(C26:C31) | D32: =SUM(D26:D31) | E32: =SUM(E26:E31) | F32: =SUM(F26:F31) | G32: =SUM(G26:G31) | H32: =SUM(H26:H31) | I32: =SUM(I26:I31) | ... BI32: =SUM(BI26:BI31)
A33: Валовая прибыль | B33: =B23-B32 | C33: =C23-C32 | D33: =D23-D32 | E33: =E23-E32 | F33: =F23-F32 | G33: =G23-G32 | H33: =H23-H32 | I33: =I23-I32 | ... BI33: =BI23-BI32
A35: БДР — OPEX
A36: ФОТ и кадровые расходы | B36: ='08_ФОТ'!B28 | C36: ='08_ФОТ'!C28 | D36: ='08_ФОТ'!D28 | E36: ='08_ФОТ'!E28 | F36: ='08_ФОТ'!F28 | G36: ='08_ФОТ'!G28 | H36: ='08_ФОТ'!H28 | I36: ='08_ФОТ'!I28 | ... BI36: ='08_ФОТ'!BI28
A37: ERP | B37: =('01_Вводные'!$B$105+(MAX(0,'06_Сеть_и_дети'!B11-'01_Вводные'!$B$106)+'06_Сеть_и_дети'!B44)*'01_Вводные'!$B$107)*'18_Календарь_тарифы'!B4 | C37: =('01_Вводные'!$B$105+(MAX(0,'06_Сеть_и_дети'!C11-'01_Вводные'!$B$106)+'06_Сеть_и_дети'!C44)*'01_Вводные'!$B$107)*'18_Календарь_тарифы'!C4 | D37: =('01_Вводные'!$B$105+(MAX(0,'06_Сеть_и_дети'!D11-'01_Вводные'!$B$106)+'06_Сеть_и_дети'!D44)*'01_Вводные'!$B$107)*'18_Календарь_тарифы'!D4 | E37: =('01_Вводные'!$B$105+(MAX(0,'06_Сеть_и_дети'!E11-'01_Вводные'!$B$106)+'06_Сеть_и_дети'!E44)*'01_Вводные'!$B$107)*'18_Календарь_тарифы'!E4 | F37: =('01_Вводные'!$B$105+(MAX(0,'06_Сеть_и_дети'!F11-'01_Вводные'!$B$106)+'06_Сеть_и_дети'!F44)*'01_Вводные'!$B$107)*'18_Календарь_тарифы'!F4 | G37: =('01_Вводные'!$B$105+(MAX(0,'06_Сеть_и_дети'!G11-'01_Вводные'!$B$106)+'06_Сеть_и_дети'!G44)*'01_Вводные'!$B$107)*'18_Календарь_тарифы'!G4 | H37: =('01_Вводные'!$B$105+(MAX(0,'06_Сеть_и_дети'!H11-'01_Вводные'!$B$106)+'06_Сеть_и_дети'!H44)*'01_Вводные'!$B$107)*'18_Календарь_тарифы'!H4 | I37: =('01_Вводные'!$B$105+(MAX(0,'06_Сеть_и_дети'!I11-'01_Вводные'!$B$106)+'06_Сеть_и_дети'!I44)*'01_Вводные'!$B$107)*'18_Календарь_тарифы'!I4 | ... BI37: =('01_Вводные'!$B$105+(MAX(0,'06_Сеть_и_дети'!BI11-'01_Вводные'!$B$106)+'06_Сеть_и_дети'!BI44)*'01_Вводные'!$B$107)*'18_Календарь_тарифы'!BI4
A38: Офис / аренда / уборка / парковка | B38: ='01_Вводные'!$B$108 | C38: ='01_Вводные'!$B$108 | D38: ='01_Вводные'!$B$108 | E38: ='01_Вводные'!$B$108 | F38: ='01_Вводные'!$B$108 | G38: ='01_Вводные'!$B$108 | H38: ='01_Вводные'!$B$108 | I38: ='01_Вводные'!$B$108 | ... BI38: ='01_Вводные'!$B$108
A39: Юристы / аудит / бухгалтерия | B39: ='01_Вводные'!$B$109*'18_Календарь_тарифы'!B4 | C39: ='01_Вводные'!$B$109*'18_Календарь_тарифы'!C4 | D39: ='01_Вводные'!$B$109*'18_Календарь_тарифы'!D4 | E39: ='01_Вводные'!$B$109*'18_Календарь_тарифы'!E4 | F39: ='01_Вводные'!$B$109*'18_Календарь_тарифы'!F4 | G39: ='01_Вводные'!$B$109*'18_Календарь_тарифы'!G4 | H39: ='01_Вводные'!$B$109*'18_Календарь_тарифы'!H4 | I39: ='01_Вводные'!$B$109*'18_Календарь_тарифы'!I4 | ... BI39: ='01_Вводные'!$B$109*'18_Календарь_тарифы'!BI4
A40: Прочие IT | B40: ='01_Вводные'!$B$110*'18_Календарь_тарифы'!B4 | C40: ='01_Вводные'!$B$110*'18_Календарь_тарифы'!C4 | D40: ='01_Вводные'!$B$110*'18_Календарь_тарифы'!D4 | E40: ='01_Вводные'!$B$110*'18_Календарь_тарифы'!E4 | F40: ='01_Вводные'!$B$110*'18_Календарь_тарифы'!F4 | G40: ='01_Вводные'!$B$110*'18_Календарь_тарифы'!G4 | H40: ='01_Вводные'!$B$110*'18_Календарь_тарифы'!H4 | I40: ='01_Вводные'!$B$110*'18_Календарь_тарифы'!I4 | ... BI40: ='01_Вводные'!$B$110*'18_Календарь_тарифы'!BI4
A41: SMM / подрядчики | B41: ='18_Календарь_тарифы'!B13 | C41: ='18_Календарь_тарифы'!C13 | D41: ='18_Календарь_тарифы'!D13 | E41: ='18_Календарь_тарифы'!E13 | F41: ='18_Календарь_тарифы'!F13 | G41: ='18_Календарь_тарифы'!G13 | H41: ='18_Календарь_тарифы'!H13 | I41: ='18_Календарь_тарифы'!I13 | ... BI41: ='18_Календарь_тарифы'!BI13
A42: Маркетинг привлечения франшиз | B42: ='04_Продажи'!B23 | C42: ='04_Продажи'!C23 | D42: ='04_Продажи'!D23 | E42: ='04_Продажи'!E23 | F42: ='04_Продажи'!F23 | G42: ='04_Продажи'!G23 | H42: ='04_Продажи'!H23 | I42: ='04_Продажи'!I23 | ... BI42: ='04_Продажи'!BI23
A43: OPEX — всего | B43: =SUM(B36:B42) | C43: =SUM(C36:C42) | D43: =SUM(D36:D42) | E43: =SUM(E36:E42) | F43: =SUM(F36:F42) | G43: =SUM(G36:G42) | H43: =SUM(H36:H42) | I43: =SUM(I36:I42) | ... BI43: =SUM(BI36:BI42)
A44: EBITDA | B44: =B33-B43 | C44: =C33-C43 | D44: =D33-D43 | E44: =E33-E43 | F44: =F33-F43 | G44: =G33-G43 | H44: =H33-H43 | I44: =I33-I43 | ... BI44: =BI33-BI43
A45: EBITDA margin | B45: =IF(B23=0,0,B44/B23) | C45: =IF(C23=0,0,C44/C23) | D45: =IF(D23=0,0,D44/D23) | E45: =IF(E23=0,0,E44/E23) | F45: =IF(F23=0,0,F44/F23) | G45: =IF(G23=0,0,G44/G23) | H45: =IF(H23=0,0,H44/H23) | I45: =IF(I23=0,0,I44/I23) | ... BI45: =IF(BI23=0,0,BI44/BI23)
A46: УСН / минимальный налог | B46: =MAX('01_Вводные'!$B$157*B23,'01_Вводные'!$B$156*MAX(0,B44)) | C46: =MAX('01_Вводные'!$B$157*C23,'01_Вводные'!$B$156*MAX(0,C44)) | D46: =MAX('01_Вводные'!$B$157*D23,'01_Вводные'!$B$156*MAX(0,D44)) | E46: =MAX('01_Вводные'!$B$157*E23,'01_Вводные'!$B$156*MAX(0,E44)) | F46: =MAX('01_Вводные'!$B$157*F23,'01_Вводные'!$B$156*MAX(0,F44)) | G46: =MAX('01_Вводные'!$B$157*G23,'01_Вводные'!$B$156*MAX(0,G44)) | H46: =MAX('01_Вводные'!$B$157*H23,'01_Вводные'!$B$156*MAX(0,H44)) | I46: =MAX('01_Вводные'!$B$157*I23,'01_Вводные'!$B$156*MAX(0,I44)) | ... BI46: =MAX('01_Вводные'!$B$157*BI23,'01_Вводные'!$B$156*MAX(0,BI44))
A47: Прибыль после УСН | B47: =B44-B46 | C47: =C44-C46 | D47: =D44-D46 | E47: =E44-E46 | F47: =F44-F46 | G47: =G44-G46 | H47: =H44-H46 | I47: =I44-I46 | ... BI47: =BI44-BI46
A50: БДДС
A51: Денежный остаток на начало | B51: ='01_Вводные'!$B$17 | C51: =B72 | D51: =C72 | E51: =D72 | F51: =E72 | G51: =F72 | H51: =G72 | I51: =H72 | J51: =I72 | ... BI51: =BH72
A52: Паушальные поступления | B52: ='04_Продажи'!B25 | C52: ='04_Продажи'!C25 | D52: ='04_Продажи'!D25 | E52: ='04_Продажи'!E25 | F52: ='04_Продажи'!F25 | G52: ='04_Продажи'!G25 | H52: ='04_Продажи'!H25 | I52: ='04_Продажи'!I25 | ... BI52: ='04_Продажи'!BI25
A53: Роялти поступления | B53: ='01_Вводные'!$B$20*(B19+B20)*(1+'01_Вводные'!$B$58)+(1-'01_Вводные'!$B$20)*0 | C53: ='01_Вводные'!$B$20*(C19+C20)*(1+'01_Вводные'!$B$58)+(1-'01_Вводные'!$B$20)*(B19+B20)*(1+'01_Вводные'!$B$58) | D53: ='01_Вводные'!$B$20*(D19+D20)*(1+'01_Вводные'!$B$58)+(1-'01_Вводные'!$B$20)*(C19+C20)*(1+'01_Вводные'!$B$58) | E53: ='01_Вводные'!$B$20*(E19+E20)*(1+'01_Вводные'!$B$58)+(1-'01_Вводные'!$B$20)*(D19+D20)*(1+'01_Вводные'!$B$58) | F53: ='01_Вводные'!$B$20*(F19+F20)*(1+'01_Вводные'!$B$58)+(1-'01_Вводные'!$B$20)*(E19+E20)*(1+'01_Вводные'!$B$58) | G53: ='01_Вводные'!$B$20*(G19+G20)*(1+'01_Вводные'!$B$58)+(1-'01_Вводные'!$B$20)*(F19+F20)*(1+'01_Вводные'!$B$58) | H53: ='01_Вводные'!$B$20*(H19+H20)*(1+'01_Вводные'!$B$58)+(1-'01_Вводные'!$B$20)*(G19+G20)*(1+'01_Вводные'!$B$58) | I53: ='01_Вводные'!$B$20*(I19+I20)*(1+'01_Вводные'!$B$58)+(1-'01_Вводные'!$B$20)*(H19+H20)*(1+'01_Вводные'!$B$58) | J53: ='01_Вводные'!$B$20*(J19+J20)*(1+'01_Вводные'!$B$58)+(1-'01_Вводные'!$B$20)*(I19+I20)*(1+'01_Вводные'!$B$58) | ... BI53: ='01_Вводные'!$B$20*(BI19+BI20)*(1+'01_Вводные'!$B$58)+(1-'01_Вводные'!$B$20)*(BH19+BH20)*(1+'01_Вводные'!$B$58)
A54: Мерч поступления | B54: ='07_Мерч'!B14 | C54: ='07_Мерч'!C14 | D54: ='07_Мерч'!D14 | E54: ='07_Мерч'!E14 | F54: ='07_Мерч'!F14 | G54: ='07_Мерч'!G14 | H54: ='07_Мерч'!H14 | I54: ='07_Мерч'!I14 | ... BI54: ='07_Мерч'!BI14
A55: Лагеря поступления | B55: ='09_Лагеря'!B8 | C55: ='09_Лагеря'!C8 | D55: ='09_Лагеря'!D8 | E55: ='09_Лагеря'!E8 | F55: ='09_Лагеря'!F8 | G55: ='09_Лагеря'!G8 | H55: ='09_Лагеря'!H8 | I55: ='09_Лагеря'!I8 | ... BI55: ='09_Лагеря'!BI8
A56: Денежные поступления — всего | B56: =SUM(B52:B55) | C56: =SUM(C52:C55) | D56: =SUM(D52:D55) | E56: =SUM(E52:E55) | F56: =SUM(F52:F55) | G56: =SUM(G52:G55) | H56: =SUM(H52:H55) | I56: =SUM(I52:I55) | ... BI56: =SUM(BI52:BI55)
A57: CAPEX — денежная оплата | B57: =B99 | C57: =C99 | D57: =D99 | E57: =E99 | F57: =F99 | G57: =G99 | H57: =H99 | I57: =I99 | ... BI57: =BI99
A58: Логистика мерча — оплата | B58: =B27 | C58: =C27 | D58: =D27 | E58: =E27 | F58: =F27 | G58: =G27 | H58: =H27 | I58: =I27 | ... BI58: =BI27
A59: Поставщицкие OPEX к оплате | B59: ='01_Вводные'!$B$21*(B37+B38+B39+B40+B41+B42+'07_Мерч'!B25)+(1-'01_Вводные'!$B$21)*0 | C59: ='01_Вводные'!$B$21*(C37+C38+C39+C40+C41+C42+'07_Мерч'!C25)+(1-'01_Вводные'!$B$21)*(B37+B38+B39+B40+B41+B42+'07_Мерч'!B25) | D59: ='01_Вводные'!$B$21*(D37+D38+D39+D40+D41+D42+'07_Мерч'!D25)+(1-'01_Вводные'!$B$21)*(C37+C38+C39+C40+C41+C42+'07_Мерч'!C25) | E59: ='01_Вводные'!$B$21*(E37+E38+E39+E40+E41+E42+'07_Мерч'!E25)+(1-'01_Вводные'!$B$21)*(D37+D38+D39+D40+D41+D42+'07_Мерч'!D25) | F59: ='01_Вводные'!$B$21*(F37+F38+F39+F40+F41+F42+'07_Мерч'!F25)+(1-'01_Вводные'!$B$21)*(E37+E38+E39+E40+E41+E42+'07_Мерч'!E25) | G59: ='01_Вводные'!$B$21*(G37+G38+G39+G40+G41+G42+'07_Мерч'!G25)+(1-'01_Вводные'!$B$21)*(F37+F38+F39+F40+F41+F42+'07_Мерч'!F25) | H59: ='01_Вводные'!$B$21*(H37+H38+H39+H40+H41+H42+'07_Мерч'!H25)+(1-'01_Вводные'!$B$21)*(G37+G38+G39+G40+G41+G42+'07_Мерч'!G25) | I59: ='01_Вводные'!$B$21*(I37+I38+I39+I40+I41+I42+'07_Мерч'!I25)+(1-'01_Вводные'!$B$21)*(H37+H38+H39+H40+H41+H42+'07_Мерч'!H25) | J59: ='01_Вводные'!$B$21*(J37+J38+J39+J40+J41+J42+'07_Мерч'!J25)+(1-'01_Вводные'!$B$21)*(I37+I38+I39+I40+I41+I42+'07_Мерч'!I25) | ... BI59: ='01_Вводные'!$B$21*(BI37+BI38+BI39+BI40+BI41+BI42+'07_Мерч'!BI25)+(1-'01_Вводные'!$B$21)*(BH37+BH38+BH39+BH40+BH41+BH42+'07_Мерч'!BH25)
A60: ФОТ / кадровые cash | B60: =B36 | C60: =C36 | D60: =D36 | E60: =E36 | F60: =F36 | G60: =G36 | H60: =H36 | I60: =I36 | ... BI60: =BI36
A61: ФК — cash | B61: =B29+(B53/(1+'01_Вводные'!$B$58))*'01_Вводные'!$B$60+B28 | C61: =C29+(C53/(1+'01_Вводные'!$B$58))*'01_Вводные'!$B$60+C28 | D61: =D29+(D53/(1+'01_Вводные'!$B$58))*'01_Вводные'!$B$60+D28 | E61: =E29+(E53/(1+'01_Вводные'!$B$58))*'01_Вводные'!$B$60+E28 | F61: =F29+(F53/(1+'01_Вводные'!$B$58))*'01_Вводные'!$B$60+F28 | G61: =G29+(G53/(1+'01_Вводные'!$B$58))*'01_Вводные'!$B$60+G28 | H61: =H29+(H53/(1+'01_Вводные'!$B$58))*'01_Вводные'!$B$60+H28 | I61: =I29+(I53/(1+'01_Вводные'!$B$58))*'01_Вводные'!$B$60+I28 | ... BI61: =BI29+(BI53/(1+'01_Вводные'!$B$58))*'01_Вводные'!$B$60+BI28
A62: НДС основной деятельности | B62: =(B52+B53+B54)-(B52+B53+B54)/(1+'01_Вводные'!$B$58) | C62: =(C52+C53+C54)-(C52+C53+C54)/(1+'01_Вводные'!$B$58) | D62: =(D52+D53+D54)-(D52+D53+D54)/(1+'01_Вводные'!$B$58) | E62: =(E52+E53+E54)-(E52+E53+E54)/(1+'01_Вводные'!$B$58) | F62: =(F52+F53+F54)-(F52+F53+F54)/(1+'01_Вводные'!$B$58) | G62: =(G52+G53+G54)-(G52+G53+G54)/(1+'01_Вводные'!$B$58) | H62: =(H52+H53+H54)-(H52+H53+H54)/(1+'01_Вводные'!$B$58) | I62: =(I52+I53+I54)-(I52+I53+I54)/(1+'01_Вводные'!$B$58) | ... BI62: =(BI52+BI53+BI54)-(BI52+BI53+BI54)/(1+'01_Вводные'!$B$58)
A63: НДС лагеря | B63: ='09_Лагеря'!B11 | C63: ='09_Лагеря'!C11 | D63: ='09_Лагеря'!D11 | E63: ='09_Лагеря'!E11 | F63: ='09_Лагеря'!F11 | G63: ='09_Лагеря'!G11 | H63: ='09_Лагеря'!H11 | I63: ='09_Лагеря'!I11 | ... BI63: ='09_Лагеря'!BI11
A64: УСН cash | B64: =B46 | C64: =C46 | D64: =D46 | E64: =E46 | F64: =F46 | G64: =G46 | H64: =H46 | I64: =I46 | ... BI64: =BI46
A65: Закупки на склад (справочно) | B65: ='07_Мерч'!B25 | C65: ='07_Мерч'!C25 | D65: ='07_Мерч'!D25 | E65: ='07_Мерч'!E25 | F65: ='07_Мерч'!F25 | G65: ='07_Мерч'!G25 | H65: ='07_Мерч'!H25 | I65: ='07_Мерч'!I25 | ... BI65: ='07_Мерч'!BI25
A66: Лагеря cash out | B66: ='09_Лагеря'!B19 | C66: ='09_Лагеря'!C19 | D66: ='09_Лагеря'!D19 | E66: ='09_Лагеря'!E19 | F66: ='09_Лагеря'!F19 | G66: ='09_Лагеря'!G19 | H66: ='09_Лагеря'!H19 | I66: ='09_Лагеря'!I19 | ... BI66: ='09_Лагеря'!BI19
A67: Денежные расходы до займа | B67: =SUM(B57:B64)+B66 | C67: =SUM(C57:C64)+C66 | D67: =SUM(D57:D64)+D66 | E67: =SUM(E57:E64)+E66 | F67: =SUM(F57:F64)+F66 | G67: =SUM(G57:G64)+G66 | H67: =SUM(H57:H64)+H66 | I67: =SUM(I57:I64)+I66 | ... BI67: =SUM(BI57:BI64)+BI66
A68: Чистый поток до займа | B68: =B56-B67 | C68: =C56-C67 | D68: =D56-D67 | E68: =E56-E67 | F68: =F56-F67 | G68: =G56-G67 | H68: =H56-H67 | I68: =I56-I67 | ... BI68: =BI56-BI67
A69: Денежный остаток до погашения займа | B69: =B51+B68 | C69: =C51+C68 | D69: =D51+D68 | E69: =E51+E68 | F69: =F51+F68 | G69: =G51+G68 | H69: =H51+H68 | I69: =I51+I68 | ... BI69: =BI51+BI68
A70: Погашение займа | B70: ='07_Мерч'!B31 | C70: ='07_Мерч'!C31 | D70: ='07_Мерч'!D31 | E70: ='07_Мерч'!E31 | F70: ='07_Мерч'!F31 | G70: ='07_Мерч'!G31 | H70: ='07_Мерч'!H31 | I70: ='07_Мерч'!I31 | ... BI70: ='07_Мерч'!BI31
A71: Чистый денежный поток | B71: =B68-B70 | C71: =C68-C70 | D71: =D68-D70 | E71: =E68-E70 | F71: =F68-F70 | G71: =G68-G70 | H71: =H68-H70 | I71: =I68-I70 | ... BI71: =BI68-BI70
A72: Денежный остаток на конец | B72: =B51+B71 | C72: =C51+C71 | D72: =D51+D71 | E72: =E51+E71 | F72: =F51+F71 | G72: =G51+G71 | H72: =H51+H71 | I72: =I51+I71 | ... BI72: =BI51+BI71
A74: Контроль оборотного капитала
A75: Займ на конец | B75: ='07_Мерч'!B32 | C75: ='07_Мерч'!C32 | D75: ='07_Мерч'!D32 | E75: ='07_Мерч'!E32 | F75: ='07_Мерч'!F32 | G75: ='07_Мерч'!G32 | H75: ='07_Мерч'!H32 | I75: ='07_Мерч'!I32 | ... BI75: ='07_Мерч'!BI32
A76: Склад на конец | B76: ='07_Мерч'!B26 | C76: ='07_Мерч'!C26 | D76: ='07_Мерч'!D26 | E76: ='07_Мерч'!E26 | F76: ='07_Мерч'!F26 | G76: ='07_Мерч'!G26 | H76: ='07_Мерч'!H26 | I76: ='07_Мерч'!I26 | ... BI76: ='07_Мерч'!BI26
A77: Целевой запас 6 мес. | B77: ='07_Мерч'!B24 | C77: ='07_Мерч'!C24 | D77: ='07_Мерч'!D24 | E77: ='07_Мерч'!E24 | F77: ='07_Мерч'!F24 | G77: ='07_Мерч'!G24 | H77: ='07_Мерч'!H24 | I77: ='07_Мерч'!I24 | ... BI77: ='07_Мерч'!BI24
A78: Дефицит склада | B78: ='07_Мерч'!B27 | C78: ='07_Мерч'!C27 | D78: ='07_Мерч'!D27 | E78: ='07_Мерч'!E27 | F78: ='07_Мерч'!F27 | G78: ='07_Мерч'!G27 | H78: ='07_Мерч'!H27 | I78: ='07_Мерч'!I27 | ... BI78: ='07_Мерч'!BI27
A80: Дебиторка роялти на конец (без НДС) | B80: =0+B19+B20-B53/(1+'01_Вводные'!$B$58) | C80: =B80+C19+C20-C53/(1+'01_Вводные'!$B$58) | D80: =C80+D19+D20-D53/(1+'01_Вводные'!$B$58) | E80: =D80+E19+E20-E53/(1+'01_Вводные'!$B$58) | F80: =E80+F19+F20-F53/(1+'01_Вводные'!$B$58) | G80: =F80+G19+G20-G53/(1+'01_Вводные'!$B$58) | H80: =G80+H19+H20-H53/(1+'01_Вводные'!$B$58) | I80: =H80+I19+I20-I53/(1+'01_Вводные'!$B$58) | J80: =I80+J19+J20-J53/(1+'01_Вводные'!$B$58) | ... BI80: =BH80+BI19+BI20-BI53/(1+'01_Вводные'!$B$58)
A81: Кредиторка OPEX / поставщиков | B81: =0+SUM(B37:B42)+'07_Мерч'!B25-B59 | C81: =B81+SUM(C37:C42)+'07_Мерч'!C25-C59 | D81: =C81+SUM(D37:D42)+'07_Мерч'!D25-D59 | E81: =D81+SUM(E37:E42)+'07_Мерч'!E25-E59 | F81: =E81+SUM(F37:F42)+'07_Мерч'!F25-F59 | G81: =F81+SUM(G37:G42)+'07_Мерч'!G25-G59 | H81: =G81+SUM(H37:H42)+'07_Мерч'!H25-H59 | I81: =H81+SUM(I37:I42)+'07_Мерч'!I25-I59 | J81: =I81+SUM(J37:J42)+'07_Мерч'!J25-J59 | ... BI81: =BH81+SUM(BI37:BI42)+'07_Мерч'!BI25-BI59
A82: Авансы клиентов лагеря на конец | B82: =0+B55-'09_Лагеря'!B10 | C82: =B82+C55-'09_Лагеря'!C10 | D82: =C82+D55-'09_Лагеря'!D10 | E82: =D82+E55-'09_Лагеря'!E10 | F82: =E82+F55-'09_Лагеря'!F10 | G82: =F82+G55-'09_Лагеря'!G10 | H82: =G82+H55-'09_Лагеря'!H10 | I82: =H82+I55-'09_Лагеря'!I10 | J82: =I82+J55-'09_Лагеря'!J10 | ... BI82: =BH82+BI55-'09_Лагеря'!BI10
A83: Предоплата проживания на конец | B83: =0+'09_Лагеря'!B16+'09_Лагеря'!B17-IF(AND('01_Вводные'!$B$241="Да",MONTH(B$3)='01_Вводные'!$B$252),'01_Вводные'!$B$170*'01_Вводные'!$B$161,0) | C83: =B83+'09_Лагеря'!C16+'09_Лагеря'!C17-IF(AND('01_Вводные'!$B$241="Да",MONTH(C$3)='01_Вводные'!$B$252),'01_Вводные'!$B$170*'01_Вводные'!$B$161,0) | D83: =C83+'09_Лагеря'!D16+'09_Лагеря'!D17-IF(AND('01_Вводные'!$B$241="Да",MONTH(D$3)='01_Вводные'!$B$252),'01_Вводные'!$B$170*'01_Вводные'!$B$161,0) | E83: =D83+'09_Лагеря'!E16+'09_Лагеря'!E17-IF(AND('01_Вводные'!$B$241="Да",MONTH(E$3)='01_Вводные'!$B$252),'01_Вводные'!$B$170*'01_Вводные'!$B$161,0) | F83: =E83+'09_Лагеря'!F16+'09_Лагеря'!F17-IF(AND('01_Вводные'!$B$241="Да",MONTH(F$3)='01_Вводные'!$B$252),'01_Вводные'!$B$170*'01_Вводные'!$B$161,0) | G83: =F83+'09_Лагеря'!G16+'09_Лагеря'!G17-IF(AND('01_Вводные'!$B$241="Да",MONTH(G$3)='01_Вводные'!$B$252),'01_Вводные'!$B$170*'01_Вводные'!$B$161,0) | H83: =G83+'09_Лагеря'!H16+'09_Лагеря'!H17-IF(AND('01_Вводные'!$B$241="Да",MONTH(H$3)='01_Вводные'!$B$252),'01_Вводные'!$B$170*'01_Вводные'!$B$161,0) | I83: =H83+'09_Лагеря'!I16+'09_Лагеря'!I17-IF(AND('01_Вводные'!$B$241="Да",MONTH(I$3)='01_Вводные'!$B$252),'01_Вводные'!$B$170*'01_Вводные'!$B$161,0) | J83: =I83+'09_Лагеря'!J16+'09_Лагеря'!J17-IF(AND('01_Вводные'!$B$241="Да",MONTH(J$3)='01_Вводные'!$B$252),'01_Вводные'!$B$170*'01_Вводные'!$B$161,0) | ... BI83: =BH83+'09_Лагеря'!BI16+'09_Лагеря'!BI17-IF(AND('01_Вводные'!$B$241="Да",MONTH(BI$3)='01_Вводные'!$B$252),'01_Вводные'!$B$170*'01_Вводные'!$B$161,0)
A84: Изменение товарного запаса | B84: ='07_Мерч'!B26-'07_Мерч'!B22 | C84: ='07_Мерч'!C26-'07_Мерч'!C22 | D84: ='07_Мерч'!D26-'07_Мерч'!D22 | E84: ='07_Мерч'!E26-'07_Мерч'!E22 | F84: ='07_Мерч'!F26-'07_Мерч'!F22 | G84: ='07_Мерч'!G26-'07_Мерч'!G22 | H84: ='07_Мерч'!H26-'07_Мерч'!H22 | I84: ='07_Мерч'!I26-'07_Мерч'!I22 | ... BI84: ='07_Мерч'!BI26-'07_Мерч'!BI22
A85: Денежный поток через мост от EBITDA | B85: =B44-B46-(B80-0)+(B81-0)+(B82-0)-(B83-0)-B84-B70+(B88-0)-B57 | C85: =C44-C46-(C80-B80)+(C81-B81)+(C82-B82)-(C83-B83)-C84-C70+(C88-B88)-C57 | D85: =D44-D46-(D80-C80)+(D81-C81)+(D82-C82)-(D83-C83)-D84-D70+(D88-C88)-D57 | E85: =E44-E46-(E80-D80)+(E81-D81)+(E82-D82)-(E83-D83)-E84-E70+(E88-D88)-E57 | F85: =F44-F46-(F80-E80)+(F81-E81)+(F82-E82)-(F83-E83)-F84-F70+(F88-E88)-F57 | G85: =G44-G46-(G80-F80)+(G81-F81)+(G82-F82)-(G83-F83)-G84-G70+(G88-F88)-G57 | H85: =H44-H46-(H80-G80)+(H81-G81)+(H82-G82)-(H83-G83)-H84-H70+(H88-G88)-H57 | I85: =I44-I46-(I80-H80)+(I81-H81)+(I82-H82)-(I83-H83)-I84-I70+(I88-H88)-I57 | J85: =J44-J46-(J80-I80)+(J81-I81)+(J82-I82)-(J83-I83)-J84-J70+(J88-I88)-J57 | ... BI85: =BI44-BI46-(BI80-BH80)+(BI81-BH81)+(BI82-BH82)-(BI83-BH83)-BI84-BI70+(BI88-BH88)-BI57
A86: Сверка БДР → БДДС (должен быть 0) | B86: =B85-B71 | C86: =C85-C71 | D86: =D85-D71 | E86: =E85-E71 | F86: =F85-F71 | G86: =G85-G71 | H86: =H85-H71 | I86: =I85-I71 | ... BI86: =BI85-BI71
A87: Баланс склада (должен быть 0) | B87: ='07_Мерч'!B22+'07_Мерч'!B25-'07_Мерч'!B23-'07_Мерч'!B26 | C87: ='07_Мерч'!C22+'07_Мерч'!C25-'07_Мерч'!C23-'07_Мерч'!C26 | D87: ='07_Мерч'!D22+'07_Мерч'!D25-'07_Мерч'!D23-'07_Мерч'!D26 | E87: ='07_Мерч'!E22+'07_Мерч'!E25-'07_Мерч'!E23-'07_Мерч'!E26 | F87: ='07_Мерч'!F22+'07_Мерч'!F25-'07_Мерч'!F23-'07_Мерч'!F26 | G87: ='07_Мерч'!G22+'07_Мерч'!G25-'07_Мерч'!G23-'07_Мерч'!G26 | H87: ='07_Мерч'!H22+'07_Мерч'!H25-'07_Мерч'!H23-'07_Мерч'!H26 | I87: ='07_Мерч'!I22+'07_Мерч'!I25-'07_Мерч'!I23-'07_Мерч'!I26 | ... BI87: ='07_Мерч'!BI22+'07_Мерч'!BI25-'07_Мерч'!BI23-'07_Мерч'!BI26
A88: Обязательство перед ФК по операционным выплатам | B88: =0+SUM(B28:B30)-B61 | C88: =B88+SUM(C28:C30)-C61 | D88: =C88+SUM(D28:D30)-D61 | E88: =D88+SUM(E28:E30)-E61 | F88: =E88+SUM(F28:F30)-F61 | G88: =F88+SUM(G28:G30)-G61 | H88: =G88+SUM(H28:H30)-H61 | I88: =H88+SUM(I28:I30)-I61 | J88: =I88+SUM(J28:J30)-J61 | ... BI88: =BH88+SUM(BI28:BI30)-BI61
A92: Helper: cash cap для займа
A93: Доступный cash до погашения займа | B93: =MAX(0,B69-'01_Вводные'!$B$237-B94) | C93: =MAX(0,C69-'01_Вводные'!$B$237-C94) | D93: =MAX(0,D69-'01_Вводные'!$B$237-D94) | E93: =MAX(0,E69-'01_Вводные'!$B$237-E94) | F93: =MAX(0,F69-'01_Вводные'!$B$237-F94) | G93: =MAX(0,G69-'01_Вводные'!$B$237-G94) | H93: =MAX(0,H69-'01_Вводные'!$B$237-H94) | I93: =MAX(0,I69-'01_Вводные'!$B$237-I94) | ... BI93: =MAX(0,BI69-'01_Вводные'!$B$237-BI94)
A94: Резерв на просадку ближайших месяцев | B94: =MAX(0,C94-C68) | C94: =MAX(0,D94-D68) | D94: =MAX(0,E94-E68) | E94: =MAX(0,F94-F68) | F94: =MAX(0,G94-G68) | G94: =MAX(0,H94-H68) | H94: =MAX(0,I94-I68) | I94: =MAX(0,J94-J68) | ... BH94: =MAX(0,BI94-BI68) | BI94: 0
A95: Инвестиции: CAPEX по правилу v4
A96: Выручка — база CAPEX | B96: =IF('01_Вводные'!$B$288="С НДС",SUM(B18:B21)*(1+'01_Вводные'!$B$58)+'09_Лагеря'!B10,B23) | C96: =IF('01_Вводные'!$B$288="С НДС",SUM(C18:C21)*(1+'01_Вводные'!$B$58)+'09_Лагеря'!C10,C23) | D96: =IF('01_Вводные'!$B$288="С НДС",SUM(D18:D21)*(1+'01_Вводные'!$B$58)+'09_Лагеря'!D10,D23) | E96: =IF('01_Вводные'!$B$288="С НДС",SUM(E18:E21)*(1+'01_Вводные'!$B$58)+'09_Лагеря'!E10,E23) | F96: =IF('01_Вводные'!$B$288="С НДС",SUM(F18:F21)*(1+'01_Вводные'!$B$58)+'09_Лагеря'!F10,F23) | G96: =IF('01_Вводные'!$B$288="С НДС",SUM(G18:G21)*(1+'01_Вводные'!$B$58)+'09_Лагеря'!G10,G23) | H96: =IF('01_Вводные'!$B$288="С НДС",SUM(H18:H21)*(1+'01_Вводные'!$B$58)+'09_Лагеря'!H10,H23) | I96: =IF('01_Вводные'!$B$288="С НДС",SUM(I18:I21)*(1+'01_Вводные'!$B$58)+'09_Лагеря'!I10,I23) | ... BI96: =IF('01_Вводные'!$B$288="С НДС",SUM(BI18:BI21)*(1+'01_Вводные'!$B$58)+'09_Лагеря'!BI10,BI23)
A97: Поддерживающий CAPEX | B97: =IF('01_Вводные'!$B$290="Да",B96*'01_Вводные'!$B$286,0) | C97: =IF('01_Вводные'!$B$290="Да",C96*'01_Вводные'!$B$286,0) | D97: =IF('01_Вводные'!$B$290="Да",D96*'01_Вводные'!$B$286,0) | E97: =IF('01_Вводные'!$B$290="Да",E96*'01_Вводные'!$B$286,0) | F97: =IF('01_Вводные'!$B$290="Да",F96*'01_Вводные'!$B$286,0) | G97: =IF('01_Вводные'!$B$290="Да",G96*'01_Вводные'!$B$286,0) | H97: =IF('01_Вводные'!$B$290="Да",H96*'01_Вводные'!$B$286,0) | I97: =IF('01_Вводные'!$B$290="Да",I96*'01_Вводные'!$B$286,0) | ... BI97: =IF('01_Вводные'!$B$290="Да",BI96*'01_Вводные'!$B$286,0)
A98: Разовый CAPEX | B98: =IF(AND('01_Вводные'!$B$290="Да",B$3='01_Вводные'!$B$289),'01_Вводные'!$B$287,0) | C98: =IF(AND('01_Вводные'!$B$290="Да",C$3='01_Вводные'!$B$289),'01_Вводные'!$B$287,0) | D98: =IF(AND('01_Вводные'!$B$290="Да",D$3='01_Вводные'!$B$289),'01_Вводные'!$B$287,0) | E98: =IF(AND('01_Вводные'!$B$290="Да",E$3='01_Вводные'!$B$289),'01_Вводные'!$B$287,0) | F98: =IF(AND('01_Вводные'!$B$290="Да",F$3='01_Вводные'!$B$289),'01_Вводные'!$B$287,0) | G98: =IF(AND('01_Вводные'!$B$290="Да",G$3='01_Вводные'!$B$289),'01_Вводные'!$B$287,0) | H98: =IF(AND('01_Вводные'!$B$290="Да",H$3='01_Вводные'!$B$289),'01_Вводные'!$B$287,0) | I98: =IF(AND('01_Вводные'!$B$290="Да",I$3='01_Вводные'!$B$289),'01_Вводные'!$B$287,0) | ... BI98: =IF(AND('01_Вводные'!$B$290="Да",BI$3='01_Вводные'!$B$289),'01_Вводные'!$B$287,0)
A99: CAPEX — всего | B99: =SUM(B97:B98) | C99: =SUM(C97:C98) | D99: =SUM(D97:D98) | E99: =SUM(E97:E98) | F99: =SUM(F97:F98) | G99: =SUM(G97:G98) | H99: =SUM(H97:H98) | I99: =SUM(I97:I98) | ... BI99: =SUM(BI97:BI98)
A100: CAPEX накопленным итогом | B100: =SUM($B99:B99) | C100: =SUM($B99:C99) | D100: =SUM($B99:D99) | E100: =SUM($B99:E99) | F100: =SUM($B99:F99) | G100: =SUM($B99:G99) | H100: =SUM($B99:H99) | I100: =SUM($B99:I99) | ... BI100: =SUM($B99:BI99)

Sheet 03_Сценарии
A1: СПАРТАК | Три сценария
A3: Сценарные множители — рабочие стресс-допущения, не утверждённый бюджет. Все суммы в млн ₽. Сценарии не зависят от выбранного варианта на дашборде.
A5: Показатель | B5: Негативный | C5: Базовый | D5: Позитивный | E5: Ед. | F5: Пояснение
A6: Выручка без НДС | B6: =SUM('19_Расчет_аналитики'!$B$717:$BI$717)/1000000 | C6: =SUM('19_Расчет_аналитики'!$B$1729:$BI$1729)/1000000 | D6: =SUM('19_Расчет_аналитики'!$B$2741:$BI$2741)/1000000 | E6: млн ₽
A7: Паушальные | B7: =SUM('19_Расчет_аналитики'!$B$712:$BI$712)/1000000 | C7: =SUM('19_Расчет_аналитики'!$B$1724:$BI$1724)/1000000 | D7: =SUM('19_Расчет_аналитики'!$B$2736:$BI$2736)/1000000 | E7: млн ₽
A8: Роялти | B8: =SUM('19_Расчет_аналитики'!$B$713:$BI$713,'19_Расчет_аналитики'!$B$714:$BI$714)/1000000 | C8: =SUM('19_Расчет_аналитики'!$B$1725:$BI$1725,'19_Расчет_аналитики'!$B$1726:$BI$1726)/1000000 | D8: =SUM('19_Расчет_аналитики'!$B$2737:$BI$2737,'19_Расчет_аналитики'!$B$2738:$BI$2738)/1000000 | E8: млн ₽
A9: Мерч | B9: =SUM('19_Расчет_аналитики'!$B$715:$BI$715)/1000000 | C9: =SUM('19_Расчет_аналитики'!$B$1727:$BI$1727)/1000000 | D9: =SUM('19_Расчет_аналитики'!$B$2739:$BI$2739)/1000000 | E9: млн ₽
A10: Лагеря | B10: =SUM('19_Расчет_аналитики'!$B$716:$BI$716)/1000000 | C10: =SUM('19_Расчет_аналитики'!$B$1728:$BI$1728)/1000000 | D10: =SUM('19_Расчет_аналитики'!$B$2740:$BI$2740)/1000000 | E10: млн ₽
A11: EBITDA | B11: =SUM('19_Расчет_аналитики'!$B$738:$BI$738)/1000000 | C11: =SUM('19_Расчет_аналитики'!$B$1750:$BI$1750)/1000000 | D11: =SUM('19_Расчет_аналитики'!$B$2762:$BI$2762)/1000000 | E11: млн ₽
A12: Рентабельность EBITDA | B12: =IF(SUM('19_Расчет_аналитики'!$B$717:$BI$717)=0,0,SUM('19_Расчет_аналитики'!$B$738:$BI$738)/SUM('19_Расчет_аналитики'!$B$717:$BI$717)) | C12: =IF(SUM('19_Расчет_аналитики'!$B$1729:$BI$1729)=0,0,SUM('19_Расчет_аналитики'!$B$1750:$BI$1750)/SUM('19_Расчет_аналитики'!$B$1729:$BI$1729)) | D12: =IF(SUM('19_Расчет_аналитики'!$B$2741:$BI$2741)=0,0,SUM('19_Расчет_аналитики'!$B$2762:$BI$2762)/SUM('19_Расчет_аналитики'!$B$2741:$BI$2741)) | E12: %
A13: Поток после CAPEX, до займа | B13: =SUM('19_Расчет_аналитики'!$B$762:$BI$762)/1000000 | C13: =SUM('19_Расчет_аналитики'!$B$1774:$BI$1774)/1000000 | D13: =SUM('19_Расчет_аналитики'!$B$2786:$BI$2786)/1000000 | E13: млн ₽
A14: Возврат займа ФК | B14: =SUM('19_Расчет_аналитики'!$B$764:$BI$764)/1000000 | C14: =SUM('19_Расчет_аналитики'!$B$1776:$BI$1776)/1000000 | D14: =SUM('19_Расчет_аналитики'!$B$2788:$BI$2788)/1000000 | E14: млн ₽
A15: Поток после займа | B15: =SUM('19_Расчет_аналитики'!$B$765:$BI$765)/1000000 | C15: =SUM('19_Расчет_аналитики'!$B$1777:$BI$1777)/1000000 | D15: =SUM('19_Расчет_аналитики'!$B$2789:$BI$2789)/1000000 | E15: млн ₽
A16: Деньги на конец | B16: ='19_Расчет_аналитики'!$BI$766/1000000 | C16: ='19_Расчет_аналитики'!$BI$1778/1000000 | D16: ='19_Расчет_аналитики'!$BI$2790/1000000 | E16: млн ₽
A17: Пиковый кассовый дефицит | B17: =MAX(0,-MIN('19_Расчет_аналитики'!$B$766:$BI$766))/1000000 | C17: =MAX(0,-MIN('19_Расчет_аналитики'!$B$1778:$BI$1778))/1000000 | D17: =MAX(0,-MIN('19_Расчет_аналитики'!$B$2790:$BI$2790))/1000000 | E17: млн ₽ | F17: Не оформленный кредит: сумма минимального отрицательного остатка. Проценты на допфинансирование не добавлены.
A18: Закупки товара | B18: =SUM('19_Расчет_аналитики'!$B$626:$BI$626)/1000000 | C18: =SUM('19_Расчет_аналитики'!$B$1638:$BI$1638)/1000000 | D18: =SUM('19_Расчет_аналитики'!$B$2650:$BI$2650)/1000000 | E18: млн ₽
A19: Пик товарного остатка | B19: =MAX('19_Расчет_аналитики'!$B$627:$BI$627)/1000000 | C19: =MAX('19_Расчет_аналитики'!$B$1639:$BI$1639)/1000000 | D19: =MAX('19_Расчет_аналитики'!$B$2651:$BI$2651)/1000000 | E19: млн ₽
A20: Склад на конец | B20: ='19_Расчет_аналитики'!$BI$770/1000000 | C20: ='19_Расчет_аналитики'!$BI$1782/1000000 | D20: ='19_Расчет_аналитики'!$BI$2794/1000000 | E20: млн ₽
A21: Займ на конец | B21: ='19_Расчет_аналитики'!$BI$769/1000000 | C21: ='19_Расчет_аналитики'!$BI$1781/1000000 | D21: ='19_Расчет_аналитики'!$BI$2793/1000000 | E21: млн ₽
A22: Нехватка товара (по себестоимости) | B22: =MAX('19_Расчет_аналитики'!$B$628:$BI$628)/1000000 | C22: =MAX('19_Расчет_аналитики'!$B$1640:$BI$1640)/1000000 | D22: =MAX('19_Расчет_аналитики'!$B$2652:$BI$2652)/1000000 | E22: млн ₽ | F22: Если >0, выручка плана не обеспечена запасом: нужны другие сроки/объёмы закупок.
A23: Продано франшиз | B23: =SUM('19_Расчет_аналитики'!$B$338:$BI$338) | C23: =SUM('19_Расчет_аналитики'!$B$1350:$BI$1350) | D23: =SUM('19_Расчет_аналитики'!$B$2362:$BI$2362) | E23: шт.
A24: Открыто школ | B24: =SUM('19_Расчет_аналитики'!$B$341:$BI$341) | C24: =SUM('19_Расчет_аналитики'!$B$1353:$BI$1353) | D24: =SUM('19_Расчет_аналитики'!$B$2365:$BI$2365) | E24: шт.
A25: Активные школы на конец | B25: ='19_Расчет_аналитики'!$BI$372 | C25: ='19_Расчет_аналитики'!$BI$1384 | D25: ='19_Расчет_аналитики'!$BI$2396 | E25: шт.
A26: Среднее активных детей в месяц | B26: =AVERAGE('19_Расчет_аналитики'!$B$380:$BI$380) | C26: =AVERAGE('19_Расчет_аналитики'!$B$1392:$BI$1392) | D26: =AVERAGE('19_Расчет_аналитики'!$B$2404:$BI$2404) | E26: чел.
A27: Операционные выплаты ФК, деньги | B27: =SUM('19_Расчет_аналитики'!$B$755:$BI$755)/1000000 | C27: =SUM('19_Расчет_аналитики'!$B$1767:$BI$1767)/1000000 | D27: =SUM('19_Расчет_аналитики'!$B$2779:$BI$2779)/1000000 | E27: млн ₽
A28: CAPEX — всего | B28: =SUM('19_Расчет_аналитики'!$B$751:$BI$751)/1000000 | C28: =SUM('19_Расчет_аналитики'!$B$1763:$BI$1763)/1000000 | D28: =SUM('19_Расчет_аналитики'!$B$2775:$BI$2775)/1000000 | E28: млн ₽
A30: EBITDA по сезонам, млн ₽
A31: 2026/27 | B31: =SUM('19_Расчет_аналитики'!$B$738:$M$738)/1000000 | C31: =SUM('19_Расчет_аналитики'!$B$1750:$M$1750)/1000000 | D31: =SUM('19_Расчет_аналитики'!$B$2762:$M$2762)/1000000
A32: 2027/28 | B32: =SUM('19_Расчет_аналитики'!$N$738:$Y$738)/1000000 | C32: =SUM('19_Расчет_аналитики'!$N$1750:$Y$1750)/1000000 | D32: =SUM('19_Расчет_аналитики'!$N$2762:$Y$2762)/1000000
A33: 2028/29 | B33: =SUM('19_Расчет_аналитики'!$Z$738:$AK$738)/1000000 | C33: =SUM('19_Расчет_аналитики'!$Z$1750:$AK$1750)/1000000 | D33: =SUM('19_Расчет_аналитики'!$Z$2762:$AK$2762)/1000000
A34: 2029/30 | B34: =SUM('19_Расчет_аналитики'!$AL$738:$AW$738)/1000000 | C34: =SUM('19_Расчет_аналитики'!$AL$1750:$AW$1750)/1000000 | D34: =SUM('19_Расчет_аналитики'!$AL$2762:$AW$2762)/1000000
A35: 2030/31 | B35: =SUM('19_Расчет_аналитики'!$AX$738:$BI$738)/1000000 | C35: =SUM('19_Расчет_аналитики'!$AX$1750:$BI$1750)/1000000 | D35: =SUM('19_Расчет_аналитики'!$AX$2762:$BI$2762)/1000000

Sheet 04_Продажи
A1: Продажи франшиз, лиды и маркетинг
A3: Контроль сезонных планов
A4: Сезон | B4: Годовой план | C4: Сумма весов | D4: Расчёт продаж | E4: Отклонение
A5: 1 | B5: ='01_Вводные'!B36 | C5: ='01_Вводные'!O36 | D5: =SUM(B15:M15) | E5: =ROUND(D5-B5,8)
A6: 2 | B6: ='01_Вводные'!B37 | C6: ='01_Вводные'!O37 | D6: =SUM(N15:Y15) | E6: =ROUND(D6-B6,8)
A7: 3 | B7: ='01_Вводные'!B38 | C7: ='01_Вводные'!O38 | D7: =SUM(Z15:AK15) | E7: =ROUND(D7-B7,8)
A8: 4 | B8: ='01_Вводные'!B39 | C8: ='01_Вводные'!O39 | D8: =SUM(AL15:AW15) | E8: =ROUND(D8-B8,8)
A9: 5 | B9: ='01_Вводные'!B40 | C9: ='01_Вводные'!O40 | D9: =SUM(AX15:BI15) | E9: =ROUND(D9-B9,8)
A10: Помесячный план
B11: =DATE(YEAR('01_Вводные'!$B$7),MONTH('01_Вводные'!$B$7)+0,1) | C11: =DATE(YEAR('01_Вводные'!$B$7),MONTH('01_Вводные'!$B$7)+1,1) | D11: =DATE(YEAR('01_Вводные'!$B$7),MONTH('01_Вводные'!$B$7)+2,1) | E11: =DATE(YEAR('01_Вводные'!$B$7),MONTH('01_Вводные'!$B$7)+3,1) | F11: =DATE(YEAR('01_Вводные'!$B$7),MONTH('01_Вводные'!$B$7)+4,1) | G11: =DATE(YEAR('01_Вводные'!$B$7),MONTH('01_Вводные'!$B$7)+5,1) | H11: =DATE(YEAR('01_Вводные'!$B$7),MONTH('01_Вводные'!$B$7)+6,1) | I11: =DATE(YEAR('01_Вводные'!$B$7),MONTH('01_Вводные'!$B$7)+7,1) | J11: =DATE(YEAR('01_Вводные'!$B$7),MONTH('01_Вводные'!$B$7)+8,1) | K11: =DATE(YEAR('01_Вводные'!$B$7),MONTH('01_Вводные'!$B$7)+9,1) | L11: =DATE(YEAR('01_Вводные'!$B$7),MONTH('01_Вводные'!$B$7)+10,1) | M11: =DATE(YEAR('01_Вводные'!$B$7),MONTH('01_Вводные'!$B$7)+11,1) | N11: =DATE(YEAR('01_Вводные'!$B$7),MONTH('01_Вводные'!$B$7)+12,1) | O11: =DATE(YEAR('01_Вводные'!$B$7),MONTH('01_Вводные'!$B$7)+13,1) | P11: =DATE(YEAR('01_Вводные'!$B$7),MONTH('01_Вводные'!$B$7)+14,1) | Q11: =DATE(YEAR('01_Вводные'!$B$7),MONTH('01_Вводные'!$B$7)+15,1) | R11: =DATE(YEAR('01_Вводные'!$B$7),MONTH('01_Вводные'!$B$7)+16,1) | S11: =DATE(YEAR('01_Вводные'!$B$7),MONTH('01_Вводные'!$B$7)+17,1) | T11: =DATE(YEAR('01_Вводные'!$B$7),MONTH('01_Вводные'!$B$7)+18,1) | U11: =DATE(YEAR('01_Вводные'!$B$7),MONTH('01_Вводные'!$B$7)+19,1) | V11: =DATE(YEAR('01_Вводные'!$B$7),MONTH('01_Вводные'!$B$7)+20,1) | W11: =DATE(YEAR('01_Вводные'!$B$7),MONTH('01_Вводные'!$B$7)+21,1) | X11: =DATE(YEAR('01_Вводные'!$B$7),MONTH('01_Вводные'!$B$7)+22,1) | Y11: =DATE(YEAR('01_Вводные'!$B$7),MONTH('01_Вводные'!$B$7)+23,1) | Z11: =DATE(YEAR('01_Вводные'!$B$7),MONTH('01_Вводные'!$B$7)+24,1) | AA11: =DATE(YEAR('01_Вводные'!$B$7),MONTH('01_Вводные'!$B$7)+25,1) | AB11: =DATE(YEAR('01_Вводные'!$B$7),MONTH('01_Вводные'!$B$7)+26,1) | AC11: =DATE(YEAR('01_Вводные'!$B$7),MONTH('01_Вводные'!$B$7)+27,1) | AD11: =DATE(YEAR('01_Вводные'!$B$7),MONTH('01_Вводные'!$B$7)+28,1) | AE11: =DATE(YEAR('01_Вводные'!$B$7),MONTH('01_Вводные'!$B$7)+29,1) | AF11: =DATE(YEAR('01_Вводные'!$B$7),MONTH('01_Вводные'!$B$7)+30,1) | AG11: =DATE(YEAR('01_Вводные'!$B$7),MONTH('01_Вводные'!$B$7)+31,1) | AH11: =DATE(YEAR('01_Вводные'!$B$7),MONTH('01_Вводные'!$B$7)+32,1) | AI11: =DATE(YEAR('01_Вводные'!$B$7),MONTH('01_Вводные'!$B$7)+33,1) | AJ11: =DATE(YEAR('01_Вводные'!$B$7),MONTH('01_Вводные'!$B$7)+34,1) | AK11: =DATE(YEAR('01_Вводные'!$B$7),MONTH('01_Вводные'!$B$7)+35,1) | AL11: =DATE(YEAR('01_Вводные'!$B$7),MONTH('01_Вводные'!$B$7)+36,1) | AM11: =DATE(YEAR('01_Вводные'!$B$7),MONTH('01_Вводные'!$B$7)+37,1) | AN11: =DATE(YEAR('01_Вводные'!$B$7),MONTH('01_Вводные'!$B$7)+38,1) | AO11: =DATE(YEAR('01_Вводные'!$B$7),MONTH('01_Вводные'!$B$7)+39,1) | AP11: =DATE(YEAR('01_Вводные'!$B$7),MONTH('01_Вводные'!$B$7)+40,1) | AQ11: =DATE(YEAR('01_Вводные'!$B$7),MONTH('01_Вводные'!$B$7)+41,1) | AR11: =DATE(YEAR('01_Вводные'!$B$7),MONTH('01_Вводные'!$B$7)+42,1) | AS11: =DATE(YEAR('01_Вводные'!$B$7),MONTH('01_Вводные'!$B$7)+43,1) | AT11: =DATE(YEAR('01_Вводные'!$B$7),MONTH('01_Вводные'!$B$7)+44,1) | AU11: =DATE(YEAR('01_Вводные'!$B$7),MONTH('01_Вводные'!$B$7)+45,1) | AV11: =DATE(YEAR('01_Вводные'!$B$7),MONTH('01_Вводные'!$B$7)+46,1) | AW11: =DATE(YEAR('01_Вводные'!$B$7),MONTH('01_Вводные'!$B$7)+47,1) | AX11: =DATE(YEAR('01_Вводные'!$B$7),MONTH('01_Вводные'!$B$7)+48,1) | AY11: =DATE(YEAR('01_Вводные'!$B$7),MONTH('01_Вводные'!$B$7)+49,1) | AZ11: =DATE(YEAR('01_Вводные'!$B$7),MONTH('01_Вводные'!$B$7)+50,1) | BA11: =DATE(YEAR('01_Вводные'!$B$7),MONTH('01_Вводные'!$B$7)+51,1) | BB11: =DATE(YEAR('01_Вводные'!$B$7),MONTH('01_Вводные'!$B$7)+52,1) | BC11: =DATE(YEAR('01_Вводные'!$B$7),MONTH('01_Вводные'!$B$7)+53,1) | BD11: =DATE(YEAR('01_Вводные'!$B$7),MONTH('01_Вводные'!$B$7)+54,1) | BE11: =DATE(YEAR('01_Вводные'!$B$7),MONTH('01_Вводные'!$B$7)+55,1) | BF11: =DATE(YEAR('01_Вводные'!$B$7),MONTH('01_Вводные'!$B$7)+56,1) | BG11: =DATE(YEAR('01_Вводные'!$B$7),MONTH('01_Вводные'!$B$7)+57,1) | BH11: =DATE(YEAR('01_Вводные'!$B$7),MONTH('01_Вводные'!$B$7)+58,1) | BI11: =DATE(YEAR('01_Вводные'!$B$7),MONTH('01_Вводные'!$B$7)+59,1)
A12: Сезон | B12: =INT((0)/12)+1 | C12: =INT((1)/12)+1 | D12: =INT((2)/12)+1 | E12: =INT((3)/12)+1 | F12: =INT((4)/12)+1 | G12: =INT((5)/12)+1 | H12: =INT((6)/12)+1 | I12: =INT((7)/12)+1 | J12: =INT((8)/12)+1 | K12: =INT((9)/12)+1 | L12: =INT((10)/12)+1 | M12: =INT((11)/12)+1 | N12: =INT((12)/12)+1 | O12: =INT((13)/12)+1 | P12: =INT((14)/12)+1 | Q12: =INT((15)/12)+1 | R12: =INT((16)/12)+1 | S12: =INT((17)/12)+1 | T12: =INT((18)/12)+1 | U12: =INT((19)/12)+1 | V12: =INT((20)/12)+1 | W12: =INT((21)/12)+1 | X12: =INT((22)/12)+1 | Y12: =INT((23)/12)+1 | Z12: =INT((24)/12)+1 | AA12: =INT((25)/12)+1 | AB12: =INT((26)/12)+1 | AC12: =INT((27)/12)+1 | AD12: =INT((28)/12)+1 | AE12: =INT((29)/12)+1 | AF12: =INT((30)/12)+1 | AG12: =INT((31)/12)+1 | AH12: =INT((32)/12)+1 | AI12: =INT((33)/12)+1 | AJ12: =INT((34)/12)+1 | AK12: =INT((35)/12)+1 | AL12: =INT((36)/12)+1 | AM12: =INT((37)/12)+1 | AN12: =INT((38)/12)+1 | AO12: =INT((39)/12)+1 | AP12: =INT((40)/12)+1 | AQ12: =INT((41)/12)+1 | AR12: =INT((42)/12)+1 | AS12: =INT((43)/12)+1 | AT12: =INT((44)/12)+1 | AU12: =INT((45)/12)+1 | AV12: =INT((46)/12)+1 | AW12: =INT((47)/12)+1 | AX12: =INT((48)/12)+1 | AY12: =INT((49)/12)+1 | AZ12: =INT((50)/12)+1 | BA12: =INT((51)/12)+1 | BB12: =INT((52)/12)+1 | BC12: =INT((53)/12)+1 | BD12: =INT((54)/12)+1 | BE12: =INT((55)/12)+1 | BF12: =INT((56)/12)+1 | BG12: =INT((57)/12)+1 | BH12: =INT((58)/12)+1 | BI12: =INT((59)/12)+1
A13: Месяц сезона | B13: 1 | C13: 2 | D13: 3 | E13: 4 | F13: 5 | G13: 6 | H13: 7 | I13: 8 | J13: 9 | K13: 10 | L13: 11 | M13: 12 | N13: 1 | O13: 2 | P13: 3 | Q13: 4 | R13: 5 | S13: 6 | T13: 7 | U13: 8 | V13: 9 | W13: 10 | X13: 11 | Y13: 12 | Z13: 1 | AA13: 2 | AB13: 3 | AC13: 4 | AD13: 5 | AE13: 6 | AF13: 7 | AG13: 8 | AH13: 9 | AI13: 10 | AJ13: 11 | AK13: 12 | AL13: 1 | AM13: 2 | AN13: 3 | AO13: 4 | AP13: 5 | AQ13: 6 | AR13: 7 | AS13: 8 | AT13: 9 | AU13: 10 | AV13: 11 | AW13: 12 | AX13: 1 | AY13: 2 | AZ13: 3 | BA13: 4 | BB13: 5 | BC13: 6 | BD13: 7 | BE13: 8 | BF13: 9 | BG13: 10 | BH13: 11 | BI13: 12
A15: Продажи франшиз — финансовый план | B15: =0 | C15: ='01_Вводные'!$B$36*INDEX('01_Вводные'!$C$36:$N$36,1,MOD(MONTH(C$11)-9,12)+1)/(SUM('01_Вводные'!$C$36:$N$36)-INDEX('01_Вводные'!$C$36:$N$36,1,MOD(MONTH('01_Вводные'!$B$7)-9,12)+1)) | D15: ='01_Вводные'!$B$36*INDEX('01_Вводные'!$C$36:$N$36,1,MOD(MONTH(D$11)-9,12)+1)/(SUM('01_Вводные'!$C$36:$N$36)-INDEX('01_Вводные'!$C$36:$N$36,1,MOD(MONTH('01_Вводные'!$B$7)-9,12)+1)) | E15: ='01_Вводные'!$B$36*INDEX('01_Вводные'!$C$36:$N$36,1,MOD(MONTH(E$11)-9,12)+1)/(SUM('01_Вводные'!$C$36:$N$36)-INDEX('01_Вводные'!$C$36:$N$36,1,MOD(MONTH('01_Вводные'!$B$7)-9,12)+1)) | F15: ='01_Вводные'!$B$36*INDEX('01_Вводные'!$C$36:$N$36,1,MOD(MONTH(F$11)-9,12)+1)/(SUM('01_Вводные'!$C$36:$N$36)-INDEX('01_Вводные'!$C$36:$N$36,1,MOD(MONTH('01_Вводные'!$B$7)-9,12)+1)) | G15: ='01_Вводные'!$B$36*INDEX('01_Вводные'!$C$36:$N$36,1,MOD(MONTH(G$11)-9,12)+1)/(SUM('01_Вводные'!$C$36:$N$36)-INDEX('01_Вводные'!$C$36:$N$36,1,MOD(MONTH('01_Вводные'!$B$7)-9,12)+1)) | H15: ='01_Вводные'!$B$36*INDEX('01_Вводные'!$C$36:$N$36,1,MOD(MONTH(H$11)-9,12)+1)/(SUM('01_Вводные'!$C$36:$N$36)-INDEX('01_Вводные'!$C$36:$N$36,1,MOD(MONTH('01_Вводные'!$B$7)-9,12)+1)) | I15: ='01_Вводные'!$B$36*INDEX('01_Вводные'!$C$36:$N$36,1,MOD(MONTH(I$11)-9,12)+1)/(SUM('01_Вводные'!$C$36:$N$36)-INDEX('01_Вводные'!$C$36:$N$36,1,MOD(MONTH('01_Вводные'!$B$7)-9,12)+1)) | J15: ='01_Вводные'!$B$36*INDEX('01_Вводные'!$C$36:$N$36,1,MOD(MONTH(J$11)-9,12)+1)/(SUM('01_Вводные'!$C$36:$N$36)-INDEX('01_Вводные'!$C$36:$N$36,1,MOD(MONTH('01_Вводные'!$B$7)-9,12)+1)) | ... M15: ='01_Вводные'!$B$36*INDEX('01_Вводные'!$C$36:$N$36,1,MOD(MONTH(M$11)-9,12)+1)/(SUM('01_Вводные'!$C$36:$N$36)-INDEX('01_Вводные'!$C$36:$N$36,1,MOD(MONTH('01_Вводные'!$B$7)-9,12)+1)) | N15: ='01_Вводные'!$B$37*INDEX('01_Вводные'!$C$37:$N$37,1,MOD(MONTH(N$11)-9,12)+1)/SUM('01_Вводные'!$C$37:$N$37) | O15: ='01_Вводные'!$B$37*INDEX('01_Вводные'!$C$37:$N$37,1,MOD(MONTH(O$11)-9,12)+1)/SUM('01_Вводные'!$C$37:$N$37) | P15: ='01_Вводные'!$B$37*INDEX('01_Вводные'!$C$37:$N$37,1,MOD(MONTH(P$11)-9,12)+1)/SUM('01_Вводные'!$C$37:$N$37) | Q15: ='01_Вводные'!$B$37*INDEX('01_Вводные'!$C$37:$N$37,1,MOD(MONTH(Q$11)-9,12)+1)/SUM('01_Вводные'!$C$37:$N$37) | R15: ='01_Вводные'!$B$37*INDEX('01_Вводные'!$C$37:$N$37,1,MOD(MONTH(R$11)-9,12)+1)/SUM('01_Вводные'!$C$37:$N$37) | S15: ='01_Вводные'!$B$37*INDEX('01_Вводные'!$C$37:$N$37,1,MOD(MONTH(S$11)-9,12)+1)/SUM('01_Вводные'!$C$37:$N$37) | T15: ='01_Вводные'!$B$37*INDEX('01_Вводные'!$C$37:$N$37,1,MOD(MONTH(T$11)-9,12)+1)/SUM('01_Вводные'!$C$37:$N$37) | U15: ='01_Вводные'!$B$37*INDEX('01_Вводные'!$C$37:$N$37,1,MOD(MONTH(U$11)-9,12)+1)/SUM('01_Вводные'!$C$37:$N$37) | ... Y15: ='01_Вводные'!$B$37*INDEX('01_Вводные'!$C$37:$N$37,1,MOD(MONTH(Y$11)-9,12)+1)/SUM('01_Вводные'!$C$37:$N$37) | Z15: ='01_Вводные'!$B$38*INDEX('01_Вводные'!$C$38:$N$38,1,MOD(MONTH(Z$11)-9,12)+1)/SUM('01_Вводные'!$C$38:$N$38) | AA15: ='01_Вводные'!$B$38*INDEX('01_Вводные'!$C$38:$N$38,1,MOD(MONTH(AA$11)-9,12)+1)/SUM('01_Вводные'!$C$38:$N$38) | AB15: ='01_Вводные'!$B$38*INDEX('01_Вводные'!$C$38:$N$38,1,MOD(MONTH(AB$11)-9,12)+1)/SUM('01_Вводные'!$C$38:$N$38) | AC15: ='01_Вводные'!$B$38*INDEX('01_Вводные'!$C$38:$N$38,1,MOD(MONTH(AC$11)-9,12)+1)/SUM('01_Вводные'!$C$38:$N$38) | AD15: ='01_Вводные'!$B$38*INDEX('01_Вводные'!$C$38:$N$38,1,MOD(MONTH(AD$11)-9,12)+1)/SUM('01_Вводные'!$C$38:$N$38) | AE15: ='01_Вводные'!$B$38*INDEX('01_Вводные'!$C$38:$N$38,1,MOD(MONTH(AE$11)-9,12)+1)/SUM('01_Вводные'!$C$38:$N$38) | AF15: ='01_Вводные'!$B$38*INDEX('01_Вводные'!$C$38:$N$38,1,MOD(MONTH(AF$11)-9,12)+1)/SUM('01_Вводные'!$C$38:$N$38) | AG15: ='01_Вводные'!$B$38*INDEX('01_Вводные'!$C$38:$N$38,1,MOD(MONTH(AG$11)-9,12)+1)/SUM('01_Вводные'!$C$38:$N$38) | ... AK15: ='01_Вводные'!$B$38*INDEX('01_Вводные'!$C$38:$N$38,1,MOD(MONTH(AK$11)-9,12)+1)/SUM('01_Вводные'!$C$38:$N$38) | AL15: ='01_Вводные'!$B$39*INDEX('01_Вводные'!$C$39:$N$39,1,MOD(MONTH(AL$11)-9,12)+1)/SUM('01_Вводные'!$C$39:$N$39) | AM15: ='01_Вводные'!$B$39*INDEX('01_Вводные'!$C$39:$N$39,1,MOD(MONTH(AM$11)-9,12)+1)/SUM('01_Вводные'!$C$39:$N$39) | AN15: ='01_Вводные'!$B$39*INDEX('01_Вводные'!$C$39:$N$39,1,MOD(MONTH(AN$11)-9,12)+1)/SUM('01_Вводные'!$C$39:$N$39) | AO15: ='01_Вводные'!$B$39*INDEX('01_Вводные'!$C$39:$N$39,1,MOD(MONTH(AO$11)-9,12)+1)/SUM('01_Вводные'!$C$39:$N$39) | AP15: ='01_Вводные'!$B$39*INDEX('01_Вводные'!$C$39:$N$39,1,MOD(MONTH(AP$11)-9,12)+1)/SUM('01_Вводные'!$C$39:$N$39) | AQ15: ='01_Вводные'!$B$39*INDEX('01_Вводные'!$C$39:$N$39,1,MOD(MONTH(AQ$11)-9,12)+1)/SUM('01_Вводные'!$C$39:$N$39) | AR15: ='01_Вводные'!$B$39*INDEX('01_Вводные'!$C$39:$N$39,1,MOD(MONTH(AR$11)-9,12)+1)/SUM('01_Вводные'!$C$39:$N$39) | AS15: ='01_Вводные'!$B$39*INDEX('01_Вводные'!$C$39:$N$39,1,MOD(MONTH(AS$11)-9,12)+1)/SUM('01_Вводные'!$C$39:$N$39) | ... AW15: ='01_Вводные'!$B$39*INDEX('01_Вводные'!$C$39:$N$39,1,MOD(MONTH(AW$11)-9,12)+1)/SUM('01_Вводные'!$C$39:$N$39) | AX15: ='01_Вводные'!$B$40*INDEX('01_Вводные'!$C$40:$N$40,1,MOD(MONTH(AX$11)-9,12)+1)/SUM('01_Вводные'!$C$40:$N$40) | AY15: ='01_Вводные'!$B$40*INDEX('01_Вводные'!$C$40:$N$40,1,MOD(MONTH(AY$11)-9,12)+1)/SUM('01_Вводные'!$C$40:$N$40) | AZ15: ='01_Вводные'!$B$40*INDEX('01_Вводные'!$C$40:$N$40,1,MOD(MONTH(AZ$11)-9,12)+1)/SUM('01_Вводные'!$C$40:$N$40) | BA15: ='01_Вводные'!$B$40*INDEX('01_Вводные'!$C$40:$N$40,1,MOD(MONTH(BA$11)-9,12)+1)/SUM('01_Вводные'!$C$40:$N$40) | BB15: ='01_Вводные'!$B$40*INDEX('01_Вводные'!$C$40:$N$40,1,MOD(MONTH(BB$11)-9,12)+1)/SUM('01_Вводные'!$C$40:$N$40) | BC15: ='01_Вводные'!$B$40*INDEX('01_Вводные'!$C$40:$N$40,1,MOD(MONTH(BC$11)-9,12)+1)/SUM('01_Вводные'!$C$40:$N$40) | BD15: ='01_Вводные'!$B$40*INDEX('01_Вводные'!$C$40:$N$40,1,MOD(MONTH(BD$11)-9,12)+1)/SUM('01_Вводные'!$C$40:$N$40) | BE15: ='01_Вводные'!$B$40*INDEX('01_Вводные'!$C$40:$N$40,1,MOD(MONTH(BE$11)-9,12)+1)/SUM('01_Вводные'!$C$40:$N$40) | ... BI15: ='01_Вводные'!$B$40*INDEX('01_Вводные'!$C$40:$N$40,1,MOD(MONTH(BI$11)-9,12)+1)/SUM('01_Вводные'!$C$40:$N$40)
A16: Операционный ориентир, целые | B16: =ROUND(B15,0) | C16: =ROUND(SUM($B15:C15),0)-ROUND(SUM($B15:B15),0) | D16: =ROUND(SUM($B15:D15),0)-ROUND(SUM($B15:C15),0) | E16: =ROUND(SUM($B15:E15),0)-ROUND(SUM($B15:D15),0) | F16: =ROUND(SUM($B15:F15),0)-ROUND(SUM($B15:E15),0) | G16: =ROUND(SUM($B15:G15),0)-ROUND(SUM($B15:F15),0) | H16: =ROUND(SUM($B15:H15),0)-ROUND(SUM($B15:G15),0) | I16: =ROUND(SUM($B15:I15),0)-ROUND(SUM($B15:H15),0) | J16: =ROUND(SUM($B15:J15),0)-ROUND(SUM($B15:I15),0) | ... M16: =ROUND(SUM($B15:M15),0)-ROUND(SUM($B15:L15),0) | N16: =ROUND(N15,0) | O16: =ROUND(SUM($N15:O15),0)-ROUND(SUM($N15:N15),0) | P16: =ROUND(SUM($N15:P15),0)-ROUND(SUM($N15:O15),0) | Q16: =ROUND(SUM($N15:Q15),0)-ROUND(SUM($N15:P15),0) | R16: =ROUND(SUM($N15:R15),0)-ROUND(SUM($N15:Q15),0) | S16: =ROUND(SUM($N15:S15),0)-ROUND(SUM($N15:R15),0) | T16: =ROUND(SUM($N15:T15),0)-ROUND(SUM($N15:S15),0) | U16: =ROUND(SUM($N15:U15),0)-ROUND(SUM($N15:T15),0) | V16: =ROUND(SUM($N15:V15),0)-ROUND(SUM($N15:U15),0) | ... Y16: =ROUND(SUM($N15:Y15),0)-ROUND(SUM($N15:X15),0) | Z16: =ROUND(Z15,0) | AA16: =ROUND(SUM($Z15:AA15),0)-ROUND(SUM($Z15:Z15),0) | AB16: =ROUND(SUM($Z15:AB15),0)-ROUND(SUM($Z15:AA15),0) | AC16: =ROUND(SUM($Z15:AC15),0)-ROUND(SUM($Z15:AB15),0) | AD16: =ROUND(SUM($Z15:AD15),0)-ROUND(SUM($Z15:AC15),0) | AE16: =ROUND(SUM($Z15:AE15),0)-ROUND(SUM($Z15:AD15),0) | AF16: =ROUND(SUM($Z15:AF15),0)-ROUND(SUM($Z15:AE15),0) | AG16: =ROUND(SUM($Z15:AG15),0)-ROUND(SUM($Z15:AF15),0) | AH16: =ROUND(SUM($Z15:AH15),0)-ROUND(SUM($Z15:AG15),0) | ... AK16: =ROUND(SUM($Z15:AK15),0)-ROUND(SUM($Z15:AJ15),0) | AL16: =ROUND(AL15,0) | AM16: =ROUND(SUM($AL15:AM15),0)-ROUND(SUM($AL15:AL15),0) | AN16: =ROUND(SUM($AL15:AN15),0)-ROUND(SUM($AL15:AM15),0) | AO16: =ROUND(SUM($AL15:AO15),0)-ROUND(SUM($AL15:AN15),0) | AP16: =ROUND(SUM($AL15:AP15),0)-ROUND(SUM($AL15:AO15),0) | AQ16: =ROUND(SUM($AL15:AQ15),0)-ROUND(SUM($AL15:AP15),0) | AR16: =ROUND(SUM($AL15:AR15),0)-ROUND(SUM($AL15:AQ15),0) | AS16: =ROUND(SUM($AL15:AS15),0)-ROUND(SUM($AL15:AR15),0) | AT16: =ROUND(SUM($AL15:AT15),0)-ROUND(SUM($AL15:AS15),0) | ... AW16: =ROUND(SUM($AL15:AW15),0)-ROUND(SUM($AL15:AV15),0) | AX16: =ROUND(AX15,0) | AY16: =ROUND(SUM($AX15:AY15),0)-ROUND(SUM($AX15:AX15),0) | AZ16: =ROUND(SUM($AX15:AZ15),0)-ROUND(SUM($AX15:AY15),0) | BA16: =ROUND(SUM($AX15:BA15),0)-ROUND(SUM($AX15:AZ15),0) | BB16: =ROUND(SUM($AX15:BB15),0)-ROUND(SUM($AX15:BA15),0) | BC16: =ROUND(SUM($AX15:BC15),0)-ROUND(SUM($AX15:BB15),0) | BD16: =ROUND(SUM($AX15:BD15),0)-ROUND(SUM($AX15:BC15),0) | BE16: =ROUND(SUM($AX15:BE15),0)-ROUND(SUM($AX15:BD15),0) | BF16: =ROUND(SUM($AX15:BF15),0)-ROUND(SUM($AX15:BE15),0) | ... BI16: =ROUND(SUM($AX15:BI15),0)-ROUND(SUM($AX15:BH15),0)
A17: Лиды | B17: =IF('01_Вводные'!$B$25>0,ROUNDUP(ROUND(B15/'01_Вводные'!$B$25,10),0),0) | C17: =IF('01_Вводные'!$B$25>0,ROUNDUP(ROUND(C15/'01_Вводные'!$B$25,10),0),0) | D17: =IF('01_Вводные'!$B$25>0,ROUNDUP(ROUND(D15/'01_Вводные'!$B$25,10),0),0) | E17: =IF('01_Вводные'!$B$25>0,ROUNDUP(ROUND(E15/'01_Вводные'!$B$25,10),0),0) | F17: =IF('01_Вводные'!$B$25>0,ROUNDUP(ROUND(F15/'01_Вводные'!$B$25,10),0),0) | G17: =IF('01_Вводные'!$B$25>0,ROUNDUP(ROUND(G15/'01_Вводные'!$B$25,10),0),0) | H17: =IF('01_Вводные'!$B$25>0,ROUNDUP(ROUND(H15/'01_Вводные'!$B$25,10),0),0) | I17: =IF('01_Вводные'!$B$25>0,ROUNDUP(ROUND(I15/'01_Вводные'!$B$25,10),0),0) | ... BI17: =IF('01_Вводные'!$B$25>0,ROUNDUP(ROUND(BI15/'01_Вводные'!$B$25,10),0),0)
A18: Открытия школ | B18: =IF(1<='01_Вводные'!$B$15,0,INDEX($B$15:$BI$15,1,1-'01_Вводные'!$B$15))*'01_Вводные'!$B$298 | C18: =IF(2<='01_Вводные'!$B$15,0,INDEX($B$15:$BI$15,1,2-'01_Вводные'!$B$15))*'01_Вводные'!$B$298 | D18: =IF(3<='01_Вводные'!$B$15,0,INDEX($B$15:$BI$15,1,3-'01_Вводные'!$B$15))*'01_Вводные'!$B$298 | E18: =IF(4<='01_Вводные'!$B$15,0,INDEX($B$15:$BI$15,1,4-'01_Вводные'!$B$15))*'01_Вводные'!$B$298 | F18: =IF(5<='01_Вводные'!$B$15,0,INDEX($B$15:$BI$15,1,5-'01_Вводные'!$B$15))*'01_Вводные'!$B$298 | G18: =IF(6<='01_Вводные'!$B$15,0,INDEX($B$15:$BI$15,1,6-'01_Вводные'!$B$15))*'01_Вводные'!$B$298 | H18: =IF(7<='01_Вводные'!$B$15,0,INDEX($B$15:$BI$15,1,7-'01_Вводные'!$B$15))*'01_Вводные'!$B$298 | I18: =IF(8<='01_Вводные'!$B$15,0,INDEX($B$15:$BI$15,1,8-'01_Вводные'!$B$15))*'01_Вводные'!$B$298 | J18: =IF(9<='01_Вводные'!$B$15,0,INDEX($B$15:$BI$15,1,9-'01_Вводные'!$B$15))*'01_Вводные'!$B$298 | K18: =IF(10<='01_Вводные'!$B$15,0,INDEX($B$15:$BI$15,1,10-'01_Вводные'!$B$15))*'01_Вводные'!$B$298 | L18: =IF(11<='01_Вводные'!$B$15,0,INDEX($B$15:$BI$15,1,11-'01_Вводные'!$B$15))*'01_Вводные'!$B$298 | M18: =IF(12<='01_Вводные'!$B$15,0,INDEX($B$15:$BI$15,1,12-'01_Вводные'!$B$15))*'01_Вводные'!$B$298 | N18: =IF(13<='01_Вводные'!$B$15,0,INDEX($B$15:$BI$15,1,13-'01_Вводные'!$B$15))*'01_Вводные'!$B$298 | O18: =IF(14<='01_Вводные'!$B$15,0,INDEX($B$15:$BI$15,1,14-'01_Вводные'!$B$15))*'01_Вводные'!$B$298 | P18: =IF(15<='01_Вводные'!$B$15,0,INDEX($B$15:$BI$15,1,15-'01_Вводные'!$B$15))*'01_Вводные'!$B$298 | Q18: =IF(16<='01_Вводные'!$B$15,0,INDEX($B$15:$BI$15,1,16-'01_Вводные'!$B$15))*'01_Вводные'!$B$298 | R18: =IF(17<='01_Вводные'!$B$15,0,INDEX($B$15:$BI$15,1,17-'01_Вводные'!$B$15))*'01_Вводные'!$B$298 | S18: =IF(18<='01_Вводные'!$B$15,0,INDEX($B$15:$BI$15,1,18-'01_Вводные'!$B$15))*'01_Вводные'!$B$298 | T18: =IF(19<='01_Вводные'!$B$15,0,INDEX($B$15:$BI$15,1,19-'01_Вводные'!$B$15))*'01_Вводные'!$B$298 | U18: =IF(20<='01_Вводные'!$B$15,0,INDEX($B$15:$BI$15,1,20-'01_Вводные'!$B$15))*'01_Вводные'!$B$298 | V18: =IF(21<='01_Вводные'!$B$15,0,INDEX($B$15:$BI$15,1,21-'01_Вводные'!$B$15))*'01_Вводные'!$B$298 | W18: =IF(22<='01_Вводные'!$B$15,0,INDEX($B$15:$BI$15,1,22-'01_Вводные'!$B$15))*'01_Вводные'!$B$298 | X18: =IF(23<='01_Вводные'!$B$15,0,INDEX($B$15:$BI$15,1,23-'01_Вводные'!$B$15))*'01_Вводные'!$B$298 | Y18: =IF(24<='01_Вводные'!$B$15,0,INDEX($B$15:$BI$15,1,24-'01_Вводные'!$B$15))*'01_Вводные'!$B$298 | Z18: =IF(25<='01_Вводные'!$B$15,0,INDEX($B$15:$BI$15,1,25-'01_Вводные'!$B$15))*'01_Вводные'!$B$298 | AA18: =IF(26<='01_Вводные'!$B$15,0,INDEX($B$15:$BI$15,1,26-'01_Вводные'!$B$15))*'01_Вводные'!$B$298 | AB18: =IF(27<='01_Вводные'!$B$15,0,INDEX($B$15:$BI$15,1,27-'01_Вводные'!$B$15))*'01_Вводные'!$B$298 | AC18: =IF(28<='01_Вводные'!$B$15,0,INDEX($B$15:$BI$15,1,28-'01_Вводные'!$B$15))*'01_Вводные'!$B$298 | AD18: =IF(29<='01_Вводные'!$B$15,0,INDEX($B$15:$BI$15,1,29-'01_Вводные'!$B$15))*'01_Вводные'!$B$298 | AE18: =IF(30<='01_Вводные'!$B$15,0,INDEX($B$15:$BI$15,1,30-'01_Вводные'!$B$15))*'01_Вводные'!$B$298 | AF18: =IF(31<='01_Вводные'!$B$15,0,INDEX($B$15:$BI$15,1,31-'01_Вводные'!$B$15))*'01_Вводные'!$B$298 | AG18: =IF(32<='01_Вводные'!$B$15,0,INDEX($B$15:$BI$15,1,32-'01_Вводные'!$B$15))*'01_Вводные'!$B$298 | AH18: =IF(33<='01_Вводные'!$B$15,0,INDEX($B$15:$BI$15,1,33-'01_Вводные'!$B$15))*'01_Вводные'!$B$298 | AI18: =IF(34<='01_Вводные'!$B$15,0,INDEX($B$15:$BI$15,1,34-'01_Вводные'!$B$15))*'01_Вводные'!$B$298 | AJ18: =IF(35<='01_Вводные'!$B$15,0,INDEX($B$15:$BI$15,1,35-'01_Вводные'!$B$15))*'01_Вводные'!$B$298 | AK18: =IF(36<='01_Вводные'!$B$15,0,INDEX($B$15:$BI$15,1,36-'01_Вводные'!$B$15))*'01_Вводные'!$B$298 | AL18: =IF(37<='01_Вводные'!$B$15,0,INDEX($B$15:$BI$15,1,37-'01_Вводные'!$B$15))*'01_Вводные'!$B$298 | AM18: =IF(38<='01_Вводные'!$B$15,0,INDEX($B$15:$BI$15,1,38-'01_Вводные'!$B$15))*'01_Вводные'!$B$298 | AN18: =IF(39<='01_Вводные'!$B$15,0,INDEX($B$15:$BI$15,1,39-'01_Вводные'!$B$15))*'01_Вводные'!$B$298 | AO18: =IF(40<='01_Вводные'!$B$15,0,INDEX($B$15:$BI$15,1,40-'01_Вводные'!$B$15))*'01_Вводные'!$B$298 | AP18: =IF(41<='01_Вводные'!$B$15,0,INDEX($B$15:$BI$15,1,41-'01_Вводные'!$B$15))*'01_Вводные'!$B$298 | AQ18: =IF(42<='01_Вводные'!$B$15,0,INDEX($B$15:$BI$15,1,42-'01_Вводные'!$B$15))*'01_Вводные'!$B$298 | AR18: =IF(43<='01_Вводные'!$B$15,0,INDEX($B$15:$BI$15,1,43-'01_Вводные'!$B$15))*'01_Вводные'!$B$298 | AS18: =IF(44<='01_Вводные'!$B$15,0,INDEX($B$15:$BI$15,1,44-'01_Вводные'!$B$15))*'01_Вводные'!$B$298 | AT18: =IF(45<='01_Вводные'!$B$15,0,INDEX($B$15:$BI$15,1,45-'01_Вводные'!$B$15))*'01_Вводные'!$B$298 | AU18: =IF(46<='01_Вводные'!$B$15,0,INDEX($B$15:$BI$15,1,46-'01_Вводные'!$B$15))*'01_Вводные'!$B$298 | AV18: =IF(47<='01_Вводные'!$B$15,0,INDEX($B$15:$BI$15,1,47-'01_Вводные'!$B$15))*'01_Вводные'!$B$298 | AW18: =IF(48<='01_Вводные'!$B$15,0,INDEX($B$15:$BI$15,1,48-'01_Вводные'!$B$15))*'01_Вводные'!$B$298 | AX18: =IF(49<='01_Вводные'!$B$15,0,INDEX($B$15:$BI$15,1,49-'01_Вводные'!$B$15))*'01_Вводные'!$B$298 | AY18: =IF(50<='01_Вводные'!$B$15,0,INDEX($B$15:$BI$15,1,50-'01_Вводные'!$B$15))*'01_Вводные'!$B$298 | AZ18: =IF(51<='01_Вводные'!$B$15,0,INDEX($B$15:$BI$15,1,51-'01_Вводные'!$B$15))*'01_Вводные'!$B$298 | BA18: =IF(52<='01_Вводные'!$B$15,0,INDEX($B$15:$BI$15,1,52-'01_Вводные'!$B$15))*'01_Вводные'!$B$298 | BB18: =IF(53<='01_Вводные'!$B$15,0,INDEX($B$15:$BI$15,1,53-'01_Вводные'!$B$15))*'01_Вводные'!$B$298 | BC18: =IF(54<='01_Вводные'!$B$15,0,INDEX($B$15:$BI$15,1,54-'01_Вводные'!$B$15))*'01_Вводные'!$B$298 | BD18: =IF(55<='01_Вводные'!$B$15,0,INDEX($B$15:$BI$15,1,55-'01_Вводные'!$B$15))*'01_Вводные'!$B$298 | BE18: =IF(56<='01_Вводные'!$B$15,0,INDEX($B$15:$BI$15,1,56-'01_Вводные'!$B$15))*'01_Вводные'!$B$298 | BF18: =IF(57<='01_Вводные'!$B$15,0,INDEX($B$15:$BI$15,1,57-'01_Вводные'!$B$15))*'01_Вводные'!$B$298 | BG18: =IF(58<='01_Вводные'!$B$15,0,INDEX($B$15:$BI$15,1,58-'01_Вводные'!$B$15))*'01_Вводные'!$B$298 | BH18: =IF(59<='01_Вводные'!$B$15,0,INDEX($B$15:$BI$15,1,59-'01_Вводные'!$B$15))*'01_Вводные'!$B$298 | BI18: =IF(60<='01_Вводные'!$B$15,0,INDEX($B$15:$BI$15,1,60-'01_Вводные'!$B$15))*'01_Вводные'!$B$298
A19: Новые юрлица | B19: =B15*'01_Вводные'!$B$16 | C19: =C15*'01_Вводные'!$B$16 | D19: =D15*'01_Вводные'!$B$16 | E19: =E15*'01_Вводные'!$B$16 | F19: =F15*'01_Вводные'!$B$16 | G19: =G15*'01_Вводные'!$B$16 | H19: =H15*'01_Вводные'!$B$16 | I19: =I15*'01_Вводные'!$B$16 | ... BI19: =BI15*'01_Вводные'!$B$16
A21: Таргет на будущие продажи | B21: =SUMIF($B$28:$BI$28,B$11,$B$15:$BI$15)*'18_Календарь_тарифы'!B11 | C21: =SUMIF($B$28:$BI$28,C$11,$B$15:$BI$15)*'18_Календарь_тарифы'!C11 | D21: =SUMIF($B$28:$BI$28,D$11,$B$15:$BI$15)*'18_Календарь_тарифы'!D11 | E21: =SUMIF($B$28:$BI$28,E$11,$B$15:$BI$15)*'18_Календарь_тарифы'!E11 | F21: =SUMIF($B$28:$BI$28,F$11,$B$15:$BI$15)*'18_Календарь_тарифы'!F11 | G21: =SUMIF($B$28:$BI$28,G$11,$B$15:$BI$15)*'18_Календарь_тарифы'!G11 | H21: =SUMIF($B$28:$BI$28,H$11,$B$15:$BI$15)*'18_Календарь_тарифы'!H11 | I21: =SUMIF($B$28:$BI$28,I$11,$B$15:$BI$15)*'18_Календарь_тарифы'!I11 | ... BI21: =SUMIF($B$28:$BI$28,BI$11,$B$15:$BI$15)*'18_Календарь_тарифы'!BI11
A22: БИБОСС / TopFranchise / Forbes | B22: =(IF(MONTH(B$11)='01_Вводные'!$B$29,'01_Вводные'!$B$28,0)+IF(MONTH(B$11)='01_Вводные'!$B$31,'01_Вводные'!$B$30,0)+IF(MONTH(B$11)='01_Вводные'!$B$33,'01_Вводные'!$B$32,0))*'18_Календарь_тарифы'!B4 | C22: =(IF(MONTH(C$11)='01_Вводные'!$B$29,'01_Вводные'!$B$28,0)+IF(MONTH(C$11)='01_Вводные'!$B$31,'01_Вводные'!$B$30,0)+IF(MONTH(C$11)='01_Вводные'!$B$33,'01_Вводные'!$B$32,0))*'18_Календарь_тарифы'!C4 | D22: =(IF(MONTH(D$11)='01_Вводные'!$B$29,'01_Вводные'!$B$28,0)+IF(MONTH(D$11)='01_Вводные'!$B$31,'01_Вводные'!$B$30,0)+IF(MONTH(D$11)='01_Вводные'!$B$33,'01_Вводные'!$B$32,0))*'18_Календарь_тарифы'!D4 | E22: =(IF(MONTH(E$11)='01_Вводные'!$B$29,'01_Вводные'!$B$28,0)+IF(MONTH(E$11)='01_Вводные'!$B$31,'01_Вводные'!$B$30,0)+IF(MONTH(E$11)='01_Вводные'!$B$33,'01_Вводные'!$B$32,0))*'18_Календарь_тарифы'!E4 | F22: =(IF(MONTH(F$11)='01_Вводные'!$B$29,'01_Вводные'!$B$28,0)+IF(MONTH(F$11)='01_Вводные'!$B$31,'01_Вводные'!$B$30,0)+IF(MONTH(F$11)='01_Вводные'!$B$33,'01_Вводные'!$B$32,0))*'18_Календарь_тарифы'!F4 | G22: =(IF(MONTH(G$11)='01_Вводные'!$B$29,'01_Вводные'!$B$28,0)+IF(MONTH(G$11)='01_Вводные'!$B$31,'01_Вводные'!$B$30,0)+IF(MONTH(G$11)='01_Вводные'!$B$33,'01_Вводные'!$B$32,0))*'18_Календарь_тарифы'!G4 | H22: =(IF(MONTH(H$11)='01_Вводные'!$B$29,'01_Вводные'!$B$28,0)+IF(MONTH(H$11)='01_Вводные'!$B$31,'01_Вводные'!$B$30,0)+IF(MONTH(H$11)='01_Вводные'!$B$33,'01_Вводные'!$B$32,0))*'18_Календарь_тарифы'!H4 | I22: =(IF(MONTH(I$11)='01_Вводные'!$B$29,'01_Вводные'!$B$28,0)+IF(MONTH(I$11)='01_Вводные'!$B$31,'01_Вводные'!$B$30,0)+IF(MONTH(I$11)='01_Вводные'!$B$33,'01_Вводные'!$B$32,0))*'18_Календарь_тарифы'!I4 | ... BI22: =(IF(MONTH(BI$11)='01_Вводные'!$B$29,'01_Вводные'!$B$28,0)+IF(MONTH(BI$11)='01_Вводные'!$B$31,'01_Вводные'!$B$30,0)+IF(MONTH(BI$11)='01_Вводные'!$B$33,'01_Вводные'!$B$32,0))*'18_Календарь_тарифы'!BI4
A23: Маркетинг привлечения — всего | B23: =B21+B22 | C23: =C21+C22 | D23: =D21+D22 | E23: =E21+E22 | F23: =F21+F22 | G23: =G21+G22 | H23: =H21+H22 | I23: =I21+I22 | ... BI23: =BI21+BI22
A25: Паушальные взносы, с НДС | B25: =B15*'18_Календарь_тарифы'!B6 | C25: =C15*'18_Календарь_тарифы'!C6 | D25: =D15*'18_Календарь_тарифы'!D6 | E25: =E15*'18_Календарь_тарифы'!E6 | F25: =F15*'18_Календарь_тарифы'!F6 | G25: =G15*'18_Календарь_тарифы'!G6 | H25: =H15*'18_Календарь_тарифы'!H6 | I25: =I15*'18_Календарь_тарифы'!I6 | ... BI25: =BI15*'18_Календарь_тарифы'!BI6
A26: Паушальные взносы, без НДС | B26: =B25/(1+'01_Вводные'!$B$58) | C26: =C25/(1+'01_Вводные'!$B$58) | D26: =D25/(1+'01_Вводные'!$B$58) | E26: =E25/(1+'01_Вводные'!$B$58) | F26: =F25/(1+'01_Вводные'!$B$58) | G26: =G25/(1+'01_Вводные'!$B$58) | H26: =H25/(1+'01_Вводные'!$B$58) | I26: =I25/(1+'01_Вводные'!$B$58) | ... BI26: =BI25/(1+'01_Вводные'!$B$58)
A28: Месяц оплаты рекламы для продажи | B28: =DATE(YEAR(B$11),MONTH(B$11)-IF(B$11='01_Вводные'!$B$242,'01_Вводные'!$B$243,'01_Вводные'!$B$27),1) | C28: =DATE(YEAR(C$11),MONTH(C$11)-IF(C$11='01_Вводные'!$B$242,'01_Вводные'!$B$243,'01_Вводные'!$B$27),1) | D28: =DATE(YEAR(D$11),MONTH(D$11)-IF(D$11='01_Вводные'!$B$242,'01_Вводные'!$B$243,'01_Вводные'!$B$27),1) | E28: =DATE(YEAR(E$11),MONTH(E$11)-IF(E$11='01_Вводные'!$B$242,'01_Вводные'!$B$243,'01_Вводные'!$B$27),1) | F28: =DATE(YEAR(F$11),MONTH(F$11)-IF(F$11='01_Вводные'!$B$242,'01_Вводные'!$B$243,'01_Вводные'!$B$27),1) | G28: =DATE(YEAR(G$11),MONTH(G$11)-IF(G$11='01_Вводные'!$B$242,'01_Вводные'!$B$243,'01_Вводные'!$B$27),1) | H28: =DATE(YEAR(H$11),MONTH(H$11)-IF(H$11='01_Вводные'!$B$242,'01_Вводные'!$B$243,'01_Вводные'!$B$27),1) | I28: =DATE(YEAR(I$11),MONTH(I$11)-IF(I$11='01_Вводные'!$B$242,'01_Вводные'!$B$243,'01_Вводные'!$B$27),1) | ... BI28: =DATE(YEAR(BI$11),MONTH(BI$11)-IF(BI$11='01_Вводные'!$B$242,'01_Вводные'!$B$243,'01_Вводные'!$B$27),1)

Sheet 05_Воронка
A1: СПАРТАК | Воронка продаж и запуск школ
A3: Плановая воронка: требуемые лиды → оплаченные продажи → открытия с лагом → ERP. Промежуточные конверсии встреч/заявок не заданы и не придуманы. Продажа считается состоявшейся после оплаты.
A5: Показатель | B5: 2026/27 | C5: 2027/28 | D5: 2028/29 | E5: 2029/30 | F5: 2030/31 | G5: Итого / конец | H5: Комментарий
A6: Требуемые лиды, расчётно | B6: =SUM('04_Продажи'!B15:M15)/'01_Вводные'!$B$25 | C6: =SUM('04_Продажи'!N15:Y15)/'01_Вводные'!$B$25 | D6: =SUM('04_Продажи'!Z15:AK15)/'01_Вводные'!$B$25 | E6: =SUM('04_Продажи'!AL15:AW15)/'01_Вводные'!$B$25 | F6: =SUM('04_Продажи'!AX15:BI15)/'01_Вводные'!$B$25 | G6: =SUM(B6:F6) | H6: Требуемый объём, не гарантия лидов от ФК.
A7: Лиды, целый операционный ориентир | B7: =SUM('04_Продажи'!B17:M17) | C7: =SUM('04_Продажи'!N17:Y17) | D7: =SUM('04_Продажи'!Z17:AK17) | E7: =SUM('04_Продажи'!AL17:AW17) | F7: =SUM('04_Продажи'!AX17:BI17) | G7: =SUM(B7:F7)
A8: Оплаченные продажи — финансовый план | B8: =SUM('04_Продажи'!B15:M15) | C8: =SUM('04_Продажи'!N15:Y15) | D8: =SUM('04_Продажи'!Z15:AK15) | E8: =SUM('04_Продажи'!AL15:AW15) | F8: =SUM('04_Продажи'!AX15:BI15) | G8: =SUM(B8:F8)
A9: Продажи — целый операционный ориентир | B9: =SUM('04_Продажи'!B16:M16) | C9: =SUM('04_Продажи'!N16:Y16) | D9: =SUM('04_Продажи'!Z16:AK16) | E9: =SUM('04_Продажи'!AL16:AW16) | F9: =SUM('04_Продажи'!AX16:BI16) | G9: =SUM(B9:F9) | H9: Округление накопленного плана; сумма сезона сохранена.
A10: Открытия школ | B10: =SUM('04_Продажи'!B18:M18) | C10: =SUM('04_Продажи'!N18:Y18) | D10: =SUM('04_Продажи'!Z18:AK18) | E10: =SUM('04_Продажи'!AL18:AW18) | F10: =SUM('04_Продажи'!AX18:BI18) | G10: =SUM(B10:F10)
A11: Подключения школ к ERP | B11: =SUM('06_Сеть_и_дети'!B43:M43) | C11: =SUM('06_Сеть_и_дети'!N43:Y43) | D11: =SUM('06_Сеть_и_дети'!Z43:AK43) | E11: =SUM('06_Сеть_и_дети'!AL43:AW43) | F11: =SUM('06_Сеть_и_дети'!AX43:BI43) | G11: =SUM(B11:F11)
A12: Продано, но ещё не открыто на конец | B12: =SUM('04_Продажи'!$B$15:M15)-SUM('04_Продажи'!$B$18:M18) | C12: =SUM('04_Продажи'!$B$15:Y15)-SUM('04_Продажи'!$B$18:Y18) | D12: =SUM('04_Продажи'!$B$15:AK15)-SUM('04_Продажи'!$B$18:AK18) | E12: =SUM('04_Продажи'!$B$15:AW15)-SUM('04_Продажи'!$B$18:AW18) | F12: =SUM('04_Продажи'!$B$15:BI15)-SUM('04_Продажи'!$B$18:BI18) | G12: =F12 | H12: Хвост последнего сезона не потерян: запуск за горизонтом.
A13: Таргетированная реклама, ₽ | B13: =SUM('04_Продажи'!B21:M21) | C13: =SUM('04_Продажи'!N21:Y21) | D13: =SUM('04_Продажи'!Z21:AK21) | E13: =SUM('04_Продажи'!AL21:AW21) | F13: =SUM('04_Продажи'!AX21:BI21) | G13: =SUM(B13:F13)
A14: Все затраты привлечения, ₽ | B14: =SUM('04_Продажи'!B23:M23) | C14: =SUM('04_Продажи'!N23:Y23) | D14: =SUM('04_Продажи'!Z23:AK23) | E14: =SUM('04_Продажи'!AL23:AW23) | F14: =SUM('04_Продажи'!AX23:BI23) | G14: =SUM(B14:F14)
A15: Конверсия лид → оплаченная продажа | B15: ='01_Вводные'!$B$25 | C15: ='01_Вводные'!$B$25 | D15: ='01_Вводные'!$B$25 | E15: ='01_Вводные'!$B$25 | F15: ='01_Вводные'!$B$25 | G15: =F15
A18: Помесячная воронка
A19: Показатель | B19: ='04_Продажи'!B11 | C19: ='04_Продажи'!C11 | D19: ='04_Продажи'!D11 | E19: ='04_Продажи'!E11 | F19: ='04_Продажи'!F11 | G19: ='04_Продажи'!G11 | H19: ='04_Продажи'!H11 | I19: ='04_Продажи'!I11 | ... BI19: ='04_Продажи'!BI11
A20: Лиды, шт. | B20: ='04_Продажи'!B17 | C20: ='04_Продажи'!C17 | D20: ='04_Продажи'!D17 | E20: ='04_Продажи'!E17 | F20: ='04_Продажи'!F17 | G20: ='04_Продажи'!G17 | H20: ='04_Продажи'!H17 | I20: ='04_Продажи'!I17 | ... BI20: ='04_Продажи'!BI17
A21: Оплаченные продажи | B21: ='04_Продажи'!B15 | C21: ='04_Продажи'!C15 | D21: ='04_Продажи'!D15 | E21: ='04_Продажи'!E15 | F21: ='04_Продажи'!F15 | G21: ='04_Продажи'!G15 | H21: ='04_Продажи'!H15 | I21: ='04_Продажи'!I15 | ... BI21: ='04_Продажи'!BI15
A22: Продажи целые | B22: ='04_Продажи'!B16 | C22: ='04_Продажи'!C16 | D22: ='04_Продажи'!D16 | E22: ='04_Продажи'!E16 | F22: ='04_Продажи'!F16 | G22: ='04_Продажи'!G16 | H22: ='04_Продажи'!H16 | I22: ='04_Продажи'!I16 | ... BI22: ='04_Продажи'!BI16
A23: Открытия школ | B23: ='04_Продажи'!B18 | C23: ='04_Продажи'!C18 | D23: ='04_Продажи'!D18 | E23: ='04_Продажи'!E18 | F23: ='04_Продажи'!F18 | G23: ='04_Продажи'!G18 | H23: ='04_Продажи'!H18 | I23: ='04_Продажи'!I18 | ... BI23: ='04_Продажи'!BI18
A24: Подключения ERP | B24: ='06_Сеть_и_дети'!B43 | C24: ='06_Сеть_и_дети'!C43 | D24: ='06_Сеть_и_дети'!D43 | E24: ='06_Сеть_и_дети'!E43 | F24: ='06_Сеть_и_дети'!F43 | G24: ='06_Сеть_и_дети'!G43 | H24: ='06_Сеть_и_дети'!H43 | I24: ='06_Сеть_и_дети'!I43 | ... BI24: ='06_Сеть_и_дети'!BI43
A25: Продано, но не открыто | B25: =SUM('04_Продажи'!$B$15:B15)-SUM('04_Продажи'!$B$18:B18) | C25: =SUM('04_Продажи'!$B$15:C15)-SUM('04_Продажи'!$B$18:C18) | D25: =SUM('04_Продажи'!$B$15:D15)-SUM('04_Продажи'!$B$18:D18) | E25: =SUM('04_Продажи'!$B$15:E15)-SUM('04_Продажи'!$B$18:E18) | F25: =SUM('04_Продажи'!$B$15:F15)-SUM('04_Продажи'!$B$18:F18) | G25: =SUM('04_Продажи'!$B$15:G15)-SUM('04_Продажи'!$B$18:G18) | H25: =SUM('04_Продажи'!$B$15:H15)-SUM('04_Продажи'!$B$18:H18) | I25: =SUM('04_Продажи'!$B$15:I15)-SUM('04_Продажи'!$B$18:I18) | ... BI25: =SUM('04_Продажи'!$B$15:BI15)-SUM('04_Продажи'!$B$18:BI18)
A26: Таргет, ₽ | B26: ='04_Продажи'!B21 | C26: ='04_Продажи'!C21 | D26: ='04_Продажи'!D21 | E26: ='04_Продажи'!E21 | F26: ='04_Продажи'!F21 | G26: ='04_Продажи'!G21 | H26: ='04_Продажи'!H21 | I26: ='04_Продажи'!I21 | ... BI26: ='04_Продажи'!BI21
A27: Маркетинг привлечения, ₽ | B27: ='04_Продажи'!B23 | C27: ='04_Продажи'!C23 | D27: ='04_Продажи'!D23 | E27: ='04_Продажи'!E23 | F27: ='04_Продажи'!F23 | G27: ='04_Продажи'!G23 | H27: ='04_Продажи'!H23 | I27: ='04_Продажи'!I23 | ... BI27: ='04_Продажи'!BI23

Sheet 06_Сеть_и_дети
A1: Сеть, постепенный набор детей и роялти по каждому тарифу
B3: =DATE(YEAR('01_Вводные'!$B$7),MONTH('01_Вводные'!$B$7)+0,1) | C3: =DATE(YEAR('01_Вводные'!$B$7),MONTH('01_Вводные'!$B$7)+1,1) | D3: =DATE(YEAR('01_Вводные'!$B$7),MONTH('01_Вводные'!$B$7)+2,1) | E3: =DATE(YEAR('01_Вводные'!$B$7),MONTH('01_Вводные'!$B$7)+3,1) | F3: =DATE(YEAR('01_Вводные'!$B$7),MONTH('01_Вводные'!$B$7)+4,1) | G3: =DATE(YEAR('01_Вводные'!$B$7),MONTH('01_Вводные'!$B$7)+5,1) | H3: =DATE(YEAR('01_Вводные'!$B$7),MONTH('01_Вводные'!$B$7)+6,1) | I3: =DATE(YEAR('01_Вводные'!$B$7),MONTH('01_Вводные'!$B$7)+7,1) | J3: =DATE(YEAR('01_Вводные'!$B$7),MONTH('01_Вводные'!$B$7)+8,1) | K3: =DATE(YEAR('01_Вводные'!$B$7),MONTH('01_Вводные'!$B$7)+9,1) | L3: =DATE(YEAR('01_Вводные'!$B$7),MONTH('01_Вводные'!$B$7)+10,1) | M3: =DATE(YEAR('01_Вводные'!$B$7),MONTH('01_Вводные'!$B$7)+11,1) | N3: =DATE(YEAR('01_Вводные'!$B$7),MONTH('01_Вводные'!$B$7)+12,1) | O3: =DATE(YEAR('01_Вводные'!$B$7),MONTH('01_Вводные'!$B$7)+13,1) | P3: =DATE(YEAR('01_Вводные'!$B$7),MONTH('01_Вводные'!$B$7)+14,1) | Q3: =DATE(YEAR('01_Вводные'!$B$7),MONTH('01_Вводные'!$B$7)+15,1) | R3: =DATE(YEAR('01_Вводные'!$B$7),MONTH('01_Вводные'!$B$7)+16,1) | S3: =DATE(YEAR('01_Вводные'!$B$7),MONTH('01_Вводные'!$B$7)+17,1) | T3: =DATE(YEAR('01_Вводные'!$B$7),MONTH('01_Вводные'!$B$7)+18,1) | U3: =DATE(YEAR('01_Вводные'!$B$7),MONTH('01_Вводные'!$B$7)+19,1) | V3: =DATE(YEAR('01_Вводные'!$B$7),MONTH('01_Вводные'!$B$7)+20,1) | W3: =DATE(YEAR('01_Вводные'!$B$7),MONTH('01_Вводные'!$B$7)+21,1) | X3: =DATE(YEAR('01_Вводные'!$B$7),MONTH('01_Вводные'!$B$7)+22,1) | Y3: =DATE(YEAR('01_Вводные'!$B$7),MONTH('01_Вводные'!$B$7)+23,1) | Z3: =DATE(YEAR('01_Вводные'!$B$7),MONTH('01_Вводные'!$B$7)+24,1) | AA3: =DATE(YEAR('01_Вводные'!$B$7),MONTH('01_Вводные'!$B$7)+25,1) | AB3: =DATE(YEAR('01_Вводные'!$B$7),MONTH('01_Вводные'!$B$7)+26,1) | AC3: =DATE(YEAR('01_Вводные'!$B$7),MONTH('01_Вводные'!$B$7)+27,1) | AD3: =DATE(YEAR('01_Вводные'!$B$7),MONTH('01_Вводные'!$B$7)+28,1) | AE3: =DATE(YEAR('01_Вводные'!$B$7),MONTH('01_Вводные'!$B$7)+29,1) | AF3: =DATE(YEAR('01_Вводные'!$B$7),MONTH('01_Вводные'!$B$7)+30,1) | AG3: =DATE(YEAR('01_Вводные'!$B$7),MONTH('01_Вводные'!$B$7)+31,1) | AH3: =DATE(YEAR('01_Вводные'!$B$7),MONTH('01_Вводные'!$B$7)+32,1) | AI3: =DATE(YEAR('01_Вводные'!$B$7),MONTH('01_Вводные'!$B$7)+33,1) | AJ3: =DATE(YEAR('01_Вводные'!$B$7),MONTH('01_Вводные'!$B$7)+34,1) | AK3: =DATE(YEAR('01_Вводные'!$B$7),MONTH('01_Вводные'!$B$7)+35,1) | AL3: =DATE(YEAR('01_Вводные'!$B$7),MONTH('01_Вводные'!$B$7)+36,1) | AM3: =DATE(YEAR('01_Вводные'!$B$7),MONTH('01_Вводные'!$B$7)+37,1) | AN3: =DATE(YEAR('01_Вводные'!$B$7),MONTH('01_Вводные'!$B$7)+38,1) | AO3: =DATE(YEAR('01_Вводные'!$B$7),MONTH('01_Вводные'!$B$7)+39,1) | AP3: =DATE(YEAR('01_Вводные'!$B$7),MONTH('01_Вводные'!$B$7)+40,1) | AQ3: =DATE(YEAR('01_Вводные'!$B$7),MONTH('01_Вводные'!$B$7)+41,1) | AR3: =DATE(YEAR('01_Вводные'!$B$7),MONTH('01_Вводные'!$B$7)+42,1) | AS3: =DATE(YEAR('01_Вводные'!$B$7),MONTH('01_Вводные'!$B$7)+43,1) | AT3: =DATE(YEAR('01_Вводные'!$B$7),MONTH('01_Вводные'!$B$7)+44,1) | AU3: =DATE(YEAR('01_Вводные'!$B$7),MONTH('01_Вводные'!$B$7)+45,1) | AV3: =DATE(YEAR('01_Вводные'!$B$7),MONTH('01_Вводные'!$B$7)+46,1) | AW3: =DATE(YEAR('01_Вводные'!$B$7),MONTH('01_Вводные'!$B$7)+47,1) | AX3: =DATE(YEAR('01_Вводные'!$B$7),MONTH('01_Вводные'!$B$7)+48,1) | AY3: =DATE(YEAR('01_Вводные'!$B$7),MONTH('01_Вводные'!$B$7)+49,1) | AZ3: =DATE(YEAR('01_Вводные'!$B$7),MONTH('01_Вводные'!$B$7)+50,1) | BA3: =DATE(YEAR('01_Вводные'!$B$7),MONTH('01_Вводные'!$B$7)+51,1) | BB3: =DATE(YEAR('01_Вводные'!$B$7),MONTH('01_Вводные'!$B$7)+52,1) | BC3: =DATE(YEAR('01_Вводные'!$B$7),MONTH('01_Вводные'!$B$7)+53,1) | BD3: =DATE(YEAR('01_Вводные'!$B$7),MONTH('01_Вводные'!$B$7)+54,1) | BE3: =DATE(YEAR('01_Вводные'!$B$7),MONTH('01_Вводные'!$B$7)+55,1) | BF3: =DATE(YEAR('01_Вводные'!$B$7),MONTH('01_Вводные'!$B$7)+56,1) | BG3: =DATE(YEAR('01_Вводные'!$B$7),MONTH('01_Вводные'!$B$7)+57,1) | BH3: =DATE(YEAR('01_Вводные'!$B$7),MONTH('01_Вводные'!$B$7)+58,1) | BI3: =DATE(YEAR('01_Вводные'!$B$7),MONTH('01_Вводные'!$B$7)+59,1) | BJ3: =DATE(YEAR('01_Вводные'!$B$7),MONTH('01_Вводные'!$B$7)+60,1) | BK3: =DATE(YEAR('01_Вводные'!$B$7),MONTH('01_Вводные'!$B$7)+61,1) | BL3: =DATE(YEAR('01_Вводные'!$B$7),MONTH('01_Вводные'!$B$7)+62,1) | BM3: =DATE(YEAR('01_Вводные'!$B$7),MONTH('01_Вводные'!$B$7)+63,1) | BN3: =DATE(YEAR('01_Вводные'!$B$7),MONTH('01_Вводные'!$B$7)+64,1) | BO3: =DATE(YEAR('01_Вводные'!$B$7),MONTH('01_Вводные'!$B$7)+65,1)
A4: Сезон | B4: =INT((0)/12)+1 | C4: =INT((1)/12)+1 | D4: =INT((2)/12)+1 | E4: =INT((3)/12)+1 | F4: =INT((4)/12)+1 | G4: =INT((5)/12)+1 | H4: =INT((6)/12)+1 | I4: =INT((7)/12)+1 | J4: =INT((8)/12)+1 | K4: =INT((9)/12)+1 | L4: =INT((10)/12)+1 | M4: =INT((11)/12)+1 | N4: =INT((12)/12)+1 | O4: =INT((13)/12)+1 | P4: =INT((14)/12)+1 | Q4: =INT((15)/12)+1 | R4: =INT((16)/12)+1 | S4: =INT((17)/12)+1 | T4: =INT((18)/12)+1 | U4: =INT((19)/12)+1 | V4: =INT((20)/12)+1 | W4: =INT((21)/12)+1 | X4: =INT((22)/12)+1 | Y4: =INT((23)/12)+1 | Z4: =INT((24)/12)+1 | AA4: =INT((25)/12)+1 | AB4: =INT((26)/12)+1 | AC4: =INT((27)/12)+1 | AD4: =INT((28)/12)+1 | AE4: =INT((29)/12)+1 | AF4: =INT((30)/12)+1 | AG4: =INT((31)/12)+1 | AH4: =INT((32)/12)+1 | AI4: =INT((33)/12)+1 | AJ4: =INT((34)/12)+1 | AK4: =INT((35)/12)+1 | AL4: =INT((36)/12)+1 | AM4: =INT((37)/12)+1 | AN4: =INT((38)/12)+1 | AO4: =INT((39)/12)+1 | AP4: =INT((40)/12)+1 | AQ4: =INT((41)/12)+1 | AR4: =INT((42)/12)+1 | AS4: =INT((43)/12)+1 | AT4: =INT((44)/12)+1 | AU4: =INT((45)/12)+1 | AV4: =INT((46)/12)+1 | AW4: =INT((47)/12)+1 | AX4: =INT((48)/12)+1 | AY4: =INT((49)/12)+1 | AZ4: =INT((50)/12)+1 | BA4: =INT((51)/12)+1 | BB4: =INT((52)/12)+1 | BC4: =INT((53)/12)+1 | BD4: =INT((54)/12)+1 | BE4: =INT((55)/12)+1 | BF4: =INT((56)/12)+1 | BG4: =INT((57)/12)+1 | BH4: =INT((58)/12)+1 | BI4: =INT((59)/12)+1 | BJ4: =INT((60)/12)+1 | BK4: =INT((61)/12)+1 | BL4: =INT((62)/12)+1 | BM4: =INT((63)/12)+1 | BN4: =INT((64)/12)+1 | BO4: =INT((65)/12)+1
A5: Сезонность посещаемости | B5: =INDEX('01_Вводные'!$B$44:$M$44,1,MONTH(B$3)) | C5: =INDEX('01_Вводные'!$B$44:$M$44,1,MONTH(C$3)) | D5: =INDEX('01_Вводные'!$B$44:$M$44,1,MONTH(D$3)) | E5: =INDEX('01_Вводные'!$B$44:$M$44,1,MONTH(E$3)) | F5: =INDEX('01_Вводные'!$B$44:$M$44,1,MONTH(F$3)) | G5: =INDEX('01_Вводные'!$B$44:$M$44,1,MONTH(G$3)) | H5: =INDEX('01_Вводные'!$B$44:$M$44,1,MONTH(H$3)) | I5: =INDEX('01_Вводные'!$B$44:$M$44,1,MONTH(I$3)) | ... BO5: =INDEX('01_Вводные'!$B$44:$M$44,1,MONTH(BO$3))
A6: Сеть
A7: Продажи | B7: ='04_Продажи'!B15 | C7: ='04_Продажи'!C15 | D7: ='04_Продажи'!D15 | E7: ='04_Продажи'!E15 | F7: ='04_Продажи'!F15 | G7: ='04_Продажи'!G15 | H7: ='04_Продажи'!H15 | I7: ='04_Продажи'!I15 | ... BI7: ='04_Продажи'!BI15 | BJ7: 0 | BK7: 0 | BL7: 0 | BM7: 0 | BN7: 0 | BO7: 0
A8: Открытия школ | B8: =IF(OR(1<='01_Вводные'!$B$15,1-'01_Вводные'!$B$15>60),0,INDEX('04_Продажи'!$B$15:$BI$15,1,1-'01_Вводные'!$B$15))*'01_Вводные'!$B$298*MIN(1,'01_Вводные'!$B$22)+IF(OR(1<=('01_Вводные'!$B$15+'01_Вводные'!$B$311),1-('01_Вводные'!$B$15+'01_Вводные'!$B$311)>60),0,INDEX('04_Продажи'!$B$15:$BI$15,1,1-('01_Вводные'!$B$15+'01_Вводные'!$B$311)))*'01_Вводные'!$B$298*MAX(0,'01_Вводные'!$B$22-1) | C8: =IF(OR(2<='01_Вводные'!$B$15,2-'01_Вводные'!$B$15>60),0,INDEX('04_Продажи'!$B$15:$BI$15,1,2-'01_Вводные'!$B$15))*'01_Вводные'!$B$298*MIN(1,'01_Вводные'!$B$22)+IF(OR(2<=('01_Вводные'!$B$15+'01_Вводные'!$B$311),2-('01_Вводные'!$B$15+'01_Вводные'!$B$311)>60),0,INDEX('04_Продажи'!$B$15:$BI$15,1,2-('01_Вводные'!$B$15+'01_Вводные'!$B$311)))*'01_Вводные'!$B$298*MAX(0,'01_Вводные'!$B$22-1) | D8: =IF(OR(3<='01_Вводные'!$B$15,3-'01_Вводные'!$B$15>60),0,INDEX('04_Продажи'!$B$15:$BI$15,1,3-'01_Вводные'!$B$15))*'01_Вводные'!$B$298*MIN(1,'01_Вводные'!$B$22)+IF(OR(3<=('01_Вводные'!$B$15+'01_Вводные'!$B$311),3-('01_Вводные'!$B$15+'01_Вводные'!$B$311)>60),0,INDEX('04_Продажи'!$B$15:$BI$15,1,3-('01_Вводные'!$B$15+'01_Вводные'!$B$311)))*'01_Вводные'!$B$298*MAX(0,'01_Вводные'!$B$22-1) | E8: =IF(OR(4<='01_Вводные'!$B$15,4-'01_Вводные'!$B$15>60),0,INDEX('04_Продажи'!$B$15:$BI$15,1,4-'01_Вводные'!$B$15))*'01_Вводные'!$B$298*MIN(1,'01_Вводные'!$B$22)+IF(OR(4<=('01_Вводные'!$B$15+'01_Вводные'!$B$311),4-('01_Вводные'!$B$15+'01_Вводные'!$B$311)>60),0,INDEX('04_Продажи'!$B$15:$BI$15,1,4-('01_Вводные'!$B$15+'01_Вводные'!$B$311)))*'01_Вводные'!$B$298*MAX(0,'01_Вводные'!$B$22-1) | F8: =IF(OR(5<='01_Вводные'!$B$15,5-'01_Вводные'!$B$15>60),0,INDEX('04_Продажи'!$B$15:$BI$15,1,5-'01_Вводные'!$B$15))*'01_Вводные'!$B$298*MIN(1,'01_Вводные'!$B$22)+IF(OR(5<=('01_Вводные'!$B$15+'01_Вводные'!$B$311),5-('01_Вводные'!$B$15+'01_Вводные'!$B$311)>60),0,INDEX('04_Продажи'!$B$15:$BI$15,1,5-('01_Вводные'!$B$15+'01_Вводные'!$B$311)))*'01_Вводные'!$B$298*MAX(0,'01_Вводные'!$B$22-1) | G8: =IF(OR(6<='01_Вводные'!$B$15,6-'01_Вводные'!$B$15>60),0,INDEX('04_Продажи'!$B$15:$BI$15,1,6-'01_Вводные'!$B$15))*'01_Вводные'!$B$298*MIN(1,'01_Вводные'!$B$22)+IF(OR(6<=('01_Вводные'!$B$15+'01_Вводные'!$B$311),6-('01_Вводные'!$B$15+'01_Вводные'!$B$311)>60),0,INDEX('04_Продажи'!$B$15:$BI$15,1,6-('01_Вводные'!$B$15+'01_Вводные'!$B$311)))*'01_Вводные'!$B$298*MAX(0,'01_Вводные'!$B$22-1) | H8: =IF(OR(7<='01_Вводные'!$B$15,7-'01_Вводные'!$B$15>60),0,INDEX('04_Продажи'!$B$15:$BI$15,1,7-'01_Вводные'!$B$15))*'01_Вводные'!$B$298*MIN(1,'01_Вводные'!$B$22)+IF(OR(7<=('01_Вводные'!$B$15+'01_Вводные'!$B$311),7-('01_Вводные'!$B$15+'01_Вводные'!$B$311)>60),0,INDEX('04_Продажи'!$B$15:$BI$15,1,7-('01_Вводные'!$B$15+'01_Вводные'!$B$311)))*'01_Вводные'!$B$298*MAX(0,'01_Вводные'!$B$22-1) | I8: =IF(OR(8<='01_Вводные'!$B$15,8-'01_Вводные'!$B$15>60),0,INDEX('04_Продажи'!$B$15:$BI$15,1,8-'01_Вводные'!$B$15))*'01_Вводные'!$B$298*MIN(1,'01_Вводные'!$B$22)+IF(OR(8<=('01_Вводные'!$B$15+'01_Вводные'!$B$311),8-('01_Вводные'!$B$15+'01_Вводные'!$B$311)>60),0,INDEX('04_Продажи'!$B$15:$BI$15,1,8-('01_Вводные'!$B$15+'01_Вводные'!$B$311)))*'01_Вводные'!$B$298*MAX(0,'01_Вводные'!$B$22-1) | J8: =IF(OR(9<='01_Вводные'!$B$15,9-'01_Вводные'!$B$15>60),0,INDEX('04_Продажи'!$B$15:$BI$15,1,9-'01_Вводные'!$B$15))*'01_Вводные'!$B$298*MIN(1,'01_Вводные'!$B$22)+IF(OR(9<=('01_Вводные'!$B$15+'01_Вводные'!$B$311),9-('01_Вводные'!$B$15+'01_Вводные'!$B$311)>60),0,INDEX('04_Продажи'!$B$15:$BI$15,1,9-('01_Вводные'!$B$15+'01_Вводные'!$B$311)))*'01_Вводные'!$B$298*MAX(0,'01_Вводные'!$B$22-1) | K8: =IF(OR(10<='01_Вводные'!$B$15,10-'01_Вводные'!$B$15>60),0,INDEX('04_Продажи'!$B$15:$BI$15,1,10-'01_Вводные'!$B$15))*'01_Вводные'!$B$298*MIN(1,'01_Вводные'!$B$22)+IF(OR(10<=('01_Вводные'!$B$15+'01_Вводные'!$B$311),10-('01_Вводные'!$B$15+'01_Вводные'!$B$311)>60),0,INDEX('04_Продажи'!$B$15:$BI$15,1,10-('01_Вводные'!$B$15+'01_Вводные'!$B$311)))*'01_Вводные'!$B$298*MAX(0,'01_Вводные'!$B$22-1) | L8: =IF(OR(11<='01_Вводные'!$B$15,11-'01_Вводные'!$B$15>60),0,INDEX('04_Продажи'!$B$15:$BI$15,1,11-'01_Вводные'!$B$15))*'01_Вводные'!$B$298*MIN(1,'01_Вводные'!$B$22)+IF(OR(11<=('01_Вводные'!$B$15+'01_Вводные'!$B$311),11-('01_Вводные'!$B$15+'01_Вводные'!$B$311)>60),0,INDEX('04_Продажи'!$B$15:$BI$15,1,11-('01_Вводные'!$B$15+'01_Вводные'!$B$311)))*'01_Вводные'!$B$298*MAX(0,'01_Вводные'!$B$22-1) | M8: =IF(OR(12<='01_Вводные'!$B$15,12-'01_Вводные'!$B$15>60),0,INDEX('04_Продажи'!$B$15:$BI$15,1,12-'01_Вводные'!$B$15))*'01_Вводные'!$B$298*MIN(1,'01_Вводные'!$B$22)+IF(OR(12<=('01_Вводные'!$B$15+'01_Вводные'!$B$311),12-('01_Вводные'!$B$15+'01_Вводные'!$B$311)>60),0,INDEX('04_Продажи'!$B$15:$BI$15,1,12-('01_Вводные'!$B$15+'01_Вводные'!$B$311)))*'01_Вводные'!$B$298*MAX(0,'01_Вводные'!$B$22-1) | N8: =IF(OR(13<='01_Вводные'!$B$15,13-'01_Вводные'!$B$15>60),0,INDEX('04_Продажи'!$B$15:$BI$15,1,13-'01_Вводные'!$B$15))*'01_Вводные'!$B$298*MIN(1,'01_Вводные'!$B$22)+IF(OR(13<=('01_Вводные'!$B$15+'01_Вводные'!$B$311),13-('01_Вводные'!$B$15+'01_Вводные'!$B$311)>60),0,INDEX('04_Продажи'!$B$15:$BI$15,1,13-('01_Вводные'!$B$15+'01_Вводные'!$B$311)))*'01_Вводные'!$B$298*MAX(0,'01_Вводные'!$B$22-1) | O8: =IF(OR(14<='01_Вводные'!$B$15,14-'01_Вводные'!$B$15>60),0,INDEX('04_Продажи'!$B$15:$BI$15,1,14-'01_Вводные'!$B$15))*'01_Вводные'!$B$298*MIN(1,'01_Вводные'!$B$22)+IF(OR(14<=('01_Вводные'!$B$15+'01_Вводные'!$B$311),14-('01_Вводные'!$B$15+'01_Вводные'!$B$311)>60),0,INDEX('04_Продажи'!$B$15:$BI$15,1,14-('01_Вводные'!$B$15+'01_Вводные'!$B$311)))*'01_Вводные'!$B$298*MAX(0,'01_Вводные'!$B$22-1) | P8: =IF(OR(15<='01_Вводные'!$B$15,15-'01_Вводные'!$B$15>60),0,INDEX('04_Продажи'!$B$15:$BI$15,1,15-'01_Вводные'!$B$15))*'01_Вводные'!$B$298*MIN(1,'01_Вводные'!$B$22)+IF(OR(15<=('01_Вводные'!$B$15+'01_Вводные'!$B$311),15-('01_Вводные'!$B$15+'01_Вводные'!$B$311)>60),0,INDEX('04_Продажи'!$B$15:$BI$15,1,15-('01_Вводные'!$B$15+'01_Вводные'!$B$311)))*'01_Вводные'!$B$298*MAX(0,'01_Вводные'!$B$22-1) | Q8: =IF(OR(16<='01_Вводные'!$B$15,16-'01_Вводные'!$B$15>60),0,INDEX('04_Продажи'!$B$15:$BI$15,1,16-'01_Вводные'!$B$15))*'01_Вводные'!$B$298*MIN(1,'01_Вводные'!$B$22)+IF(OR(16<=('01_Вводные'!$B$15+'01_Вводные'!$B$311),16-('01_Вводные'!$B$15+'01_Вводные'!$B$311)>60),0,INDEX('04_Продажи'!$B$15:$BI$15,1,16-('01_Вводные'!$B$15+'01_Вводные'!$B$311)))*'01_Вводные'!$B$298*MAX(0,'01_Вводные'!$B$22-1) | R8: =IF(OR(17<='01_Вводные'!$B$15,17-'01_Вводные'!$B$15>60),0,INDEX('04_Продажи'!$B$15:$BI$15,1,17-'01_Вводные'!$B$15))*'01_Вводные'!$B$298*MIN(1,'01_Вводные'!$B$22)+IF(OR(17<=('01_Вводные'!$B$15+'01_Вводные'!$B$311),17-('01_Вводные'!$B$15+'01_Вводные'!$B$311)>60),0,INDEX('04_Продажи'!$B$15:$BI$15,1,17-('01_Вводные'!$B$15+'01_Вводные'!$B$311)))*'01_Вводные'!$B$298*MAX(0,'01_Вводные'!$B$22-1) | S8: =IF(OR(18<='01_Вводные'!$B$15,18-'01_Вводные'!$B$15>60),0,INDEX('04_Продажи'!$B$15:$BI$15,1,18-'01_Вводные'!$B$15))*'01_Вводные'!$B$298*MIN(1,'01_Вводные'!$B$22)+IF(OR(18<=('01_Вводные'!$B$15+'01_Вводные'!$B$311),18-('01_Вводные'!$B$15+'01_Вводные'!$B$311)>60),0,INDEX('04_Продажи'!$B$15:$BI$15,1,18-('01_Вводные'!$B$15+'01_Вводные'!$B$311)))*'01_Вводные'!$B$298*MAX(0,'01_Вводные'!$B$22-1) | T8: =IF(OR(19<='01_Вводные'!$B$15,19-'01_Вводные'!$B$15>60),0,INDEX('04_Продажи'!$B$15:$BI$15,1,19-'01_Вводные'!$B$15))*'01_Вводные'!$B$298*MIN(1,'01_Вводные'!$B$22)+IF(OR(19<=('01_Вводные'!$B$15+'01_Вводные'!$B$311),19-('01_Вводные'!$B$15+'01_Вводные'!$B$311)>60),0,INDEX('04_Продажи'!$B$15:$BI$15,1,19-('01_Вводные'!$B$15+'01_Вводные'!$B$311)))*'01_Вводные'!$B$298*MAX(0,'01_Вводные'!$B$22-1) | U8: =IF(OR(20<='01_Вводные'!$B$15,20-'01_Вводные'!$B$15>60),0,INDEX('04_Продажи'!$B$15:$BI$15,1,20-'01_Вводные'!$B$15))*'01_Вводные'!$B$298*MIN(1,'01_Вводные'!$B$22)+IF(OR(20<=('01_Вводные'!$B$15+'01_Вводные'!$B$311),20-('01_Вводные'!$B$15+'01_Вводные'!$B$311)>60),0,INDEX('04_Продажи'!$B$15:$BI$15,1,20-('01_Вводные'!$B$15+'01_Вводные'!$B$311)))*'01_Вводные'!$B$298*MAX(0,'01_Вводные'!$B$22-1) | V8: =IF(OR(21<='01_Вводные'!$B$15,21-'01_Вводные'!$B$15>60),0,INDEX('04_Продажи'!$B$15:$BI$15,1,21-'01_Вводные'!$B$15))*'01_Вводные'!$B$298*MIN(1,'01_Вводные'!$B$22)+IF(OR(21<=('01_Вводные'!$B$15+'01_Вводные'!$B$311),21-('01_Вводные'!$B$15+'01_Вводные'!$B$311)>60),0,INDEX('04_Продажи'!$B$15:$BI$15,1,21-('01_Вводные'!$B$15+'01_Вводные'!$B$311)))*'01_Вводные'!$B$298*MAX(0,'01_Вводные'!$B$22-1) | W8: =IF(OR(22<='01_Вводные'!$B$15,22-'01_Вводные'!$B$15>60),0,INDEX('04_Продажи'!$B$15:$BI$15,1,22-'01_Вводные'!$B$15))*'01_Вводные'!$B$298*MIN(1,'01_Вводные'!$B$22)+IF(OR(22<=('01_Вводные'!$B$15+'01_Вводные'!$B$311),22-('01_Вводные'!$B$15+'01_Вводные'!$B$311)>60),0,INDEX('04_Продажи'!$B$15:$BI$15,1,22-('01_Вводные'!$B$15+'01_Вводные'!$B$311)))*'01_Вводные'!$B$298*MAX(0,'01_Вводные'!$B$22-1) | X8: =IF(OR(23<='01_Вводные'!$B$15,23-'01_Вводные'!$B$15>60),0,INDEX('04_Продажи'!$B$15:$BI$15,1,23-'01_Вводные'!$B$15))*'01_Вводные'!$B$298*MIN(1,'01_Вводные'!$B$22)+IF(OR(23<=('01_Вводные'!$B$15+'01_Вводные'!$B$311),23-('01_Вводные'!$B$15+'01_Вводные'!$B$311)>60),0,INDEX('04_Продажи'!$B$15:$BI$15,1,23-('01_Вводные'!$B$15+'01_Вводные'!$B$311)))*'01_Вводные'!$B$298*MAX(0,'01_Вводные'!$B$22-1) | Y8: =IF(OR(24<='01_Вводные'!$B$15,24-'01_Вводные'!$B$15>60),0,INDEX('04_Продажи'!$B$15:$BI$15,1,24-'01_Вводные'!$B$15))*'01_Вводные'!$B$298*MIN(1,'01_Вводные'!$B$22)+IF(OR(24<=('01_Вводные'!$B$15+'01_Вводные'!$B$311),24-('01_Вводные'!$B$15+'01_Вводные'!$B$311)>60),0,INDEX('04_Продажи'!$B$15:$BI$15,1,24-('01_Вводные'!$B$15+'01_Вводные'!$B$311)))*'01_Вводные'!$B$298*MAX(0,'01_Вводные'!$B$22-1) | Z8: =IF(OR(25<='01_Вводные'!$B$15,25-'01_Вводные'!$B$15>60),0,INDEX('04_Продажи'!$B$15:$BI$15,1,25-'01_Вводные'!$B$15))*'01_Вводные'!$B$298*MIN(1,'01_Вводные'!$B$22)+IF(OR(25<=('01_Вводные'!$B$15+'01_Вводные'!$B$311),25-('01_Вводные'!$B$15+'01_Вводные'!$B$311)>60),0,INDEX('04_Продажи'!$B$15:$BI$15,1,25-('01_Вводные'!$B$15+'01_Вводные'!$B$311)))*'01_Вводные'!$B$298*MAX(0,'01_Вводные'!$B$22-1) | AA8: =IF(OR(26<='01_Вводные'!$B$15,26-'01_Вводные'!$B$15>60),0,INDEX('04_Продажи'!$B$15:$BI$15,1,26-'01_Вводные'!$B$15))*'01_Вводные'!$B$298*MIN(1,'01_Вводные'!$B$22)+IF(OR(26<=('01_Вводные'!$B$15+'01_Вводные'!$B$311),26-('01_Вводные'!$B$15+'01_Вводные'!$B$311)>60),0,INDEX('04_Продажи'!$B$15:$BI$15,1,26-('01_Вводные'!$B$15+'01_Вводные'!$B$311)))*'01_Вводные'!$B$298*MAX(0,'01_Вводные'!$B$22-1) | AB8: =IF(OR(27<='01_Вводные'!$B$15,27-'01_Вводные'!$B$15>60),0,INDEX('04_Продажи'!$B$15:$BI$15,1,27-'01_Вводные'!$B$15))*'01_Вводные'!$B$298*MIN(1,'01_Вводные'!$B$22)+IF(OR(27<=('01_Вводные'!$B$15+'01_Вводные'!$B$311),27-('01_Вводные'!$B$15+'01_Вводные'!$B$311)>60),0,INDEX('04_Продажи'!$B$15:$BI$15,1,27-('01_Вводные'!$B$15+'01_Вводные'!$B$311)))*'01_Вводные'!$B$298*MAX(0,'01_Вводные'!$B$22-1) | AC8: =IF(OR(28<='01_Вводные'!$B$15,28-'01_Вводные'!$B$15>60),0,INDEX('04_Продажи'!$B$15:$BI$15,1,28-'01_Вводные'!$B$15))*'01_Вводные'!$B$298*MIN(1,'01_Вводные'!$B$22)+IF(OR(28<=('01_Вводные'!$B$15+'01_Вводные'!$B$311),28-('01_Вводные'!$B$15+'01_Вводные'!$B$311)>60),0,INDEX('04_Продажи'!$B$15:$BI$15,1,28-('01_Вводные'!$B$15+'01_Вводные'!$B$311)))*'01_Вводные'!$B$298*MAX(0,'01_Вводные'!$B$22-1) | AD8: =IF(OR(29<='01_Вводные'!$B$15,29-'01_Вводные'!$B$15>60),0,INDEX('04_Продажи'!$B$15:$BI$15,1,29-'01_Вводные'!$B$15))*'01_Вводные'!$B$298*MIN(1,'01_Вводные'!$B$22)+IF(OR(29<=('01_Вводные'!$B$15+'01_Вводные'!$B$311),29-('01_Вводные'!$B$15+'01_Вводные'!$B$311)>60),0,INDEX('04_Продажи'!$B$15:$BI$15,1,29-('01_Вводные'!$B$15+'01_Вводные'!$B$311)))*'01_Вводные'!$B$298*MAX(0,'01_Вводные'!$B$22-1) | AE8: =IF(OR(30<='01_Вводные'!$B$15,30-'01_Вводные'!$B$15>60),0,INDEX('04_Продажи'!$B$15:$BI$15,1,30-'01_Вводные'!$B$15))*'01_Вводные'!$B$298*MIN(1,'01_Вводные'!$B$22)+IF(OR(30<=('01_Вводные'!$B$15+'01_Вводные'!$B$311),30-('01_Вводные'!$B$15+'01_Вводные'!$B$311)>60),0,INDEX('04_Продажи'!$B$15:$BI$15,1,30-('01_Вводные'!$B$15+'01_Вводные'!$B$311)))*'01_Вводные'!$B$298*MAX(0,'01_Вводные'!$B$22-1) | AF8: =IF(OR(31<='01_Вводные'!$B$15,31-'01_Вводные'!$B$15>60),0,INDEX('04_Продажи'!$B$15:$BI$15,1,31-'01_Вводные'!$B$15))*'01_Вводные'!$B$298*MIN(1,'01_Вводные'!$B$22)+IF(OR(31<=('01_Вводные'!$B$15+'01_Вводные'!$B$311),31-('01_Вводные'!$B$15+'01_Вводные'!$B$311)>60),0,INDEX('04_Продажи'!$B$15:$BI$15,1,31-('01_Вводные'!$B$15+'01_Вводные'!$B$311)))*'01_Вводные'!$B$298*MAX(0,'01_Вводные'!$B$22-1) | AG8: =IF(OR(32<='01_Вводные'!$B$15,32-'01_Вводные'!$B$15>60),0,INDEX('04_Продажи'!$B$15:$BI$15,1,32-'01_Вводные'!$B$15))*'01_Вводные'!$B$298*MIN(1,'01_Вводные'!$B$22)+IF(OR(32<=('01_Вводные'!$B$15+'01_Вводные'!$B$311),32-('01_Вводные'!$B$15+'01_Вводные'!$B$311)>60),0,INDEX('04_Продажи'!$B$15:$BI$15,1,32-('01_Вводные'!$B$15+'01_Вводные'!$B$311)))*'01_Вводные'!$B$298*MAX(0,'01_Вводные'!$B$22-1) | AH8: =IF(OR(33<='01_Вводные'!$B$15,33-'01_Вводные'!$B$15>60),0,INDEX('04_Продажи'!$B$15:$BI$15,1,33-'01_Вводные'!$B$15))*'01_Вводные'!$B$298*MIN(1,'01_Вводные'!$B$22)+IF(OR(33<=('01_Вводные'!$B$15+'01_Вводные'!$B$311),33-('01_Вводные'!$B$15+'01_Вводные'!$B$311)>60),0,INDEX('04_Продажи'!$B$15:$BI$15,1,33-('01_Вводные'!$B$15+'01_Вводные'!$B$311)))*'01_Вводные'!$B$298*MAX(0,'01_Вводные'!$B$22-1) | AI8: =IF(OR(34<='01_Вводные'!$B$15,34-'01_Вводные'!$B$15>60),0,INDEX('04_Продажи'!$B$15:$BI$15,1,34-'01_Вводные'!$B$15))*'01_Вводные'!$B$298*MIN(1,'01_Вводные'!$B$22)+IF(OR(34<=('01_Вводные'!$B$15+'01_Вводные'!$B$311),34-('01_Вводные'!$B$15+'01_Вводные'!$B$311)>60),0,INDEX('04_Продажи'!$B$15:$BI$15,1,34-('01_Вводные'!$B$15+'01_Вводные'!$B$311)))*'01_Вводные'!$B$298*MAX(0,'01_Вводные'!$B$22-1) | AJ8: =IF(OR(35<='01_Вводные'!$B$15,35-'01_Вводные'!$B$15>60),0,INDEX('04_Продажи'!$B$15:$BI$15,1,35-'01_Вводные'!$B$15))*'01_Вводные'!$B$298*MIN(1,'01_Вводные'!$B$22)+IF(OR(35<=('01_Вводные'!$B$15+'01_Вводные'!$B$311),35-('01_Вводные'!$B$15+'01_Вводные'!$B$311)>60),0,INDEX('04_Продажи'!$B$15:$BI$15,1,35-('01_Вводные'!$B$15+'01_Вводные'!$B$311)))*'01_Вводные'!$B$298*MAX(0,'01_Вводные'!$B$22-1) | AK8: =IF(OR(36<='01_Вводные'!$B$15,36-'01_Вводные'!$B$15>60),0,INDEX('04_Продажи'!$B$15:$BI$15,1,36-'01_Вводные'!$B$15))*'01_Вводные'!$B$298*MIN(1,'01_Вводные'!$B$22)+IF(OR(36<=('01_Вводные'!$B$15+'01_Вводные'!$B$311),36-('01_Вводные'!$B$15+'01_Вводные'!$B$311)>60),0,INDEX('04_Продажи'!$B$15:$BI$15,1,36-('01_Вводные'!$B$15+'01_Вводные'!$B$311)))*'01_Вводные'!$B$298*MAX(0,'01_Вводные'!$B$22-1) | AL8: =IF(OR(37<='01_Вводные'!$B$15,37-'01_Вводные'!$B$15>60),0,INDEX('04_Продажи'!$B$15:$BI$15,1,37-'01_Вводные'!$B$15))*'01_Вводные'!$B$298*MIN(1,'01_Вводные'!$B$22)+IF(OR(37<=('01_Вводные'!$B$15+'01_Вводные'!$B$311),37-('01_Вводные'!$B$15+'01_Вводные'!$B$311)>60),0,INDEX('04_Продажи'!$B$15:$BI$15,1,37-('01_Вводные'!$B$15+'01_Вводные'!$B$311)))*'01_Вводные'!$B$298*MAX(0,'01_Вводные'!$B$22-1) | AM8: =IF(OR(38<='01_Вводные'!$B$15,38-'01_Вводные'!$B$15>60),0,INDEX('04_Продажи'!$B$15:$BI$15,1,38-'01_Вводные'!$B$15))*'01_Вводные'!$B$298*MIN(1,'01_Вводные'!$B$22)+IF(OR(38<=('01_Вводные'!$B$15+'01_Вводные'!$B$311),38-('01_Вводные'!$B$15+'01_Вводные'!$B$311)>60),0,INDEX('04_Продажи'!$B$15:$BI$15,1,38-('01_Вводные'!$B$15+'01_Вводные'!$B$311)))*'01_Вводные'!$B$298*MAX(0,'01_Вводные'!$B$22-1) | AN8: =IF(OR(39<='01_Вводные'!$B$15,39-'01_Вводные'!$B$15>60),0,INDEX('04_Продажи'!$B$15:$BI$15,1,39-'01_Вводные'!$B$15))*'01_Вводные'!$B$298*MIN(1,'01_Вводные'!$B$22)+IF(OR(39<=('01_Вводные'!$B$15+'01_Вводные'!$B$311),39-('01_Вводные'!$B$15+'01_Вводные'!$B$311)>60),0,INDEX('04_Продажи'!$B$15:$BI$15,1,39-('01_Вводные'!$B$15+'01_Вводные'!$B$311)))*'01_Вводные'!$B$298*MAX(0,'01_Вводные'!$B$22-1) | AO8: =IF(OR(40<='01_Вводные'!$B$15,40-'01_Вводные'!$B$15>60),0,INDEX('04_Продажи'!$B$15:$BI$15,1,40-'01_Вводные'!$B$15))*'01_Вводные'!$B$298*MIN(1,'01_Вводные'!$B$22)+IF(OR(40<=('01_Вводные'!$B$15+'01_Вводные'!$B$311),40-('01_Вводные'!$B$15+'01_Вводные'!$B$311)>60),0,INDEX('04_Продажи'!$B$15:$BI$15,1,40-('01_Вводные'!$B$15+'01_Вводные'!$B$311)))*'01_Вводные'!$B$298*MAX(0,'01_Вводные'!$B$22-1) | AP8: =IF(OR(41<='01_Вводные'!$B$15,41-'01_Вводные'!$B$15>60),0,INDEX('04_Продажи'!$B$15:$BI$15,1,41-'01_Вводные'!$B$15))*'01_Вводные'!$B$298*MIN(1,'01_Вводные'!$B$22)+IF(OR(41<=('01_Вводные'!$B$15+'01_Вводные'!$B$311),41-('01_Вводные'!$B$15+'01_Вводные'!$B$311)>60),0,INDEX('04_Продажи'!$B$15:$BI$15,1,41-('01_Вводные'!$B$15+'01_Вводные'!$B$311)))*'01_Вводные'!$B$298*MAX(0,'01_Вводные'!$B$22-1) | AQ8: =IF(OR(42<='01_Вводные'!$B$15,42-'01_Вводные'!$B$15>60),0,INDEX('04_Продажи'!$B$15:$BI$15,1,42-'01_Вводные'!$B$15))*'01_Вводные'!$B$298*MIN(1,'01_Вводные'!$B$22)+IF(OR(42<=('01_Вводные'!$B$15+'01_Вводные'!$B$311),42-('01_Вводные'!$B$15+'01_Вводные'!$B$311)>60),0,INDEX('04_Продажи'!$B$15:$BI$15,1,42-('01_Вводные'!$B$15+'01_Вводные'!$B$311)))*'01_Вводные'!$B$298*MAX(0,'01_Вводные'!$B$22-1) | AR8: =IF(OR(43<='01_Вводные'!$B$15,43-'01_Вводные'!$B$15>60),0,INDEX('04_Продажи'!$B$15:$BI$15,1,43-'01_Вводные'!$B$15))*'01_Вводные'!$B$298*MIN(1,'01_Вводные'!$B$22)+IF(OR(43<=('01_Вводные'!$B$15+'01_Вводные'!$B$311),43-('01_Вводные'!$B$15+'01_Вводные'!$B$311)>60),0,INDEX('04_Продажи'!$B$15:$BI$15,1,43-('01_Вводные'!$B$15+'01_Вводные'!$B$311)))*'01_Вводные'!$B$298*MAX(0,'01_Вводные'!$B$22-1) | AS8: =IF(OR(44<='01_Вводные'!$B$15,44-'01_Вводные'!$B$15>60),0,INDEX('04_Продажи'!$B$15:$BI$15,1,44-'01_Вводные'!$B$15))*'01_Вводные'!$B$298*MIN(1,'01_Вводные'!$B$22)+IF(OR(44<=('01_Вводные'!$B$15+'01_Вводные'!$B$311),44-('01_Вводные'!$B$15+'01_Вводные'!$B$311)>60),0,INDEX('04_Продажи'!$B$15:$BI$15,1,44-('01_Вводные'!$B$15+'01_Вводные'!$B$311)))*'01_Вводные'!$B$298*MAX(0,'01_Вводные'!$B$22-1) | AT8: =IF(OR(45<='01_Вводные'!$B$15,45-'01_Вводные'!$B$15>60),0,INDEX('04_Продажи'!$B$15:$BI$15,1,45-'01_Вводные'!$B$15))*'01_Вводные'!$B$298*MIN(1,'01_Вводные'!$B$22)+IF(OR(45<=('01_Вводные'!$B$15+'01_Вводные'!$B$311),45-('01_Вводные'!$B$15+'01_Вводные'!$B$311)>60),0,INDEX('04_Продажи'!$B$15:$BI$15,1,45-('01_Вводные'!$B$15+'01_Вводные'!$B$311)))*'01_Вводные'!$B$298*MAX(0,'01_Вводные'!$B$22-1) | AU8: =IF(OR(46<='01_Вводные'!$B$15,46-'01_Вводные'!$B$15>60),0,INDEX('04_Продажи'!$B$15:$BI$15,1,46-'01_Вводные'!$B$15))*'01_Вводные'!$B$298*MIN(1,'01_Вводные'!$B$22)+IF(OR(46<=('01_Вводные'!$B$15+'01_Вводные'!$B$311),46-('01_Вводные'!$B$15+'01_Вводные'!$B$311)>60),0,INDEX('04_Продажи'!$B$15:$BI$15,1,46-('01_Вводные'!$B$15+'01_Вводные'!$B$311)))*'01_Вводные'!$B$298*MAX(0,'01_Вводные'!$B$22-1) | AV8: =IF(OR(47<='01_Вводные'!$B$15,47-'01_Вводные'!$B$15>60),0,INDEX('04_Продажи'!$B$15:$BI$15,1,47-'01_Вводные'!$B$15))*'01_Вводные'!$B$298*MIN(1,'01_Вводные'!$B$22)+IF(OR(47<=('01_Вводные'!$B$15+'01_Вводные'!$B$311),47-('01_Вводные'!$B$15+'01_Вводные'!$B$311)>60),0,INDEX('04_Продажи'!$B$15:$BI$15,1,47-('01_Вводные'!$B$15+'01_Вводные'!$B$311)))*'01_Вводные'!$B$298*MAX(0,'01_Вводные'!$B$22-1) | AW8: =IF(OR(48<='01_Вводные'!$B$15,48-'01_Вводные'!$B$15>60),0,INDEX('04_Продажи'!$B$15:$BI$15,1,48-'01_Вводные'!$B$15))*'01_Вводные'!$B$298*MIN(1,'01_Вводные'!$B$22)+IF(OR(48<=('01_Вводные'!$B$15+'01_Вводные'!$B$311),48-('01_Вводные'!$B$15+'01_Вводные'!$B$311)>60),0,INDEX('04_Продажи'!$B$15:$BI$15,1,48-('01_Вводные'!$B$15+'01_Вводные'!$B$311)))*'01_Вводные'!$B$298*MAX(0,'01_Вводные'!$B$22-1) | AX8: =IF(OR(49<='01_Вводные'!$B$15,49-'01_Вводные'!$B$15>60),0,INDEX('04_Продажи'!$B$15:$BI$15,1,49-'01_Вводные'!$B$15))*'01_Вводные'!$B$298*MIN(1,'01_Вводные'!$B$22)+IF(OR(49<=('01_Вводные'!$B$15+'01_Вводные'!$B$311),49-('01_Вводные'!$B$15+'01_Вводные'!$B$311)>60),0,INDEX('04_Продажи'!$B$15:$BI$15,1,49-('01_Вводные'!$B$15+'01_Вводные'!$B$311)))*'01_Вводные'!$B$298*MAX(0,'01_Вводные'!$B$22-1) | AY8: =IF(OR(50<='01_Вводные'!$B$15,50-'01_Вводные'!$B$15>60),0,INDEX('04_Продажи'!$B$15:$BI$15,1,50-'01_Вводные'!$B$15))*'01_Вводные'!$B$298*MIN(1,'01_Вводные'!$B$22)+IF(OR(50<=('01_Вводные'!$B$15+'01_Вводные'!$B$311),50-('01_Вводные'!$B$15+'01_Вводные'!$B$311)>60),0,INDEX('04_Продажи'!$B$15:$BI$15,1,50-('01_Вводные'!$B$15+'01_Вводные'!$B$311)))*'01_Вводные'!$B$298*MAX(0,'01_Вводные'!$B$22-1) | AZ8: =IF(OR(51<='01_Вводные'!$B$15,51-'01_Вводные'!$B$15>60),0,INDEX('04_Продажи'!$B$15:$BI$15,1,51-'01_Вводные'!$B$15))*'01_Вводные'!$B$298*MIN(1,'01_Вводные'!$B$22)+IF(OR(51<=('01_Вводные'!$B$15+'01_Вводные'!$B$311),51-('01_Вводные'!$B$15+'01_Вводные'!$B$311)>60),0,INDEX('04_Продажи'!$B$15:$BI$15,1,51-('01_Вводные'!$B$15+'01_Вводные'!$B$311)))*'01_Вводные'!$B$298*MAX(0,'01_Вводные'!$B$22-1) | BA8: =IF(OR(52<='01_Вводные'!$B$15,52-'01_Вводные'!$B$15>60),0,INDEX('04_Продажи'!$B$15:$BI$15,1,52-'01_Вводные'!$B$15))*'01_Вводные'!$B$298*MIN(1,'01_Вводные'!$B$22)+IF(OR(52<=('01_Вводные'!$B$15+'01_Вводные'!$B$311),52-('01_Вводные'!$B$15+'01_Вводные'!$B$311)>60),0,INDEX('04_Продажи'!$B$15:$BI$15,1,52-('01_Вводные'!$B$15+'01_Вводные'!$B$311)))*'01_Вводные'!$B$298*MAX(0,'01_Вводные'!$B$22-1) | BB8: =IF(OR(53<='01_Вводные'!$B$15,53-'01_Вводные'!$B$15>60),0,INDEX('04_Продажи'!$B$15:$BI$15,1,53-'01_Вводные'!$B$15))*'01_Вводные'!$B$298*MIN(1,'01_Вводные'!$B$22)+IF(OR(53<=('01_Вводные'!$B$15+'01_Вводные'!$B$311),53-('01_Вводные'!$B$15+'01_Вводные'!$B$311)>60),0,INDEX('04_Продажи'!$B$15:$BI$15,1,53-('01_Вводные'!$B$15+'01_Вводные'!$B$311)))*'01_Вводные'!$B$298*MAX(0,'01_Вводные'!$B$22-1) | BC8: =IF(OR(54<='01_Вводные'!$B$15,54-'01_Вводные'!$B$15>60),0,INDEX('04_Продажи'!$B$15:$BI$15,1,54-'01_Вводные'!$B$15))*'01_Вводные'!$B$298*MIN(1,'01_Вводные'!$B$22)+IF(OR(54<=('01_Вводные'!$B$15+'01_Вводные'!$B$311),54-('01_Вводные'!$B$15+'01_Вводные'!$B$311)>60),0,INDEX('04_Продажи'!$B$15:$BI$15,1,54-('01_Вводные'!$B$15+'01_Вводные'!$B$311)))*'01_Вводные'!$B$298*MAX(0,'01_Вводные'!$B$22-1) | BD8: =IF(OR(55<='01_Вводные'!$B$15,55-'01_Вводные'!$B$15>60),0,INDEX('04_Продажи'!$B$15:$BI$15,1,55-'01_Вводные'!$B$15))*'01_Вводные'!$B$298*MIN(1,'01_Вводные'!$B$22)+IF(OR(55<=('01_Вводные'!$B$15+'01_Вводные'!$B$311),55-('01_Вводные'!$B$15+'01_Вводные'!$B$311)>60),0,INDEX('04_Продажи'!$B$15:$BI$15,1,55-('01_Вводные'!$B$15+'01_Вводные'!$B$311)))*'01_Вводные'!$B$298*MAX(0,'01_Вводные'!$B$22-1) | BE8: =IF(OR(56<='01_Вводные'!$B$15,56-'01_Вводные'!$B$15>60),0,INDEX('04_Продажи'!$B$15:$BI$15,1,56-'01_Вводные'!$B$15))*'01_Вводные'!$B$298*MIN(1,'01_Вводные'!$B$22)+IF(OR(56<=('01_Вводные'!$B$15+'01_Вводные'!$B$311),56-('01_Вводные'!$B$15+'01_Вводные'!$B$311)>60),0,INDEX('04_Продажи'!$B$15:$BI$15,1,56-('01_Вводные'!$B$15+'01_Вводные'!$B$311)))*'01_Вводные'!$B$298*MAX(0,'01_Вводные'!$B$22-1) | BF8: =IF(OR(57<='01_Вводные'!$B$15,57-'01_Вводные'!$B$15>60),0,INDEX('04_Продажи'!$B$15:$BI$15,1,57-'01_Вводные'!$B$15))*'01_Вводные'!$B$298*MIN(1,'01_Вводные'!$B$22)+IF(OR(57<=('01_Вводные'!$B$15+'01_Вводные'!$B$311),57-('01_Вводные'!$B$15+'01_Вводные'!$B$311)>60),0,INDEX('04_Продажи'!$B$15:$BI$15,1,57-('01_Вводные'!$B$15+'01_Вводные'!$B$311)))*'01_Вводные'!$B$298*MAX(0,'01_Вводные'!$B$22-1) | BG8: =IF(OR(58<='01_Вводные'!$B$15,58-'01_Вводные'!$B$15>60),0,INDEX('04_Продажи'!$B$15:$BI$15,1,58-'01_Вводные'!$B$15))*'01_Вводные'!$B$298*MIN(1,'01_Вводные'!$B$22)+IF(OR(58<=('01_Вводные'!$B$15+'01_Вводные'!$B$311),58-('01_Вводные'!$B$15+'01_Вводные'!$B$311)>60),0,INDEX('04_Продажи'!$B$15:$BI$15,1,58-('01_Вводные'!$B$15+'01_Вводные'!$B$311)))*'01_Вводные'!$B$298*MAX(0,'01_Вводные'!$B$22-1) | BH8: =IF(OR(59<='01_Вводные'!$B$15,59-'01_Вводные'!$B$15>60),0,INDEX('04_Продажи'!$B$15:$BI$15,1,59-'01_Вводные'!$B$15))*'01_Вводные'!$B$298*MIN(1,'01_Вводные'!$B$22)+IF(OR(59<=('01_Вводные'!$B$15+'01_Вводные'!$B$311),59-('01_Вводные'!$B$15+'01_Вводные'!$B$311)>60),0,INDEX('04_Продажи'!$B$15:$BI$15,1,59-('01_Вводные'!$B$15+'01_Вводные'!$B$311)))*'01_Вводные'!$B$298*MAX(0,'01_Вводные'!$B$22-1) | BI8: =IF(OR(60<='01_Вводные'!$B$15,60-'01_Вводные'!$B$15>60),0,INDEX('04_Продажи'!$B$15:$BI$15,1,60-'01_Вводные'!$B$15))*'01_Вводные'!$B$298*MIN(1,'01_Вводные'!$B$22)+IF(OR(60<=('01_Вводные'!$B$15+'01_Вводные'!$B$311),60-('01_Вводные'!$B$15+'01_Вводные'!$B$311)>60),0,INDEX('04_Продажи'!$B$15:$BI$15,1,60-('01_Вводные'!$B$15+'01_Вводные'!$B$311)))*'01_Вводные'!$B$298*MAX(0,'01_Вводные'!$B$22-1) | BJ8: =IF(OR(61<='01_Вводные'!$B$15,61-'01_Вводные'!$B$15>60),0,INDEX('04_Продажи'!$B$15:$BI$15,1,61-'01_Вводные'!$B$15))*'01_Вводные'!$B$298*MIN(1,'01_Вводные'!$B$22)+IF(OR(61<=('01_Вводные'!$B$15+'01_Вводные'!$B$311),61-('01_Вводные'!$B$15+'01_Вводные'!$B$311)>60),0,INDEX('04_Продажи'!$B$15:$BI$15,1,61-('01_Вводные'!$B$15+'01_Вводные'!$B$311)))*'01_Вводные'!$B$298*MAX(0,'01_Вводные'!$B$22-1) | BK8: =IF(OR(62<='01_Вводные'!$B$15,62-'01_Вводные'!$B$15>60),0,INDEX('04_Продажи'!$B$15:$BI$15,1,62-'01_Вводные'!$B$15))*'01_Вводные'!$B$298*MIN(1,'01_Вводные'!$B$22)+IF(OR(62<=('01_Вводные'!$B$15+'01_Вводные'!$B$311),62-('01_Вводные'!$B$15+'01_Вводные'!$B$311)>60),0,INDEX('04_Продажи'!$B$15:$BI$15,1,62-('01_Вводные'!$B$15+'01_Вводные'!$B$311)))*'01_Вводные'!$B$298*MAX(0,'01_Вводные'!$B$22-1) | BL8: =IF(OR(63<='01_Вводные'!$B$15,63-'01_Вводные'!$B$15>60),0,INDEX('04_Продажи'!$B$15:$BI$15,1,63-'01_Вводные'!$B$15))*'01_Вводные'!$B$298*MIN(1,'01_Вводные'!$B$22)+IF(OR(63<=('01_Вводные'!$B$15+'01_Вводные'!$B$311),63-('01_Вводные'!$B$15+'01_Вводные'!$B$311)>60),0,INDEX('04_Продажи'!$B$15:$BI$15,1,63-('01_Вводные'!$B$15+'01_Вводные'!$B$311)))*'01_Вводные'!$B$298*MAX(0,'01_Вводные'!$B$22-1) | BM8: =IF(OR(64<='01_Вводные'!$B$15,64-'01_Вводные'!$B$15>60),0,INDEX('04_Продажи'!$B$15:$BI$15,1,64-'01_Вводные'!$B$15))*'01_Вводные'!$B$298*MIN(1,'01_Вводные'!$B$22)+IF(OR(64<=('01_Вводные'!$B$15+'01_Вводные'!$B$311),64-('01_Вводные'!$B$15+'01_Вводные'!$B$311)>60),0,INDEX('04_Продажи'!$B$15:$BI$15,1,64-('01_Вводные'!$B$15+'01_Вводные'!$B$311)))*'01_Вводные'!$B$298*MAX(0,'01_Вводные'!$B$22-1) | BN8: =IF(OR(65<='01_Вводные'!$B$15,65-'01_Вводные'!$B$15>60),0,INDEX('04_Продажи'!$B$15:$BI$15,1,65-'01_Вводные'!$B$15))*'01_Вводные'!$B$298*MIN(1,'01_Вводные'!$B$22)+IF(OR(65<=('01_Вводные'!$B$15+'01_Вводные'!$B$311),65-('01_Вводные'!$B$15+'01_Вводные'!$B$311)>60),0,INDEX('04_Продажи'!$B$15:$BI$15,1,65-('01_Вводные'!$B$15+'01_Вводные'!$B$311)))*'01_Вводные'!$B$298*MAX(0,'01_Вводные'!$B$22-1) | BO8: =IF(OR(66<='01_Вводные'!$B$15,66-'01_Вводные'!$B$15>60),0,INDEX('04_Продажи'!$B$15:$BI$15,1,66-'01_Вводные'!$B$15))*'01_Вводные'!$B$298*MIN(1,'01_Вводные'!$B$22)+IF(OR(66<=('01_Вводные'!$B$15+'01_Вводные'!$B$311),66-('01_Вводные'!$B$15+'01_Вводные'!$B$311)>60),0,INDEX('04_Продажи'!$B$15:$BI$15,1,66-('01_Вводные'!$B$15+'01_Вводные'!$B$311)))*'01_Вводные'!$B$298*MAX(0,'01_Вводные'!$B$22-1)
A9: Новые юрлица | B9: =B7*'01_Вводные'!$B$16 | C9: =C7*'01_Вводные'!$B$16 | D9: =D7*'01_Вводные'!$B$16 | E9: =E7*'01_Вводные'!$B$16 | F9: =F7*'01_Вводные'!$B$16 | G9: =G7*'01_Вводные'!$B$16 | H9: =H7*'01_Вводные'!$B$16 | I9: =I7*'01_Вводные'!$B$16 | ... BO9: =BO7*'01_Вводные'!$B$16
A10: Активные юрлица | B10: ='01_Вводные'!$B$10*'01_Вводные'!$B$14+B9 | C10: =B10*'01_Вводные'!$B$14+C9 | D10: =C10*'01_Вводные'!$B$14+D9 | E10: =D10*'01_Вводные'!$B$14+E9 | F10: =E10*'01_Вводные'!$B$14+F9 | G10: =F10*'01_Вводные'!$B$14+G9 | H10: =G10*'01_Вводные'!$B$14+H9 | I10: =H10*'01_Вводные'!$B$14+I9 | J10: =I10*'01_Вводные'!$B$14+J9 | ... BO10: =BN10*'01_Вводные'!$B$14+BO9
A11: Действующая сеть — школы | B11: ='01_Вводные'!$B$9*'01_Вводные'!$B$14 | C11: =B11*'01_Вводные'!$B$14 | D11: =C11*'01_Вводные'!$B$14 | E11: =D11*'01_Вводные'!$B$14 | F11: =E11*'01_Вводные'!$B$14 | G11: =F11*'01_Вводные'!$B$14 | H11: =G11*'01_Вводные'!$B$14 | I11: =H11*'01_Вводные'!$B$14 | J11: =I11*'01_Вводные'!$B$14 | ... BO11: =BN11*'01_Вводные'!$B$14
A13: Новые школы — 1–12 мес. | B13: =SUM(B53:B64) | C13: =SUM(C53:C64) | D13: =SUM(D53:D64) | E13: =SUM(E53:E64) | F13: =SUM(F53:F64) | G13: =SUM(G53:G64) | H13: =SUM(H53:H64) | I13: =SUM(I53:I64) | ... BO13: =SUM(BO53:BO64)
A14: Новые школы — 13–24 мес. | B14: =SUM(B65:B76) | C14: =SUM(C65:C76) | D14: =SUM(D65:D76) | E14: =SUM(E65:E76) | F14: =SUM(F65:F76) | G14: =SUM(G65:G76) | H14: =SUM(H65:H76) | I14: =SUM(I65:I76) | ... BO14: =SUM(BO65:BO76)
A15: Новые школы — зрелые | B15: =B77 | C15: =C77 | D15: =D77 | E15: =E77 | F15: =F77 | G15: =G77 | H15: =H77 | I15: =I77 | ... BO15: =BO77
A16: Новые школы — всего | B16: =SUM(B13:B15) | C16: =SUM(C13:C15) | D16: =SUM(D13:D15) | E16: =SUM(E13:E15) | F16: =SUM(F13:F15) | G16: =SUM(G13:G15) | H16: =SUM(H13:H15) | I16: =SUM(I13:I15) | ... BO16: =SUM(BO13:BO15)
A17: Активные школы — всего | B17: =B11+B16 | C17: =C11+C16 | D17: =D11+D16 | E17: =E11+E16 | F17: =F11+F16 | G17: =G11+G16 | H17: =H11+H16 | I17: =I11+I16 | ... BO17: =BO11+BO16
A18: Дети
A19: Действующая сеть — дети 100% | B19: ='01_Вводные'!$B$11*(1+'01_Вводные'!$B$12)^(B4-1)*IF('01_Вводные'!$B$9=0,0,B11/'01_Вводные'!$B$9) | C19: ='01_Вводные'!$B$11*(1+'01_Вводные'!$B$12)^(C4-1)*IF('01_Вводные'!$B$9=0,0,C11/'01_Вводные'!$B$9) | D19: ='01_Вводные'!$B$11*(1+'01_Вводные'!$B$12)^(D4-1)*IF('01_Вводные'!$B$9=0,0,D11/'01_Вводные'!$B$9) | E19: ='01_Вводные'!$B$11*(1+'01_Вводные'!$B$12)^(E4-1)*IF('01_Вводные'!$B$9=0,0,E11/'01_Вводные'!$B$9) | F19: ='01_Вводные'!$B$11*(1+'01_Вводные'!$B$12)^(F4-1)*IF('01_Вводные'!$B$9=0,0,F11/'01_Вводные'!$B$9) | G19: ='01_Вводные'!$B$11*(1+'01_Вводные'!$B$12)^(G4-1)*IF('01_Вводные'!$B$9=0,0,G11/'01_Вводные'!$B$9) | H19: ='01_Вводные'!$B$11*(1+'01_Вводные'!$B$12)^(H4-1)*IF('01_Вводные'!$B$9=0,0,H11/'01_Вводные'!$B$9) | I19: ='01_Вводные'!$B$11*(1+'01_Вводные'!$B$12)^(I4-1)*IF('01_Вводные'!$B$9=0,0,I11/'01_Вводные'!$B$9) | ... BO19: ='01_Вводные'!$B$11*(1+'01_Вводные'!$B$12)^(BO4-1)*IF('01_Вводные'!$B$9=0,0,BO11/'01_Вводные'!$B$9)
A20: Действующая сеть — активные дети | B20: =B19*B5 | C20: =C19*C5 | D20: =D19*D5 | E20: =E19*E5 | F20: =F19*F5 | G20: =G19*G5 | H20: =H19*H5 | I20: =I19*I5 | ... BO20: =BO19*BO5
A21: Новые школы - дети в мес. 1-12, набор | B21: =SUMPRODUCT(B53:B64,CapacityYear1)*'01_Вводные'!$F$199*B5 | C21: =SUMPRODUCT(C53:C64,CapacityYear1)*'01_Вводные'!$F$199*C5 | D21: =SUMPRODUCT(D53:D64,CapacityYear1)*'01_Вводные'!$F$199*D5 | E21: =SUMPRODUCT(E53:E64,CapacityYear1)*'01_Вводные'!$F$199*E5 | F21: =SUMPRODUCT(F53:F64,CapacityYear1)*'01_Вводные'!$F$199*F5 | G21: =SUMPRODUCT(G53:G64,CapacityYear1)*'01_Вводные'!$F$199*G5 | H21: =SUMPRODUCT(H53:H64,CapacityYear1)*'01_Вводные'!$F$199*H5 | I21: =SUMPRODUCT(I53:I64,CapacityYear1)*'01_Вводные'!$F$199*I5 | ... BO21: =SUMPRODUCT(BO53:BO64,CapacityYear1)*'01_Вводные'!$F$199*BO5
A22: Новые школы - дети в мес. 13-24, рост | B22: =SUMPRODUCT(B65:B76,CapacityYear2)*'01_Вводные'!$F$199*B5 | C22: =SUMPRODUCT(C65:C76,CapacityYear2)*'01_Вводные'!$F$199*C5 | D22: =SUMPRODUCT(D65:D76,CapacityYear2)*'01_Вводные'!$F$199*D5 | E22: =SUMPRODUCT(E65:E76,CapacityYear2)*'01_Вводные'!$F$199*E5 | F22: =SUMPRODUCT(F65:F76,CapacityYear2)*'01_Вводные'!$F$199*F5 | G22: =SUMPRODUCT(G65:G76,CapacityYear2)*'01_Вводные'!$F$199*G5 | H22: =SUMPRODUCT(H65:H76,CapacityYear2)*'01_Вводные'!$F$199*H5 | I22: =SUMPRODUCT(I65:I76,CapacityYear2)*'01_Вводные'!$F$199*I5 | ... BO22: =SUMPRODUCT(BO65:BO76,CapacityYear2)*'01_Вводные'!$F$199*BO5
A23: Новые школы — дети зрелые | B23: =B77*CapacityAge25*'01_Вводные'!$F$199*B5 | C23: =C77*CapacityAge25*'01_Вводные'!$F$199*C5 | D23: =D77*CapacityAge25*'01_Вводные'!$F$199*D5 | E23: =E77*CapacityAge25*'01_Вводные'!$F$199*E5 | F23: =F77*CapacityAge25*'01_Вводные'!$F$199*F5 | G23: =G77*CapacityAge25*'01_Вводные'!$F$199*G5 | H23: =H77*CapacityAge25*'01_Вводные'!$F$199*H5 | I23: =I77*CapacityAge25*'01_Вводные'!$F$199*I5 | ... BO23: =BO77*CapacityAge25*'01_Вводные'!$F$199*BO5
A24: Новые школы — дети всего | B24: =SUM(B21:B23) | C24: =SUM(C21:C23) | D24: =SUM(D21:D23) | E24: =SUM(E21:E23) | F24: =SUM(F21:F23) | G24: =SUM(G21:G23) | H24: =SUM(H21:H23) | I24: =SUM(I21:I23) | ... BO24: =SUM(BO21:BO23)
A25: Всего активных детей | B25: =B20+B24 | C25: =C20+C24 | D25: =D20+D24 | E25: =E20+E24 | F25: =F20+F24 | G25: =G20+G24 | H25: =H20+H24 | I25: =I20+I24 | ... BO25: =BO20+BO24
A27: Роялти
A28: Роялти действующей сети, с НДС | B28: =SUMPRODUCT(('01_Вводные'!$D$314:$D$318*'01_Вводные'!$B$314:$B$318*IF('01_Вводные'!$B$9=0,0,B11/'01_Вводные'!$B$9)+B20*'18_Календарь_тарифы'!B8*'01_Вводные'!$C$314:$C$318*('01_Вводные'!$E$314:$E$318*(B$3<'01_Вводные'!$B$245)+'01_Вводные'!$B$57*(B$3>='01_Вводные'!$B$245))+ABS('01_Вводные'!$D$314:$D$318*'01_Вводные'!$B$314:$B$318*IF('01_Вводные'!$B$9=0,0,B11/'01_Вводные'!$B$9)-B20*'18_Календарь_тарифы'!B8*'01_Вводные'!$C$314:$C$318*('01_Вводные'!$E$314:$E$318*(B$3<'01_Вводные'!$B$245)+'01_Вводные'!$B$57*(B$3>='01_Вводные'!$B$245))))/2) | C28: =SUMPRODUCT(('01_Вводные'!$D$314:$D$318*'01_Вводные'!$B$314:$B$318*IF('01_Вводные'!$B$9=0,0,C11/'01_Вводные'!$B$9)+C20*'18_Календарь_тарифы'!C8*'01_Вводные'!$C$314:$C$318*('01_Вводные'!$E$314:$E$318*(C$3<'01_Вводные'!$B$245)+'01_Вводные'!$B$57*(C$3>='01_Вводные'!$B$245))+ABS('01_Вводные'!$D$314:$D$318*'01_Вводные'!$B$314:$B$318*IF('01_Вводные'!$B$9=0,0,C11/'01_Вводные'!$B$9)-C20*'18_Календарь_тарифы'!C8*'01_Вводные'!$C$314:$C$318*('01_Вводные'!$E$314:$E$318*(C$3<'01_Вводные'!$B$245)+'01_Вводные'!$B$57*(C$3>='01_Вводные'!$B$245))))/2) | D28: =SUMPRODUCT(('01_Вводные'!$D$314:$D$318*'01_Вводные'!$B$314:$B$318*IF('01_Вводные'!$B$9=0,0,D11/'01_Вводные'!$B$9)+D20*'18_Календарь_тарифы'!D8*'01_Вводные'!$C$314:$C$318*('01_Вводные'!$E$314:$E$318*(D$3<'01_Вводные'!$B$245)+'01_Вводные'!$B$57*(D$3>='01_Вводные'!$B$245))+ABS('01_Вводные'!$D$314:$D$318*'01_Вводные'!$B$314:$B$318*IF('01_Вводные'!$B$9=0,0,D11/'01_Вводные'!$B$9)-D20*'18_Календарь_тарифы'!D8*'01_Вводные'!$C$314:$C$318*('01_Вводные'!$E$314:$E$318*(D$3<'01_Вводные'!$B$245)+'01_Вводные'!$B$57*(D$3>='01_Вводные'!$B$245))))/2) | E28: =SUMPRODUCT(('01_Вводные'!$D$314:$D$318*'01_Вводные'!$B$314:$B$318*IF('01_Вводные'!$B$9=0,0,E11/'01_Вводные'!$B$9)+E20*'18_Календарь_тарифы'!E8*'01_Вводные'!$C$314:$C$318*('01_Вводные'!$E$314:$E$318*(E$3<'01_Вводные'!$B$245)+'01_Вводные'!$B$57*(E$3>='01_Вводные'!$B$245))+ABS('01_Вводные'!$D$314:$D$318*'01_Вводные'!$B$314:$B$318*IF('01_Вводные'!$B$9=0,0,E11/'01_Вводные'!$B$9)-E20*'18_Календарь_тарифы'!E8*'01_Вводные'!$C$314:$C$318*('01_Вводные'!$E$314:$E$318*(E$3<'01_Вводные'!$B$245)+'01_Вводные'!$B$57*(E$3>='01_Вводные'!$B$245))))/2) | F28: =SUMPRODUCT(('01_Вводные'!$D$314:$D$318*'01_Вводные'!$B$314:$B$318*IF('01_Вводные'!$B$9=0,0,F11/'01_Вводные'!$B$9)+F20*'18_Календарь_тарифы'!F8*'01_Вводные'!$C$314:$C$318*('01_Вводные'!$E$314:$E$318*(F$3<'01_Вводные'!$B$245)+'01_Вводные'!$B$57*(F$3>='01_Вводные'!$B$245))+ABS('01_Вводные'!$D$314:$D$318*'01_Вводные'!$B$314:$B$318*IF('01_Вводные'!$B$9=0,0,F11/'01_Вводные'!$B$9)-F20*'18_Календарь_тарифы'!F8*'01_Вводные'!$C$314:$C$318*('01_Вводные'!$E$314:$E$318*(F$3<'01_Вводные'!$B$245)+'01_Вводные'!$B$57*(F$3>='01_Вводные'!$B$245))))/2) | G28: =SUMPRODUCT(('01_Вводные'!$D$314:$D$318*'01_Вводные'!$B$314:$B$318*IF('01_Вводные'!$B$9=0,0,G11/'01_Вводные'!$B$9)+G20*'18_Календарь_тарифы'!G8*'01_Вводные'!$C$314:$C$318*('01_Вводные'!$E$314:$E$318*(G$3<'01_Вводные'!$B$245)+'01_Вводные'!$B$57*(G$3>='01_Вводные'!$B$245))+ABS('01_Вводные'!$D$314:$D$318*'01_Вводные'!$B$314:$B$318*IF('01_Вводные'!$B$9=0,0,G11/'01_Вводные'!$B$9)-G20*'18_Календарь_тарифы'!G8*'01_Вводные'!$C$314:$C$318*('01_Вводные'!$E$314:$E$318*(G$3<'01_Вводные'!$B$245)+'01_Вводные'!$B$57*(G$3>='01_Вводные'!$B$245))))/2) | H28: =SUMPRODUCT(('01_Вводные'!$D$314:$D$318*'01_Вводные'!$B$314:$B$318*IF('01_Вводные'!$B$9=0,0,H11/'01_Вводные'!$B$9)+H20*'18_Календарь_тарифы'!H8*'01_Вводные'!$C$314:$C$318*('01_Вводные'!$E$314:$E$318*(H$3<'01_Вводные'!$B$245)+'01_Вводные'!$B$57*(H$3>='01_Вводные'!$B$245))+ABS('01_Вводные'!$D$314:$D$318*'01_Вводные'!$B$314:$B$318*IF('01_Вводные'!$B$9=0,0,H11/'01_Вводные'!$B$9)-H20*'18_Календарь_тарифы'!H8*'01_Вводные'!$C$314:$C$318*('01_Вводные'!$E$314:$E$318*(H$3<'01_Вводные'!$B$245)+'01_Вводные'!$B$57*(H$3>='01_Вводные'!$B$245))))/2) | I28: =SUMPRODUCT(('01_Вводные'!$D$314:$D$318*'01_Вводные'!$B$314:$B$318*IF('01_Вводные'!$B$9=0,0,I11/'01_Вводные'!$B$9)+I20*'18_Календарь_тарифы'!I8*'01_Вводные'!$C$314:$C$318*('01_Вводные'!$E$314:$E$318*(I$3<'01_Вводные'!$B$245)+'01_Вводные'!$B$57*(I$3>='01_Вводные'!$B$245))+ABS('01_Вводные'!$D$314:$D$318*'01_Вводные'!$B$314:$B$318*IF('01_Вводные'!$B$9=0,0,I11/'01_Вводные'!$B$9)-I20*'18_Календарь_тарифы'!I8*'01_Вводные'!$C$314:$C$318*('01_Вводные'!$E$314:$E$318*(I$3<'01_Вводные'!$B$245)+'01_Вводные'!$B$57*(I$3>='01_Вводные'!$B$245))))/2) | ... BO28: =SUMPRODUCT(('01_Вводные'!$D$314:$D$318*'01_Вводные'!$B$314:$B$318*IF('01_Вводные'!$B$9=0,0,BO11/'01_Вводные'!$B$9)+BO20*'18_Календарь_тарифы'!BO8*'01_Вводные'!$C$314:$C$318*('01_Вводные'!$E$314:$E$318*(BO$3<'01_Вводные'!$B$245)+'01_Вводные'!$B$57*(BO$3>='01_Вводные'!$B$245))+ABS('01_Вводные'!$D$314:$D$318*'01_Вводные'!$B$314:$B$318*IF('01_Вводные'!$B$9=0,0,BO11/'01_Вводные'!$B$9)-BO20*'18_Календарь_тарифы'!BO8*'01_Вводные'!$C$314:$C$318*('01_Вводные'!$E$314:$E$318*(BO$3<'01_Вводные'!$B$245)+'01_Вводные'!$B$57*(BO$3>='01_Вводные'!$B$245))))/2)
A29: Роялти новых школ, с НДС | B29: =SUM(B109:B133,B137:B161) | C29: =SUM(C109:C133,C137:C161) | D29: =SUM(D109:D133,D137:D161) | E29: =SUM(E109:E133,E137:E161) | F29: =SUM(F109:F133,F137:F161) | G29: =SUM(G109:G133,G137:G161) | H29: =SUM(H109:H133,H137:H161) | I29: =SUM(I109:I133,I137:I161) | ... BO29: =SUM(BO109:BO133,BO137:BO161)
A30: Роялти всего, с НДС | B30: =B28+B29 | C30: =C28+C29 | D30: =D28+D29 | E30: =E28+E29 | F30: =F28+F29 | G30: =G28+G29 | H30: =H28+H29 | I30: =I28+I29 | ... BO30: =BO28+BO29
A32: Helper для ставок роялти
A33: Legacy открытия (продажи до 31.12.26) | B33: =IF(OR(1<='01_Вводные'!$B$15,1-'01_Вводные'!$B$15>60),0,IF(INDEX('04_Продажи'!$B$11:$BI$11,1,1-'01_Вводные'!$B$15)<='01_Вводные'!$B$244,B8,0)) | C33: =IF(OR(2<='01_Вводные'!$B$15,2-'01_Вводные'!$B$15>60),0,IF(INDEX('04_Продажи'!$B$11:$BI$11,1,2-'01_Вводные'!$B$15)<='01_Вводные'!$B$244,C8,0)) | D33: =IF(OR(3<='01_Вводные'!$B$15,3-'01_Вводные'!$B$15>60),0,IF(INDEX('04_Продажи'!$B$11:$BI$11,1,3-'01_Вводные'!$B$15)<='01_Вводные'!$B$244,D8,0)) | E33: =IF(OR(4<='01_Вводные'!$B$15,4-'01_Вводные'!$B$15>60),0,IF(INDEX('04_Продажи'!$B$11:$BI$11,1,4-'01_Вводные'!$B$15)<='01_Вводные'!$B$244,E8,0)) | F33: =IF(OR(5<='01_Вводные'!$B$15,5-'01_Вводные'!$B$15>60),0,IF(INDEX('04_Продажи'!$B$11:$BI$11,1,5-'01_Вводные'!$B$15)<='01_Вводные'!$B$244,F8,0)) | G33: =IF(OR(6<='01_Вводные'!$B$15,6-'01_Вводные'!$B$15>60),0,IF(INDEX('04_Продажи'!$B$11:$BI$11,1,6-'01_Вводные'!$B$15)<='01_Вводные'!$B$244,G8,0)) | H33: =IF(OR(7<='01_Вводные'!$B$15,7-'01_Вводные'!$B$15>60),0,IF(INDEX('04_Продажи'!$B$11:$BI$11,1,7-'01_Вводные'!$B$15)<='01_Вводные'!$B$244,H8,0)) | I33: =IF(OR(8<='01_Вводные'!$B$15,8-'01_Вводные'!$B$15>60),0,IF(INDEX('04_Продажи'!$B$11:$BI$11,1,8-'01_Вводные'!$B$15)<='01_Вводные'!$B$244,I8,0)) | J33: =IF(OR(9<='01_Вводные'!$B$15,9-'01_Вводные'!$B$15>60),0,IF(INDEX('04_Продажи'!$B$11:$BI$11,1,9-'01_Вводные'!$B$15)<='01_Вводные'!$B$244,J8,0)) | K33: =IF(OR(10<='01_Вводные'!$B$15,10-'01_Вводные'!$B$15>60),0,IF(INDEX('04_Продажи'!$B$11:$BI$11,1,10-'01_Вводные'!$B$15)<='01_Вводные'!$B$244,K8,0)) | L33: =IF(OR(11<='01_Вводные'!$B$15,11-'01_Вводные'!$B$15>60),0,IF(INDEX('04_Продажи'!$B$11:$BI$11,1,11-'01_Вводные'!$B$15)<='01_Вводные'!$B$244,L8,0)) | M33: =IF(OR(12<='01_Вводные'!$B$15,12-'01_Вводные'!$B$15>60),0,IF(INDEX('04_Продажи'!$B$11:$BI$11,1,12-'01_Вводные'!$B$15)<='01_Вводные'!$B$244,M8,0)) | N33: =IF(OR(13<='01_Вводные'!$B$15,13-'01_Вводные'!$B$15>60),0,IF(INDEX('04_Продажи'!$B$11:$BI$11,1,13-'01_Вводные'!$B$15)<='01_Вводные'!$B$244,N8,0)) | O33: =IF(OR(14<='01_Вводные'!$B$15,14-'01_Вводные'!$B$15>60),0,IF(INDEX('04_Продажи'!$B$11:$BI$11,1,14-'01_Вводные'!$B$15)<='01_Вводные'!$B$244,O8,0)) | P33: =IF(OR(15<='01_Вводные'!$B$15,15-'01_Вводные'!$B$15>60),0,IF(INDEX('04_Продажи'!$B$11:$BI$11,1,15-'01_Вводные'!$B$15)<='01_Вводные'!$B$244,P8,0)) | Q33: =IF(OR(16<='01_Вводные'!$B$15,16-'01_Вводные'!$B$15>60),0,IF(INDEX('04_Продажи'!$B$11:$BI$11,1,16-'01_Вводные'!$B$15)<='01_Вводные'!$B$244,Q8,0)) | R33: =IF(OR(17<='01_Вводные'!$B$15,17-'01_Вводные'!$B$15>60),0,IF(INDEX('04_Продажи'!$B$11:$BI$11,1,17-'01_Вводные'!$B$15)<='01_Вводные'!$B$244,R8,0)) | S33: =IF(OR(18<='01_Вводные'!$B$15,18-'01_Вводные'!$B$15>60),0,IF(INDEX('04_Продажи'!$B$11:$BI$11,1,18-'01_Вводные'!$B$15)<='01_Вводные'!$B$244,S8,0)) | T33: =IF(OR(19<='01_Вводные'!$B$15,19-'01_Вводные'!$B$15>60),0,IF(INDEX('04_Продажи'!$B$11:$BI$11,1,19-'01_Вводные'!$B$15)<='01_Вводные'!$B$244,T8,0)) | U33: =IF(OR(20<='01_Вводные'!$B$15,20-'01_Вводные'!$B$15>60),0,IF(INDEX('04_Продажи'!$B$11:$BI$11,1,20-'01_Вводные'!$B$15)<='01_Вводные'!$B$244,U8,0)) | V33: =IF(OR(21<='01_Вводные'!$B$15,21-'01_Вводные'!$B$15>60),0,IF(INDEX('04_Продажи'!$B$11:$BI$11,1,21-'01_Вводные'!$B$15)<='01_Вводные'!$B$244,V8,0)) | W33: =IF(OR(22<='01_Вводные'!$B$15,22-'01_Вводные'!$B$15>60),0,IF(INDEX('04_Продажи'!$B$11:$BI$11,1,22-'01_Вводные'!$B$15)<='01_Вводные'!$B$244,W8,0)) | X33: =IF(OR(23<='01_Вводные'!$B$15,23-'01_Вводные'!$B$15>60),0,IF(INDEX('04_Продажи'!$B$11:$BI$11,1,23-'01_Вводные'!$B$15)<='01_Вводные'!$B$244,X8,0)) | Y33: =IF(OR(24<='01_Вводные'!$B$15,24-'01_Вводные'!$B$15>60),0,IF(INDEX('04_Продажи'!$B$11:$BI$11,1,24-'01_Вводные'!$B$15)<='01_Вводные'!$B$244,Y8,0)) | Z33: =IF(OR(25<='01_Вводные'!$B$15,25-'01_Вводные'!$B$15>60),0,IF(INDEX('04_Продажи'!$B$11:$BI$11,1,25-'01_Вводные'!$B$15)<='01_Вводные'!$B$244,Z8,0)) | AA33: =IF(OR(26<='01_Вводные'!$B$15,26-'01_Вводные'!$B$15>60),0,IF(INDEX('04_Продажи'!$B$11:$BI$11,1,26-'01_Вводные'!$B$15)<='01_Вводные'!$B$244,AA8,0)) | AB33: =IF(OR(27<='01_Вводные'!$B$15,27-'01_Вводные'!$B$15>60),0,IF(INDEX('04_Продажи'!$B$11:$BI$11,1,27-'01_Вводные'!$B$15)<='01_Вводные'!$B$244,AB8,0)) | AC33: =IF(OR(28<='01_Вводные'!$B$15,28-'01_Вводные'!$B$15>60),0,IF(INDEX('04_Продажи'!$B$11:$BI$11,1,28-'01_Вводные'!$B$15)<='01_Вводные'!$B$244,AC8,0)) | AD33: =IF(OR(29<='01_Вводные'!$B$15,29-'01_Вводные'!$B$15>60),0,IF(INDEX('04_Продажи'!$B$11:$BI$11,1,29-'01_Вводные'!$B$15)<='01_Вводные'!$B$244,AD8,0)) | AE33: =IF(OR(30<='01_Вводные'!$B$15,30-'01_Вводные'!$B$15>60),0,IF(INDEX('04_Продажи'!$B$11:$BI$11,1,30-'01_Вводные'!$B$15)<='01_Вводные'!$B$244,AE8,0)) | AF33: =IF(OR(31<='01_Вводные'!$B$15,31-'01_Вводные'!$B$15>60),0,IF(INDEX('04_Продажи'!$B$11:$BI$11,1,31-'01_Вводные'!$B$15)<='01_Вводные'!$B$244,AF8,0)) | AG33: =IF(OR(32<='01_Вводные'!$B$15,32-'01_Вводные'!$B$15>60),0,IF(INDEX('04_Продажи'!$B$11:$BI$11,1,32-'01_Вводные'!$B$15)<='01_Вводные'!$B$244,AG8,0)) | AH33: =IF(OR(33<='01_Вводные'!$B$15,33-'01_Вводные'!$B$15>60),0,IF(INDEX('04_Продажи'!$B$11:$BI$11,1,33-'01_Вводные'!$B$15)<='01_Вводные'!$B$244,AH8,0)) | AI33: =IF(OR(34<='01_Вводные'!$B$15,34-'01_Вводные'!$B$15>60),0,IF(INDEX('04_Продажи'!$B$11:$BI$11,1,34-'01_Вводные'!$B$15)<='01_Вводные'!$B$244,AI8,0)) | AJ33: =IF(OR(35<='01_Вводные'!$B$15,35-'01_Вводные'!$B$15>60),0,IF(INDEX('04_Продажи'!$B$11:$BI$11,1,35-'01_Вводные'!$B$15)<='01_Вводные'!$B$244,AJ8,0)) | AK33: =IF(OR(36<='01_Вводные'!$B$15,36-'01_Вводные'!$B$15>60),0,IF(INDEX('04_Продажи'!$B$11:$BI$11,1,36-'01_Вводные'!$B$15)<='01_Вводные'!$B$244,AK8,0)) | AL33: =IF(OR(37<='01_Вводные'!$B$15,37-'01_Вводные'!$B$15>60),0,IF(INDEX('04_Продажи'!$B$11:$BI$11,1,37-'01_Вводные'!$B$15)<='01_Вводные'!$B$244,AL8,0)) | AM33: =IF(OR(38<='01_Вводные'!$B$15,38-'01_Вводные'!$B$15>60),0,IF(INDEX('04_Продажи'!$B$11:$BI$11,1,38-'01_Вводные'!$B$15)<='01_Вводные'!$B$244,AM8,0)) | AN33: =IF(OR(39<='01_Вводные'!$B$15,39-'01_Вводные'!$B$15>60),0,IF(INDEX('04_Продажи'!$B$11:$BI$11,1,39-'01_Вводные'!$B$15)<='01_Вводные'!$B$244,AN8,0)) | AO33: =IF(OR(40<='01_Вводные'!$B$15,40-'01_Вводные'!$B$15>60),0,IF(INDEX('04_Продажи'!$B$11:$BI$11,1,40-'01_Вводные'!$B$15)<='01_Вводные'!$B$244,AO8,0)) | AP33: =IF(OR(41<='01_Вводные'!$B$15,41-'01_Вводные'!$B$15>60),0,IF(INDEX('04_Продажи'!$B$11:$BI$11,1,41-'01_Вводные'!$B$15)<='01_Вводные'!$B$244,AP8,0)) | AQ33: =IF(OR(42<='01_Вводные'!$B$15,42-'01_Вводные'!$B$15>60),0,IF(INDEX('04_Продажи'!$B$11:$BI$11,1,42-'01_Вводные'!$B$15)<='01_Вводные'!$B$244,AQ8,0)) | AR33: =IF(OR(43<='01_Вводные'!$B$15,43-'01_Вводные'!$B$15>60),0,IF(INDEX('04_Продажи'!$B$11:$BI$11,1,43-'01_Вводные'!$B$15)<='01_Вводные'!$B$244,AR8,0)) | AS33: =IF(OR(44<='01_Вводные'!$B$15,44-'01_Вводные'!$B$15>60),0,IF(INDEX('04_Продажи'!$B$11:$BI$11,1,44-'01_Вводные'!$B$15)<='01_Вводные'!$B$244,AS8,0)) | AT33: =IF(OR(45<='01_Вводные'!$B$15,45-'01_Вводные'!$B$15>60),0,IF(INDEX('04_Продажи'!$B$11:$BI$11,1,45-'01_Вводные'!$B$15)<='01_Вводные'!$B$244,AT8,0)) | AU33: =IF(OR(46<='01_Вводные'!$B$15,46-'01_Вводные'!$B$15>60),0,IF(INDEX('04_Продажи'!$B$11:$BI$11,1,46-'01_Вводные'!$B$15)<='01_Вводные'!$B$244,AU8,0)) | AV33: =IF(OR(47<='01_Вводные'!$B$15,47-'01_Вводные'!$B$15>60),0,IF(INDEX('04_Продажи'!$B$11:$BI$11,1,47-'01_Вводные'!$B$15)<='01_Вводные'!$B$244,AV8,0)) | AW33: =IF(OR(48<='01_Вводные'!$B$15,48-'01_Вводные'!$B$15>60),0,IF(INDEX('04_Продажи'!$B$11:$BI$11,1,48-'01_Вводные'!$B$15)<='01_Вводные'!$B$244,AW8,0)) | AX33: =IF(OR(49<='01_Вводные'!$B$15,49-'01_Вводные'!$B$15>60),0,IF(INDEX('04_Продажи'!$B$11:$BI$11,1,49-'01_Вводные'!$B$15)<='01_Вводные'!$B$244,AX8,0)) | AY33: =IF(OR(50<='01_Вводные'!$B$15,50-'01_Вводные'!$B$15>60),0,IF(INDEX('04_Продажи'!$B$11:$BI$11,1,50-'01_Вводные'!$B$15)<='01_Вводные'!$B$244,AY8,0)) | AZ33: =IF(OR(51<='01_Вводные'!$B$15,51-'01_Вводные'!$B$15>60),0,IF(INDEX('04_Продажи'!$B$11:$BI$11,1,51-'01_Вводные'!$B$15)<='01_Вводные'!$B$244,AZ8,0)) | BA33: =IF(OR(52<='01_Вводные'!$B$15,52-'01_Вводные'!$B$15>60),0,IF(INDEX('04_Продажи'!$B$11:$BI$11,1,52-'01_Вводные'!$B$15)<='01_Вводные'!$B$244,BA8,0)) | BB33: =IF(OR(53<='01_Вводные'!$B$15,53-'01_Вводные'!$B$15>60),0,IF(INDEX('04_Продажи'!$B$11:$BI$11,1,53-'01_Вводные'!$B$15)<='01_Вводные'!$B$244,BB8,0)) | BC33: =IF(OR(54<='01_Вводные'!$B$15,54-'01_Вводные'!$B$15>60),0,IF(INDEX('04_Продажи'!$B$11:$BI$11,1,54-'01_Вводные'!$B$15)<='01_Вводные'!$B$244,BC8,0)) | BD33: =IF(OR(55<='01_Вводные'!$B$15,55-'01_Вводные'!$B$15>60),0,IF(INDEX('04_Продажи'!$B$11:$BI$11,1,55-'01_Вводные'!$B$15)<='01_Вводные'!$B$244,BD8,0)) | BE33: =IF(OR(56<='01_Вводные'!$B$15,56-'01_Вводные'!$B$15>60),0,IF(INDEX('04_Продажи'!$B$11:$BI$11,1,56-'01_Вводные'!$B$15)<='01_Вводные'!$B$244,BE8,0)) | BF33: =IF(OR(57<='01_Вводные'!$B$15,57-'01_Вводные'!$B$15>60),0,IF(INDEX('04_Продажи'!$B$11:$BI$11,1,57-'01_Вводные'!$B$15)<='01_Вводные'!$B$244,BF8,0)) | BG33: =IF(OR(58<='01_Вводные'!$B$15,58-'01_Вводные'!$B$15>60),0,IF(INDEX('04_Продажи'!$B$11:$BI$11,1,58-'01_Вводные'!$B$15)<='01_Вводные'!$B$244,BG8,0)) | BH33: =IF(OR(59<='01_Вводные'!$B$15,59-'01_Вводные'!$B$15>60),0,IF(INDEX('04_Продажи'!$B$11:$BI$11,1,59-'01_Вводные'!$B$15)<='01_Вводные'!$B$244,BH8,0)) | BI33: =IF(OR(60<='01_Вводные'!$B$15,60-'01_Вводные'!$B$15>60),0,IF(INDEX('04_Продажи'!$B$11:$BI$11,1,60-'01_Вводные'!$B$15)<='01_Вводные'!$B$244,BI8,0)) | BJ33: =IF(OR(61<='01_Вводные'!$B$15,61-'01_Вводные'!$B$15>60),0,IF(INDEX('04_Продажи'!$B$11:$BI$11,1,61-'01_Вводные'!$B$15)<='01_Вводные'!$B$244,BJ8,0)) | BK33: =IF(OR(62<='01_Вводные'!$B$15,62-'01_Вводные'!$B$15>60),0,IF(INDEX('04_Продажи'!$B$11:$BI$11,1,62-'01_Вводные'!$B$15)<='01_Вводные'!$B$244,BK8,0)) | BL33: =IF(OR(63<='01_Вводные'!$B$15,63-'01_Вводные'!$B$15>60),0,IF(INDEX('04_Продажи'!$B$11:$BI$11,1,63-'01_Вводные'!$B$15)<='01_Вводные'!$B$244,BL8,0)) | BM33: =IF(OR(64<='01_Вводные'!$B$15,64-'01_Вводные'!$B$15>60),0,IF(INDEX('04_Продажи'!$B$11:$BI$11,1,64-'01_Вводные'!$B$15)<='01_Вводные'!$B$244,BM8,0)) | BN33: =IF(OR(65<='01_Вводные'!$B$15,65-'01_Вводные'!$B$15>60),0,IF(INDEX('04_Продажи'!$B$11:$BI$11,1,65-'01_Вводные'!$B$15)<='01_Вводные'!$B$244,BN8,0)) | BO33: =IF(OR(66<='01_Вводные'!$B$15,66-'01_Вводные'!$B$15>60),0,IF(INDEX('04_Продажи'!$B$11:$BI$11,1,66-'01_Вводные'!$B$15)<='01_Вводные'!$B$244,BO8,0))
A34: Legacy школы 1–12 мес. | B34: =SUM(B81:B92) | C34: =SUM(C81:C92) | D34: =SUM(D81:D92) | E34: =SUM(E81:E92) | F34: =SUM(F81:F92) | G34: =SUM(G81:G92) | H34: =SUM(H81:H92) | I34: =SUM(I81:I92) | ... BO34: =SUM(BO81:BO92)
A35: Legacy школы 13+ мес. | B35: =SUM(B93:B105) | C35: =SUM(C93:C105) | D35: =SUM(D93:D105) | E35: =SUM(E93:E105) | F35: =SUM(F93:F105) | G35: =SUM(G93:G105) | H35: =SUM(H93:H105) | I35: =SUM(I93:I105) | ... BO35: =SUM(BO93:BO105)
A36: Новые 01.01.27+ школы 1–12 мес. | B36: =MAX(0,B13-B34) | C36: =MAX(0,C13-C34) | D36: =MAX(0,D13-D34) | E36: =MAX(0,E13-E34) | F36: =MAX(0,F13-F34) | G36: =MAX(0,G13-G34) | H36: =MAX(0,H13-H34) | I36: =MAX(0,I13-I34) | ... BO36: =MAX(0,BO13-BO34)
A37: Новые 01.01.27+ школы 13+ мес. | B37: =MAX(0,B14+B15-B35) | C37: =MAX(0,C14+C15-C35) | D37: =MAX(0,D14+D15-D35) | E37: =MAX(0,E14+E15-E35) | F37: =MAX(0,F14+F15-F35) | G37: =MAX(0,G14+G15-G35) | H37: =MAX(0,H14+H15-H35) | I37: =MAX(0,I14+I15-I35) | ... BO37: =MAX(0,BO14+BO15-BO35)
A43: Подключения новых школ к ERP | B43: =IF(1<='01_Вводные'!$B$235,0,INDEX($B$8:$BO$8,1,1-'01_Вводные'!$B$235)*'01_Вводные'!$B$14^'01_Вводные'!$B$235) | C43: =IF(2<='01_Вводные'!$B$235,0,INDEX($B$8:$BO$8,1,2-'01_Вводные'!$B$235)*'01_Вводные'!$B$14^'01_Вводные'!$B$235) | D43: =IF(3<='01_Вводные'!$B$235,0,INDEX($B$8:$BO$8,1,3-'01_Вводные'!$B$235)*'01_Вводные'!$B$14^'01_Вводные'!$B$235) | E43: =IF(4<='01_Вводные'!$B$235,0,INDEX($B$8:$BO$8,1,4-'01_Вводные'!$B$235)*'01_Вводные'!$B$14^'01_Вводные'!$B$235) | F43: =IF(5<='01_Вводные'!$B$235,0,INDEX($B$8:$BO$8,1,5-'01_Вводные'!$B$235)*'01_Вводные'!$B$14^'01_Вводные'!$B$235) | G43: =IF(6<='01_Вводные'!$B$235,0,INDEX($B$8:$BO$8,1,6-'01_Вводные'!$B$235)*'01_Вводные'!$B$14^'01_Вводные'!$B$235) | H43: =IF(7<='01_Вводные'!$B$235,0,INDEX($B$8:$BO$8,1,7-'01_Вводные'!$B$235)*'01_Вводные'!$B$14^'01_Вводные'!$B$235) | I43: =IF(8<='01_Вводные'!$B$235,0,INDEX($B$8:$BO$8,1,8-'01_Вводные'!$B$235)*'01_Вводные'!$B$14^'01_Вводные'!$B$235) | J43: =IF(9<='01_Вводные'!$B$235,0,INDEX($B$8:$BO$8,1,9-'01_Вводные'!$B$235)*'01_Вводные'!$B$14^'01_Вводные'!$B$235) | K43: =IF(10<='01_Вводные'!$B$235,0,INDEX($B$8:$BO$8,1,10-'01_Вводные'!$B$235)*'01_Вводные'!$B$14^'01_Вводные'!$B$235) | L43: =IF(11<='01_Вводные'!$B$235,0,INDEX($B$8:$BO$8,1,11-'01_Вводные'!$B$235)*'01_Вводные'!$B$14^'01_Вводные'!$B$235) | M43: =IF(12<='01_Вводные'!$B$235,0,INDEX($B$8:$BO$8,1,12-'01_Вводные'!$B$235)*'01_Вводные'!$B$14^'01_Вводные'!$B$235) | N43: =IF(13<='01_Вводные'!$B$235,0,INDEX($B$8:$BO$8,1,13-'01_Вводные'!$B$235)*'01_Вводные'!$B$14^'01_Вводные'!$B$235) | O43: =IF(14<='01_Вводные'!$B$235,0,INDEX($B$8:$BO$8,1,14-'01_Вводные'!$B$235)*'01_Вводные'!$B$14^'01_Вводные'!$B$235) | P43: =IF(15<='01_Вводные'!$B$235,0,INDEX($B$8:$BO$8,1,15-'01_Вводные'!$B$235)*'01_Вводные'!$B$14^'01_Вводные'!$B$235) | Q43: =IF(16<='01_Вводные'!$B$235,0,INDEX($B$8:$BO$8,1,16-'01_Вводные'!$B$235)*'01_Вводные'!$B$14^'01_Вводные'!$B$235) | R43: =IF(17<='01_Вводные'!$B$235,0,INDEX($B$8:$BO$8,1,17-'01_Вводные'!$B$235)*'01_Вводные'!$B$14^'01_Вводные'!$B$235) | S43: =IF(18<='01_Вводные'!$B$235,0,INDEX($B$8:$BO$8,1,18-'01_Вводные'!$B$235)*'01_Вводные'!$B$14^'01_Вводные'!$B$235) | T43: =IF(19<='01_Вводные'!$B$235,0,INDEX($B$8:$BO$8,1,19-'01_Вводные'!$B$235)*'01_Вводные'!$B$14^'01_Вводные'!$B$235) | U43: =IF(20<='01_Вводные'!$B$235,0,INDEX($B$8:$BO$8,1,20-'01_Вводные'!$B$235)*'01_Вводные'!$B$14^'01_Вводные'!$B$235) | V43: =IF(21<='01_Вводные'!$B$235,0,INDEX($B$8:$BO$8,1,21-'01_Вводные'!$B$235)*'01_Вводные'!$B$14^'01_Вводные'!$B$235) | W43: =IF(22<='01_Вводные'!$B$235,0,INDEX($B$8:$BO$8,1,22-'01_Вводные'!$B$235)*'01_Вводные'!$B$14^'01_Вводные'!$B$235) | X43: =IF(23<='01_Вводные'!$B$235,0,INDEX($B$8:$BO$8,1,23-'01_Вводные'!$B$235)*'01_Вводные'!$B$14^'01_Вводные'!$B$235) | Y43: =IF(24<='01_Вводные'!$B$235,0,INDEX($B$8:$BO$8,1,24-'01_Вводные'!$B$235)*'01_Вводные'!$B$14^'01_Вводные'!$B$235) | Z43: =IF(25<='01_Вводные'!$B$235,0,INDEX($B$8:$BO$8,1,25-'01_Вводные'!$B$235)*'01_Вводные'!$B$14^'01_Вводные'!$B$235) | AA43: =IF(26<='01_Вводные'!$B$235,0,INDEX($B$8:$BO$8,1,26-'01_Вводные'!$B$235)*'01_Вводные'!$B$14^'01_Вводные'!$B$235) | AB43: =IF(27<='01_Вводные'!$B$235,0,INDEX($B$8:$BO$8,1,27-'01_Вводные'!$B$235)*'01_Вводные'!$B$14^'01_Вводные'!$B$235) | AC43: =IF(28<='01_Вводные'!$B$235,0,INDEX($B$8:$BO$8,1,28-'01_Вводные'!$B$235)*'01_Вводные'!$B$14^'01_Вводные'!$B$235) | AD43: =IF(29<='01_Вводные'!$B$235,0,INDEX($B$8:$BO$8,1,29-'01_Вводные'!$B$235)*'01_Вводные'!$B$14^'01_Вводные'!$B$235) | AE43: =IF(30<='01_Вводные'!$B$235,0,INDEX($B$8:$BO$8,1,30-'01_Вводные'!$B$235)*'01_Вводные'!$B$14^'01_Вводные'!$B$235) | AF43: =IF(31<='01_Вводные'!$B$235,0,INDEX($B$8:$BO$8,1,31-'01_Вводные'!$B$235)*'01_Вводные'!$B$14^'01_Вводные'!$B$235) | AG43: =IF(32<='01_Вводные'!$B$235,0,INDEX($B$8:$BO$8,1,32-'01_Вводные'!$B$235)*'01_Вводные'!$B$14^'01_Вводные'!$B$235) | AH43: =IF(33<='01_Вводные'!$B$235,0,INDEX($B$8:$BO$8,1,33-'01_Вводные'!$B$235)*'01_Вводные'!$B$14^'01_Вводные'!$B$235) | AI43: =IF(34<='01_Вводные'!$B$235,0,INDEX($B$8:$BO$8,1,34-'01_Вводные'!$B$235)*'01_Вводные'!$B$14^'01_Вводные'!$B$235) | AJ43: =IF(35<='01_Вводные'!$B$235,0,INDEX($B$8:$BO$8,1,35-'01_Вводные'!$B$235)*'01_Вводные'!$B$14^'01_Вводные'!$B$235) | AK43: =IF(36<='01_Вводные'!$B$235,0,INDEX($B$8:$BO$8,1,36-'01_Вводные'!$B$235)*'01_Вводные'!$B$14^'01_Вводные'!$B$235) | AL43: =IF(37<='01_Вводные'!$B$235,0,INDEX($B$8:$BO$8,1,37-'01_Вводные'!$B$235)*'01_Вводные'!$B$14^'01_Вводные'!$B$235) | AM43: =IF(38<='01_Вводные'!$B$235,0,INDEX($B$8:$BO$8,1,38-'01_Вводные'!$B$235)*'01_Вводные'!$B$14^'01_Вводные'!$B$235) | AN43: =IF(39<='01_Вводные'!$B$235,0,INDEX($B$8:$BO$8,1,39-'01_Вводные'!$B$235)*'01_Вводные'!$B$14^'01_Вводные'!$B$235) | AO43: =IF(40<='01_Вводные'!$B$235,0,INDEX($B$8:$BO$8,1,40-'01_Вводные'!$B$235)*'01_Вводные'!$B$14^'01_Вводные'!$B$235) | AP43: =IF(41<='01_Вводные'!$B$235,0,INDEX($B$8:$BO$8,1,41-'01_Вводные'!$B$235)*'01_Вводные'!$B$14^'01_Вводные'!$B$235) | AQ43: =IF(42<='01_Вводные'!$B$235,0,INDEX($B$8:$BO$8,1,42-'01_Вводные'!$B$235)*'01_Вводные'!$B$14^'01_Вводные'!$B$235) | AR43: =IF(43<='01_Вводные'!$B$235,0,INDEX($B$8:$BO$8,1,43-'01_Вводные'!$B$235)*'01_Вводные'!$B$14^'01_Вводные'!$B$235) | AS43: =IF(44<='01_Вводные'!$B$235,0,INDEX($B$8:$BO$8,1,44-'01_Вводные'!$B$235)*'01_Вводные'!$B$14^'01_Вводные'!$B$235) | AT43: =IF(45<='01_Вводные'!$B$235,0,INDEX($B$8:$BO$8,1,45-'01_Вводные'!$B$235)*'01_Вводные'!$B$14^'01_Вводные'!$B$235) | AU43: =IF(46<='01_Вводные'!$B$235,0,INDEX($B$8:$BO$8,1,46-'01_Вводные'!$B$235)*'01_Вводные'!$B$14^'01_Вводные'!$B$235) | AV43: =IF(47<='01_Вводные'!$B$235,0,INDEX($B$8:$BO$8,1,47-'01_Вводные'!$B$235)*'01_Вводные'!$B$14^'01_Вводные'!$B$235) | AW43: =IF(48<='01_Вводные'!$B$235,0,INDEX($B$8:$BO$8,1,48-'01_Вводные'!$B$235)*'01_Вводные'!$B$14^'01_Вводные'!$B$235) | AX43: =IF(49<='01_Вводные'!$B$235,0,INDEX($B$8:$BO$8,1,49-'01_Вводные'!$B$235)*'01_Вводные'!$B$14^'01_Вводные'!$B$235) | AY43: =IF(50<='01_Вводные'!$B$235,0,INDEX($B$8:$BO$8,1,50-'01_Вводные'!$B$235)*'01_Вводные'!$B$14^'01_Вводные'!$B$235) | AZ43: =IF(51<='01_Вводные'!$B$235,0,INDEX($B$8:$BO$8,1,51-'01_Вводные'!$B$235)*'01_Вводные'!$B$14^'01_Вводные'!$B$235) | BA43: =IF(52<='01_Вводные'!$B$235,0,INDEX($B$8:$BO$8,1,52-'01_Вводные'!$B$235)*'01_Вводные'!$B$14^'01_Вводные'!$B$235) | BB43: =IF(53<='01_Вводные'!$B$235,0,INDEX($B$8:$BO$8,1,53-'01_Вводные'!$B$235)*'01_Вводные'!$B$14^'01_Вводные'!$B$235) | BC43: =IF(54<='01_Вводные'!$B$235,0,INDEX($B$8:$BO$8,1,54-'01_Вводные'!$B$235)*'01_Вводные'!$B$14^'01_Вводные'!$B$235) | BD43: =IF(55<='01_Вводные'!$B$235,0,INDEX($B$8:$BO$8,1,55-'01_Вводные'!$B$235)*'01_Вводные'!$B$14^'01_Вводные'!$B$235) | BE43: =IF(56<='01_Вводные'!$B$235,0,INDEX($B$8:$BO$8,1,56-'01_Вводные'!$B$235)*'01_Вводные'!$B$14^'01_Вводные'!$B$235) | BF43: =IF(57<='01_Вводные'!$B$235,0,INDEX($B$8:$BO$8,1,57-'01_Вводные'!$B$235)*'01_Вводные'!$B$14^'01_Вводные'!$B$235) | BG43: =IF(58<='01_Вводные'!$B$235,0,INDEX($B$8:$BO$8,1,58-'01_Вводные'!$B$235)*'01_Вводные'!$B$14^'01_Вводные'!$B$235) | BH43: =IF(59<='01_Вводные'!$B$235,0,INDEX($B$8:$BO$8,1,59-'01_Вводные'!$B$235)*'01_Вводные'!$B$14^'01_Вводные'!$B$235) | BI43: =IF(60<='01_Вводные'!$B$235,0,INDEX($B$8:$BO$8,1,60-'01_Вводные'!$B$235)*'01_Вводные'!$B$14^'01_Вводные'!$B$235) | BJ43: =IF(61<='01_Вводные'!$B$235,0,INDEX($B$8:$BO$8,1,61-'01_Вводные'!$B$235)*'01_Вводные'!$B$14^'01_Вводные'!$B$235) | BK43: =IF(62<='01_Вводные'!$B$235,0,INDEX($B$8:$BO$8,1,62-'01_Вводные'!$B$235)*'01_Вводные'!$B$14^'01_Вводные'!$B$235) | BL43: =IF(63<='01_Вводные'!$B$235,0,INDEX($B$8:$BO$8,1,63-'01_Вводные'!$B$235)*'01_Вводные'!$B$14^'01_Вводные'!$B$235) | BM43: =IF(64<='01_Вводные'!$B$235,0,INDEX($B$8:$BO$8,1,64-'01_Вводные'!$B$235)*'01_Вводные'!$B$14^'01_Вводные'!$B$235) | BN43: =IF(65<='01_Вводные'!$B$235,0,INDEX($B$8:$BO$8,1,65-'01_Вводные'!$B$235)*'01_Вводные'!$B$14^'01_Вводные'!$B$235) | BO43: =IF(66<='01_Вводные'!$B$235,0,INDEX($B$8:$BO$8,1,66-'01_Вводные'!$B$235)*'01_Вводные'!$B$14^'01_Вводные'!$B$235)
A44: Активные новые школы в ERP | B44: =B43 | C44: =B44*'01_Вводные'!$B$14+C43 | D44: =C44*'01_Вводные'!$B$14+D43 | E44: =D44*'01_Вводные'!$B$14+E43 | F44: =E44*'01_Вводные'!$B$14+F43 | G44: =F44*'01_Вводные'!$B$14+G43 | H44: =G44*'01_Вводные'!$B$14+H43 | I44: =H44*'01_Вводные'!$B$14+I43 | J44: =I44*'01_Вводные'!$B$14+J43 | ... BO44: =BN44*'01_Вводные'!$B$14+BO43
B45: =B105 | C45: =C105 | D45: =D105 | E45: =E105 | F45: =F105 | G45: =G105 | H45: =H105 | I45: =I105 | ... BO45: =BO105
B46: =SUM(B93:B104) | C46: =SUM(C93:C104) | D46: =SUM(D93:D104) | E46: =SUM(E93:E104) | F46: =SUM(F93:F104) | G46: =SUM(G93:G104) | H46: =SUM(H93:H104) | I46: =SUM(I93:I104) | ... BO46: =SUM(BO93:BO104)
B47: =B14-B46 | C47: =C14-C46 | D47: =D14-D46 | E47: =E14-E46 | F47: =F14-F46 | G47: =G14-G46 | H47: =H14-H46 | I47: =I14-I46 | ... BO47: =BO14-BO46
B48: =B15-B45 | C48: =C15-C45 | D48: =D15-D45 | E48: =E15-E45 | F48: =F15-F45 | G48: =G15-G45 | H48: =H15-H45 | I48: =I15-I45 | ... BO48: =BO15-BO45
A52: Школы по месяцам жизни
A53: 1 мес. | B53: =B8 | C53: =C8 | D53: =D8 | E53: =E8 | F53: =F8 | G53: =G8 | H53: =H8 | I53: =I8 | ... BO53: =BO8
A54: 2 мес. | B54: =0 | C54: =B53*'01_Вводные'!$B$14 | D54: =C53*'01_Вводные'!$B$14 | E54: =D53*'01_Вводные'!$B$14 | F54: =E53*'01_Вводные'!$B$14 | G54: =F53*'01_Вводные'!$B$14 | H54: =G53*'01_Вводные'!$B$14 | I54: =H53*'01_Вводные'!$B$14 | J54: =I53*'01_Вводные'!$B$14 | ... BO54: =BN53*'01_Вводные'!$B$14
A55: 3 мес. | B55: =0 | C55: =B54*'01_Вводные'!$B$14 | D55: =C54*'01_Вводные'!$B$14 | E55: =D54*'01_Вводные'!$B$14 | F55: =E54*'01_Вводные'!$B$14 | G55: =F54*'01_Вводные'!$B$14 | H55: =G54*'01_Вводные'!$B$14 | I55: =H54*'01_Вводные'!$B$14 | J55: =I54*'01_Вводные'!$B$14 | ... BO55: =BN54*'01_Вводные'!$B$14
A56: 4 мес. | B56: =0 | C56: =B55*'01_Вводные'!$B$14 | D56: =C55*'01_Вводные'!$B$14 | E56: =D55*'01_Вводные'!$B$14 | F56: =E55*'01_Вводные'!$B$14 | G56: =F55*'01_Вводные'!$B$14 | H56: =G55*'01_Вводные'!$B$14 | I56: =H55*'01_Вводные'!$B$14 | J56: =I55*'01_Вводные'!$B$14 | ... BO56: =BN55*'01_Вводные'!$B$14
A57: 5 мес. | B57: =0 | C57: =B56*'01_Вводные'!$B$14 | D57: =C56*'01_Вводные'!$B$14 | E57: =D56*'01_Вводные'!$B$14 | F57: =E56*'01_Вводные'!$B$14 | G57: =F56*'01_Вводные'!$B$14 | H57: =G56*'01_Вводные'!$B$14 | I57: =H56*'01_Вводные'!$B$14 | J57: =I56*'01_Вводные'!$B$14 | ... BO57: =BN56*'01_Вводные'!$B$14
A58: 6 мес. | B58: =0 | C58: =B57*'01_Вводные'!$B$14 | D58: =C57*'01_Вводные'!$B$14 | E58: =D57*'01_Вводные'!$B$14 | F58: =E57*'01_Вводные'!$B$14 | G58: =F57*'01_Вводные'!$B$14 | H58: =G57*'01_Вводные'!$B$14 | I58: =H57*'01_Вводные'!$B$14 | J58: =I57*'01_Вводные'!$B$14 | ... BO58: =BN57*'01_Вводные'!$B$14
A59: 7 мес. | B59: =0 | C59: =B58*'01_Вводные'!$B$14 | D59: =C58*'01_Вводные'!$B$14 | E59: =D58*'01_Вводные'!$B$14 | F59: =E58*'01_Вводные'!$B$14 | G59: =F58*'01_Вводные'!$B$14 | H59: =G58*'01_Вводные'!$B$14 | I59: =H58*'01_Вводные'!$B$14 | J59: =I58*'01_Вводные'!$B$14 | ... BO59: =BN58*'01_Вводные'!$B$14
A60: 8 мес. | B60: =0 | C60: =B59*'01_Вводные'!$B$14 | D60: =C59*'01_Вводные'!$B$14 | E60: =D59*'01_Вводные'!$B$14 | F60: =E59*'01_Вводные'!$B$14 | G60: =F59*'01_Вводные'!$B$14 | H60: =G59*'01_Вводные'!$B$14 | I60: =H59*'01_Вводные'!$B$14 | J60: =I59*'01_Вводные'!$B$14 | ... BO60: =BN59*'01_Вводные'!$B$14
A61: 9 мес. | B61: =0 | C61: =B60*'01_Вводные'!$B$14 | D61: =C60*'01_Вводные'!$B$14 | E61: =D60*'01_Вводные'!$B$14 | F61: =E60*'01_Вводные'!$B$14 | G61: =F60*'01_Вводные'!$B$14 | H61: =G60*'01_Вводные'!$B$14 | I61: =H60*'01_Вводные'!$B$14 | J61: =I60*'01_Вводные'!$B$14 | ... BO61: =BN60*'01_Вводные'!$B$14
A62: 10 мес. | B62: =0 | C62: =B61*'01_Вводные'!$B$14 | D62: =C61*'01_Вводные'!$B$14 | E62: =D61*'01_Вводные'!$B$14 | F62: =E61*'01_Вводные'!$B$14 | G62: =F61*'01_Вводные'!$B$14 | H62: =G61*'01_Вводные'!$B$14 | I62: =H61*'01_Вводные'!$B$14 | J62: =I61*'01_Вводные'!$B$14 | ... BO62: =BN61*'01_Вводные'!$B$14
A63: 11 мес. | B63: =0 | C63: =B62*'01_Вводные'!$B$14 | D63: =C62*'01_Вводные'!$B$14 | E63: =D62*'01_Вводные'!$B$14 | F63: =E62*'01_Вводные'!$B$14 | G63: =F62*'01_Вводные'!$B$14 | H63: =G62*'01_Вводные'!$B$14 | I63: =H62*'01_Вводные'!$B$14 | J63: =I62*'01_Вводные'!$B$14 | ... BO63: =BN62*'01_Вводные'!$B$14
A64: 12 мес. | B64: =0 | C64: =B63*'01_Вводные'!$B$14 | D64: =C63*'01_Вводные'!$B$14 | E64: =D63*'01_Вводные'!$B$14 | F64: =E63*'01_Вводные'!$B$14 | G64: =F63*'01_Вводные'!$B$14 | H64: =G63*'01_Вводные'!$B$14 | I64: =H63*'01_Вводные'!$B$14 | J64: =I63*'01_Вводные'!$B$14 | ... BO64: =BN63*'01_Вводные'!$B$14
A65: 13 мес. | B65: =0 | C65: =B64*'01_Вводные'!$B$14 | D65: =C64*'01_Вводные'!$B$14 | E65: =D64*'01_Вводные'!$B$14 | F65: =E64*'01_Вводные'!$B$14 | G65: =F64*'01_Вводные'!$B$14 | H65: =G64*'01_Вводные'!$B$14 | I65: =H64*'01_Вводные'!$B$14 | J65: =I64*'01_Вводные'!$B$14 | ... BO65: =BN64*'01_Вводные'!$B$14
... A76: 24 мес. | B76: =0 | C76: =B75*'01_Вводные'!$B$14 | D76: =C75*'01_Вводные'!$B$14 | E76: =D75*'01_Вводные'!$B$14 | F76: =E75*'01_Вводные'!$B$14 | G76: =F75*'01_Вводные'!$B$14 | H76: =G75*'01_Вводные'!$B$14 | I76: =H75*'01_Вводные'!$B$14 | J76: =I75*'01_Вводные'!$B$14 | ... BO76: =BN75*'01_Вводные'!$B$14
A77: 25+ мес. | B77: =0 | C77: =SUM(B76:B77)*'01_Вводные'!$B$14 | D77: =SUM(C76:C77)*'01_Вводные'!$B$14 | E77: =SUM(D76:D77)*'01_Вводные'!$B$14 | F77: =SUM(E76:E77)*'01_Вводные'!$B$14 | G77: =SUM(F76:F77)*'01_Вводные'!$B$14 | H77: =SUM(G76:G77)*'01_Вводные'!$B$14 | I77: =SUM(H76:H77)*'01_Вводные'!$B$14 | J77: =SUM(I76:I77)*'01_Вводные'!$B$14 | ... BO77: =SUM(BN76:BN77)*'01_Вводные'!$B$14
A80: Из них: договоры по старой ставке
A81: 1 мес. | B81: =B33 | C81: =C33 | D81: =D33 | E81: =E33 | F81: =F33 | G81: =G33 | H81: =H33 | I81: =I33 | ... BO81: =BO33
A82: 2 мес. | B82: =0 | C82: =B81*'01_Вводные'!$B$14 | D82: =C81*'01_Вводные'!$B$14 | E82: =D81*'01_Вводные'!$B$14 | F82: =E81*'01_Вводные'!$B$14 | G82: =F81*'01_Вводные'!$B$14 | H82: =G81*'01_Вводные'!$B$14 | I82: =H81*'01_Вводные'!$B$14 | J82: =I81*'01_Вводные'!$B$14 | ... BO82: =BN81*'01_Вводные'!$B$14
A83: 3 мес. | B83: =0 | C83: =B82*'01_Вводные'!$B$14 | D83: =C82*'01_Вводные'!$B$14 | E83: =D82*'01_Вводные'!$B$14 | F83: =E82*'01_Вводные'!$B$14 | G83: =F82*'01_Вводные'!$B$14 | H83: =G82*'01_Вводные'!$B$14 | I83: =H82*'01_Вводные'!$B$14 | J83: =I82*'01_Вводные'!$B$14 | ... BO83: =BN82*'01_Вводные'!$B$14
A84: 4 мес. | B84: =0 | C84: =B83*'01_Вводные'!$B$14 | D84: =C83*'01_Вводные'!$B$14 | E84: =D83*'01_Вводные'!$B$14 | F84: =E83*'01_Вводные'!$B$14 | G84: =F83*'01_Вводные'!$B$14 | H84: =G83*'01_Вводные'!$B$14 | I84: =H83*'01_Вводные'!$B$14 | J84: =I83*'01_Вводные'!$B$14 | ... BO84: =BN83*'01_Вводные'!$B$14
A85: 5 мес. | B85: =0 | C85: =B84*'01_Вводные'!$B$14 | D85: =C84*'01_Вводные'!$B$14 | E85: =D84*'01_Вводные'!$B$14 | F85: =E84*'01_Вводные'!$B$14 | G85: =F84*'01_Вводные'!$B$14 | H85: =G84*'01_Вводные'!$B$14 | I85: =H84*'01_Вводные'!$B$14 | J85: =I84*'01_Вводные'!$B$14 | ... BO85: =BN84*'01_Вводные'!$B$14
A86: 6 мес. | B86: =0 | C86: =B85*'01_Вводные'!$B$14 | D86: =C85*'01_Вводные'!$B$14 | E86: =D85*'01_Вводные'!$B$14 | F86: =E85*'01_Вводные'!$B$14 | G86: =F85*'01_Вводные'!$B$14 | H86: =G85*'01_Вводные'!$B$14 | I86: =H85*'01_Вводные'!$B$14 | J86: =I85*'01_Вводные'!$B$14 | ... BO86: =BN85*'01_Вводные'!$B$14
A87: 7 мес. | B87: =0 | C87: =B86*'01_Вводные'!$B$14 | D87: =C86*'01_Вводные'!$B$14 | E87: =D86*'01_Вводные'!$B$14 | F87: =E86*'01_Вводные'!$B$14 | G87: =F86*'01_Вводные'!$B$14 | H87: =G86*'01_Вводные'!$B$14 | I87: =H86*'01_Вводные'!$B$14 | J87: =I86*'01_Вводные'!$B$14 | ... BO87: =BN86*'01_Вводные'!$B$14
A88: 8 мес. | B88: =0 | C88: =B87*'01_Вводные'!$B$14 | D88: =C87*'01_Вводные'!$B$14 | E88: =D87*'01_Вводные'!$B$14 | F88: =E87*'01_Вводные'!$B$14 | G88: =F87*'01_Вводные'!$B$14 | H88: =G87*'01_Вводные'!$B$14 | I88: =H87*'01_Вводные'!$B$14 | J88: =I87*'01_Вводные'!$B$14 | ... BO88: =BN87*'01_Вводные'!$B$14
A89: 9 мес. | B89: =0 | C89: =B88*'01_Вводные'!$B$14 | D89: =C88*'01_Вводные'!$B$14 | E89: =D88*'01_Вводные'!$B$14 | F89: =E88*'01_Вводные'!$B$14 | G89: =F88*'01_Вводные'!$B$14 | H89: =G88*'01_Вводные'!$B$14 | I89: =H88*'01_Вводные'!$B$14 | J89: =I88*'01_Вводные'!$B$14 | ... BO89: =BN88*'01_Вводные'!$B$14
A90: 10 мес. | B90: =0 | C90: =B89*'01_Вводные'!$B$14 | D90: =C89*'01_Вводные'!$B$14 | E90: =D89*'01_Вводные'!$B$14 | F90: =E89*'01_Вводные'!$B$14 | G90: =F89*'01_Вводные'!$B$14 | H90: =G89*'01_Вводные'!$B$14 | I90: =H89*'01_Вводные'!$B$14 | J90: =I89*'01_Вводные'!$B$14 | ... BO90: =BN89*'01_Вводные'!$B$14
A91: 11 мес. | B91: =0 | C91: =B90*'01_Вводные'!$B$14 | D91: =C90*'01_Вводные'!$B$14 | E91: =D90*'01_Вводные'!$B$14 | F91: =E90*'01_Вводные'!$B$14 | G91: =F90*'01_Вводные'!$B$14 | H91: =G90*'01_Вводные'!$B$14 | I91: =H90*'01_Вводные'!$B$14 | J91: =I90*'01_Вводные'!$B$14 | ... BO91: =BN90*'01_Вводные'!$B$14
A92: 12 мес. | B92: =0 | C92: =B91*'01_Вводные'!$B$14 | D92: =C91*'01_Вводные'!$B$14 | E92: =D91*'01_Вводные'!$B$14 | F92: =E91*'01_Вводные'!$B$14 | G92: =F91*'01_Вводные'!$B$14 | H92: =G91*'01_Вводные'!$B$14 | I92: =H91*'01_Вводные'!$B$14 | J92: =I91*'01_Вводные'!$B$14 | ... BO92: =BN91*'01_Вводные'!$B$14
A93: 13 мес. | B93: =0 | C93: =B92*'01_Вводные'!$B$14 | D93: =C92*'01_Вводные'!$B$14 | E93: =D92*'01_Вводные'!$B$14 | F93: =E92*'01_Вводные'!$B$14 | G93: =F92*'01_Вводные'!$B$14 | H93: =G92*'01_Вводные'!$B$14 | I93: =H92*'01_Вводные'!$B$14 | J93: =I92*'01_Вводные'!$B$14 | ... BO93: =BN92*'01_Вводные'!$B$14
... A104: 24 мес. | B104: =0 | C104: =B103*'01_Вводные'!$B$14 | D104: =C103*'01_Вводные'!$B$14 | E104: =D103*'01_Вводные'!$B$14 | F104: =E103*'01_Вводные'!$B$14 | G104: =F103*'01_Вводные'!$B$14 | H104: =G103*'01_Вводные'!$B$14 | I104: =H103*'01_Вводные'!$B$14 | J104: =I103*'01_Вводные'!$B$14 | ... BO104: =BN103*'01_Вводные'!$B$14
A105: 25+ мес. | B105: =0 | C105: =SUM(B104:B105)*'01_Вводные'!$B$14 | D105: =SUM(C104:C105)*'01_Вводные'!$B$14 | E105: =SUM(D104:D105)*'01_Вводные'!$B$14 | F105: =SUM(E104:E105)*'01_Вводные'!$B$14 | G105: =SUM(F104:F105)*'01_Вводные'!$B$14 | H105: =SUM(G104:G105)*'01_Вводные'!$B$14 | I105: =SUM(H104:H105)*'01_Вводные'!$B$14 | J105: =SUM(I104:I105)*'01_Вводные'!$B$14 | ... BO105: =SUM(BN104:BN105)*'01_Вводные'!$B$14
A108: Роялти: старая ставка, по возрасту
